Workbook

Sheet indice Carburant
A1: INDICE 2026
E4: DIREM
A5: CNR Base 100 Décembre 2000 | B5: 45931 | C5: 45962 | D5: 45992 | E5: 46023 | F5: 46054 | G5: 46082 | H5: 46113 | I5: 46143 | J5: 46174 | K5: 46204 | L5: 46235 | M5: 46266 | N5: 46296 | O5: 46327 | P5: 46357
A6: Indice CNR gazole professionnel | B6: 183.84 | C6: 192.03 | D6: 181.52 | E6: 187.66 | F6: 193.34 | G6: 248.08
A7: Indice CNR gazole hors TVA | B7: 192.92 | C7: 200.49 | D7: 190.79 | E7: 196.16 | F7: 201.41 | G7: 251.94
A8: Prix CNR gazole CUVE moyenne mensuelle | B8: 1.2965 | C8: 1.345 | D8: 1.2687 | E8: 1.3218 | F8: 1.3547 | G8: 1.7575
A9: Prix CNR gazole cuve fin de mois | B9: 1.3111 | C9: 1.34 | D9: 1.2472 | E9: - | F9: - | G9: - | H9: - | I9: - | J9: - | K9: - | L9: - | M9: - | N9: - | O9: - | P9: -
A10: Prix gazole POMPE moyenne mensuelle (DIREM) | B10: 1.3322 | C10: 1.3882 | D10: 1.3384 | E10: 1.362 | F10: 1.3937 | G10: 1.7224 | Q10: DIREM à partir de Janvier 2026
A11: Prix gazole pompe fin de mois (DIREM) | B11: 1.3253 | C11: 1.4141 | D11: 1.2749 | E11: 1.3663 | F11: 1.3748 | G11: 1.7573
A13: Indice CNR carburant GNV | B13: 165.31 | C13: 166.16 | D13: 161.43 | E13: 159.61 | F13: 177.68
A14: ENGIE Hors TICGN COMPTE VIAPOST | B14: 1.004 | C14: 0.9954 | D14: 0.9834 | E14: 0.9356 | F14: 1.03
A15: AS 24 - Carburant BIO GNC - Tarif PARNASS | B15: 1.1409 | C15: 1.1408 | D15: 1.1408 | E15: 1.1008 | F15: 1.2192 | G15: 1.1983
A16: ENGIE - Carburant GNC L - Tarif PARNASS | B16: 1.2241 | C16: 1.2156 | D16: 1.2043 | E16: 1.156 | F16: 1.251 | G16: 1.2264 | H16: 1.5505
A17: ENGIE - Carburant BIO GNC - Tarif PARNASS | B17: 1.2246 | C17: 1.2159 | D17: 1.2019 | E17: 1.1962 | F17: 1.3068 | G17: 1.28031 | H17: 1.5859
A18: ENGIE - Carburant GNL - Tarif PARNASS | B18: 1.1788 | C18: 1.1703 | D18: 1.1588 | E18: 1.1105 | F18: 1.2053 | G18: 1.1806 | H18: 1.5032
A20: AS 24 - Carburant GO - Tarif PARNASS | B20: 1.3925 | C20: 1.4562 | D20: 1.3838 | E20: 1.3995 | F20: 1.4348 | G20: 1.8088
A22: Indice CNR Carburant groupe froid autonome GNR | B22: 272.73 | C22: 289.28 | D22: 268.99 | E22: 282.47 | F22: 297.24 | G22: 393.85
A25: Remise Partiel TICPE Forfait | B25: 0.1571 | C25: 0.1571 | D25: 0.1571 | E25: 0.1575 | F25: 0.1575 | G25: 0.1575 | H25: 0.1575 | I25: 0.1575 | J25: 0.1575 | K25: 0.1575 | L25: 0.1575 | M25: 0.1575 | N25: 0.1575 | O25: 0.1575 | P25: 0.1575
A26: REMISE PARTIEL TICPE AUCHAN | E26: 0.1556 | F26: 0.1556 | G26: 0.1556 | H26: 0.1556 | I26: 0.1556 | J26: 0.1556 | K26: 0.1556 | L26: 0.1556 | M26: 0.1556 | N26: 0.1556 | O26: 0.1556 | P26: 0.1556

Sheet Indexation Client 2026
A1: INDEXATION CARBURANT Clients 2026
G2: Jours | H2: Ouvrables | J2: 26 | K2: 24 | L2: 26 | M2: 25 | N2: 22 | O2: 26 | P2: 26 | Q2: 25 | R2: 26 | S2: 27 | T2: 24 | U2: 26
H3: Ouvrés | J3: 21 | K3: 20 | L3: 22 | M3: 21 | N3: 17 | O3: 22 | P3: 22 | Q3: 21 | R3: 22 | S3: 22 | T3: 20 | U3: 22
A5: CLIENTS | B5: Contrats | C5: Code Facturation | D5: Indice de Référence | E5: Base indice | F5: Pondération | G5: Mode de Facturation IGO | H5: Valeur de Réf. | J5: 46023 | K5: 46054 | L5: 46082 | M5: 46113 | N5: 46143 | O5: 46174 | P5: 46204 | Q5: 46235 | R5: 46266 | S5: 46296 | T5: 46327 | U5: 46357
A6: CAT | B6: IVELI_FRIDF SR1 | C6: CAT | D6: 174.88 | E6: CNR GO PRO M-1 | F6: 0.25 | G6: % Pied de facture | J6: =((('indice Carburant'!D6/'Indexation Client 2026'!$D$6)-1)*'Indexation Client 2026'!$F$6) -> 0.0094922232 | K6: =((('indice Carburant'!E6/'Indexation Client 2026'!$D$6)-1)*'Indexation Client 2026'!$F$6) -> 0.018269671 | L6: =((('indice Carburant'!F6/'Indexation Client 2026'!$D$6)-1)*'Indexation Client 2026'!$F$6) -> 0.026389524 | M6: =((('indice Carburant'!G6/'Indexation Client 2026'!$D$6)-1)*'Indexation Client 2026'!$F$6) -> 0.10464318 | N6: =((('indice Carburant'!H6/'Indexation Client 2026'!$D$6)-1)*'Indexation Client 2026'!$F$6) -> -0.25 | O6: =((('indice Carburant'!I6/'Indexation Client 2026'!$D$6)-1)*'Indexation Client 2026'!$F$6) -> -0.25 | P6: =((('indice Carburant'!J6/'Indexation Client 2026'!$D$6)-1)*'Indexation Client 2026'!$F$6) -> -0.25 | Q6: =((('indice Carburant'!K6/'Indexation Client 2026'!$D$6)-1)*'Indexation Client 2026'!$F$6) -> -0.25 | ... U6: =((('indice Carburant'!O6/'Indexation Client 2026'!$D$6)-1)*'Indexation Client 2026'!$F$6) -> -0.25
A7: CAT | B7: JCBBO_FRIDF | C7: CAT | D7: 174.88 | E7: CNR GO PRO M-1 | F7: 0.25 | G7: % Pied de facture | J7: =((('indice Carburant'!D6/'Indexation Client 2026'!$D$7)-1)*'Indexation Client 2026'!$F$7) -> 0.0094922232 | K7: =((('indice Carburant'!E6/'Indexation Client 2026'!$D$7)-1)*'Indexation Client 2026'!$F$7) -> 0.018269671 | L7: =((('indice Carburant'!F6/'Indexation Client 2026'!$D$7)-1)*'Indexation Client 2026'!$F$7) -> 0.026389524 | M7: =((('indice Carburant'!G6/'Indexation Client 2026'!$D$7)-1)*'Indexation Client 2026'!$F$7) -> 0.10464318 | N7: =((('indice Carburant'!H6/'Indexation Client 2026'!$D$7)-1)*'Indexation Client 2026'!$F$7) -> -0.25 | O7: =((('indice Carburant'!I6/'Indexation Client 2026'!$D$7)-1)*'Indexation Client 2026'!$F$7) -> -0.25 | P7: =((('indice Carburant'!J6/'Indexation Client 2026'!$D$7)-1)*'Indexation Client 2026'!$F$7) -> -0.25 | Q7: =((('indice Carburant'!K6/'Indexation Client 2026'!$D$7)-1)*'Indexation Client 2026'!$F$7) -> -0.25 | ... U7: =((('indice Carburant'!O6/'Indexation Client 2026'!$D$7)-1)*'Indexation Client 2026'!$F$7) -> -0.25
A8: CEVA LOGISTIC | B8: CEVA GENNEVILLIERS | C8: CEVAGEN | D8: ?
A9: CEVA LOGISTIC | B9: CEVA MOISSY | C9: CEVAMOI | D9: ?
A10: CHRONOPOST CHILLY | B10: 40U62 - Conforma / MGF | C10: CHCMZ | D10: 1.1654 | E10: PMM DIREM M-1 | F10: 0.28 | G10: Sur Km | H10: 62 | J10: =(('indice Carburant'!D10-'Indexation Client 2026'!$D$10)*'Indexation Client 2026'!$F$10)*'Indexation Client 2026'!$H$10 -> 3.00328 | K10: =(('indice Carburant'!E10-'Indexation Client 2026'!$D$10)*'Indexation Client 2026'!$F$10)*'Indexation Client 2026'!$H$10 -> 3.412976 | L10: =(('indice Carburant'!F10-'Indexation Client 2026'!$D$10)*'Indexation Client 2026'!$F$10)*'Indexation Client 2026'!$H$10 -> 3.963288 | M10: =(('indice Carburant'!G10-'Indexation Client 2026'!$D$10)*'Indexation Client 2026'!$F$10)*'Indexation Client 2026'!$H$10 -> 9.66952 | N10: =(('indice Carburant'!H10-'Indexation Client 2026'!$D$10)*'Indexation Client 2026'!$F$10)*'Indexation Client 2026'!$H$10 -> -20.231344 | O10: =(('indice Carburant'!I10-'Indexation Client 2026'!$D$10)*'Indexation Client 2026'!$F$10)*'Indexation Client 2026'!$H$10 -> -20.231344 | P10: =(('indice Carburant'!J10-'Indexation Client 2026'!$D$10)*'Indexation Client 2026'!$F$10)*'Indexation Client 2026'!$H$10 -> -20.231344 | Q10: =(('indice Carburant'!K10-'Indexation Client 2026'!$D$10)*'Indexation Client 2026'!$F$10)*'Indexation Client 2026'!$H$10 -> -20.231344 | ... U10: =(('indice Carburant'!O10-'Indexation Client 2026'!$D$10)*'Indexation Client 2026'!$F$10)*'Indexation Client 2026'!$H$10 -> -20.231344
A11: CHRONOPOST CHILLY | B11: 40U71 - Alloga | C11: CHCMZ | D11: 1.6915 | E11: PMM DIREM M-1 | F11: 0.28 | G11: Sur Km | H11: 129 | J11: =(('indice Carburant'!D10-'Indexation Client 2026'!$D$11)*'Indexation Client 2026'!$F$11)*'Indexation Client 2026'!$H$11 -> -12.753972 | K11: =(('indice Carburant'!E10-'Indexation Client 2026'!$D$11)*'Indexation Client 2026'!$F$11)*'Indexation Client 2026'!$H$11 -> -11.90154 | L11: =(('indice Carburant'!F10-'Indexation Client 2026'!$D$11)*'Indexation Client 2026'!$F$11)*'Indexation Client 2026'!$H$11 -> -10.756536 | M11: =(('indice Carburant'!G10-'Indexation Client 2026'!$D$11)*'Indexation Client 2026'!$F$11)*'Indexation Client 2026'!$H$11 -> 1.116108 | N11: =(('indice Carburant'!H10-'Indexation Client 2026'!$D$11)*'Indexation Client 2026'!$F$11)*'Indexation Client 2026'!$H$11 -> -61.09698 | O11: =(('indice Carburant'!I10-'Indexation Client 2026'!$D$11)*'Indexation Client 2026'!$F$11)*'Indexation Client 2026'!$H$11 -> -61.09698 | P11: =(('indice Carburant'!J10-'Indexation Client 2026'!$D$11)*'Indexation Client 2026'!$F$11)*'Indexation Client 2026'!$H$11 -> -61.09698 | Q11: =(('indice Carburant'!K10-'Indexation Client 2026'!$D$11)*'Indexation Client 2026'!$F$11)*'Indexation Client 2026'!$H$11 -> -61.09698 | ... U11: =(('indice Carburant'!O10-'Indexation Client 2026'!$D$11)*'Indexation Client 2026'!$F$11)*'Indexation Client 2026'!$H$11 -> -61.09698
A12: CHRONOPOST CHILLY | B12: 40U72 - Dyson | C12: CHCMZ | D12: 1.2187 | E12: PMM DIREM M-1 | F12: 0.28 | G12: Sur Km | H12: 129 | J12: =(('indice Carburant'!D10-'Indexation Client 2026'!$D$12)*'Indexation Client 2026'!$F$12)*'Indexation Client 2026'!$H$12 -> 4.323564 | K12: =(('indice Carburant'!E10-'Indexation Client 2026'!$D$12)*'Indexation Client 2026'!$F$12)*'Indexation Client 2026'!$H$12 -> 5.175996 | L12: =(('indice Carburant'!F10-'Indexation Client 2026'!$D$12)*'Indexation Client 2026'!$F$12)*'Indexation Client 2026'!$H$12 -> 6.321 | M12: =(('indice Carburant'!G10-'Indexation Client 2026'!$D$12)*'Indexation Client 2026'!$F$12)*'Indexation Client 2026'!$H$12 -> 18.193644 | N12: =(('indice Carburant'!H10-'Indexation Client 2026'!$D$12)*'Indexation Client 2026'!$F$12)*'Indexation Client 2026'!$H$12 -> -44.019444 | O12: =(('indice Carburant'!I10-'Indexation Client 2026'!$D$12)*'Indexation Client 2026'!$F$12)*'Indexation Client 2026'!$H$12 -> -44.019444 | P12: =(('indice Carburant'!J10-'Indexation Client 2026'!$D$12)*'Indexation Client 2026'!$F$12)*'Indexation Client 2026'!$H$12 -> -44.019444 | Q12: =(('indice Carburant'!K10-'Indexation Client 2026'!$D$12)*'Indexation Client 2026'!$F$12)*'Indexation Client 2026'!$H$12 -> -44.019444 | ... U12: =(('indice Carburant'!O10-'Indexation Client 2026'!$D$12)*'Indexation Client 2026'!$F$12)*'Indexation Client 2026'!$H$12 -> -44.019444
A13: CHRONOPOST CHILLY | B13: 40U76 - AMAZON (HNI) | C13: CHCMZ | D13: 1.376 | E13: PMM DIREM M-1 | F13: 0.28 | G13: Sur Km | H13: 64 | J13: =(('indice Carburant'!D10-'Indexation Client 2026'!$D$13)*'Indexation Client 2026'!$F$13)*'Indexation Client 2026'!$H$13 -> -0.673792 | K13: =(('indice Carburant'!E10-'Indexation Client 2026'!$D$13)*'Indexation Client 2026'!$F$13)*'Indexation Client 2026'!$H$13 -> -0.25088 | L13: =(('indice Carburant'!F10-'Indexation Client 2026'!$D$13)*'Indexation Client 2026'!$F$13)*'Indexation Client 2026'!$H$13 -> 0.317184 | M13: =(('indice Carburant'!G10-'Indexation Client 2026'!$D$13)*'Indexation Client 2026'!$F$13)*'Indexation Client 2026'!$H$13 -> 6.207488 | N13: =(('indice Carburant'!H10-'Indexation Client 2026'!$D$13)*'Indexation Client 2026'!$F$13)*'Indexation Client 2026'!$H$13 -> -24.65792 | O13: =(('indice Carburant'!I10-'Indexation Client 2026'!$D$13)*'Indexation Client 2026'!$F$13)*'Indexation Client 2026'!$H$13 -> -24.65792 | P13: =(('indice Carburant'!J10-'Indexation Client 2026'!$D$13)*'Indexation Client 2026'!$F$13)*'Indexation Client 2026'!$H$13 -> -24.65792 | Q13: =(('indice Carburant'!K10-'Indexation Client 2026'!$D$13)*'Indexation Client 2026'!$F$13)*'Indexation Client 2026'!$H$13 -> -24.65792 | ... U13: =(('indice Carburant'!O10-'Indexation Client 2026'!$D$13)*'Indexation Client 2026'!$F$13)*'Indexation Client 2026'!$H$13 -> -24.65792
A14: CHRONOPOST CHILLY | B14: 40U76 - AMAZON (CMZ) | C14: CHCMZ | D14: 1.376 | E14: PMM DIREM M-1 | F14: 0.28 | G14: Sur Km | H14: 34 | J14: =(('indice Carburant'!D10-'Indexation Client 2026'!$D$14)*'Indexation Client 2026'!$F$14)*'Indexation Client 2026'!$H$14 -> -0.357952 | K14: =(('indice Carburant'!E10-'Indexation Client 2026'!$D$14)*'Indexation Client 2026'!$F$14)*'Indexation Client 2026'!$H$14 -> -0.13328 | L14: =(('indice Carburant'!F10-'Indexation Client 2026'!$D$14)*'Indexation Client 2026'!$F$14)*'Indexation Client 2026'!$H$14 -> 0.168504 | M14: =(('indice Carburant'!G10-'Indexation Client 2026'!$D$14)*'Indexation Client 2026'!$F$14)*'Indexation Client 2026'!$H$14 -> 3.297728 | N14: =(('indice Carburant'!H10-'Indexation Client 2026'!$D$14)*'Indexation Client 2026'!$F$14)*'Indexation Client 2026'!$H$14 -> -13.09952 | O14: =(('indice Carburant'!I10-'Indexation Client 2026'!$D$14)*'Indexation Client 2026'!$F$14)*'Indexation Client 2026'!$H$14 -> -13.09952 | P14: =(('indice Carburant'!J10-'Indexation Client 2026'!$D$14)*'Indexation Client 2026'!$F$14)*'Indexation Client 2026'!$H$14 -> -13.09952 | Q14: =(('indice Carburant'!K10-'Indexation Client 2026'!$D$14)*'Indexation Client 2026'!$F$14)*'Indexation Client 2026'!$H$14 -> -13.09952 | ... U14: =(('indice Carburant'!O10-'Indexation Client 2026'!$D$14)*'Indexation Client 2026'!$F$14)*'Indexation Client 2026'!$H$14 -> -13.09952
A15: CHRONOPOST CHILLY | B15: 40U88 (Gaz) - CDISCOUNT CMZ | C15: CHCMZ | D15: 1.1431 | E15: PMM DIREM M-1 | F15: 0.28 | G15: Sur Km | H15: 35 | J15: =(('indice Carburant'!D10-'Indexation Client 2026'!$D$15)*'Indexation Client 2026'!$F$15)*'Indexation Client 2026'!$H$15 -> 1.91394 | K15: =(('indice Carburant'!E10-'Indexation Client 2026'!$D$15)*'Indexation Client 2026'!$F$15)*'Indexation Client 2026'!$H$15 -> 2.14522 | L15: =(('indice Carburant'!F10-'Indexation Client 2026'!$D$15)*'Indexation Client 2026'!$F$15)*'Indexation Client 2026'!$H$15 -> 2.45588 | M15: =(('indice Carburant'!G10-'Indexation Client 2026'!$D$15)*'Indexation Client 2026'!$F$15)*'Indexation Client 2026'!$H$15 -> 5.67714 | N15: =(('indice Carburant'!H10-'Indexation Client 2026'!$D$15)*'Indexation Client 2026'!$F$15)*'Indexation Client 2026'!$H$15 -> -11.20238 | O15: =(('indice Carburant'!I10-'Indexation Client 2026'!$D$15)*'Indexation Client 2026'!$F$15)*'Indexation Client 2026'!$H$15 -> -11.20238 | P15: =(('indice Carburant'!J10-'Indexation Client 2026'!$D$15)*'Indexation Client 2026'!$F$15)*'Indexation Client 2026'!$H$15 -> -11.20238 | Q15: =(('indice Carburant'!K10-'Indexation Client 2026'!$D$15)*'Indexation Client 2026'!$F$15)*'Indexation Client 2026'!$H$15 -> -11.20238 | ... U15: =(('indice Carburant'!O10-'Indexation Client 2026'!$D$15)*'Indexation Client 2026'!$F$15)*'Indexation Client 2026'!$H$15 -> -11.20238
A16: CHRONOPOST CHILLY | B16: 40U88 (Gaz) - CDISCOUNT HNI | C16: CHCMZ | D16: 1.1431 | E16: PMM DIREM M-1 | F16: 0.28 | G16: Sur Km | H16: 54 | J16: =(('indice Carburant'!D10-'Indexation Client 2026'!$D$16)*'Indexation Client 2026'!$F$16)*'Indexation Client 2026'!$H$16 -> 2.952936 | K16: =(('indice Carburant'!E10-'Indexation Client 2026'!$D$16)*'Indexation Client 2026'!$F$16)*'Indexation Client 2026'!$H$16 -> 3.309768 | L16: =(('indice Carburant'!F10-'Indexation Client 2026'!$D$16)*'Indexation Client 2026'!$F$16)*'Indexation Client 2026'!$H$16 -> 3.789072 | M16: =(('indice Carburant'!G10-'Indexation Client 2026'!$D$16)*'Indexation Client 2026'!$F$16)*'Indexation Client 2026'!$H$16 -> 8.759016 | N16: =(('indice Carburant'!H10-'Indexation Client 2026'!$D$16)*'Indexation Client 2026'!$F$16)*'Indexation Client 2026'!$H$16 -> -17.283672 | O16: =(('indice Carburant'!I10-'Indexation Client 2026'!$D$16)*'Indexation Client 2026'!$F$16)*'Indexation Client 2026'!$H$16 -> -17.283672 | P16: =(('indice Carburant'!J10-'Indexation Client 2026'!$D$16)*'Indexation Client 2026'!$F$16)*'Indexation Client 2026'!$H$16 -> -17.283672 | Q16: =(('indice Carburant'!K10-'Indexation Client 2026'!$D$16)*'Indexation Client 2026'!$F$16)*'Indexation Client 2026'!$H$16 -> -17.283672 | ... U16: =(('indice Carburant'!O10-'Indexation Client 2026'!$D$16)*'Indexation Client 2026'!$F$16)*'Indexation Client 2026'!$H$16 -> -17.283672
A17: CHRONOPOST CHILLY | B17: 40U96 | C17: CHCMZ | D17: 1.1431 | E17: PMM DIREM M-1 | F17: 0.28 | G17: Sur Km | H17: 4 | J17: =(('indice Carburant'!D10-'Indexation Client 2026'!$D$17)*'Indexation Client 2026'!$F$17)*'Indexation Client 2026'!$H$17 -> 0.218736 | K17: =(('indice Carburant'!E10-'Indexation Client 2026'!$D$17)*'Indexation Client 2026'!$F$17)*'Indexation Client 2026'!$H$17 -> 0.245168 | L17: =(('indice Carburant'!F10-'Indexation Client 2026'!$D$17)*'Indexation Client 2026'!$F$17)*'Indexation Client 2026'!$H$17 -> 0.280672 | M17: =(('indice Carburant'!G10-'Indexation Client 2026'!$D$17)*'Indexation Client 2026'!$F$17)*'Indexation Client 2026'!$H$17 -> 0.648816 | N17: =(('indice Carburant'!H10-'Indexation Client 2026'!$D$17)*'Indexation Client 2026'!$F$17)*'Indexation Client 2026'!$H$17 -> -1.280272 | O17: =(('indice Carburant'!I10-'Indexation Client 2026'!$D$17)*'Indexation Client 2026'!$F$17)*'Indexation Client 2026'!$H$17 -> -1.280272 | P17: =(('indice Carburant'!J10-'Indexation Client 2026'!$D$17)*'Indexation Client 2026'!$F$17)*'Indexation Client 2026'!$H$17 -> -1.280272 | Q17: =(('indice Carburant'!K10-'Indexation Client 2026'!$D$17)*'Indexation Client 2026'!$F$17)*'Indexation Client 2026'!$H$17 -> -1.280272 | ... U17: =(('indice Carburant'!O10-'Indexation Client 2026'!$D$17)*'Indexation Client 2026'!$F$17)*'Indexation Client 2026'!$H$17 -> -1.280272
A18: CHRONOPOST HNI | B18: 23R03 | C18: CHAUL | D18: 1.6994 | E18: PMM DIREM M-1 | F18: 0.28 | G18: Sur Km | H18: 55.6 | J18: =(('indice Carburant'!D10-'Indexation Client 2026'!$D$18)*'Indexation Client 2026'!$F$18)*'Indexation Client 2026'!$H$18 -> -5.620048 | K18: =(('indice Carburant'!E10-'Indexation Client 2026'!$D$18)*'Indexation Client 2026'!$F$18)*'Indexation Client 2026'!$H$18 -> -5.2526432 | L18: =(('indice Carburant'!F10-'Indexation Client 2026'!$D$18)*'Indexation Client 2026'!$F$18)*'Indexation Client 2026'!$H$18 -> -4.7591376 | M18: =(('indice Carburant'!G10-'Indexation Client 2026'!$D$18)*'Indexation Client 2026'!$F$18)*'Indexation Client 2026'!$H$18 -> 0.358064 | N18: =(('indice Carburant'!H10-'Indexation Client 2026'!$D$18)*'Indexation Client 2026'!$F$18)*'Indexation Client 2026'!$H$18 -> -26.456259 | O18: =(('indice Carburant'!I10-'Indexation Client 2026'!$D$18)*'Indexation Client 2026'!$F$18)*'Indexation Client 2026'!$H$18 -> -26.456259 | P18: =(('indice Carburant'!J10-'Indexation Client 2026'!$D$18)*'Indexation Client 2026'!$F$18)*'Indexation Client 2026'!$H$18 -> -26.456259 | Q18: =(('indice Carburant'!K10-'Indexation Client 2026'!$D$18)*'Indexation Client 2026'!$F$18)*'Indexation Client 2026'!$H$18 -> -26.456259 | ... U18: =(('indice Carburant'!O10-'Indexation Client 2026'!$D$18)*'Indexation Client 2026'!$F$18)*'Indexation Client 2026'!$H$18 -> -26.456259
A19: CHRONOPOST HNI | B19: 23R68 | C19: CHAUL | D19: 1.6908 | E19: PMM DIREM M-1 | F19: 0.3 | G19: Sur Km | H19: 169.5 | J19: =(('indice Carburant'!D10-'Indexation Client 2026'!$D$19)*'Indexation Client 2026'!$F$19)*'Indexation Client 2026'!$H$19 -> -17.91954 | K19: =(('indice Carburant'!E10-'Indexation Client 2026'!$D$19)*'Indexation Client 2026'!$F$19)*'Indexation Client 2026'!$H$19 -> -16.71948 | L19: =(('indice Carburant'!F10-'Indexation Client 2026'!$D$19)*'Indexation Client 2026'!$F$19)*'Indexation Client 2026'!$H$19 -> -15.107535 | M19: =(('indice Carburant'!G10-'Indexation Client 2026'!$D$19)*'Indexation Client 2026'!$F$19)*'Indexation Client 2026'!$H$19 -> 1.60686 | N19: =(('indice Carburant'!H10-'Indexation Client 2026'!$D$19)*'Indexation Client 2026'!$F$19)*'Indexation Client 2026'!$H$19 -> -85.97718 | O19: =(('indice Carburant'!I10-'Indexation Client 2026'!$D$19)*'Indexation Client 2026'!$F$19)*'Indexation Client 2026'!$H$19 -> -85.97718 | P19: =(('indice Carburant'!J10-'Indexation Client 2026'!$D$19)*'Indexation Client 2026'!$F$19)*'Indexation Client 2026'!$H$19 -> -85.97718 | Q19: =(('indice Carburant'!K10-'Indexation Client 2026'!$D$19)*'Indexation Client 2026'!$F$19)*'Indexation Client 2026'!$H$19 -> -85.97718 | ... U19: =(('indice Carburant'!O10-'Indexation Client 2026'!$D$19)*'Indexation Client 2026'!$F$19)*'Indexation Client 2026'!$H$19 -> -85.97718
A20: CHRONOPOST HNI | B20: 23R68 | C20: CHAUL | D20: 1.6908 | E20: PMM DIREM M-1 | F20: 0.3 | G20: Sur Km | H20: 56.7 | J20: =(('indice Carburant'!D10-'Indexation Client 2026'!$D$20)*'Indexation Client 2026'!$F$20)*'Indexation Client 2026'!$H$20 -> -5.994324 | K20: =(('indice Carburant'!E10-'Indexation Client 2026'!$D$20)*'Indexation Client 2026'!$F$20)*'Indexation Client 2026'!$H$20 -> -5.592888 | L20: =(('indice Carburant'!F10-'Indexation Client 2026'!$D$20)*'Indexation Client 2026'!$F$20)*'Indexation Client 2026'!$H$20 -> -5.053671 | M20: =(('indice Carburant'!G10-'Indexation Client 2026'!$D$20)*'Indexation Client 2026'!$F$20)*'Indexation Client 2026'!$H$20 -> 0.537516 | N20: =(('indice Carburant'!H10-'Indexation Client 2026'!$D$20)*'Indexation Client 2026'!$F$20)*'Indexation Client 2026'!$H$20 -> -28.760508 | O20: =(('indice Carburant'!I10-'Indexation Client 2026'!$D$20)*'Indexation Client 2026'!$F$20)*'Indexation Client 2026'!$H$20 -> -28.760508 | P20: =(('indice Carburant'!J10-'Indexation Client 2026'!$D$20)*'Indexation Client 2026'!$F$20)*'Indexation Client 2026'!$H$20 -> -28.760508 | Q20: =(('indice Carburant'!K10-'Indexation Client 2026'!$D$20)*'Indexation Client 2026'!$F$20)*'Indexation Client 2026'!$H$20 -> -28.760508 | ... U20: =(('indice Carburant'!O10-'Indexation Client 2026'!$D$20)*'Indexation Client 2026'!$F$20)*'Indexation Client 2026'!$H$20 -> -28.760508
A21: CHRONOPOST HNI | B21: 23R67 | C21: CHAUL | D21: 1.1784 | E21: PMM DIREM M-1 | F21: 0.3 | G21: Sur Km | H21: 49.4 | J21: =(('indice Carburant'!D10-'Indexation Client 2026'!$D$21)*'Indexation Client 2026'!$F$21)*'Indexation Client 2026'!$H$21 -> 2.3712 | K21: =(('indice Carburant'!E10-'Indexation Client 2026'!$D$21)*'Indexation Client 2026'!$F$21)*'Indexation Client 2026'!$H$21 -> 2.720952 | L21: =(('indice Carburant'!F10-'Indexation Client 2026'!$D$21)*'Indexation Client 2026'!$F$21)*'Indexation Client 2026'!$H$21 -> 3.190746 | M21: =(('indice Carburant'!G10-'Indexation Client 2026'!$D$21)*'Indexation Client 2026'!$F$21)*'Indexation Client 2026'!$H$21 -> 8.06208 | N21: =(('indice Carburant'!H10-'Indexation Client 2026'!$D$21)*'Indexation Client 2026'!$F$21)*'Indexation Client 2026'!$H$21 -> -17.463888 | O21: =(('indice Carburant'!I10-'Indexation Client 2026'!$D$21)*'Indexation Client 2026'!$F$21)*'Indexation Client 2026'!$H$21 -> -17.463888 | P21: =(('indice Carburant'!J10-'Indexation Client 2026'!$D$21)*'Indexation Client 2026'!$F$21)*'Indexation Client 2026'!$H$21 -> -17.463888 | Q21: =(('indice Carburant'!K10-'Indexation Client 2026'!$D$21)*'Indexation Client 2026'!$F$21)*'Indexation Client 2026'!$H$21 -> -17.463888 | ... U21: =(('indice Carburant'!O10-'Indexation Client 2026'!$D$21)*'Indexation Client 2026'!$F$21)*'Indexation Client 2026'!$H$21 -> -17.463888
A22: CHRONOPOST RESEAU | B22: SWAP GAZ | C22: CHRON | D22: 0.94 | E22: CNR GNV M-1/100 | F22: 0.29 | G22: Sur Km | J22: =((('indice Carburant'!D13/100)-'Indexation Client 2026'!$D$22)*'Indexation Client 2026'!$F$22) -> 0.195547 | K22: =((('indice Carburant'!E13/100)-'Indexation Client 2026'!$D$22)*'Indexation Client 2026'!$F$22) -> 0.190269 | L22: =((('indice Carburant'!F13/100)-'Indexation Client 2026'!$D$22)*'Indexation Client 2026'!$F$22) -> 0.242672 | M22: =((('indice Carburant'!G13/100)-'Indexation Client 2026'!$D$22)*'Indexation Client 2026'!$F$22) -> -0.2726 | N22: =((('indice Carburant'!H13/100)-'Indexation Client 2026'!$D$22)*'Indexation Client 2026'!$F$22) -> -0.2726 | O22: =((('indice Carburant'!I13/100)-'Indexation Client 2026'!$D$22)*'Indexation Client 2026'!$F$22) -> -0.2726 | P22: =((('indice Carburant'!J13/100)-'Indexation Client 2026'!$D$22)*'Indexation Client 2026'!$F$22) -> -0.2726 | Q22: =((('indice Carburant'!K13/100)-'Indexation Client 2026'!$D$22)*'Indexation Client 2026'!$F$22) -> -0.2726 | ... U22: =((('indice Carburant'!O13/100)-'Indexation Client 2026'!$D$22)*'Indexation Client 2026'!$F$22) -> -0.2726
A23: CHRONOPOST RESEAU | B23: SWAP GO | C23: CHRON | D23: 0.8318 | E23: PMM DIREM M-1 | F23: 0.29 | G23: Sur Km | J23: =(('indice Carburant'!D10-'Indexation Client 2026'!$D$23)*'Indexation Client 2026'!$F$23) -> 0.146914 | K23: =(('indice Carburant'!E10-'Indexation Client 2026'!$D$23)*'Indexation Client 2026'!$F$23) -> 0.153758 | L23: =(('indice Carburant'!F10-'Indexation Client 2026'!$D$23)*'Indexation Client 2026'!$F$23) -> 0.162951 | M23: =(('indice Carburant'!G10-'Indexation Client 2026'!$D$23)*'Indexation Client 2026'!$F$23) -> 0.258274 | N23: =(('indice Carburant'!H10-'Indexation Client 2026'!$D$23)*'Indexation Client 2026'!$F$23) -> -0.241222 | O23: =(('indice Carburant'!I10-'Indexation Client 2026'!$D$23)*'Indexation Client 2026'!$F$23) -> -0.241222 | P23: =(('indice Carburant'!J10-'Indexation Client 2026'!$D$23)*'Indexation Client 2026'!$F$23) -> -0.241222 | Q23: =(('indice Carburant'!K10-'Indexation Client 2026'!$D$23)*'Indexation Client 2026'!$F$23) -> -0.241222 | ... U23: =(('indice Carburant'!O10-'Indexation Client 2026'!$D$23)*'Indexation Client 2026'!$F$23) -> -0.241222
A24: CHRONOPOST RESEAU | B24: SPL GAZ | C24: CHRON | D24: 0.94 | E24: CNR GNV M-1/100 | F24: 0.26 | G24: Sur Km | J24: =((('indice Carburant'!D13/100)-'Indexation Client 2026'!$D$24)*'Indexation Client 2026'!$F$24) -> 0.175318 | K24: =((('indice Carburant'!E13/100)-'Indexation Client 2026'!$D$24)*'Indexation Client 2026'!$F$24) -> 0.170586 | L24: =((('indice Carburant'!F13/100)-'Indexation Client 2026'!$D$24)*'Indexation Client 2026'!$F$24) -> 0.217568 | M24: =((('indice Carburant'!G13/100)-'Indexation Client 2026'!$D$24)*'Indexation Client 2026'!$F$24) -> -0.2444 | N24: =((('indice Carburant'!H13/100)-'Indexation Client 2026'!$D$24)*'Indexation Client 2026'!$F$24) -> -0.2444 | O24: =((('indice Carburant'!I13/100)-'Indexation Client 2026'!$D$24)*'Indexation Client 2026'!$F$24) -> -0.2444 | P24: =((('indice Carburant'!J13/100)-'Indexation Client 2026'!$D$24)*'Indexation Client 2026'!$F$24) -> -0.2444 | Q24: =((('indice Carburant'!K13/100)-'Indexation Client 2026'!$D$24)*'Indexation Client 2026'!$F$24) -> -0.2444 | ... U24: =((('indice Carburant'!O13/100)-'Indexation Client 2026'!$D$24)*'Indexation Client 2026'!$F$24) -> -0.2444
A25: CHRONOPOST RESEAU | B25: VL GO | C25: CHRON | D25: 0.8318 | E25: PMM DIREM M-1 | F25: 0.15 | G25: Sur Km | J25: =(('indice Carburant'!D10-'Indexation Client 2026'!$D$25)*'Indexation Client 2026'!$F$25) -> 0.07599 | K25: =(('indice Carburant'!E10-'Indexation Client 2026'!$D$25)*'Indexation Client 2026'!$F$25) -> 0.07953 | L25: =(('indice Carburant'!F10-'Indexation Client 2026'!$D$25)*'Indexation Client 2026'!$F$25) -> 0.084285 | M25: =(('indice Carburant'!G10-'Indexation Client 2026'!$D$25)*'Indexation Client 2026'!$F$25) -> 0.13359 | N25: =(('indice Carburant'!H10-'Indexation Client 2026'!$D$25)*'Indexation Client 2026'!$F$25) -> -0.12477 | O25: =(('indice Carburant'!I10-'Indexation Client 2026'!$D$25)*'Indexation Client 2026'!$F$25) -> -0.12477 | P25: =(('indice Carburant'!J10-'Indexation Client 2026'!$D$25)*'Indexation Client 2026'!$F$25) -> -0.12477 | Q25: =(('indice Carburant'!K10-'Indexation Client 2026'!$D$25)*'Indexation Client 2026'!$F$25) -> -0.12477 | ... U25: =(('indice Carburant'!O10-'Indexation Client 2026'!$D$25)*'Indexation Client 2026'!$F$25) -> -0.12477
A26: CHRONOPOST RESEAU | B26: SPL GO | C26: CHRON | D26: 0.8318 | E26: PMM DIREM M-1 | F26: 0.26 | G26: Sur Km | J26: =(('indice Carburant'!D10-'Indexation Client 2026'!$D$26)*'Indexation Client 2026'!$F$26) -> 0.131716 | K26: =(('indice Carburant'!E10-'Indexation Client 2026'!$D$26)*'Indexation Client 2026'!$F$26) -> 0.137852 | L26: =(('indice Carburant'!F10-'Indexation Client 2026'!$D$26)*'Indexation Client 2026'!$F$26) -> 0.146094 | M26: =(('indice Carburant'!G10-'Indexation Client 2026'!$D$26)*'Indexation Client 2026'!$F$26) -> 0.231556 | N26: =(('indice Carburant'!H10-'Indexation Client 2026'!$D$26)*'Indexation Client 2026'!$F$26) -> -0.216268 | O26: =(('indice Carburant'!I10-'Indexation Client 2026'!$D$26)*'Indexation Client 2026'!$F$26) -> -0.216268 | P26: =(('indice Carburant'!J10-'Indexation Client 2026'!$D$26)*'Indexation Client 2026'!$F$26) -> -0.216268 | Q26: =(('indice Carburant'!K10-'Indexation Client 2026'!$D$26)*'Indexation Client 2026'!$F$26) -> -0.216268 | ... U26: =(('indice Carburant'!O10-'Indexation Client 2026'!$D$26)*'Indexation Client 2026'!$F$26) -> -0.216268
A27: CHRONOPOST ROISSY | B27: LRCDGORY01 | C27: CHROI | D27: 1.3384 | E27: PMM DIREM M-1 | F27: 0.26 | G27: Sur Km | H27: 44 | J27: =(('indice Carburant'!D10-'Indexation Client 2026'!$D$27)*'Indexation Client 2026'!$F$27)*'Indexation Client 2026'!$H$27 -> 0 | K27: =(('indice Carburant'!E10-'Indexation Client 2026'!$D$27)*'Indexation Client 2026'!$F$27)*'Indexation Client 2026'!$H$27 -> 0.269984 | L27: =(('indice Carburant'!F10-'Indexation Client 2026'!$D$27)*'Indexation Client 2026'!$F$27)*'Indexation Client 2026'!$H$27 -> 0.632632 | M27: =(('indice Carburant'!G10-'Indexation Client 2026'!$D$27)*'Indexation Client 2026'!$F$27)*'Indexation Client 2026'!$H$27 -> 4.39296 | N27: =(('indice Carburant'!H10-'Indexation Client 2026'!$D$27)*'Indexation Client 2026'!$F$27)*'Indexation Client 2026'!$H$27 -> -15.311296 | O27: =(('indice Carburant'!I10-'Indexation Client 2026'!$D$27)*'Indexation Client 2026'!$F$27)*'Indexation Client 2026'!$H$27 -> -15.311296 | P27: =(('indice Carburant'!J10-'Indexation Client 2026'!$D$27)*'Indexation Client 2026'!$F$27)*'Indexation Client 2026'!$H$27 -> -15.311296 | Q27: =(('indice Carburant'!K10-'Indexation Client 2026'!$D$27)*'Indexation Client 2026'!$F$27)*'Indexation Client 2026'!$H$27 -> -15.311296 | ... U27: =(('indice Carburant'!O10-'Indexation Client 2026'!$D$27)*'Indexation Client 2026'!$F$27)*'Indexation Client 2026'!$H$27 -> -15.311296
A28: CHRONOPOST ROISSY | B28: LRCDGORY02 | C28: CHROI | D28: 1.3384 | E28: PMM DIREM M-1 | F28: 0.26 | G28: Sur Km | H28: 44 | J28: =(('indice Carburant'!D10-'Indexation Client 2026'!$D$28)*'Indexation Client 2026'!$F$28)*'Indexation Client 2026'!$H$28 -> 0 | K28: =(('indice Carburant'!E10-'Indexation Client 2026'!$D$28)*'Indexation Client 2026'!$F$28)*'Indexation Client 2026'!$H$28 -> 0.269984 | L28: =(('indice Carburant'!F10-'Indexation Client 2026'!$D$28)*'Indexation Client 2026'!$F$28)*'Indexation Client 2026'!$H$28 -> 0.632632 | M28: =(('indice Carburant'!G10-'Indexation Client 2026'!$D$28)*'Indexation Client 2026'!$F$28)*'Indexation Client 2026'!$H$28 -> 4.39296 | N28: =(('indice Carburant'!H10-'Indexation Client 2026'!$D$28)*'Indexation Client 2026'!$F$28)*'Indexation Client 2026'!$H$28 -> -15.311296 | O28: =(('indice Carburant'!I10-'Indexation Client 2026'!$D$28)*'Indexation Client 2026'!$F$28)*'Indexation Client 2026'!$H$28 -> -15.311296 | P28: =(('indice Carburant'!J10-'Indexation Client 2026'!$D$28)*'Indexation Client 2026'!$F$28)*'Indexation Client 2026'!$H$28 -> -15.311296 | Q28: =(('indice Carburant'!K10-'Indexation Client 2026'!$D$28)*'Indexation Client 2026'!$F$28)*'Indexation Client 2026'!$H$28 -> -15.311296 | ... U28: =(('indice Carburant'!O10-'Indexation Client 2026'!$D$28)*'Indexation Client 2026'!$F$28)*'Indexation Client 2026'!$H$28 -> -15.311296
A29: COLISSIMO | B29: CTRT 202213366 | C29: CSPN | D29: PARC
A30: COLISSIMO | B30: GEN202212891SLOT04 | C30: CSPN | D30: 180.42 | E30: CNR GO PRO M-1 | F30: 0.1398 | G30: Variation TK | H30: 3.4 | J30: =((('indice Carburant'!D6/'Indexation Client 2026'!$D$30)-1)*'Indexation Client 2026'!$F$30)*'Indexation Client 2026'!$H$30+$H$30 -> 3.402898 | K30: =((('indice Carburant'!E6/'Indexation Client 2026'!$D$30)-1)*'Indexation Client 2026'!$F$30)*'Indexation Client 2026'!$H$30+$H$30 -> 3.4190739 | L30: =((('indice Carburant'!F6/'Indexation Client 2026'!$D$30)-1)*'Indexation Client 2026'!$F$30)*'Indexation Client 2026'!$H$30+$H$30 -> 3.434038 | M30: =((('indice Carburant'!G6/'Indexation Client 2026'!$D$30)-1)*'Indexation Client 2026'!$F$30)*'Indexation Client 2026'!$H$30+$H$30 -> 3.5782516 | N30: =((('indice Carburant'!H6/'Indexation Client 2026'!$D$30)-1)*'Indexation Client 2026'!$F$30)*'Indexation Client 2026'!$H$30+$H$30 -> 2.92468 | O30: =((('indice Carburant'!I6/'Indexation Client 2026'!$D$30)-1)*'Indexation Client 2026'!$F$30)*'Indexation Client 2026'!$H$30+$H$30 -> 2.92468 | P30: =((('indice Carburant'!J6/'Indexation Client 2026'!$D$30)-1)*'Indexation Client 2026'!$F$30)*'Indexation Client 2026'!$H$30+$H$30 -> 2.92468 | Q30: =((('indice Carburant'!K6/'Indexation Client 2026'!$D$30)-1)*'Indexation Client 2026'!$F$30)*'Indexation Client 2026'!$H$30+$H$30 -> 2.92468 | ... U30: =((('indice Carburant'!O6/'Indexation Client 2026'!$D$30)-1)*'Indexation Client 2026'!$F$30)*'Indexation Client 2026'!$H$30+$H$30 -> 2.92468
A31: COLISSIMO | B31: IDFLTHCGENC9595 | C31: CSPN | D31: 273.99 | E31: CNR GO PRO M-1 | F31: 0.2137 | G31: Variation TK | H31: 2.5021 | J31: =((('indice Carburant'!D6/'Indexation Client 2026'!$D$31)-1)*'Indexation Client 2026'!$F$31)*'Indexation Client 2026'!$H$31+$H$31 -> 2.3216423 | K31: =((('indice Carburant'!E6/'Indexation Client 2026'!$D$31)-1)*'Indexation Client 2026'!$F$31)*'Indexation Client 2026'!$H$31+$H$31 -> 2.3336247 | L31: =((('indice Carburant'!F6/'Indexation Client 2026'!$D$31)-1)*'Indexation Client 2026'!$F$31)*'Indexation Client 2026'!$H$31+$H$31 -> 2.3447094 | M31: =((('indice Carburant'!G6/'Indexation Client 2026'!$D$31)-1)*'Indexation Client 2026'!$F$31)*'Indexation Client 2026'!$H$31+$H$31 -> 2.4515359 | N31: =((('indice Carburant'!H6/'Indexation Client 2026'!$D$31)-1)*'Indexation Client 2026'!$F$31)*'Indexation Client 2026'!$H$31+$H$31 -> 1.9674012 | O31: =((('indice Carburant'!I6/'Indexation Client 2026'!$D$31)-1)*'Indexation Client 2026'!$F$31)*'Indexation Client 2026'!$H$31+$H$31 -> 1.9674012 | P31: =((('indice Carburant'!J6/'Indexation Client 2026'!$D$31)-1)*'Indexation Client 2026'!$F$31)*'Indexation Client 2026'!$H$31+$H$31 -> 1.9674012 | Q31: =((('indice Carburant'!K6/'Indexation Client 2026'!$D$31)-1)*'Indexation Client 2026'!$F$31)*'Indexation Client 2026'!$H$31+$H$31 -> 1.9674012 | ... U31: =((('indice Carburant'!O6/'Indexation Client 2026'!$D$31)-1)*'Indexation Client 2026'!$F$31)*'Indexation Client 2026'!$H$31+$H$31 -> 1.9674012
A32: COLISSIMO | B32: IDFN-DOT-00A-CM | C32: CSPN | D32: 182.15 | E32: CNR GNV M-1 | F32: 0.1684 | G32: Variation TK | H32: 2.413 | J32: =((('indice Carburant'!D13/'Indexation Client 2026'!$D$32)-1)*'Indexation Client 2026'!$F$32)*'Indexation Client 2026'!$H$32+$H$32 -> 2.3667768 | K32: =((('indice Carburant'!E13/'Indexation Client 2026'!$D$32)-1)*'Indexation Client 2026'!$F$32)*'Indexation Client 2026'!$H$32+$H$32 -> 2.3627167 | L32: =((('indice Carburant'!F13/'Indexation Client 2026'!$D$32)-1)*'Indexation Client 2026'!$F$32)*'Indexation Client 2026'!$H$32+$H$32 -> 2.4030281 | M32: =((('indice Carburant'!G13/'Indexation Client 2026'!$D$32)-1)*'Indexation Client 2026'!$F$32)*'Indexation Client 2026'!$H$32+$H$32 -> 2.0066508 | N32: =((('indice Carburant'!H13/'Indexation Client 2026'!$D$32)-1)*'Indexation Client 2026'!$F$32)*'Indexation Client 2026'!$H$32+$H$32 -> 2.0066508 | O32: =((('indice Carburant'!I13/'Indexation Client 2026'!$D$32)-1)*'Indexation Client 2026'!$F$32)*'Indexation Client 2026'!$H$32+$H$32 -> 2.0066508 | P32: =((('indice Carburant'!J13/'Indexation Client 2026'!$D$32)-1)*'Indexation Client 2026'!$F$32)*'Indexation Client 2026'!$H$32+$H$32 -> 2.0066508 | Q32: =((('indice Carburant'!K13/'Indexation Client 2026'!$D$32)-1)*'Indexation Client 2026'!$F$32)*'Indexation Client 2026'!$H$32+$H$32 -> 2.0066508 | ... U32: =((('indice Carburant'!O13/'Indexation Client 2026'!$D$32)-1)*'Indexation Client 2026'!$F$32)*'Indexation Client 2026'!$H$32+$H$32 -> 2.0066508
A33: COLISSIMO | B33: IDFN-LTH-004-CM | C33: CSPN | D33: 182.15 | E33: CNR GNV M-1 | F33: 0.0983 | G33: Variation TK | H33: 4.135 | J33: =((('indice Carburant'!D13/'Indexation Client 2026'!$D$33)-1)*'Indexation Client 2026'!$F$33)*'Indexation Client 2026'!$H$33+$H$33 -> 4.088763 | K33: =((('indice Carburant'!E13/'Indexation Client 2026'!$D$33)-1)*'Indexation Client 2026'!$F$33)*'Indexation Client 2026'!$H$33+$H$33 -> 4.0847016 | L33: =((('indice Carburant'!F13/'Indexation Client 2026'!$D$33)-1)*'Indexation Client 2026'!$F$33)*'Indexation Client 2026'!$H$33+$H$33 -> 4.1250251 | M33: =((('indice Carburant'!G13/'Indexation Client 2026'!$D$33)-1)*'Indexation Client 2026'!$F$33)*'Indexation Client 2026'!$H$33+$H$33 -> 3.7285295 | N33: =((('indice Carburant'!H13/'Indexation Client 2026'!$D$33)-1)*'Indexation Client 2026'!$F$33)*'Indexation Client 2026'!$H$33+$H$33 -> 3.7285295 | O33: =((('indice Carburant'!I13/'Indexation Client 2026'!$D$33)-1)*'Indexation Client 2026'!$F$33)*'Indexation Client 2026'!$H$33+$H$33 -> 3.7285295 | P33: =((('indice Carburant'!J13/'Indexation Client 2026'!$D$33)-1)*'Indexation Client 2026'!$F$33)*'Indexation Client 2026'!$H$33+$H$33 -> 3.7285295 | Q33: =((('indice Carburant'!K13/'Indexation Client 2026'!$D$33)-1)*'Indexation Client 2026'!$F$33)*'Indexation Client 2026'!$H$33+$H$33 -> 3.7285295 | ... U33: =((('indice Carburant'!O13/'Indexation Client 2026'!$D$33)-1)*'Indexation Client 2026'!$F$33)*'Indexation Client 2026'!$H$33+$H$33 -> 3.7285295
A34: COLISSIMO | B34: IDFN-LTH-007-CM | C34: CSPN | D34: 182.15 | E34: CNR GNV M-1 | F34: 0.169 | G34: Variation TK | H34: 2.2548 | J34: =((('indice Carburant'!D13/'Indexation Client 2026'!$D$34)-1)*'Indexation Client 2026'!$F$34)*'Indexation Client 2026'!$H$34+$H$34 -> 2.2114534 | K34: =((('indice Carburant'!E13/'Indexation Client 2026'!$D$34)-1)*'Indexation Client 2026'!$F$34)*'Indexation Client 2026'!$H$34+$H$34 -> 2.2076459 | L34: =((('indice Carburant'!F13/'Indexation Client 2026'!$D$34)-1)*'Indexation Client 2026'!$F$34)*'Indexation Client 2026'!$H$34+$H$34 -> 2.2454487 | M34: =((('indice Carburant'!G13/'Indexation Client 2026'!$D$34)-1)*'Indexation Client 2026'!$F$34)*'Indexation Client 2026'!$H$34+$H$34 -> 1.8737388 | N34: =((('indice Carburant'!H13/'Indexation Client 2026'!$D$34)-1)*'Indexation Client 2026'!$F$34)*'Indexation Client 2026'!$H$34+$H$34 -> 1.8737388 | O34: =((('indice Carburant'!I13/'Indexation Client 2026'!$D$34)-1)*'Indexation Client 2026'!$F$34)*'Indexation Client 2026'!$H$34+$H$34 -> 1.8737388 | P34: =((('indice Carburant'!J13/'Indexation Client 2026'!$D$34)-1)*'Indexation Client 2026'!$F$34)*'Indexation Client 2026'!$H$34+$H$34 -> 1.8737388 | Q34: =((('indice Carburant'!K13/'Indexation Client 2026'!$D$34)-1)*'Indexation Client 2026'!$F$34)*'Indexation Client 2026'!$H$34+$H$34 -> 1.8737388 | ... U34: =((('indice Carburant'!O13/'Indexation Client 2026'!$D$34)-1)*'Indexation Client 2026'!$F$34)*'Indexation Client 2026'!$H$34+$H$34 -> 1.8737388
A35: COLISSIMO | B35: IDFN-LTH-009-S33 | C35: CSPN | D35: 182.15 | E35: CNR GNV M-1 | F35: 0.1942 | G35: Variation TK | H35: 2.0315 | J35: =((('indice Carburant'!D13/'Indexation Client 2026'!$D$35)-1)*'Indexation Client 2026'!$F$35)*'Indexation Client 2026'!$H$35+$H$35 -> 1.9866227 | K35: =((('indice Carburant'!E13/'Indexation Client 2026'!$D$35)-1)*'Indexation Client 2026'!$F$35)*'Indexation Client 2026'!$H$35+$H$35 -> 1.9826808 | L35: =((('indice Carburant'!F13/'Indexation Client 2026'!$D$35)-1)*'Indexation Client 2026'!$F$35)*'Indexation Client 2026'!$H$35+$H$35 -> 2.0218185 | M35: =((('indice Carburant'!G13/'Indexation Client 2026'!$D$35)-1)*'Indexation Client 2026'!$F$35)*'Indexation Client 2026'!$H$35+$H$35 -> 1.6369827 | N35: =((('indice Carburant'!H13/'Indexation Client 2026'!$D$35)-1)*'Indexation Client 2026'!$F$35)*'Indexation Client 2026'!$H$35+$H$35 -> 1.6369827 | O35: =((('indice Carburant'!I13/'Indexation Client 2026'!$D$35)-1)*'Indexation Client 2026'!$F$35)*'Indexation Client 2026'!$H$35+$H$35 -> 1.6369827 | P35: =((('indice Carburant'!J13/'Indexation Client 2026'!$D$35)-1)*'Indexation Client 2026'!$F$35)*'Indexation Client 2026'!$H$35+$H$35 -> 1.6369827 | Q35: =((('indice Carburant'!K13/'Indexation Client 2026'!$D$35)-1)*'Indexation Client 2026'!$F$35)*'Indexation Client 2026'!$H$35+$H$35 -> 1.6369827 | ... U35: =((('indice Carburant'!O13/'Indexation Client 2026'!$D$35)-1)*'Indexation Client 2026'!$F$35)*'Indexation Client 2026'!$H$35+$H$35 -> 1.6369827
A36: COLISSIMO | B36: IDFN-LTH-011-CM | C36: CSPN | D36: 182.15 | E36: CNR GNV M-1 | F36: 0.238 | G36: Variation TK | H36: 1.7074 | J36: =((('indice Carburant'!D13/'Indexation Client 2026'!$D$36)-1)*'Indexation Client 2026'!$F$36)*'Indexation Client 2026'!$H$36+$H$36 -> 1.6611754 | K36: =((('indice Carburant'!E13/'Indexation Client 2026'!$D$36)-1)*'Indexation Client 2026'!$F$36)*'Indexation Client 2026'!$H$36+$H$36 -> 1.6571152 | L36: =((('indice Carburant'!F13/'Indexation Client 2026'!$D$36)-1)*'Indexation Client 2026'!$F$36)*'Indexation Client 2026'!$H$36+$H$36 -> 1.6974278 | M36: =((('indice Carburant'!G13/'Indexation Client 2026'!$D$36)-1)*'Indexation Client 2026'!$F$36)*'Indexation Client 2026'!$H$36+$H$36 -> 1.3010388 | N36: =((('indice Carburant'!H13/'Indexation Client 2026'!$D$36)-1)*'Indexation Client 2026'!$F$36)*'Indexation Client 2026'!$H$36+$H$36 -> 1.3010388 | O36: =((('indice Carburant'!I13/'Indexation Client 2026'!$D$36)-1)*'Indexation Client 2026'!$F$36)*'Indexation Client 2026'!$H$36+$H$36 -> 1.3010388 | P36: =((('indice Carburant'!J13/'Indexation Client 2026'!$D$36)-1)*'Indexation Client 2026'!$F$36)*'Indexation Client 2026'!$H$36+$H$36 -> 1.3010388 | Q36: =((('indice Carburant'!K13/'Indexation Client 2026'!$D$36)-1)*'Indexation Client 2026'!$F$36)*'Indexation Client 2026'!$H$36+$H$36 -> 1.3010388 | ... U36: =((('indice Carburant'!O13/'Indexation Client 2026'!$D$36)-1)*'Indexation Client 2026'!$F$36)*'Indexation Client 2026'!$H$36+$H$36 -> 1.3010388
A37: COLISSIMO | B37: IDFN-LTH-014-CM | C37: CSPN | D37: 182.15 | E37: CNR GNV M-1 | F37: 0.2003 | G37: Variation TK | H37: 2.47 | J37: =((('indice Carburant'!D13/'Indexation Client 2026'!$D$37)-1)*'Indexation Client 2026'!$F$37)*'Indexation Client 2026'!$H$37+$H$37 -> 2.413722 | K37: =((('indice Carburant'!E13/'Indexation Client 2026'!$D$37)-1)*'Indexation Client 2026'!$F$37)*'Indexation Client 2026'!$H$37+$H$37 -> 2.4087787 | L37: =((('indice Carburant'!F13/'Indexation Client 2026'!$D$37)-1)*'Indexation Client 2026'!$F$37)*'Indexation Client 2026'!$H$37+$H$37 -> 2.4578589 | M37: =((('indice Carburant'!G13/'Indexation Client 2026'!$D$37)-1)*'Indexation Client 2026'!$F$37)*'Indexation Client 2026'!$H$37+$H$37 -> 1.975259 | N37: =((('indice Carburant'!H13/'Indexation Client 2026'!$D$37)-1)*'Indexation Client 2026'!$F$37)*'Indexation Client 2026'!$H$37+$H$37 -> 1.975259 | O37: =((('indice Carburant'!I13/'Indexation Client 2026'!$D$37)-1)*'Indexation Client 2026'!$F$37)*'Indexation Client 2026'!$H$37+$H$37 -> 1.975259 | P37: =((('indice Carburant'!J13/'Indexation Client 2026'!$D$37)-1)*'Indexation Client 2026'!$F$37)*'Indexation Client 2026'!$H$37+$H$37 -> 1.975259 | Q37: =((('indice Carburant'!K13/'Indexation Client 2026'!$D$37)-1)*'Indexation Client 2026'!$F$37)*'Indexation Client 2026'!$H$37+$H$37 -> 1.975259 | ... U37: =((('indice Carburant'!O13/'Indexation Client 2026'!$D$37)-1)*'Indexation Client 2026'!$F$37)*'Indexation Client 2026'!$H$37+$H$37 -> 1.975259
A38: COLISSIMO | B38: IDFN-LTH-016-S33 | C38: CSPN | D38: 153.94 | E38: CNR GNV M-1 | F38: 0.1376 | G38: Variation TK | H38: 4.4842 | J38: =((('indice Carburant'!D13/'Indexation Client 2026'!$D$38)-1)*'Indexation Client 2026'!$F$38)*'Indexation Client 2026'!$H$38+$H$38 -> 4.5142216 | K38: =((('indice Carburant'!E13/'Indexation Client 2026'!$D$38)-1)*'Indexation Client 2026'!$F$38)*'Indexation Client 2026'!$H$38+$H$38 -> 4.5069266 | L38: =((('indice Carburant'!F13/'Indexation Client 2026'!$D$38)-1)*'Indexation Client 2026'!$F$38)*'Indexation Client 2026'!$H$38+$H$38 -> 4.5793552 | M38: =((('indice Carburant'!G13/'Indexation Client 2026'!$D$38)-1)*'Indexation Client 2026'!$F$38)*'Indexation Client 2026'!$H$38+$H$38 -> 3.8671741 | N38: =((('indice Carburant'!H13/'Indexation Client 2026'!$D$38)-1)*'Indexation Client 2026'!$F$38)*'Indexation Client 2026'!$H$38+$H$38 -> 3.8671741 | O38: =((('indice Carburant'!I13/'Indexation Client 2026'!$D$38)-1)*'Indexation Client 2026'!$F$38)*'Indexation Client 2026'!$H$38+$H$38 -> 3.8671741 | P38: =((('indice Carburant'!J13/'Indexation Client 2026'!$D$38)-1)*'Indexation Client 2026'!$F$38)*'Indexation Client 2026'!$H$38+$H$38 -> 3.8671741 | Q38: =((('indice Carburant'!K13/'Indexation Client 2026'!$D$38)-1)*'Indexation Client 2026'!$F$38)*'Indexation Client 2026'!$H$38+$H$38 -> 3.8671741 | ... U38: =((('indice Carburant'!O13/'Indexation Client 2026'!$D$38)-1)*'Indexation Client 2026'!$F$38)*'Indexation Client 2026'!$H$38+$H$38 -> 3.8671741
A39: COLISSIMO | B39: IDFN-LTH-017-S33 | C39: CSPN | D39: 153.94 | E39: CNR GNV M-1 | F39: 0.1564 | G39: Variation TK | H39: 2.4922 | J39: =((('indice Carburant'!D13/'Indexation Client 2026'!$D$39)-1)*'Indexation Client 2026'!$F$39)*'Indexation Client 2026'!$H$39+$H$39 -> 2.5111649 | K39: =((('indice Carburant'!E13/'Indexation Client 2026'!$D$39)-1)*'Indexation Client 2026'!$F$39)*'Indexation Client 2026'!$H$39+$H$39 -> 2.5065566 | L39: =((('indice Carburant'!F13/'Indexation Client 2026'!$D$39)-1)*'Indexation Client 2026'!$F$39)*'Indexation Client 2026'!$H$39+$H$39 -> 2.5523103 | M39: =((('indice Carburant'!G13/'Indexation Client 2026'!$D$39)-1)*'Indexation Client 2026'!$F$39)*'Indexation Client 2026'!$H$39+$H$39 -> 2.1024199 | N39: =((('indice Carburant'!H13/'Indexation Client 2026'!$D$39)-1)*'Indexation Client 2026'!$F$39)*'Indexation Client 2026'!$H$39+$H$39 -> 2.1024199 | O39: =((('indice Carburant'!I13/'Indexation Client 2026'!$D$39)-1)*'Indexation Client 2026'!$F$39)*'Indexation Client 2026'!$H$39+$H$39 -> 2.1024199 | P39: =((('indice Carburant'!J13/'Indexation Client 2026'!$D$39)-1)*'Indexation Client 2026'!$F$39)*'Indexation Client 2026'!$H$39+$H$39 -> 2.1024199 | Q39: =((('indice Carburant'!K13/'Indexation Client 2026'!$D$39)-1)*'Indexation Client 2026'!$F$39)*'Indexation Client 2026'!$H$39+$H$39 -> 2.1024199 | ... U39: =((('indice Carburant'!O13/'Indexation Client 2026'!$D$39)-1)*'Indexation Client 2026'!$F$39)*'Indexation Client 2026'!$H$39+$H$39 -> 2.1024199
A40: COLISSIMO | B40: IDFN-LTH-081-CM | C40: CSPN | D40: 153.94 | E40: CNR GNV M-1 | F40: 0.1557 | G40: Variation TK | H40: 2.3944 | J40: =((('indice Carburant'!D13/'Indexation Client 2026'!$D$40)-1)*'Indexation Client 2026'!$F$40)*'Indexation Client 2026'!$H$40+$H$40 -> 2.4125391 | K40: =((('indice Carburant'!E13/'Indexation Client 2026'!$D$40)-1)*'Indexation Client 2026'!$F$40)*'Indexation Client 2026'!$H$40+$H$40 -> 2.4081315 | L40: =((('indice Carburant'!F13/'Indexation Client 2026'!$D$40)-1)*'Indexation Client 2026'!$F$40)*'Indexation Client 2026'!$H$40+$H$40 -> 2.4518929 | M40: =((('indice Carburant'!G13/'Indexation Client 2026'!$D$40)-1)*'Indexation Client 2026'!$F$40)*'Indexation Client 2026'!$H$40+$H$40 -> 2.0215919 | N40: =((('indice Carburant'!H13/'Indexation Client 2026'!$D$40)-1)*'Indexation Client 2026'!$F$40)*'Indexation Client 2026'!$H$40+$H$40 -> 2.0215919 | O40: =((('indice Carburant'!I13/'Indexation Client 2026'!$D$40)-1)*'Indexation Client 2026'!$F$40)*'Indexation Client 2026'!$H$40+$H$40 -> 2.0215919 | P40: =((('indice Carburant'!J13/'Indexation Client 2026'!$D$40)-1)*'Indexation Client 2026'!$F$40)*'Indexation Client 2026'!$H$40+$H$40 -> 2.0215919 | Q40: =((('indice Carburant'!K13/'Indexation Client 2026'!$D$40)-1)*'Indexation Client 2026'!$F$40)*'Indexation Client 2026'!$H$40+$H$40 -> 2.0215919 | ... U40: =((('indice Carburant'!O13/'Indexation Client 2026'!$D$40)-1)*'Indexation Client 2026'!$F$40)*'Indexation Client 2026'!$H$40+$H$40 -> 2.0215919
A41: COLISSIMO | B41: IDFS-MJD-88-CM | C41: CSPN | D41: 153.94 | E41: CNR GNV M-1 | F41: 0.2347 | G41: Variation TK | H41: 1.5889 | J41: =((('indice Carburant'!D13/'Indexation Client 2026'!$D$41)-1)*'Indexation Client 2026'!$F$41)*'Indexation Client 2026'!$H$41+$H$41 -> 1.6070443 | K41: =((('indice Carburant'!E13/'Indexation Client 2026'!$D$41)-1)*'Indexation Client 2026'!$F$41)*'Indexation Client 2026'!$H$41+$H$41 -> 1.6026354 | L41: =((('indice Carburant'!F13/'Indexation Client 2026'!$D$41)-1)*'Indexation Client 2026'!$F$41)*'Indexation Client 2026'!$H$41+$H$41 -> 1.6464094 | M41: =((('indice Carburant'!G13/'Indexation Client 2026'!$D$41)-1)*'Indexation Client 2026'!$F$41)*'Indexation Client 2026'!$H$41+$H$41 -> 1.2159852 | N41: =((('indice Carburant'!H13/'Indexation Client 2026'!$D$41)-1)*'Indexation Client 2026'!$F$41)*'Indexation Client 2026'!$H$41+$H$41 -> 1.2159852 | O41: =((('indice Carburant'!I13/'Indexation Client 2026'!$D$41)-1)*'Indexation Client 2026'!$F$41)*'Indexation Client 2026'!$H$41+$H$41 -> 1.2159852 | P41: =((('indice Carburant'!J13/'Indexation Client 2026'!$D$41)-1)*'Indexation Client 2026'!$F$41)*'Indexation Client 2026'!$H$41+$H$41 -> 1.2159852 | Q41: =((('indice Carburant'!K13/'Indexation Client 2026'!$D$41)-1)*'Indexation Client 2026'!$F$41)*'Indexation Client 2026'!$H$41+$H$41 -> 1.2159852 | ... U41: =((('indice Carburant'!O13/'Indexation Client 2026'!$D$41)-1)*'Indexation Client 2026'!$F$41)*'Indexation Client 2026'!$H$41+$H$41 -> 1.2159852
A42: COLISSIMO | B42: IDFS-MOI-136-S33 | C42: CSPN | D42: 153.94 | E42: CNR GNV M-1 | F42: 0.2898 | G42: Variation TK | H42: 1.5169 | J42: =((('indice Carburant'!D13/'Indexation Client 2026'!$D$42)-1)*'Indexation Client 2026'!$F$42)*'Indexation Client 2026'!$H$42+$H$42 -> 1.5382888 | K42: =((('indice Carburant'!E13/'Indexation Client 2026'!$D$42)-1)*'Indexation Client 2026'!$F$42)*'Indexation Client 2026'!$H$42+$H$42 -> 1.5330915 | L42: =((('indice Carburant'!F13/'Indexation Client 2026'!$D$42)-1)*'Indexation Client 2026'!$F$42)*'Indexation Client 2026'!$H$42+$H$42 -> 1.584693 | M42: =((('indice Carburant'!G13/'Indexation Client 2026'!$D$42)-1)*'Indexation Client 2026'!$F$42)*'Indexation Client 2026'!$H$42+$H$42 -> 1.0773024 | N42: =((('indice Carburant'!H13/'Indexation Client 2026'!$D$42)-1)*'Indexation Client 2026'!$F$42)*'Indexation Client 2026'!$H$42+$H$42 -> 1.0773024 | O42: =((('indice Carburant'!I13/'Indexation Client 2026'!$D$42)-1)*'Indexation Client 2026'!$F$42)*'Indexation Client 2026'!$H$42+$H$42 -> 1.0773024 | P42: =((('indice Carburant'!J13/'Indexation Client 2026'!$D$42)-1)*'Indexation Client 2026'!$F$42)*'Indexation Client 2026'!$H$42+$H$42 -> 1.0773024 | Q42: =((('indice Carburant'!K13/'Indexation Client 2026'!$D$42)-1)*'Indexation Client 2026'!$F$42)*'Indexation Client 2026'!$H$42+$H$42 -> 1.0773024 | ... U42: =((('indice Carburant'!O13/'Indexation Client 2026'!$D$42)-1)*'Indexation Client 2026'!$F$42)*'Indexation Client 2026'!$H$42+$H$42 -> 1.0773024
A43: COLISSIMO | B43: IZPFC69SLM090 | C43: CSPN | D43: Astreinte
A44: COLISSIMO | B44: LII043C9267CR | C44: CSPN | D44: 180.42 | E44: CNR GO PRO M-1 | F44: 0.3713 | G44: Variation TK | H44: 1.0369 | J44: =((('indice Carburant'!D6/'Indexation Client 2026'!$D$44)-1)*'Indexation Client 2026'!$F$44)*'Indexation Client 2026'!$H$44+$H$44 -> 1.0392473 | K44: =((('indice Carburant'!E6/'Indexation Client 2026'!$D$44)-1)*'Indexation Client 2026'!$F$44)*'Indexation Client 2026'!$H$44+$H$44 -> 1.0523495 | L44: =((('indice Carburant'!F6/'Indexation Client 2026'!$D$44)-1)*'Indexation Client 2026'!$F$44)*'Indexation Client 2026'!$H$44+$H$44 -> 1.0644702 | M44: =((('indice Carburant'!G6/'Indexation Client 2026'!$D$44)-1)*'Indexation Client 2026'!$F$44)*'Indexation Client 2026'!$H$44+$H$44 -> 1.1812807 | N44: =((('indice Carburant'!H6/'Indexation Client 2026'!$D$44)-1)*'Indexation Client 2026'!$F$44)*'Indexation Client 2026'!$H$44+$H$44 -> 0.65189903 | O44: =((('indice Carburant'!I6/'Indexation Client 2026'!$D$44)-1)*'Indexation Client 2026'!$F$44)*'Indexation Client 2026'!$H$44+$H$44 -> 0.65189903 | P44: =((('indice Carburant'!J6/'Indexation Client 2026'!$D$44)-1)*'Indexation Client 2026'!$F$44)*'Indexation Client 2026'!$H$44+$H$44 -> 0.65189903 | Q44: =((('indice Carburant'!K6/'Indexation Client 2026'!$D$44)-1)*'Indexation Client 2026'!$F$44)*'Indexation Client 2026'!$H$44+$H$44 -> 0.65189903 | ... U44: =((('indice Carburant'!O6/'Indexation Client 2026'!$D$44)-1)*'Indexation Client 2026'!$F$44)*'Indexation Client 2026'!$H$44+$H$44 -> 0.65189903
A45: COLISSIMO | B45: LIN128C9562AR | C45: CSPN | D45: 167.18 | E45: CNR GNV M-1 | F45: 0.2523 | G45: Variation TK | H45: 1.51 | J45: =((('indice Carburant'!D13/'Indexation Client 2026'!$D$45)-1)*'Indexation Client 2026'!$F$45)*'Indexation Client 2026'!$H$45+$H$45 -> 1.4968968 | K45: =((('indice Carburant'!E13/'Indexation Client 2026'!$D$45)-1)*'Indexation Client 2026'!$F$45)*'Indexation Client 2026'!$H$45+$H$45 -> 1.4927493 | L45: =((('indice Carburant'!F13/'Indexation Client 2026'!$D$45)-1)*'Indexation Client 2026'!$F$45)*'Indexation Client 2026'!$H$45+$H$45 -> 1.5339276 | M45: =((('indice Carburant'!G13/'Indexation Client 2026'!$D$45)-1)*'Indexation Client 2026'!$F$45)*'Indexation Client 2026'!$H$45+$H$45 -> 1.129027 | N45: =((('indice Carburant'!H13/'Indexation Client 2026'!$D$45)-1)*'Indexation Client 2026'!$F$45)*'Indexation Client 2026'!$H$45+$H$45 -> 1.129027 | O45: =((('indice Carburant'!I13/'Indexation Client 2026'!$D$45)-1)*'Indexation Client 2026'!$F$45)*'Indexation Client 2026'!$H$45+$H$45 -> 1.129027 | P45: =((('indice Carburant'!J13/'Indexation Client 2026'!$D$45)-1)*'Indexation Client 2026'!$F$45)*'Indexation Client 2026'!$H$45+$H$45 -> 1.129027 | Q45: =((('indice Carburant'!K13/'Indexation Client 2026'!$D$45)-1)*'Indexation Client 2026'!$F$45)*'Indexation Client 2026'!$H$45+$H$45 -> 1.129027 | ... U45: =((('indice Carburant'!O13/'Indexation Client 2026'!$D$45)-1)*'Indexation Client 2026'!$F$45)*'Indexation Client 2026'!$H$45+$H$45 -> 1.129027
A46: COLISSIMO | B46: LIN198S7776AS | C46: CSPN | D46: 195.67 | E46: CNR GO PRO M-1 | F46: 0.3099 | G46: Variation TK | H46: 1.4662 | J46: =((('indice Carburant'!D6/'Indexation Client 2026'!$D$46)-1)*'Indexation Client 2026'!$F$46)*'Indexation Client 2026'!$H$46+$H$46 -> 1.4333416 | K46: =((('indice Carburant'!E6/'Indexation Client 2026'!$D$46)-1)*'Indexation Client 2026'!$F$46)*'Indexation Client 2026'!$H$46+$H$46 -> 1.4475996 | L46: =((('indice Carburant'!F6/'Indexation Client 2026'!$D$46)-1)*'Indexation Client 2026'!$F$46)*'Indexation Client 2026'!$H$46+$H$46 -> 1.4607894 | M46: =((('indice Carburant'!G6/'Indexation Client 2026'!$D$46)-1)*'Indexation Client 2026'!$F$46)*'Indexation Client 2026'!$H$46+$H$46 -> 1.587904 | N46: =((('indice Carburant'!H6/'Indexation Client 2026'!$D$46)-1)*'Indexation Client 2026'!$F$46)*'Indexation Client 2026'!$H$46+$H$46 -> 1.0118246 | O46: =((('indice Carburant'!I6/'Indexation Client 2026'!$D$46)-1)*'Indexation Client 2026'!$F$46)*'Indexation Client 2026'!$H$46+$H$46 -> 1.0118246 | P46: =((('indice Carburant'!J6/'Indexation Client 2026'!$D$46)-1)*'Indexation Client 2026'!$F$46)*'Indexation Client 2026'!$H$46+$H$46 -> 1.0118246 | Q46: =((('indice Carburant'!K6/'Indexation Client 2026'!$D$46)-1)*'Indexation Client 2026'!$F$46)*'Indexation Client 2026'!$H$46+$H$46 -> 1.0118246 | ... U46: =((('indice Carburant'!O6/'Indexation Client 2026'!$D$46)-1)*'Indexation Client 2026'!$F$46)*'Indexation Client 2026'!$H$46+$H$46 -> 1.0118246
A47: COLISSIMO | B47: LIN177C6238CR | C47: CSPN | D47: 204.89 | E47: CNR GO PRO M-1 | F47: 0.336 | G47: Variation TK | H47: 1.3298 | J47: =((('indice Carburant'!D6/'Indexation Client 2026'!$D$47)-1)*'Indexation Client 2026'!$F$47)*'Indexation Client 2026'!$H$47+$H$47 -> 1.278836 | K47: =((('indice Carburant'!E6/'Indexation Client 2026'!$D$47)-1)*'Indexation Client 2026'!$F$47)*'Indexation Client 2026'!$H$47+$H$47 -> 1.2922258 | L47: =((('indice Carburant'!F6/'Indexation Client 2026'!$D$47)-1)*'Indexation Client 2026'!$F$47)*'Indexation Client 2026'!$H$47+$H$47 -> 1.3046124 | M47: =((('indice Carburant'!G6/'Indexation Client 2026'!$D$47)-1)*'Indexation Client 2026'!$F$47)*'Indexation Client 2026'!$H$47+$H$47 -> 1.4239864 | N47: =((('indice Carburant'!H6/'Indexation Client 2026'!$D$47)-1)*'Indexation Client 2026'!$F$47)*'Indexation Client 2026'!$H$47+$H$47 -> 0.8829872 | O47: =((('indice Carburant'!I6/'Indexation Client 2026'!$D$47)-1)*'Indexation Client 2026'!$F$47)*'Indexation Client 2026'!$H$47+$H$47 -> 0.8829872 | P47: =((('indice Carburant'!J6/'Indexation Client 2026'!$D$47)-1)*'Indexation Client 2026'!$F$47)*'Indexation Client 2026'!$H$47+$H$47 -> 0.8829872 | Q47: =((('indice Carburant'!K6/'Indexation Client 2026'!$D$47)-1)*'Indexation Client 2026'!$F$47)*'Indexation Client 2026'!$H$47+$H$47 -> 0.8829872 | ... U47: =((('indice Carburant'!O6/'Indexation Client 2026'!$D$47)-1)*'Indexation Client 2026'!$F$47)*'Indexation Client 2026'!$H$47+$H$47 -> 0.8829872
A48: COLISSIMO | B48: LIO087C9541AR | C48: CSPN | D48: 167.18 | E48: CNR GNV M-1 | F48: 0.2711 | G48: Variation TK | H48: 1.4055 | J48: =((('indice Carburant'!D13/'Indexation Client 2026'!$D$48)-1)*'Indexation Client 2026'!$F$48)*'Indexation Client 2026'!$H$48+$H$48 -> 1.3923948 | K48: =((('indice Carburant'!E13/'Indexation Client 2026'!$D$48)-1)*'Indexation Client 2026'!$F$48)*'Indexation Client 2026'!$H$48+$H$48 -> 1.3882467 | L48: =((('indice Carburant'!F13/'Indexation Client 2026'!$D$48)-1)*'Indexation Client 2026'!$F$48)*'Indexation Client 2026'!$H$48+$H$48 -> 1.4294312 | M48: =((('indice Carburant'!G13/'Indexation Client 2026'!$D$48)-1)*'Indexation Client 2026'!$F$48)*'Indexation Client 2026'!$H$48+$H$48 -> 1.0244689 | N48: =((('indice Carburant'!H13/'Indexation Client 2026'!$D$48)-1)*'Indexation Client 2026'!$F$48)*'Indexation Client 2026'!$H$48+$H$48 -> 1.0244689 | O48: =((('indice Carburant'!I13/'Indexation Client 2026'!$D$48)-1)*'Indexation Client 2026'!$F$48)*'Indexation Client 2026'!$H$48+$H$48 -> 1.0244689 | P48: =((('indice Carburant'!J13/'Indexation Client 2026'!$D$48)-1)*'Indexation Client 2026'!$F$48)*'Indexation Client 2026'!$H$48+$H$48 -> 1.0244689 | Q48: =((('indice Carburant'!K13/'Indexation Client 2026'!$D$48)-1)*'Indexation Client 2026'!$F$48)*'Indexation Client 2026'!$H$48+$H$48 -> 1.0244689 | ... U48: =((('indice Carburant'!O13/'Indexation Client 2026'!$D$48)-1)*'Indexation Client 2026'!$F$48)*'Indexation Client 2026'!$H$48+$H$48 -> 1.0244689
A49: COLISSIMO | B49: LIO088C9541AR | C49: CSPN | D49: 167.18 | E49: CNR GNV M-1 | F49: 0.2634 | G49: Variation TK | H49: 1.4467 | J49: =((('indice Carburant'!D13/'Indexation Client 2026'!$D$49)-1)*'Indexation Client 2026'!$F$49)*'Indexation Client 2026'!$H$49+$H$49 -> 1.4335938 | K49: =((('indice Carburant'!E13/'Indexation Client 2026'!$D$49)-1)*'Indexation Client 2026'!$F$49)*'Indexation Client 2026'!$H$49+$H$49 -> 1.4294454 | L49: =((('indice Carburant'!F13/'Indexation Client 2026'!$D$49)-1)*'Indexation Client 2026'!$F$49)*'Indexation Client 2026'!$H$49+$H$49 -> 1.4706331 | M49: =((('indice Carburant'!G13/'Indexation Client 2026'!$D$49)-1)*'Indexation Client 2026'!$F$49)*'Indexation Client 2026'!$H$49+$H$49 -> 1.0656392 | N49: =((('indice Carburant'!H13/'Indexation Client 2026'!$D$49)-1)*'Indexation Client 2026'!$F$49)*'Indexation Client 2026'!$H$49+$H$49 -> 1.0656392 | O49: =((('indice Carburant'!I13/'Indexation Client 2026'!$D$49)-1)*'Indexation Client 2026'!$F$49)*'Indexation Client 2026'!$H$49+$H$49 -> 1.0656392 | P49: =((('indice Carburant'!J13/'Indexation Client 2026'!$D$49)-1)*'Indexation Client 2026'!$F$49)*'Indexation Client 2026'!$H$49+$H$49 -> 1.0656392 | Q49: =((('indice Carburant'!K13/'Indexation Client 2026'!$D$49)-1)*'Indexation Client 2026'!$F$49)*'Indexation Client 2026'!$H$49+$H$49 -> 1.0656392 | ... U49: =((('indice Carburant'!O13/'Indexation Client 2026'!$D$49)-1)*'Indexation Client 2026'!$F$49)*'Indexation Client 2026'!$H$49+$H$49 -> 1.0656392
A50: COLISSIMO | B50: LIO099C7741AR | C50: CSPN | D50: 142.37 | E50: CNR GNV M-1 | F50: 0.2398 | G50: Variation TK | H50: 1.5548 | J50: =((('indice Carburant'!D13/'Indexation Client 2026'!$D$50)-1)*'Indexation Client 2026'!$F$50)*'Indexation Client 2026'!$H$50+$H$50 -> 1.6047147 | K50: =((('indice Carburant'!E13/'Indexation Client 2026'!$D$50)-1)*'Indexation Client 2026'!$F$50)*'Indexation Client 2026'!$H$50+$H$50 -> 1.5999484 | L50: =((('indice Carburant'!F13/'Indexation Client 2026'!$D$50)-1)*'Indexation Client 2026'!$F$50)*'Indexation Client 2026'!$H$50+$H$50 -> 1.6472704 | M50: =((('indice Carburant'!G13/'Indexation Client 2026'!$D$50)-1)*'Indexation Client 2026'!$F$50)*'Indexation Client 2026'!$H$50+$H$50 -> 1.181959 | N50: =((('indice Carburant'!H13/'Indexation Client 2026'!$D$50)-1)*'Indexation Client 2026'!$F$50)*'Indexation Client 2026'!$H$50+$H$50 -> 1.181959 | O50: =((('indice Carburant'!I13/'Indexation Client 2026'!$D$50)-1)*'Indexation Client 2026'!$F$50)*'Indexation Client 2026'!$H$50+$H$50 -> 1.181959 | P50: =((('indice Carburant'!J13/'Indexation Client 2026'!$D$50)-1)*'Indexation Client 2026'!$F$50)*'Indexation Client 2026'!$H$50+$H$50 -> 1.181959 | Q50: =((('indice Carburant'!K13/'Indexation Client 2026'!$D$50)-1)*'Indexation Client 2026'!$F$50)*'Indexation Client 2026'!$H$50+$H$50 -> 1.181959 | ... U50: =((('indice Carburant'!O13/'Indexation Client 2026'!$D$50)-1)*'Indexation Client 2026'!$F$50)*'Indexation Client 2026'!$H$50+$H$50 -> 1.181959
A51: COLISSIMO | B51: LIS124C7769CR | C51: CSPN | D51: 204.89 | E51: CNR GO PRO M-1 | F51: 0.3201 | G51: Variation TK | H51: 1.3957 | J51: =((('indice Carburant'!D6/'Indexation Client 2026'!$D$51)-1)*'Indexation Client 2026'!$F$51)*'Indexation Client 2026'!$H$51+$H$51 -> 1.3447416 | K51: =((('indice Carburant'!E6/'Indexation Client 2026'!$D$51)-1)*'Indexation Client 2026'!$F$51)*'Indexation Client 2026'!$H$51+$H$51 -> 1.3581299 | L51: =((('indice Carburant'!F6/'Indexation Client 2026'!$D$51)-1)*'Indexation Client 2026'!$F$51)*'Indexation Client 2026'!$H$51+$H$51 -> 1.3705152 | M51: =((('indice Carburant'!G6/'Indexation Client 2026'!$D$51)-1)*'Indexation Client 2026'!$F$51)*'Indexation Client 2026'!$H$51+$H$51 -> 1.489876 | N51: =((('indice Carburant'!H6/'Indexation Client 2026'!$D$51)-1)*'Indexation Client 2026'!$F$51)*'Indexation Client 2026'!$H$51+$H$51 -> 0.94893643 | O51: =((('indice Carburant'!I6/'Indexation Client 2026'!$D$51)-1)*'Indexation Client 2026'!$F$51)*'Indexation Client 2026'!$H$51+$H$51 -> 0.94893643 | P51: =((('indice Carburant'!J6/'Indexation Client 2026'!$D$51)-1)*'Indexation Client 2026'!$F$51)*'Indexation Client 2026'!$H$51+$H$51 -> 0.94893643 | Q51: =((('indice Carburant'!K6/'Indexation Client 2026'!$D$51)-1)*'Indexation Client 2026'!$F$51)*'Indexation Client 2026'!$H$51+$H$51 -> 0.94893643 | ... U51: =((('indice Carburant'!O6/'Indexation Client 2026'!$D$51)-1)*'Indexation Client 2026'!$F$51)*'Indexation Client 2026'!$H$51+$H$51 -> 0.94893643
A52: COLISSIMO | B52: LOT 08 - Porteur de Cour NANTERRE | C52: CSPN | D52: 180.81 | E52: CNR GO PRO M-1 | F52: 0.14 | G52: Variation Tx Horaire | H52: 38.65 | J52: =((('indice Carburant'!D6/'Indexation Client 2026'!$D$52)-1)*'Indexation Client 2026'!$F$52)*'Indexation Client 2026'!$H$52+$H$52 -> 38.671248 | K52: =((('indice Carburant'!E6/'Indexation Client 2026'!$D$52)-1)*'Indexation Client 2026'!$F$52)*'Indexation Client 2026'!$H$52+$H$52 -> 38.854996 | L52: =((('indice Carburant'!F6/'Indexation Client 2026'!$D$52)-1)*'Indexation Client 2026'!$F$52)*'Indexation Client 2026'!$H$52+$H$52 -> 39.024978 | M52: =((('indice Carburant'!G6/'Indexation Client 2026'!$D$52)-1)*'Indexation Client 2026'!$F$52)*'Indexation Client 2026'!$H$52+$H$52 -> 40.663152 | N52: =((('indice Carburant'!H6/'Indexation Client 2026'!$D$52)-1)*'Indexation Client 2026'!$F$52)*'Indexation Client 2026'!$H$52+$H$52 -> 33.239 | O52: =((('indice Carburant'!I6/'Indexation Client 2026'!$D$52)-1)*'Indexation Client 2026'!$F$52)*'Indexation Client 2026'!$H$52+$H$52 -> 33.239 | P52: =((('indice Carburant'!J6/'Indexation Client 2026'!$D$52)-1)*'Indexation Client 2026'!$F$52)*'Indexation Client 2026'!$H$52+$H$52 -> 33.239 | Q52: =((('indice Carburant'!K6/'Indexation Client 2026'!$D$52)-1)*'Indexation Client 2026'!$F$52)*'Indexation Client 2026'!$H$52+$H$52 -> 33.239 | ... U52: =((('indice Carburant'!O6/'Indexation Client 2026'!$D$52)-1)*'Indexation Client 2026'!$F$52)*'Indexation Client 2026'!$H$52+$H$52 -> 33.239
A53: COLISSIMO | B53: IDFN-LTH-017-CM | C53: CSPN | D53: 153.94 | E53: CNR GNV M-1 | F53: 0.2021 | G53: Variation TK | H53: 2.3748 | J53: =((('indice Carburant'!D13/'Indexation Client 2026'!$D$53)-1)*'Indexation Client 2026'!$F$53)*'Indexation Client 2026'!$H$53+$H$53 -> 2.398152 | K53: =((('indice Carburant'!E13/'Indexation Client 2026'!$D$53)-1)*'Indexation Client 2026'!$F$53)*'Indexation Client 2026'!$H$53+$H$53 -> 2.3924777 | L53: =((('indice Carburant'!F13/'Indexation Client 2026'!$D$53)-1)*'Indexation Client 2026'!$F$53)*'Indexation Client 2026'!$H$53+$H$53 -> 2.4488155 | M53: =((('indice Carburant'!G13/'Indexation Client 2026'!$D$53)-1)*'Indexation Client 2026'!$F$53)*'Indexation Client 2026'!$H$53+$H$53 -> 1.8948529 | N53: =((('indice Carburant'!H13/'Indexation Client 2026'!$D$53)-1)*'Indexation Client 2026'!$F$53)*'Indexation Client 2026'!$H$53+$H$53 -> 1.8948529 | O53: =((('indice Carburant'!I13/'Indexation Client 2026'!$D$53)-1)*'Indexation Client 2026'!$F$53)*'Indexation Client 2026'!$H$53+$H$53 -> 1.8948529 | P53: =((('indice Carburant'!J13/'Indexation Client 2026'!$D$53)-1)*'Indexation Client 2026'!$F$53)*'Indexation Client 2026'!$H$53+$H$53 -> 1.8948529 | Q53: =((('indice Carburant'!K13/'Indexation Client 2026'!$D$53)-1)*'Indexation Client 2026'!$F$53)*'Indexation Client 2026'!$H$53+$H$53 -> 1.8948529 | ... U53: =((('indice Carburant'!O13/'Indexation Client 2026'!$D$53)-1)*'Indexation Client 2026'!$F$53)*'Indexation Client 2026'!$H$53+$H$53 -> 1.8948529
A54: COLISSIMO | B54: IDFS-MOI-307-CM | C54: CSPN | D54: 179.54 | E54: CNR GNV M-1 | F54: 0.2098 | G54: Variation TK | H54: 1.3559 | J54: =((('indice Carburant'!D13/'Indexation Client 2026'!$D$54)-1)*'Indexation Client 2026'!$F$54)*'Indexation Client 2026'!$H$53+$H$54 -> 1.3056438 | K54: =((('indice Carburant'!E13/'Indexation Client 2026'!$D$54)-1)*'Indexation Client 2026'!$F$54)*'Indexation Client 2026'!$H$53+$H$54 -> 1.3005932 | L54: =((('indice Carburant'!F13/'Indexation Client 2026'!$D$54)-1)*'Indexation Client 2026'!$F$54)*'Indexation Client 2026'!$H$53+$H$54 -> 1.3507384 | M54: =((('indice Carburant'!G13/'Indexation Client 2026'!$D$54)-1)*'Indexation Client 2026'!$F$54)*'Indexation Client 2026'!$H$53+$H$54 -> 0.85766696 | N54: =((('indice Carburant'!H13/'Indexation Client 2026'!$D$54)-1)*'Indexation Client 2026'!$F$54)*'Indexation Client 2026'!$H$53+$H$54 -> 0.85766696 | O54: =((('indice Carburant'!I13/'Indexation Client 2026'!$D$54)-1)*'Indexation Client 2026'!$F$54)*'Indexation Client 2026'!$H$53+$H$54 -> 0.85766696 | P54: =((('indice Carburant'!J13/'Indexation Client 2026'!$D$54)-1)*'Indexation Client 2026'!$F$54)*'Indexation Client 2026'!$H$53+$H$54 -> 0.85766696 | Q54: =((('indice Carburant'!K13/'Indexation Client 2026'!$D$54)-1)*'Indexation Client 2026'!$F$54)*'Indexation Client 2026'!$H$53+$H$54 -> 0.85766696 | ... U54: =((('indice Carburant'!O13/'Indexation Client 2026'!$D$54)-1)*'Indexation Client 2026'!$F$54)*'Indexation Client 2026'!$H$53+$H$54 -> 0.85766696
A55: COLISSIMO | B55: IDFN-LTH-115-CM | C55: CSPN | D55: 179.54 | E55: CNR GNV M-1 | F55: 0.1869 | G55: Variation TK | H55: 2.3948 | J55: =((('indice Carburant'!D13/'Indexation Client 2026'!$D$55)-1)*'Indexation Client 2026'!$F$55)*'Indexation Client 2026'!$H$53+$H$55 -> 2.3500293 | K55: =((('indice Carburant'!E13/'Indexation Client 2026'!$D$55)-1)*'Indexation Client 2026'!$F$55)*'Indexation Client 2026'!$H$53+$H$55 -> 2.34553 | L55: =((('indice Carburant'!F13/'Indexation Client 2026'!$D$55)-1)*'Indexation Client 2026'!$F$55)*'Indexation Client 2026'!$H$53+$H$55 -> 2.3902018 | M55: =((('indice Carburant'!G13/'Indexation Client 2026'!$D$55)-1)*'Indexation Client 2026'!$F$55)*'Indexation Client 2026'!$H$53+$H$55 -> 1.9509499 | N55: =((('indice Carburant'!H13/'Indexation Client 2026'!$D$55)-1)*'Indexation Client 2026'!$F$55)*'Indexation Client 2026'!$H$53+$H$55 -> 1.9509499 | O55: =((('indice Carburant'!I13/'Indexation Client 2026'!$D$55)-1)*'Indexation Client 2026'!$F$55)*'Indexation Client 2026'!$H$53+$H$55 -> 1.9509499 | P55: =((('indice Carburant'!J13/'Indexation Client 2026'!$D$55)-1)*'Indexation Client 2026'!$F$55)*'Indexation Client 2026'!$H$53+$H$55 -> 1.9509499 | Q55: =((('indice Carburant'!K13/'Indexation Client 2026'!$D$55)-1)*'Indexation Client 2026'!$F$55)*'Indexation Client 2026'!$H$53+$H$55 -> 1.9509499 | ... U55: =((('indice Carburant'!O13/'Indexation Client 2026'!$D$55)-1)*'Indexation Client 2026'!$F$55)*'Indexation Client 2026'!$H$53+$H$55 -> 1.9509499
A56: COLISSIMO | B56: LIO124S7741AR | C56: CSPN | D56: 195.67 | E56: CNR GO PRO M-1 | F56: 0.3078 | G56: Variation TK | H56: 1.1937 | J56: =((('indice Carburant'!D6/'Indexation Client 2026'!$D$56)-1)*'Indexation Client 2026'!$F$56)*'Indexation Client 2026'!$H$56+$H$56 -> 1.1671297 | K56: =((('indice Carburant'!E6/'Indexation Client 2026'!$D$56)-1)*'Indexation Client 2026'!$F$56)*'Indexation Client 2026'!$H$56+$H$56 -> 1.1786592 | L56: =((('indice Carburant'!F6/'Indexation Client 2026'!$D$56)-1)*'Indexation Client 2026'!$F$56)*'Indexation Client 2026'!$H$56+$H$56 -> 1.1893248 | M56: =((('indice Carburant'!G6/'Indexation Client 2026'!$D$56)-1)*'Indexation Client 2026'!$F$56)*'Indexation Client 2026'!$H$56+$H$56 -> 1.2921133 | N56: =((('indice Carburant'!H6/'Indexation Client 2026'!$D$56)-1)*'Indexation Client 2026'!$F$56)*'Indexation Client 2026'!$H$56+$H$56 -> 0.82627914 | O56: =((('indice Carburant'!I6/'Indexation Client 2026'!$D$56)-1)*'Indexation Client 2026'!$F$56)*'Indexation Client 2026'!$H$56+$H$56 -> 0.82627914 | P56: =((('indice Carburant'!J6/'Indexation Client 2026'!$D$56)-1)*'Indexation Client 2026'!$F$56)*'Indexation Client 2026'!$H$56+$H$56 -> 0.82627914 | Q56: =((('indice Carburant'!K6/'Indexation Client 2026'!$D$56)-1)*'Indexation Client 2026'!$F$56)*'Indexation Client 2026'!$H$56+$H$56 -> 0.82627914 | ... U56: =((('indice Carburant'!O6/'Indexation Client 2026'!$D$56)-1)*'Indexation Client 2026'!$F$56)*'Indexation Client 2026'!$H$56+$H$56 -> 0.82627914
A57: COLISSIMO | B57: IDFS-MJD-207-CM | C57: CSPN | D57: 192.18 | E57: CNR GNV M-1 | F57: 0.2445 | G57: Variation TK | H57: 1.8084 | J57: =((('indice Carburant'!D13/'Indexation Client 2026'!$D$57)-1)*'Indexation Client 2026'!$F$57)*'Indexation Client 2026'!$H$57+$H$57 -> 1.7376526 | K57: =((('indice Carburant'!E13/'Indexation Client 2026'!$D$57)-1)*'Indexation Client 2026'!$F$57)*'Indexation Client 2026'!$H$57+$H$57 -> 1.7334653 | L57: =((('indice Carburant'!F13/'Indexation Client 2026'!$D$57)-1)*'Indexation Client 2026'!$F$57)*'Indexation Client 2026'!$H$57+$H$57 -> 1.7750395 | M57: =((('indice Carburant'!G13/'Indexation Client 2026'!$D$57)-1)*'Indexation Client 2026'!$F$57)*'Indexation Client 2026'!$H$57+$H$57 -> 1.3662462 | N57: =((('indice Carburant'!H13/'Indexation Client 2026'!$D$57)-1)*'Indexation Client 2026'!$F$57)*'Indexation Client 2026'!$H$57+$H$57 -> 1.3662462 | O57: =((('indice Carburant'!I13/'Indexation Client 2026'!$D$57)-1)*'Indexation Client 2026'!$F$57)*'Indexation Client 2026'!$H$57+$H$57 -> 1.3662462 | P57: =((('indice Carburant'!J13/'Indexation Client 2026'!$D$57)-1)*'Indexation Client 2026'!$F$57)*'Indexation Client 2026'!$H$57+$H$57 -> 1.3662462 | Q57: =((('indice Carburant'!K13/'Indexation Client 2026'!$D$57)-1)*'Indexation Client 2026'!$F$57)*'Indexation Client 2026'!$H$57+$H$57 -> 1.3662462 | ... U57: =((('indice Carburant'!O13/'Indexation Client 2026'!$D$57)-1)*'Indexation Client 2026'!$F$57)*'Indexation Client 2026'!$H$57+$H$57 -> 1.3662462
A58: COLISSIMO | B58: IDFS-MJD-104-S33 | C58: CSPN | D58: 170.34 | E58: CNR GNV M-1 | F58: 0.2501 | G58: Variation TK | H58: 1.6503 | J58: =((('indice Carburant'!D13/'Indexation Client 2026'!$D$58)-1)*'Indexation Client 2026'!$F$58)*'Indexation Client 2026'!$H$58+$H$58 -> 1.6287107 | K58: =((('indice Carburant'!E13/'Indexation Client 2026'!$D$58)-1)*'Indexation Client 2026'!$F$58)*'Indexation Client 2026'!$H$58+$H$58 -> 1.6243008 | L58: =((('indice Carburant'!F13/'Indexation Client 2026'!$D$58)-1)*'Indexation Client 2026'!$F$58)*'Indexation Client 2026'!$H$58+$H$58 -> 1.6680851 | M58: =((('indice Carburant'!G13/'Indexation Client 2026'!$D$58)-1)*'Indexation Client 2026'!$F$58)*'Indexation Client 2026'!$H$58+$H$58 -> 1.23756 | N58: =((('indice Carburant'!H13/'Indexation Client 2026'!$D$58)-1)*'Indexation Client 2026'!$F$58)*'Indexation Client 2026'!$H$58+$H$58 -> 1.23756 | O58: =((('indice Carburant'!I13/'Indexation Client 2026'!$D$58)-1)*'Indexation Client 2026'!$F$58)*'Indexation Client 2026'!$H$58+$H$58 -> 1.23756 | P58: =((('indice Carburant'!J13/'Indexation Client 2026'!$D$58)-1)*'Indexation Client 2026'!$F$58)*'Indexation Client 2026'!$H$58+$H$58 -> 1.23756 | Q58: =((('indice Carburant'!K13/'Indexation Client 2026'!$D$58)-1)*'Indexation Client 2026'!$F$58)*'Indexation Client 2026'!$H$58+$H$58 -> 1.23756 | ... U58: =((('indice Carburant'!O13/'Indexation Client 2026'!$D$58)-1)*'Indexation Client 2026'!$F$58)*'Indexation Client 2026'!$H$58+$H$58 -> 1.23756
A59: COLISSIMO | B59: IDFS-MJD-106-S33 | C59: CSPN | D59: 170.34 | E59: CNR GNV M-1 | F59: 0.181 | G59: Variation TK | H59: 2.164 | J59: =((('indice Carburant'!D13/'Indexation Client 2026'!$D$59)-1)*'Indexation Client 2026'!$F$59)*'Indexation Client 2026'!$H$59+$H$59 -> 2.1435121 | K59: =((('indice Carburant'!E13/'Indexation Client 2026'!$D$59)-1)*'Indexation Client 2026'!$F$59)*'Indexation Client 2026'!$H$59+$H$59 -> 2.1393272 | L59: =((('indice Carburant'!F13/'Indexation Client 2026'!$D$59)-1)*'Indexation Client 2026'!$F$59)*'Indexation Client 2026'!$H$59+$H$59 -> 2.1808778 | M59: =((('indice Carburant'!G13/'Indexation Client 2026'!$D$59)-1)*'Indexation Client 2026'!$F$59)*'Indexation Client 2026'!$H$59+$H$59 -> 1.772316 | N59: =((('indice Carburant'!H13/'Indexation Client 2026'!$D$59)-1)*'Indexation Client 2026'!$F$59)*'Indexation Client 2026'!$H$59+$H$59 -> 1.772316 | O59: =((('indice Carburant'!I13/'Indexation Client 2026'!$D$59)-1)*'Indexation Client 2026'!$F$59)*'Indexation Client 2026'!$H$59+$H$59 -> 1.772316 | P59: =((('indice Carburant'!J13/'Indexation Client 2026'!$D$59)-1)*'Indexation Client 2026'!$F$59)*'Indexation Client 2026'!$H$59+$H$59 -> 1.772316 | Q59: =((('indice Carburant'!K13/'Indexation Client 2026'!$D$59)-1)*'Indexation Client 2026'!$F$59)*'Indexation Client 2026'!$H$59+$H$59 -> 1.772316 | ... U59: =((('indice Carburant'!O13/'Indexation Client 2026'!$D$59)-1)*'Indexation Client 2026'!$F$59)*'Indexation Client 2026'!$H$59+$H$59 -> 1.772316
A60: COLISSIMO | B60: LIN204C9576AR | C60: CSPN | D60: 163.31 | E60: CNR GNV M-1 | F60: 0.2769 | G60: Variation TK | H60: 1.421 | J60: =((('indice Carburant'!D13/'Indexation Client 2026'!$D$60)-1)*'Indexation Client 2026'!$F$60)*'Indexation Client 2026'!$H$60+$H$60 -> 1.4164704 | K60: =((('indice Carburant'!E13/'Indexation Client 2026'!$D$60)-1)*'Indexation Client 2026'!$F$60)*'Indexation Client 2026'!$H$60+$H$60 -> 1.4120853 | L60: =((('indice Carburant'!F13/'Indexation Client 2026'!$D$60)-1)*'Indexation Client 2026'!$F$60)*'Indexation Client 2026'!$H$60+$H$60 -> 1.4556227 | M60: =((('indice Carburant'!G13/'Indexation Client 2026'!$D$60)-1)*'Indexation Client 2026'!$F$60)*'Indexation Client 2026'!$H$60+$H$60 -> 1.0275251 | N60: =((('indice Carburant'!H13/'Indexation Client 2026'!$D$60)-1)*'Indexation Client 2026'!$F$60)*'Indexation Client 2026'!$H$60+$H$60 -> 1.0275251 | O60: =((('indice Carburant'!I13/'Indexation Client 2026'!$D$60)-1)*'Indexation Client 2026'!$F$60)*'Indexation Client 2026'!$H$60+$H$60 -> 1.0275251 | P60: =((('indice Carburant'!J13/'Indexation Client 2026'!$D$60)-1)*'Indexation Client 2026'!$F$60)*'Indexation Client 2026'!$H$60+$H$60 -> 1.0275251 | Q60: =((('indice Carburant'!K13/'Indexation Client 2026'!$D$60)-1)*'Indexation Client 2026'!$F$60)*'Indexation Client 2026'!$H$60+$H$60 -> 1.0275251 | ... U60: =((('indice Carburant'!O13/'Indexation Client 2026'!$D$60)-1)*'Indexation Client 2026'!$F$60)*'Indexation Client 2026'!$H$60+$H$60 -> 1.0275251
A61: COLISSIMO | B61: LIN205C9576AR | C61: CSPN | D61: 163.31 | E61: CNR GNV M-1 | F61: 0.2798 | G61: Variation TK | H61: 1.452 | J61: =((('indice Carburant'!D13/'Indexation Client 2026'!$D$61)-1)*'Indexation Client 2026'!$F$61)*'Indexation Client 2026'!$H$61+$H$61 -> 1.4473231 | K61: =((('indice Carburant'!E13/'Indexation Client 2026'!$D$61)-1)*'Indexation Client 2026'!$F$61)*'Indexation Client 2026'!$H$61+$H$61 -> 1.4427954 | L61: =((('indice Carburant'!F13/'Indexation Client 2026'!$D$61)-1)*'Indexation Client 2026'!$F$61)*'Indexation Client 2026'!$H$61+$H$61 -> 1.4877485 | M61: =((('indice Carburant'!G13/'Indexation Client 2026'!$D$61)-1)*'Indexation Client 2026'!$F$61)*'Indexation Client 2026'!$H$61+$H$61 -> 1.0457304 | N61: =((('indice Carburant'!H13/'Indexation Client 2026'!$D$61)-1)*'Indexation Client 2026'!$F$61)*'Indexation Client 2026'!$H$61+$H$61 -> 1.0457304 | O61: =((('indice Carburant'!I13/'Indexation Client 2026'!$D$61)-1)*'Indexation Client 2026'!$F$61)*'Indexation Client 2026'!$H$61+$H$61 -> 1.0457304 | P61: =((('indice Carburant'!J13/'Indexation Client 2026'!$D$61)-1)*'Indexation Client 2026'!$F$61)*'Indexation Client 2026'!$H$61+$H$61 -> 1.0457304 | Q61: =((('indice Carburant'!K13/'Indexation Client 2026'!$D$61)-1)*'Indexation Client 2026'!$F$61)*'Indexation Client 2026'!$H$61+$H$61 -> 1.0457304 | ... U61: =((('indice Carburant'!O13/'Indexation Client 2026'!$D$61)-1)*'Indexation Client 2026'!$F$61)*'Indexation Client 2026'!$H$61+$H$61 -> 1.0457304
A62: DACHSER CERGY | B62: 532_FT_113 | C62: DACER | D62: 182.05 | E62: CNR GO PRO M-1 | F62: 0.265 | G62: % Pied de facture | J62: 0.044972672 | K62: =((('indice Carburant'!E6/'Indexation Client 2026'!$D$62)-1)*'Indexation Client 2026'!$F$62) -> 0.0081661631 | L62: =((('indice Carburant'!F6/'Indexation Client 2026'!$D$62)-1)*'Indexation Client 2026'!$F$62) -> 0.016434221 | M62: =((('indice Carburant'!G6/'Indexation Client 2026'!$D$62)-1)*'Indexation Client 2026'!$F$62) -> 0.096116177 | N62: =((('indice Carburant'!H6/'Indexation Client 2026'!$D$62)-1)*'Indexation Client 2026'!$F$62) -> -0.265 | O62: =((('indice Carburant'!I6/'Indexation Client 2026'!$D$62)-1)*'Indexation Client 2026'!$F$62) -> -0.265 | P62: =((('indice Carburant'!J6/'Indexation Client 2026'!$D$62)-1)*'Indexation Client 2026'!$F$62) -> -0.265 | Q62: =((('indice Carburant'!K6/'Indexation Client 2026'!$D$62)-1)*'Indexation Client 2026'!$F$62) -> -0.265 | R62: =((('indice Carburant'!L6/'Indexation Client 2026'!$D$62)-1)*'Indexation Client 2026'!$F$62) -> -0.265 | ... U62: =((('indice Carburant'!O6/'Indexation Client 2026'!$D$62)-1)*'Indexation Client 2026'!$F$62) -> -0.265
A63: DACHSER CERGY | B63: 532_FT_148 | C63: DACER | D63: 182.05 | E63: CNR GO PRO M-1 | F63: 0.265 | G63: % Pied de facture | J63: -0.045419132 | K63: =((('indice Carburant'!E6/'Indexation Client 2026'!$D$63)-1)*'Indexation Client 2026'!$F$63) -> 0.0081661631 | L63: =((('indice Carburant'!F6/'Indexation Client 2026'!$D$63)-1)*'Indexation Client 2026'!$F$63) -> 0.016434221 | M63: =((('indice Carburant'!G6/'Indexation Client 2026'!$D$63)-1)*'Indexation Client 2026'!$F$63) -> 0.096116177 | N63: =((('indice Carburant'!H6/'Indexation Client 2026'!$D$63)-1)*'Indexation Client 2026'!$F$63) -> -0.265 | O63: =((('indice Carburant'!I6/'Indexation Client 2026'!$D$63)-1)*'Indexation Client 2026'!$F$63) -> -0.265 | P63: =((('indice Carburant'!J6/'Indexation Client 2026'!$D$63)-1)*'Indexation Client 2026'!$F$63) -> -0.265 | Q63: =((('indice Carburant'!K6/'Indexation Client 2026'!$D$63)-1)*'Indexation Client 2026'!$F$63) -> -0.265 | R63: =((('indice Carburant'!L6/'Indexation Client 2026'!$D$63)-1)*'Indexation Client 2026'!$F$63) -> -0.265 | ... U63: =((('indice Carburant'!O6/'Indexation Client 2026'!$D$63)-1)*'Indexation Client 2026'!$F$63) -> -0.265
A64: DACHSER CERGY | B64: 532_FT_151 | C64: DACER | D64: 182.05 | E64: CNR GO PRO M-1 | F64: 0.265 | G64: % Pied de facture | J64: -0.046985309 | K64: =((('indice Carburant'!E6/'Indexation Client 2026'!$D$64)-1)*'Indexation Client 2026'!$F$64) -> 0.0081661631 | L64: =((('indice Carburant'!F6/'Indexation Client 2026'!$D$64)-1)*'Indexation Client 2026'!$F$64) -> 0.016434221 | M64: =((('indice Carburant'!G6/'Indexation Client 2026'!$D$64)-1)*'Indexation Client 2026'!$F$64) -> 0.096116177 | N64: =((('indice Carburant'!H6/'Indexation Client 2026'!$D$64)-1)*'Indexation Client 2026'!$F$64) -> -0.265 | O64: =((('indice Carburant'!I6/'Indexation Client 2026'!$D$64)-1)*'Indexation Client 2026'!$F$64) -> -0.265 | P64: =((('indice Carburant'!J6/'Indexation Client 2026'!$D$64)-1)*'Indexation Client 2026'!$F$64) -> -0.265 | Q64: =((('indice Carburant'!K6/'Indexation Client 2026'!$D$64)-1)*'Indexation Client 2026'!$F$64) -> -0.265 | R64: =((('indice Carburant'!L6/'Indexation Client 2026'!$D$64)-1)*'Indexation Client 2026'!$F$64) -> -0.265 | ... U64: =((('indice Carburant'!O6/'Indexation Client 2026'!$D$64)-1)*'Indexation Client 2026'!$F$64) -> -0.265
A65: DACHSER CERGY | B65: 532_FT_25 | C65: DACER | D65: 182.05 | E65: CNR GO PRO M-1 | F65: 0.265 | G65: % Pied de facture | J65: -0.042286778 | K65: =((('indice Carburant'!E6/'Indexation Client 2026'!$D$65)-1)*'Indexation Client 2026'!$F$65) -> 0.0081661631 | L65: =((('indice Carburant'!F6/'Indexation Client 2026'!$D$65)-1)*'Indexation Client 2026'!$F$65) -> 0.016434221 | M65: =((('indice Carburant'!G6/'Indexation Client 2026'!$D$65)-1)*'Indexation Client 2026'!$F$65) -> 0.096116177 | N65: =((('indice Carburant'!H6/'Indexation Client 2026'!$D$65)-1)*'Indexation Client 2026'!$F$65) -> -0.265 | O65: =((('indice Carburant'!I6/'Indexation Client 2026'!$D$65)-1)*'Indexation Client 2026'!$F$65) -> -0.265 | P65: =((('indice Carburant'!J6/'Indexation Client 2026'!$D$65)-1)*'Indexation Client 2026'!$F$65) -> -0.265 | Q65: =((('indice Carburant'!K6/'Indexation Client 2026'!$D$65)-1)*'Indexation Client 2026'!$F$65) -> -0.265 | R65: =((('indice Carburant'!L6/'Indexation Client 2026'!$D$65)-1)*'Indexation Client 2026'!$F$65) -> -0.265 | ... U65: =((('indice Carburant'!O6/'Indexation Client 2026'!$D$65)-1)*'Indexation Client 2026'!$F$65) -> -0.265
A66: DACHSER CERGY | B66: 532_FT_445 | C66: DACER | D66: 182.05 | E66: CNR GO PRO M-1 | F66: 0.265 | G66: % Pied de facture | J66: -0.048601401 | K66: =((('indice Carburant'!E6/'Indexation Client 2026'!$D$66)-1)*'Indexation Client 2026'!$F$66) -> 0.0081661631 | L66: =((('indice Carburant'!F6/'Indexation Client 2026'!$D$66)-1)*'Indexation Client 2026'!$F$66) -> 0.016434221 | M66: =((('indice Carburant'!G6/'Indexation Client 2026'!$D$66)-1)*'Indexation Client 2026'!$F$66) -> 0.096116177 | N66: =((('indice Carburant'!H6/'Indexation Client 2026'!$D$66)-1)*'Indexation Client 2026'!$F$66) -> -0.265 | O66: =((('indice Carburant'!I6/'Indexation Client 2026'!$D$66)-1)*'Indexation Client 2026'!$F$66) -> -0.265 | P66: =((('indice Carburant'!J6/'Indexation Client 2026'!$D$66)-1)*'Indexation Client 2026'!$F$66) -> -0.265 | Q66: =((('indice Carburant'!K6/'Indexation Client 2026'!$D$66)-1)*'Indexation Client 2026'!$F$66) -> -0.265 | R66: =((('indice Carburant'!L6/'Indexation Client 2026'!$D$66)-1)*'Indexation Client 2026'!$F$66) -> -0.265 | ... U66: =((('indice Carburant'!O6/'Indexation Client 2026'!$D$66)-1)*'Indexation Client 2026'!$F$66) -> -0.265
A67: DACHSER CERGY | B67: AR Cergy - Pantin | C67: DACER | D67: 188.39 | E67: CNR GO PRO M-1 | F67: 0.169 | G67: % Pied de facture | J67: =((('indice Carburant'!D6/'Indexation Client 2026'!$D$67)-1)*'Indexation Client 2026'!$F$67) -> -0.0061629067 | K67: =((('indice Carburant'!E6/'Indexation Client 2026'!$D$67)-1)*'Indexation Client 2026'!$F$67) -> -0.00065486491 | L67: =((('indice Carburant'!F6/'Indexation Client 2026'!$D$67)-1)*'Indexation Client 2026'!$F$67) -> 0.0044405223 | M67: =((('indice Carburant'!G6/'Indexation Client 2026'!$D$67)-1)*'Indexation Client 2026'!$F$67) -> 0.05354642 | N67: =((('indice Carburant'!H6/'Indexation Client 2026'!$D$67)-1)*'Indexation Client 2026'!$F$67) -> -0.169 | O67: =((('indice Carburant'!I6/'Indexation Client 2026'!$D$67)-1)*'Indexation Client 2026'!$F$67) -> -0.169 | P67: =((('indice Carburant'!J6/'Indexation Client 2026'!$D$67)-1)*'Indexation Client 2026'!$F$67) -> -0.169 | Q67: =((('indice Carburant'!K6/'Indexation Client 2026'!$D$67)-1)*'Indexation Client 2026'!$F$67) -> -0.169 | ... U67: =((('indice Carburant'!O6/'Indexation Client 2026'!$D$67)-1)*'Indexation Client 2026'!$F$67) -> -0.169
A68: Dachser HOLNON | B68: 537_FT_141 | C68: DASTQ | D68: 181.52 | E68: CNR GO PRO M-1 | F68: 0.28 | G68: % Pied de facture | J68: =((('indice Carburant'!D6/'Indexation Client 2026'!$D$68)-1)*'Indexation Client 2026'!$F$68) -> 0 | K68: =((('indice Carburant'!E6/'Indexation Client 2026'!$D$68)-1)*'Indexation Client 2026'!$F$68) -> 0.0094711327 | L68: =((('indice Carburant'!F6/'Indexation Client 2026'!$D$68)-1)*'Indexation Client 2026'!$F$68) -> 0.018232702 | M68: =((('indice Carburant'!G6/'Indexation Client 2026'!$D$68)-1)*'Indexation Client 2026'!$F$68) -> 0.10267078 | N68: =((('indice Carburant'!H6/'Indexation Client 2026'!$D$68)-1)*'Indexation Client 2026'!$F$68) -> -0.28 | O68: =((('indice Carburant'!I6/'Indexation Client 2026'!$D$68)-1)*'Indexation Client 2026'!$F$68) -> -0.28 | P68: =((('indice Carburant'!J6/'Indexation Client 2026'!$D$68)-1)*'Indexation Client 2026'!$F$68) -> -0.28 | Q68: =((('indice Carburant'!K6/'Indexation Client 2026'!$D$68)-1)*'Indexation Client 2026'!$F$68) -> -0.28 | ... U68: =((('indice Carburant'!O6/'Indexation Client 2026'!$D$68)-1)*'Indexation Client 2026'!$F$68) -> -0.28
A69: Dachser HOLNON | B69: NAVETTE LC | C69: DASTQ | D69: 181.52 | E69: CNR GO PRO M-1 | F69: 0.28 | G69: % Pied de facture | J69: =((('indice Carburant'!D6/'Indexation Client 2026'!$D$68)-1)*'Indexation Client 2026'!$F$68) -> 0 | K69: =((('indice Carburant'!E6/'Indexation Client 2026'!$D$68)-1)*'Indexation Client 2026'!$F$68) -> 0.0094711327 | L69: =((('indice Carburant'!F6/'Indexation Client 2026'!$D$68)-1)*'Indexation Client 2026'!$F$68) -> 0.018232702 | M69: =((('indice Carburant'!G6/'Indexation Client 2026'!$D$68)-1)*'Indexation Client 2026'!$F$68) -> 0.10267078 | N69: =((('indice Carburant'!H6/'Indexation Client 2026'!$D$68)-1)*'Indexation Client 2026'!$F$68) -> -0.28 | O69: =((('indice Carburant'!I6/'Indexation Client 2026'!$D$68)-1)*'Indexation Client 2026'!$F$68) -> -0.28 | P69: =((('indice Carburant'!J6/'Indexation Client 2026'!$D$68)-1)*'Indexation Client 2026'!$F$68) -> -0.28 | Q69: =((('indice Carburant'!K6/'Indexation Client 2026'!$D$68)-1)*'Indexation Client 2026'!$F$68) -> -0.28 | ... U69: =((('indice Carburant'!O6/'Indexation Client 2026'!$D$68)-1)*'Indexation Client 2026'!$F$68) -> -0.28
A70: DACHSER PANTIN | B70: 567_FT_423 | C70: DAPAN | D70: 142.37 | E70: CNR GNV M-1 | F70: 0.257 | G70: % Pied de facture | J70: =((('indice Carburant'!D13/'Indexation Client 2026'!$D$70)-1)*'Indexation Client 2026'!$F$70) -> 0.034406265 | K70: =((('indice Carburant'!E13/'Indexation Client 2026'!$D$70)-1)*'Indexation Client 2026'!$F$70) -> 0.031120882 | L70: =((('indice Carburant'!F13/'Indexation Client 2026'!$D$70)-1)*'Indexation Client 2026'!$F$70) -> 0.063740044 | M70: =((('indice Carburant'!G13/'Indexation Client 2026'!$D$70)-1)*'Indexation Client 2026'!$F$70) -> -0.257 | N70: =((('indice Carburant'!H13/'Indexation Client 2026'!$D$70)-1)*'Indexation Client 2026'!$F$70) -> -0.257 | O70: =((('indice Carburant'!I13/'Indexation Client 2026'!$D$70)-1)*'Indexation Client 2026'!$F$70) -> -0.257 | P70: =((('indice Carburant'!J13/'Indexation Client 2026'!$D$70)-1)*'Indexation Client 2026'!$F$70) -> -0.257 | Q70: =((('indice Carburant'!K13/'Indexation Client 2026'!$D$70)-1)*'Indexation Client 2026'!$F$70) -> -0.257 | ... U70: =((('indice Carburant'!O13/'Indexation Client 2026'!$D$70)-1)*'Indexation Client 2026'!$F$70) -> -0.257
A71: DACHSER STRASBOURG | B71: 538_FT_70 | C71: DASTR | D71: 1.1549 | E71: CMM M-1 | F71: 0.28 | G71: % Pied de facture | J71: 0.027590268 | K71: =((('indice Carburant'!E8/'Indexation Client 2026'!$D$71)-1)*'Indexation Client 2026'!$F$71) -> 0.040464109 | L71: =((('indice Carburant'!F8/'Indexation Client 2026'!$D$71)-1)*'Indexation Client 2026'!$F$71) -> 0.048440558 | M71: =((('indice Carburant'!G8/'Indexation Client 2026'!$D$71)-1)*'Indexation Client 2026'!$F$71) -> 0.1460975 | N71: =((('indice Carburant'!H8/'Indexation Client 2026'!$D$71)-1)*'Indexation Client 2026'!$F$71) -> -0.28 | O71: =((('indice Carburant'!I8/'Indexation Client 2026'!$D$71)-1)*'Indexation Client 2026'!$F$71) -> -0.28 | P71: =((('indice Carburant'!J8/'Indexation Client 2026'!$D$71)-1)*'Indexation Client 2026'!$F$71) -> -0.28 | Q71: =((('indice Carburant'!K8/'Indexation Client 2026'!$D$71)-1)*'Indexation Client 2026'!$F$71) -> -0.28 | R71: =((('indice Carburant'!L8/'Indexation Client 2026'!$D$71)-1)*'Indexation Client 2026'!$F$71) -> -0.28 | ... U71: =((('indice Carburant'!O8/'Indexation Client 2026'!$D$71)-1)*'Indexation Client 2026'!$F$71) -> -0.28
A72: DACHSER VILLEPARISIS | B72: 535_FT_297 | C72: DACHS | D72: 182.05 | E72: CNR GO PRO M-1 | F72: 0.265 | G72: % Pied de facture | J72: 0.053408076 | K72: =((('indice Carburant'!E6/'Indexation Client 2026'!$D$72)-1)*'Indexation Client 2026'!$F$72) -> 0.0081661631 | L72: =((('indice Carburant'!F6/'Indexation Client 2026'!$D$72)-1)*'Indexation Client 2026'!$F$72) -> 0.016434221 | M72: =((('indice Carburant'!G6/'Indexation Client 2026'!$D$72)-1)*'Indexation Client 2026'!$F$72) -> 0.096116177 | N72: =((('indice Carburant'!H6/'Indexation Client 2026'!$D$72)-1)*'Indexation Client 2026'!$F$72) -> -0.265 | O72: =((('indice Carburant'!I6/'Indexation Client 2026'!$D$72)-1)*'Indexation Client 2026'!$F$72) -> -0.265 | P72: =((('indice Carburant'!J6/'Indexation Client 2026'!$D$72)-1)*'Indexation Client 2026'!$F$72) -> -0.265 | Q72: =((('indice Carburant'!K6/'Indexation Client 2026'!$D$72)-1)*'Indexation Client 2026'!$F$72) -> -0.265 | R72: =((('indice Carburant'!L6/'Indexation Client 2026'!$D$72)-1)*'Indexation Client 2026'!$F$72) -> -0.265 | ... U72: =((('indice Carburant'!O6/'Indexation Client 2026'!$D$72)-1)*'Indexation Client 2026'!$F$72) -> -0.265
A73: DACHSER VILLEPARISIS | B73: 535_FT_378 | C73: DACHS | D73: 182.05 | E73: CNR GO PRO M-1 | F73: 0.265 | G73: % Pied de facture | J73: 0.099131192 | K73: =((('indice Carburant'!E6/'Indexation Client 2026'!$D$73)-1)*'Indexation Client 2026'!$F$73) -> 0.0081661631 | L73: =((('indice Carburant'!F6/'Indexation Client 2026'!$D$73)-1)*'Indexation Client 2026'!$F$73) -> 0.016434221 | M73: =((('indice Carburant'!G6/'Indexation Client 2026'!$D$73)-1)*'Indexation Client 2026'!$F$73) -> 0.096116177 | N73: =((('indice Carburant'!H6/'Indexation Client 2026'!$D$73)-1)*'Indexation Client 2026'!$F$73) -> -0.265 | O73: =((('indice Carburant'!I6/'Indexation Client 2026'!$D$73)-1)*'Indexation Client 2026'!$F$73) -> -0.265 | P73: =((('indice Carburant'!J6/'Indexation Client 2026'!$D$73)-1)*'Indexation Client 2026'!$F$73) -> -0.265 | Q73: =((('indice Carburant'!K6/'Indexation Client 2026'!$D$73)-1)*'Indexation Client 2026'!$F$73) -> -0.265 | R73: =((('indice Carburant'!L6/'Indexation Client 2026'!$D$73)-1)*'Indexation Client 2026'!$F$73) -> -0.265 | ... U73: =((('indice Carburant'!O6/'Indexation Client 2026'!$D$73)-1)*'Indexation Client 2026'!$F$73) -> -0.265
A74: DACHSER VILLEPARISIS | B74: 535_FT_5048 | C74: DACHS | D74: 182.05 | E74: CNR GO PRO M-1 | F74: 0.265 | G74: % Pied de facture | J74: 0.09897852 | K74: =((('indice Carburant'!E6/'Indexation Client 2026'!$D$74)-1)*'Indexation Client 2026'!$F$74) -> 0.0081661631 | L74: =((('indice Carburant'!F6/'Indexation Client 2026'!$D$74)-1)*'Indexation Client 2026'!$F$74) -> 0.016434221 | M74: =((('indice Carburant'!G6/'Indexation Client 2026'!$D$74)-1)*'Indexation Client 2026'!$F$74) -> 0.096116177 | N74: =((('indice Carburant'!H6/'Indexation Client 2026'!$D$74)-1)*'Indexation Client 2026'!$F$74) -> -0.265 | O74: =((('indice Carburant'!I6/'Indexation Client 2026'!$D$74)-1)*'Indexation Client 2026'!$F$74) -> -0.265 | P74: =((('indice Carburant'!J6/'Indexation Client 2026'!$D$74)-1)*'Indexation Client 2026'!$F$74) -> -0.265 | Q74: =((('indice Carburant'!K6/'Indexation Client 2026'!$D$74)-1)*'Indexation Client 2026'!$F$74) -> -0.265 | R74: =((('indice Carburant'!L6/'Indexation Client 2026'!$D$74)-1)*'Indexation Client 2026'!$F$74) -> -0.265 | ... U74: =((('indice Carburant'!O6/'Indexation Client 2026'!$D$74)-1)*'Indexation Client 2026'!$F$74) -> -0.265
A75: DACHSER VILLEPARISIS | B75: T 962 | C75: DACHS | D75: 187.15 | E75: CNR GO PRO M-2 | F75: 0.17 | G75: % Pied de facture | J75: 0.069048615 | K75: =((('indice Carburant'!D6/'Indexation Client 2026'!$D$75)-1)*'Indexation Client 2026'!$F$75) -> -0.0051140796 | L75: =((('indice Carburant'!E6/'Indexation Client 2026'!$D$75)-1)*'Indexation Client 2026'!$F$75) -> 0.00046326476 | M75: =((('indice Carburant'!F6/'Indexation Client 2026'!$D$75)-1)*'Indexation Client 2026'!$F$75) -> 0.0056227625 | N75: =((('indice Carburant'!G6/'Indexation Client 2026'!$D$75)-1)*'Indexation Client 2026'!$F$75) -> 0.055346513 | O75: =((('indice Carburant'!H6/'Indexation Client 2026'!$D$75)-1)*'Indexation Client 2026'!$F$75) -> -0.17 | P75: =((('indice Carburant'!I6/'Indexation Client 2026'!$D$75)-1)*'Indexation Client 2026'!$F$75) -> -0.17 | Q75: =((('indice Carburant'!J6/'Indexation Client 2026'!$D$75)-1)*'Indexation Client 2026'!$F$75) -> -0.17 | R75: =((('indice Carburant'!K6/'Indexation Client 2026'!$D$75)-1)*'Indexation Client 2026'!$F$75) -> -0.17 | ... U75: =((('indice Carburant'!N6/'Indexation Client 2026'!$D$75)-1)*'Indexation Client 2026'!$F$75) -> -0.17
A76: DACHSER VILLEPARISIS | B76: T 964 | C76: DACHS | D76: 187.15 | E76: CNR GO PRO M-2 | F76: 0.17 | G76: % Pied de facture | J76: 0.069048615 | K76: =((('indice Carburant'!D6/'Indexation Client 2026'!$D$76)-1)*'Indexation Client 2026'!$F$76) -> -0.0051140796 | L76: =((('indice Carburant'!E6/'Indexation Client 2026'!$D$76)-1)*'Indexation Client 2026'!$F$76) -> 0.00046326476 | M76: =((('indice Carburant'!F6/'Indexation Client 2026'!$D$76)-1)*'Indexation Client 2026'!$F$76) -> 0.0056227625 | N76: =((('indice Carburant'!G6/'Indexation Client 2026'!$D$76)-1)*'Indexation Client 2026'!$F$76) -> 0.055346513 | O76: =((('indice Carburant'!H6/'Indexation Client 2026'!$D$76)-1)*'Indexation Client 2026'!$F$76) -> -0.17 | P76: =((('indice Carburant'!I6/'Indexation Client 2026'!$D$76)-1)*'Indexation Client 2026'!$F$76) -> -0.17 | Q76: =((('indice Carburant'!J6/'Indexation Client 2026'!$D$76)-1)*'Indexation Client 2026'!$F$76) -> -0.17 | R76: =((('indice Carburant'!K6/'Indexation Client 2026'!$D$76)-1)*'Indexation Client 2026'!$F$76) -> -0.17 | ... U76: =((('indice Carburant'!N6/'Indexation Client 2026'!$D$76)-1)*'Indexation Client 2026'!$F$76) -> -0.17
A77: DACHSER VILLEPARISIS | B77: T963 | C77: DACHS | D77: 187.15 | E77: CNR GO PRO M-2 | F77: 0.17 | G77: % Pied de facture | J77: 0.069048615 | K77: =((('indice Carburant'!D6/'Indexation Client 2026'!$D$77)-1)*'Indexation Client 2026'!$F$77) -> -0.0051140796 | L77: =((('indice Carburant'!E6/'Indexation Client 2026'!$D$77)-1)*'Indexation Client 2026'!$F$77) -> 0.00046326476 | M77: =((('indice Carburant'!F6/'Indexation Client 2026'!$D$77)-1)*'Indexation Client 2026'!$F$77) -> 0.0056227625 | N77: =((('indice Carburant'!G6/'Indexation Client 2026'!$D$77)-1)*'Indexation Client 2026'!$F$77) -> 0.055346513 | O77: =((('indice Carburant'!H6/'Indexation Client 2026'!$D$77)-1)*'Indexation Client 2026'!$F$77) -> -0.17 | P77: =((('indice Carburant'!I6/'Indexation Client 2026'!$D$77)-1)*'Indexation Client 2026'!$F$77) -> -0.17 | Q77: =((('indice Carburant'!J6/'Indexation Client 2026'!$D$77)-1)*'Indexation Client 2026'!$F$77) -> -0.17 | R77: =((('indice Carburant'!K6/'Indexation Client 2026'!$D$77)-1)*'Indexation Client 2026'!$F$77) -> -0.17 | ... U77: =((('indice Carburant'!N6/'Indexation Client 2026'!$D$77)-1)*'Indexation Client 2026'!$F$77) -> -0.17
A78: DACHSER VILLEPARISIS | B78: 917 | C78: DACHS | D78: 187.15 | E78: CNR GO PRO M-1 | F78: 0.221 | G78: % Pied de facture | J78: =((('indice Carburant'!D6/'Indexation Client 2026'!$D$78)-1)*'Indexation Client 2026'!$F$78) -> -0.0066483035 | K78: =((('indice Carburant'!E6/'Indexation Client 2026'!$D$78)-1)*'Indexation Client 2026'!$F$78) -> 0.00060224419 | L78: =((('indice Carburant'!F6/'Indexation Client 2026'!$D$78)-1)*'Indexation Client 2026'!$F$78) -> 0.0073095912 | M78: =((('indice Carburant'!G6/'Indexation Client 2026'!$D$78)-1)*'Indexation Client 2026'!$F$78) -> 0.071950468 | N78: =((('indice Carburant'!H6/'Indexation Client 2026'!$D$78)-1)*'Indexation Client 2026'!$F$78) -> -0.221 | O78: =((('indice Carburant'!I6/'Indexation Client 2026'!$D$78)-1)*'Indexation Client 2026'!$F$78) -> -0.221 | P78: =((('indice Carburant'!J6/'Indexation Client 2026'!$D$78)-1)*'Indexation Client 2026'!$F$78) -> -0.221 | Q78: =((('indice Carburant'!K6/'Indexation Client 2026'!$D$78)-1)*'Indexation Client 2026'!$F$78) -> -0.221 | ... U78: =((('indice Carburant'!O6/'Indexation Client 2026'!$D$78)-1)*'Indexation Client 2026'!$F$78) -> -0.221
A79: DACHSER VILLEPARISIS | B79: 527_535_FT_425 | C79: DACHS | D79: 183.25 | E79: CNR GO PRO M-1 | F79: 0.224 | G79: % Pied de facture | J79: =((('indice Carburant'!D6/'Indexation Client 2026'!$D$79)-1)*'Indexation Client 2026'!$F$79) -> -0.0021147067 | K79: =((('indice Carburant'!E6/'Indexation Client 2026'!$D$79)-1)*'Indexation Client 2026'!$F$79) -> 0.0053906685 | L79: =((('indice Carburant'!F6/'Indexation Client 2026'!$D$79)-1)*'Indexation Client 2026'!$F$79) -> 0.012333752 | M79: =((('indice Carburant'!G6/'Indexation Client 2026'!$D$79)-1)*'Indexation Client 2026'!$F$79) -> 0.079246494 | N79: =((('indice Carburant'!H6/'Indexation Client 2026'!$D$79)-1)*'Indexation Client 2026'!$F$79) -> -0.224 | O79: =((('indice Carburant'!I6/'Indexation Client 2026'!$D$79)-1)*'Indexation Client 2026'!$F$79) -> -0.224 | P79: =((('indice Carburant'!J6/'Indexation Client 2026'!$D$79)-1)*'Indexation Client 2026'!$F$79) -> -0.224 | Q79: =((('indice Carburant'!K6/'Indexation Client 2026'!$D$79)-1)*'Indexation Client 2026'!$F$79) -> -0.224 | ... U79: =((('indice Carburant'!O6/'Indexation Client 2026'!$D$79)-1)*'Indexation Client 2026'!$F$79) -> -0.224
A80: DACHSER WISSOUS | B80: 534_FT_115 | C80: DAWIS | D80: 182.05 | E80: CNR GO PRO M-1 | F80: 0.265 | G80: % Pied de facture | J80: 0.01647473 | K80: =((('indice Carburant'!E6/'Indexation Client 2026'!$D$80)-1)*'Indexation Client 2026'!$F$80) -> 0.0081661631 | L80: =((('indice Carburant'!F6/'Indexation Client 2026'!$D$80)-1)*'Indexation Client 2026'!$F$80) -> 0.016434221 | M80: =((('indice Carburant'!G6/'Indexation Client 2026'!$D$80)-1)*'Indexation Client 2026'!$F$80) -> 0.096116177 | N80: =((('indice Carburant'!H6/'Indexation Client 2026'!$D$80)-1)*'Indexation Client 2026'!$F$80) -> -0.265 | O80: =((('indice Carburant'!I6/'Indexation Client 2026'!$D$80)-1)*'Indexation Client 2026'!$F$80) -> -0.265 | P80: =((('indice Carburant'!J6/'Indexation Client 2026'!$D$80)-1)*'Indexation Client 2026'!$F$80) -> -0.265 | Q80: =((('indice Carburant'!K6/'Indexation Client 2026'!$D$80)-1)*'Indexation Client 2026'!$F$80) -> -0.265 | R80: =((('indice Carburant'!L6/'Indexation Client 2026'!$D$80)-1)*'Indexation Client 2026'!$F$80) -> -0.265 | ... U80: =((('indice Carburant'!O6/'Indexation Client 2026'!$D$80)-1)*'Indexation Client 2026'!$F$80) -> -0.265
A81: DACHSER WISSOUS | B81: 534_FT_5022 | C81: DAWIS | D81: 182.05 | E81: CNR GO PRO M-1 | F81: 0.265 | G81: % Pied de facture | J81: 0.087692978 | K81: =((('indice Carburant'!E6/'Indexation Client 2026'!$D$81)-1)*'Indexation Client 2026'!$F$81) -> 0.0081661631 | L81: =((('indice Carburant'!F6/'Indexation Client 2026'!$D$81)-1)*'Indexation Client 2026'!$F$81) -> 0.016434221 | M81: =((('indice Carburant'!G6/'Indexation Client 2026'!$D$81)-1)*'Indexation Client 2026'!$F$81) -> 0.096116177 | N81: =((('indice Carburant'!H6/'Indexation Client 2026'!$D$81)-1)*'Indexation Client 2026'!$F$81) -> -0.265 | O81: =((('indice Carburant'!I6/'Indexation Client 2026'!$D$81)-1)*'Indexation Client 2026'!$F$81) -> -0.265 | P81: =((('indice Carburant'!J6/'Indexation Client 2026'!$D$81)-1)*'Indexation Client 2026'!$F$81) -> -0.265 | Q81: =((('indice Carburant'!K6/'Indexation Client 2026'!$D$81)-1)*'Indexation Client 2026'!$F$81) -> -0.265 | R81: =((('indice Carburant'!L6/'Indexation Client 2026'!$D$81)-1)*'Indexation Client 2026'!$F$81) -> -0.265 | ... U81: =((('indice Carburant'!O6/'Indexation Client 2026'!$D$81)-1)*'Indexation Client 2026'!$F$81) -> -0.265
A82: DGF | C82: DGF
A83: DHL AVIATION | C83: DHLAV
A84: DHL EUROAD | B84: COST CENTER 925201 | C84: DHLGM | D84: 0.8986 | E84: CMM M-1 | F84: 0.13 | G84: % Pied de facture | J84: =((('indice Carburant'!D8/'Indexation Client 2026'!$D$84)-1)*'Indexation Client 2026'!$F$84) -> 0.053542177 | K84: =((('indice Carburant'!E8/'Indexation Client 2026'!$D$84)-1)*'Indexation Client 2026'!$F$84) -> 0.061224126 | L84: =((('indice Carburant'!F8/'Indexation Client 2026'!$D$84)-1)*'Indexation Client 2026'!$F$84) -> 0.065983753 | M84: =((('indice Carburant'!G8/'Indexation Client 2026'!$D$84)-1)*'Indexation Client 2026'!$F$84) -> 0.12425662 | N84: =((('indice Carburant'!H8/'Indexation Client 2026'!$D$84)-1)*'Indexation Client 2026'!$F$84) -> -0.13 | O84: =((('indice Carburant'!I8/'Indexation Client 2026'!$D$84)-1)*'Indexation Client 2026'!$F$84) -> -0.13 | P84: =((('indice Carburant'!J8/'Indexation Client 2026'!$D$84)-1)*'Indexation Client 2026'!$F$84) -> -0.13 | Q84: =((('indice Carburant'!K8/'Indexation Client 2026'!$D$84)-1)*'Indexation Client 2026'!$F$84) -> -0.13 | ... U84: =((('indice Carburant'!O8/'Indexation Client 2026'!$D$84)-1)*'Indexation Client 2026'!$F$84) -> -0.13
A85: DHL EXPRESS | B85: CONTRAT FRD | C85: DHLINT | D85: 0
A86: DHL EXPRESS | B86: COURSE-SPL | C86: DHLINT
A87: DHL EXPRESS | B87: PRESTATIONS IDF GAZ | C87: DHLINT | D87: 162.44 | E87: CNR GNV M-1 | F87: 0.18 | G87: % Pied de facture | J87: =((('indice Carburant'!D13/'Indexation Client 2026'!$D$87)-1)*'Indexation Client 2026'!$F$87) -> -0.0011191825 | K87: =((('indice Carburant'!E13/'Indexation Client 2026'!$D$87)-1)*'Indexation Client 2026'!$F$87) -> -0.0031359271 | L87: =((('indice Carburant'!F13/'Indexation Client 2026'!$D$87)-1)*'Indexation Client 2026'!$F$87) -> 0.016887466 | M87: =((('indice Carburant'!G13/'Indexation Client 2026'!$D$87)-1)*'Indexation Client 2026'!$F$87) -> -0.18 | N87: =((('indice Carburant'!H13/'Indexation Client 2026'!$D$87)-1)*'Indexation Client 2026'!$F$87) -> -0.18 | O87: =((('indice Carburant'!I13/'Indexation Client 2026'!$D$87)-1)*'Indexation Client 2026'!$F$87) -> -0.18 | P87: =((('indice Carburant'!J13/'Indexation Client 2026'!$D$87)-1)*'Indexation Client 2026'!$F$87) -> -0.18 | Q87: =((('indice Carburant'!K13/'Indexation Client 2026'!$D$87)-1)*'Indexation Client 2026'!$F$87) -> -0.18 | ... U87: =((('indice Carburant'!O13/'Indexation Client 2026'!$D$87)-1)*'Indexation Client 2026'!$F$87) -> -0.18
A88: DHL EXPRESS | B88: PRESTATIONS IDF GO | C88: DHLINT | D88: 224.45 | E88: CNR GO PRO M-1 | F88: 0.18 | G88: % Pied de facture | J88: =((('indice Carburant'!D6/'Indexation Client 2026'!$D$88)-1)*'Indexation Client 2026'!$F$88) -> -0.034428158 | K88: =((('indice Carburant'!E6/'Indexation Client 2026'!$D$88)-1)*'Indexation Client 2026'!$F$88) -> -0.029504121 | L88: =((('indice Carburant'!F6/'Indexation Client 2026'!$D$88)-1)*'Indexation Client 2026'!$F$88) -> -0.024948986 | M88: =((('indice Carburant'!G6/'Indexation Client 2026'!$D$88)-1)*'Indexation Client 2026'!$F$88) -> 0.018950323 | N88: =((('indice Carburant'!H6/'Indexation Client 2026'!$D$88)-1)*'Indexation Client 2026'!$F$88) -> -0.18 | O88: =((('indice Carburant'!I6/'Indexation Client 2026'!$D$88)-1)*'Indexation Client 2026'!$F$88) -> -0.18 | P88: =((('indice Carburant'!J6/'Indexation Client 2026'!$D$88)-1)*'Indexation Client 2026'!$F$88) -> -0.18 | Q88: =((('indice Carburant'!K6/'Indexation Client 2026'!$D$88)-1)*'Indexation Client 2026'!$F$88) -> -0.18 | ... U88: =((('indice Carburant'!O6/'Indexation Client 2026'!$D$88)-1)*'Indexation Client 2026'!$F$88) -> -0.18
A89: DHL EXPRESS | B89: PRESTATIONS LYON GO | C89: DHLINT | D89: 152.93 | E89: CNR GO PRO M-1 | F89: 0.18 | G89: % Pied de facture | J89: =((('indice Carburant'!D6/'Indexation Client 2026'!$D$89)-1)*'Indexation Client 2026'!$F$89) -> 0.03365069 | K89: =((('indice Carburant'!E6/'Indexation Client 2026'!$D$89)-1)*'Indexation Client 2026'!$F$89) -> 0.040877526 | L89: =((('indice Carburant'!F6/'Indexation Client 2026'!$D$89)-1)*'Indexation Client 2026'!$F$89) -> 0.047562937 | M89: =((('indice Carburant'!G6/'Indexation Client 2026'!$D$89)-1)*'Indexation Client 2026'!$F$89) -> 0.11199241 | N89: =((('indice Carburant'!H6/'Indexation Client 2026'!$D$89)-1)*'Indexation Client 2026'!$F$89) -> -0.18 | O89: =((('indice Carburant'!I6/'Indexation Client 2026'!$D$89)-1)*'Indexation Client 2026'!$F$89) -> -0.18 | P89: =((('indice Carburant'!J6/'Indexation Client 2026'!$D$89)-1)*'Indexation Client 2026'!$F$89) -> -0.18 | Q89: =((('indice Carburant'!K6/'Indexation Client 2026'!$D$89)-1)*'Indexation Client 2026'!$F$89) -> -0.18 | ... U89: =((('indice Carburant'!O6/'Indexation Client 2026'!$D$89)-1)*'Indexation Client 2026'!$F$89) -> -0.18
A90: DHL FREIGHT | C90: DHLFREI | D90: ?
A91: DPD 78 | C91: DPD078 | D91: 1.0643 | E91: DIREM M-1 | F91: 0.2 | G91: % Pied de facture | J91: =((('indice Carburant'!D10/'Indexation Client 2026'!$D$91)-1)*'Indexation Client 2026'!$F$91) -> 0.051508033 | K91: =((('indice Carburant'!E10/'Indexation Client 2026'!$D$91)-1)*'Indexation Client 2026'!$F$91) -> 0.055942873 | L91: =((('indice Carburant'!F10/'Indexation Client 2026'!$D$91)-1)*'Indexation Client 2026'!$F$91) -> 0.06189984 | M91: =((('indice Carburant'!G10/'Indexation Client 2026'!$D$91)-1)*'Indexation Client 2026'!$F$91) -> 0.12366814 | N91: =((('indice Carburant'!H10/'Indexation Client 2026'!$D$91)-1)*'Indexation Client 2026'!$F$91) -> -0.2 | O91: =((('indice Carburant'!I10/'Indexation Client 2026'!$D$91)-1)*'Indexation Client 2026'!$F$91) -> -0.2 | P91: =((('indice Carburant'!J10/'Indexation Client 2026'!$D$91)-1)*'Indexation Client 2026'!$F$91) -> -0.2 | Q91: =((('indice Carburant'!K10/'Indexation Client 2026'!$D$91)-1)*'Indexation Client 2026'!$F$91) -> -0.2 | ... U91: =((('indice Carburant'!O10/'Indexation Client 2026'!$D$91)-1)*'Indexation Client 2026'!$F$91) -> -0.2
A92: EXAPAQ | B92: 095_175_095 | C92: EXAPAQ | D92: 0.8661 | E92: DIREM du mois M | F92: 0.28 | G92: Sur Km | H92: 180 | J92: =((('indice Carburant'!E11-'Indexation Client 2026'!$D$92)*'Indexation Client 2026'!$F$92)) -> 0.140056 | K92: =((('indice Carburant'!F11-'Indexation Client 2026'!$D$92)*'Indexation Client 2026'!$F$92)) -> 0.142436 | L92: =((('indice Carburant'!G11-'Indexation Client 2026'!$D$92)*'Indexation Client 2026'!$F$92)) -> 0.249536 | M92: =((('indice Carburant'!H11-'Indexation Client 2026'!$D$92)*'Indexation Client 2026'!$F$92)) -> -0.242508 | N92: =((('indice Carburant'!I11-'Indexation Client 2026'!$D$92)*'Indexation Client 2026'!$F$92)) -> -0.242508 | O92: =((('indice Carburant'!J11-'Indexation Client 2026'!$D$92)*'Indexation Client 2026'!$F$92)) -> -0.242508 | P92: =((('indice Carburant'!K11-'Indexation Client 2026'!$D$92)*'Indexation Client 2026'!$F$92)) -> -0.242508 | Q92: =((('indice Carburant'!L11-'Indexation Client 2026'!$D$92)*'Indexation Client 2026'!$F$92)) -> -0.242508 | ... U92: =((('indice Carburant'!P11-'Indexation Client 2026'!$D$92)*'Indexation Client 2026'!$F$92)) -> -0.242508
A93: EXAPAQ | B93: 078 MINOLTA | C93: EXAPAQ | D93: 0.8661 | E93: DIREM du mois M | F93: 0.3 | G93: Sur Km | H93: 280 | J93: =((('indice Carburant'!E11-'Indexation Client 2026'!$D$93)*'Indexation Client 2026'!$F$93)) -> 0.15006 | K93: =((('indice Carburant'!F11-'Indexation Client 2026'!$D$93)*'Indexation Client 2026'!$F$93)) -> 0.15261 | L93: =((('indice Carburant'!G11-'Indexation Client 2026'!$D$93)*'Indexation Client 2026'!$F$93)) -> 0.26736 | M93: =((('indice Carburant'!H11-'Indexation Client 2026'!$D$93)*'Indexation Client 2026'!$F$93)) -> -0.25983 | N93: =((('indice Carburant'!I11-'Indexation Client 2026'!$D$93)*'Indexation Client 2026'!$F$93)) -> -0.25983 | O93: =((('indice Carburant'!J11-'Indexation Client 2026'!$D$93)*'Indexation Client 2026'!$F$93)) -> -0.25983 | P93: =((('indice Carburant'!K11-'Indexation Client 2026'!$D$93)*'Indexation Client 2026'!$F$93)) -> -0.25983 | Q93: =((('indice Carburant'!L11-'Indexation Client 2026'!$D$93)*'Indexation Client 2026'!$F$93)) -> -0.25983 | ... U93: =((('indice Carburant'!P11-'Indexation Client 2026'!$D$93)*'Indexation Client 2026'!$F$93)) -> -0.25983
A94: EXAPAQ | B94: 078_175_076_175_078 | C94: EXAPAQ | D94: 0.8661 | E94: DIREM du mois M | F94: 0.3 | G94: Sur Km | H94: 484 | J94: =((('indice Carburant'!E11-'Indexation Client 2026'!$D$94)*'Indexation Client 2026'!$F$94)) -> 0.15006 | K94: =((('indice Carburant'!F11-'Indexation Client 2026'!$D$94)*'Indexation Client 2026'!$F$94)) -> 0.15261 | L94: =((('indice Carburant'!G11-'Indexation Client 2026'!$D$94)*'Indexation Client 2026'!$F$94)) -> 0.26736 | M94: =((('indice Carburant'!H11-'Indexation Client 2026'!$D$94)*'Indexation Client 2026'!$F$94)) -> -0.25983 | N94: =((('indice Carburant'!I11-'Indexation Client 2026'!$D$94)*'Indexation Client 2026'!$F$94)) -> -0.25983 | O94: =((('indice Carburant'!J11-'Indexation Client 2026'!$D$94)*'Indexation Client 2026'!$F$94)) -> -0.25983 | P94: =((('indice Carburant'!K11-'Indexation Client 2026'!$D$94)*'Indexation Client 2026'!$F$94)) -> -0.25983 | Q94: =((('indice Carburant'!L11-'Indexation Client 2026'!$D$94)*'Indexation Client 2026'!$F$94)) -> -0.25983 | ... U94: =((('indice Carburant'!P11-'Indexation Client 2026'!$D$94)*'Indexation Client 2026'!$F$94)) -> -0.25983
A95: EXAPAQ | B95: 078_Ramasses_078_175_078 | C95: EXAPAQ | D95: 0.8661 | E95: DIREM du mois M | F95: 0.3 | G95: Sur Km | H95: 340 | J95: =((('indice Carburant'!E11-'Indexation Client 2026'!$D$95)*'Indexation Client 2026'!$F$95)) -> 0.15006 | K95: =((('indice Carburant'!F11-'Indexation Client 2026'!$D$95)*'Indexation Client 2026'!$F$95)) -> 0.15261 | L95: =((('indice Carburant'!G11-'Indexation Client 2026'!$D$95)*'Indexation Client 2026'!$F$95)) -> 0.26736 | M95: =((('indice Carburant'!H11-'Indexation Client 2026'!$D$95)*'Indexation Client 2026'!$F$95)) -> -0.25983 | N95: =((('indice Carburant'!I11-'Indexation Client 2026'!$D$95)*'Indexation Client 2026'!$F$95)) -> -0.25983 | O95: =((('indice Carburant'!J11-'Indexation Client 2026'!$D$95)*'Indexation Client 2026'!$F$95)) -> -0.25983 | P95: =((('indice Carburant'!K11-'Indexation Client 2026'!$D$95)*'Indexation Client 2026'!$F$95)) -> -0.25983 | Q95: =((('indice Carburant'!L11-'Indexation Client 2026'!$D$95)*'Indexation Client 2026'!$F$95)) -> -0.25983 | ... U95: =((('indice Carburant'!P11-'Indexation Client 2026'!$D$95)*'Indexation Client 2026'!$F$95)) -> -0.25983
A96: EXAPAQ | B96: Amblainville | C96: EXAPAQ | D96: 0.975 | E96: CNR GNV M-1/100 | F96: 0.26 | G96: Sur Km | H96: 237 | J96: =((('indice Carburant'!D13/100)-'Indexation Client 2026'!$D$96)*'Indexation Client 2026'!$F$96) -> 0.166218 | K96: =((('indice Carburant'!E13/100)-'Indexation Client 2026'!$D$96)*'Indexation Client 2026'!$F$96) -> 0.161486 | L96: =((('indice Carburant'!F13/100)-'Indexation Client 2026'!$D$96)*'Indexation Client 2026'!$F$96) -> 0.208468 | M96: =((('indice Carburant'!G13/100)-'Indexation Client 2026'!$D$96)*'Indexation Client 2026'!$F$96) -> -0.2535 | N96: =((('indice Carburant'!H13/100)-'Indexation Client 2026'!$D$96)*'Indexation Client 2026'!$F$96) -> -0.2535 | O96: =((('indice Carburant'!I13/100)-'Indexation Client 2026'!$D$96)*'Indexation Client 2026'!$F$96) -> -0.2535 | P96: =((('indice Carburant'!J13/100)-'Indexation Client 2026'!$D$96)*'Indexation Client 2026'!$F$96) -> -0.2535 | Q96: =((('indice Carburant'!K13/100)-'Indexation Client 2026'!$D$96)*'Indexation Client 2026'!$F$96) -> -0.2535 | ... U96: =((('indice Carburant'!O13/100)-'Indexation Client 2026'!$D$96)*'Indexation Client 2026'!$F$96) -> -0.2535
A97: EXAPAQ | B97: Vemars | C97: EXAPAQ | D97: 0.975 | E97: CNR GNV M-1/100 | F97: 0.28 | G97: Sur Km | H97: 161 | J97: =((('indice Carburant'!D13/100)-'Indexation Client 2026'!$D$97)*'Indexation Client 2026'!$F$97) -> 0.179004 | K97: =((('indice Carburant'!E13/100)-'Indexation Client 2026'!$D$97)*'Indexation Client 2026'!$F$97) -> 0.173908 | L97: =((('indice Carburant'!F13/100)-'Indexation Client 2026'!$D$97)*'Indexation Client 2026'!$F$97) -> 0.224504 | M97: =((('indice Carburant'!G13/100)-'Indexation Client 2026'!$D$97)*'Indexation Client 2026'!$F$97) -> -0.273 | N97: =((('indice Carburant'!H13/100)-'Indexation Client 2026'!$D$97)*'Indexation Client 2026'!$F$97) -> -0.273 | O97: =((('indice Carburant'!I13/100)-'Indexation Client 2026'!$D$97)*'Indexation Client 2026'!$F$97) -> -0.273 | P97: =((('indice Carburant'!J13/100)-'Indexation Client 2026'!$D$97)*'Indexation Client 2026'!$F$97) -> -0.273 | Q97: =((('indice Carburant'!K13/100)-'Indexation Client 2026'!$D$97)*'Indexation Client 2026'!$F$97) -> -0.273 | ... U97: =((('indice Carburant'!O13/100)-'Indexation Client 2026'!$D$97)*'Indexation Client 2026'!$F$97) -> -0.273
A98: FEDEX AGENCE TREMBLAY | B98: R404 | C98: FEDEX | D98: 183.55 | E98: ???? | F98: 0.1271 | G98: % Pied de facture
A99: FEDEX AGENCE TREMBLAY | B99: R528 | C99: FEDEX | D99: 222.12 | E99: ???? | F99: 0.26 | G99: % Pied de facture
A100: FEDEX AGENCE TREMBLAY | B100: R487 | C100: FEDEX | D100: 222.12 | E100: ???? | F100: 0.26 | G100: % Pied de facture
A101: FEDEX AGENCE TREMBLAY | B101: R488 | C101: FEDEX | D101: 222.12 | E101: ???? | F101: 0.26 | G101: % Pied de facture
...
