Workbook
Name Moteurs: 'CM4'!#REF!

Sheet Liste
A1: Type vehicule | B1: Energie | C1: Désignation | D1: Loyer actuel | E1: TK Global | F1: Tx Pneu €/km | G1: Tx Entretien €/km | H1: CONSO
A2: Porteur SWAP | B2: GO | C2: =+CONCATENATE(A2,B2) -> Porteur SWAPGO | D2: 2500 | E2: =+F2+G2 -> 0.07 | F2: 0.035 | G2: 0.035 | H2: 30
A3: Tracteur | B3: GO | C3: =+CONCATENATE(A3,B3) -> Tracteur GO | D3: 2300 | E3: =+F3+G3 -> 0.05 | F3: 0.025 | G3: 0.025 | H3: 28
A4: Porteur SWAP | B4: GNC | C4: =+CONCATENATE(A4,B4) -> Porteur SWAPGNC | D4: 3000 | E4: =+F4+G4 -> 0.08 | F4: 0.035 | G4: 0.045 | H4: 33
A5: Tracteur | B5: GNC | C5: =+CONCATENATE(A5,B5) -> Tracteur GNC | D5: 2500 | E5: =+F5+G5 -> 0.06 | F5: 0.025 | G5: 0.035 | H5: 30.5
A7: Aérienne Bachée | C7: =+CONCATENATE(A7,B7) -> Aérienne Bachée | D7: 1200 | E7: =+F7+G7 -> 0.05 | F7: 0.025 | G7: 0.025
A8: Aérienne Classique | C8: =+CONCATENATE(A8,B8) -> Aérienne Classique | D8: 1200 | E8: =+F8+G8 -> 0.05 | F8: 0.025 | G8: 0.025
A9: Aérienne Frigo | C9: =+CONCATENATE(A9,B9) -> Aérienne Frigo | D9: 1400 | E9: =+F9+G9 -> 0.05 | F9: 0.025 | G9: 0.025
A10: Aérienne Méga | C10: =+CONCATENATE(A10,B10) -> Aérienne Méga | D10: 1400 | E10: =+F10+G10 -> 0.05 | F10: 0.025 | G10: 0.025
A11: SR Classique | C11: =+CONCATENATE(A11,B11) -> SR Classique | D11: 1000 | E11: =+F11+G11 -> 0.05 | F11: 0.025 | G11: 0.025
A12: SR Frigo | C12: =+CONCATENATE(A12,B12) -> SR Frigo | D12: 1400 | E12: =+F12+G12 -> 0.05 | F12: 0.025 | G12: 0.025
A13: SR Méga & Frigo | C13: =+CONCATENATE(A13,B13) -> SR Méga & Frigo | D13: 1400 | E13: =+F13+G13 -> 0.05 | F13: 0.025 | G13: 0.025
A14: SR Porte Conteneur | C14: =+CONCATENATE(A14,B14) -> SR Porte Conteneur | D14: 400 | E14: =+F14+G14 -> 0.07 | F14: 0.035 | G14: 0.035
A15: Remorque SWAP | C15: =+CONCATENATE(A15,B15) -> Remorque SWAP | D15: 400 | E15: =+F15+G15 -> 0.07 | F15: 0.035 | G15: 0.035
A16: AUCUNE | C16: =+CONCATENATE(A16,B16) -> AUCUNE | D16: 0
A17: Loyer = Loyer + Assurance + Geoloc
A18: Tirpalette | B18: 55.28 | C18: Mois
A20: Taux horaire
A21: SPL | B21: 1000 | C21: € / hebdo
A22: CM | B22: 1100 | C22: € / Hebdo
A24: OUI
A25: NON

Sheet Sommaire
A1: ETUDES RENTABILITE : AVRIL 2025
K5: Liens | L5: % Marge
A6: Tournée | B6: Client | C6: Conducteur 1 | D6: Conducteur 2 | E6: Conducteur 3 | F6: Lignes | G6: Liens | H6: % Marge | J6: CUMUL CM | K6: CUMUL CM | L6: ='Cumul CM'!D48 -> 0.17798099
A7: SPL7 | B7: STG | C7: ='SPL7'!B7 -> AMRAOUI | D7: ='SPL7'!C7 -> TURQUETIL Y. | F7: CREPY + SCAPNOR + ADM | G7: SPL7'!A1 | H7: ='SPL7'!D48 -> -0.13886197
A8: SPL75 | B8: GLS | C8: ='SPL75'!B7 -> JADE ZINE | F8: Trappes- Coudray | G8: SPL75'!A1 | H8: ='SPL75'!D48 -> -0.081202868 | J8: CUMUL SPL | K8: CUMUL SPL | L8: ='CUMUL SPL'!D48 -> 0.21601596
A9: SPL44 | B9: DHL / CHRONOPOST HNI | C9: ='SPL44'!B7 -> FOFANA M. | F9: CAEN - 23R13 | G9: SPL44'!A1 | H9: ='SPL44'!D48 -> -0.077949229
A10: SPL76 | B10: GLS | C10: ='SPL76'!B7 -> EL MOUMNI | F10: Trappes - Coudray - Gennevilliers | G10: SPL76'!A1 | H10: ='SPL76'!D48 -> -0.036739297
A11: CM42 | B11: UPS | C11: ='CM42'!B7 -> MADANI | F11: Lesquin | G11: CM42'!A1 | H11: ='CM42'!D48 -> -0.028390254
A12: CM24 | B12: UPS | C12: ='CM24'!B7 -> MOREL | F12: Tours | G12: CM24'!A1 | H12: ='CM24'!D48 -> -0.012645373
A13: CM48 | B13: UPS | C13: ='CM48'!B7 -> BOUTCHIHI | F13: Le Mans - Angers | H13: ='CM48'!D48 -> -0.0022539431
A14: CM27 | B14: CHRONOPOST | C14: ='CM27'!B7 -> JARDANI | F14: Amiens - Chilly | G14: CM27'!A1 | H14: ='CM27'!D48 -> -0.0005852447
A15: CM4 | B15: DACHSER CERGY / COLISSIMO | C15: ='CM4'!B7 -> VITALI | F15: Parisienne / IDFN-LTH-017-CM | G15: CM4'!A1 | H15: ='CM4'!D48 -> 0.033649267
A16: CM44 | B16: DACHSER CERGY / COLISSIMO | C16: ='CM44'!B7 -> MALLE Karim | D16: ='CM44'!C7 -> PIEL Flavien | F16: NIORT / IDFN-LTH-014-CM | G16: CM44'!A1 | H16: ='CM44'!D49 -> 0.044856021
A17: CM23 | B17: CHRONOPOST RESEAU | C17: ='CM23'!B7 -> ANSEUR | F17: Arras - Rouen | G17: CM23'!A1 | H17: ='CM23'!D48 -> 0.056751615
A18: SPL73 | B18: STG | C18: ='SPL73'!B7 -> BURLACU | F18: Scapnor Matin | G18: SPL73'!A1 | H18: ='SPL73'!D48 -> 0.065171273
A19: CM5 | B19: DACHSER VILLEPARISIS / COLISSIMO | C19: ='CM5'!B7 -> KONTE | D19: ='CM5'!C7 -> DAJ Victor | E19: ='CM5'!D7 -> ABDAL | F19: T962 / LA VERRIE / IDFN-LTH-004-CM | G19: CM5'!A1 | H19: ='CM5'!D49 -> 0.07338738
A20: SPL45 | B20: DHL | C20: ='SPL45'!B7 -> TATAR M. | F20: Tours | G20: SPL45'!A1 | H20: ='SPL45'!D48 -> 0.074034289
A21: SPL54 | B21: DHL - CHRONOPOST | C21: ='SPL54'!B7 -> JEBALI | F21: Troyes | G21: SPL54'!A1 | H21: ='SPL54'!D48 -> 0.076281167
A22: CM26 | B22: CHRONOPOST | C22: ='CM26'!B7 -> BENALI | F22: ARRAS - Aulnay | G22: CM26'!A1 | H22: ='CM26'!D48 -> 0.078860025
A23: SPL22 | B23: STG | C23: ='SPL22'!B7 -> TOUHAMI | F23: Barbery | G23: SPL22'!A1 | H23: ='SPL22'!D48 -> 0.08536904
A24: CM60 | B24: COLISSIMO | C24: ='CM60'!B7 -> MOROAINU ION | F24: Creil | G24: CM60'!A1 | H24: ='CM60'!D48 -> 0.092716275
A25: SPL8 | B25: GLS | C25: ='SPL8'!B7 -> PARISOT | F25: Coudray - Troyes | G25: SPL8'!A1 | H25: ='SPL8'!D48 -> 0.10224958
A26: SPL74 | B26: VIAPOSTE - CHRONOPOST | C26: ='SPL74'!B7 -> OLIMPIO (AT) | D26: ='SPL74'!C7 -> BENDRIF | F26: Lot 163 | G26: SPL74'!A1 | H26: ='SPL74'!D48 -> 0.10284571
A27: SPL53 | B27: DHL | C27: ='SPL53'!B7 -> DIFALLAH | F27: REIMS | G27: SPL53'!A1 | H27: ='SPL53'!D48 -> 0.11111696
A28: SPL13 | B28: CEVA / VIAPOSTE | C28: ='SPL13'!B7 -> BODEA | D28: ='SPL13'!C7 -> VIVIENS | F28: Kiabi + Lot 170 | G28: SPL13'!A1 | H28: ='SPL13'!D48 -> 0.11801566
A29: CM61 | B29: PARC NANTERRE | C29: ='CM61'!B7 -> ALI MOHAMED | G29: CM61'!A1 | H29: ='CM61'!D48 -> 0.12323997
A30: CM53 | B30: DACHSER CERGY / COLISSIMO | C30: ='CM53'!B7 -> HAMMADI Redha | D30: ='CM53'!C7 -> TAGMI Karim | F30: NANTES / IDFN-LTH-017-CM | G30: CM53'!A1 | H30: ='CM53'!D49 -> 0.1238652
A31: SPL33 | B31: STG | C31: ='SPL33'!B7 -> MOREIRA | F31: SU Nanteuil | G31: SPL33'!A1 | H31: ='SPL33'!D48 -> 0.12679643
A32: CM34 | B32: CHRONOPOST | C32: ='CM34'!B7 -> Faveur | F32: Aulnay - Orleans | G32: CM34'!A1 | H32: ='CM34'!D48 -> 0.13142815
A33: CM29 | B33: CHRONOPOST | C33: ='CM29'!B7 -> BOUGHEZAL | F33: Arras - Seclin | G33: CM29'!A1 | H33: ='CM29'!D48 -> 0.13988954
A34: CM6 | B34: DACHSER CERGY / Chronopost Reseau | C34: ='CM6'!B7 -> TATAR F. | F34: Orleans / Beaugrenelle | G34: CM6'!A1 | H34: ='CM6'!D48 -> 0.14442794
A35: CM21 | B35: TAB | C35: ='CM21'!B7 -> BAJURA | F35: TAB : Petite Caisse | G35: CM21'!A1 | H35: ='CM21'!D48 -> 0.14879782
A36: SPL77 | B36: GLS | C36: ='SPL77'!B7 -> KONE | F36: Coudray - Gennevilliers | G36: SPL77'!A1 | H36: ='SPL77'!D48 -> 0.15483819
A37: SPL36 | B37: VIAPOSTE | C37: ='SPL36'!B7 -> SAGAL | D37: ='SPL36'!C7 -> LATIFA | F37: LOT163-170 | G37: SPL36'!A1 | H37: ='SPL36'!D48 -> 0.15509409
A38: SPL14 | B38: VIAPOSTE / CHRONOPOST | C38: ='SPL14'!B7 -> DIALLO O. | D38: ='SPL14'!C7 -> KAMARA | F38: Lot163 - Dyson | G38: SPL14'!A1 | H38: ='SPL14'!D49 -> 0.1618651
A39: SPL9 | B39: FEDEX GB4 | C39: ='SPL9'!B7 -> WILSON | F39: GB4 | G39: SPL9'!A1 | H39: ='SPL9'!D48 -> 0.16648161
A40: SPL62 | B40: MONDIAL RELAY - UPS | C40: ='SPL62'!B7 -> CISSE M. | F40: Oscaro - Fontenay tressigny | G40: SPL62'!A1 | H40: ='SPL62'!D48 -> 0.16662613
A41: CM14 | B41: CHRONOPOST RESEAU / COLISSIMO | C41: ='CM14'!B7 -> BEZDIGA | D41: ='CM14'!C7 -> ANDRY | F41: Bourges / IDFN-DOT-00A-CM | G41: CM14'!A1 | H41: ='CM14'!D48 -> 0.16789322
A42: SPL72 | B42: DACHSER PANTIN | C42: ='SPL72'!B7 -> Hanzi | F42: PERNOD | G42: SPL72'!A1 | H42: ='SPL72'!D48 -> 0.16894883
A43: SPL51 | B43: TAB | C43: ='SPL51'!B7 -> BAHYAYA | F43: TAB : Grande Caisse | G43: SPL51'!A1 | H43: ='SPL51'!D48 -> 0.16996499
A44: SPL30 | B44: VIAPOSTE | C44: ='SPL30'!B7 -> GUEYE | F44: LOT 163 | G44: SPL30'!A1 | H44: ='SPL30'!D48 -> 0.19621606
A45: SPL16 | B45: VIAPOSTE / DHL | C45: ='SPL16'!B7 -> HAMID | D45: ='SPL16'!C7 -> BORGES | F45: Lot 164 - Creteil | G45: SPL16'!A1 | H45: ='SPL16'!D49 -> 0.20062399
A46: SPL67 | B46: DHL - FEDEX | C46: ='SPL67'!B7 -> CIMPEAN | F46: Harfleur | G46: SPL67'!A1 | H46: ='SPL67'!D48 -> 0.21615125
A47: CM15 | B47: UPS / CHRONOPOST | C47: ='CM15'!B7 -> VIOREL | F47: PA07 - Beaugrenelle | G47: CM15'!A1 | H47: ='CM15'!D48 -> 0.2204442
A48: SPL69 | B48: VIAPOSTE | C48: ='SPL69'!B7 -> COSTA | D48: ='SPL69'!C7 -> DIABATE | F48: LOT 163 | G48: SPL69'!A1 | H48: ='SPL69'!D48 -> 0.22250268
A49: CM8 | B49: DACHSER VILLEPARISIS | C49: ='CM8'!B7 -> AZZOUZ Nordine | D49: ='CM8'!C7 -> AZZOUZ Mustapha | F49: T962 / UBERHERRN | G49: CM8'!A1 | H49: ='CM8'!D48 -> 0.22469447
A50: CM37 | B50: CHRONOPOST | C50: ='CM37'!B7 -> HELLOU | F50: MAD Chilly | G50: CM37'!A1 | H50: ='CM37'!D48 -> 0.23442549
A51: SPL47 | B51: CHRONOPOST - FEDEX | C51: ='SPL47'!B7 -> CHLIBET | F51: Meung sur loire - Elancourt | G51: SPL47'!A1 | H51: ='SPL47'!D48 -> 0.24059177
A52: SPL27 | B52: VIAPOSTE / UPS | C52: ='SPL27'!B7 -> AGOUA | D52: ='SPL27'!C7 -> SINGH | F52: LOT 168/170 + Amazon | G52: SPL27'!A1 | H52: ='SPL27'!D48 -> 0.24624761
A53: SPL20 | B53: VIAPOSTE | C53: ='SPL20'!B7 -> MBEKA R. | D53: ='SPL20'!C7 -> QUINOL | F53: LOTS 164 | G53: SPL20'!A1 | H53: ='SPL20'!D48 -> 0.25421334
A54: CM25 | B54: CHRONOPOST RESEAU | C54: ='CM25'!B7 -> WAGNER | F54: Amiens | G54: CM25'!A1 | H54: ='CM25'!D48 -> 0.26162983
A55: CM9 | B55: DACHSER VILLEPARISIS / Chronopost | C55: ='CM9'!B7 -> MIC Marius | D55: ='CM9'!C7 -> OUAHABI Mourad | F55: T964 / DIJON / Chrono 27860 | G55: CM9'!A1 | H55: ='CM9'!D48 -> 0.26593398
A56: SPL25 | B56: DHL / CHRONOPOST | C56: ='SPL25'!B7 -> CRISAN G. | F56: LE mans - Orléans | G56: SPL25'!A1 | H56: ='SPL25'!D48 -> 0.28579668
A57: CM59 | B57: CHRONOPOST | C57: ='CM59'!B7 -> MOROAINU Mihail | F57: Montataire - Aulnay | G57: CM59'!A1 | H57: ='CM59'!D48 -> 0.29274224
A58: SPL59 | B58: UPS - DGF - SCHENKER | C58: ='SPL59'!B7 -> PHILIBERT | D58: ='SPL59'!C7 -> GONCALVES Kama | F58: Airbus - La ferté bernard | G58: SPL59'!A1 | H58: ='SPL59'!D48 -> 0.30262597
A59: CM39 | B59: CHRONOPOST | C59: ='CM39'!B7 -> ROMAN Alexandru | F59: Boulevard Ney | G59: CM39'!A1 | H59: ='CM39'!D48 -> 0.3057336
A60: SPL26 | B60: FEDEX / CEVA / CHRONOPOST | C60: ='SPL26'!B7 -> LEKRICHI | D60: ='SPL26'!C7 -> AZZIZ CHEMLAL | F60: 23R09 - Kiabi | G60: SPL26'!A1 | H60: ='SPL26'!D48 -> 0.3110691
A61: SPL18 | B61: DHL / VIAPOSTE | C61: ='SPL18'!B7 -> ROMUALD | D61: ='SPL18'!C7 -> KILIAN | F61: 9877A - Lots 170 et 164 | G61: SPL18'!A1 | H61: ='SPL18'!D49 -> 0.31619774
A62: CM19 | B62: CHRONOPOST RESEAU | C62: ='CM19'!B7 -> TAHLA | D62: ='CM19'!C7 -> NAILI | F62: Annecy | G62: CM19'!A1 | H62: ='CM19'!D49 -> 0.3456946
A63: SPL37 | B63: DHL / FEDEX | C63: ='SPL37'!B7 -> KAMAGATE | F63: Orléans / Marly | G63: SPL37'!A1 | H63: ='SPL37'!D48 -> 0.34881411
A64: SPL17 | B64: VIAPOSTE | C64: ='SPL17'!B7 -> PECCATUS | D64: ='SPL17'!C7 -> Moreira Tavares | F64: Lot 163 | G64: SPL17'!A1 | H64: ='SPL17'!D48 -> 0.35481603
A65: SPL34 | B65: VIAPOSTE | C65: ='SPL34'!B7 -> BEN SALEM | D65: ='SPL34'!C7 -> COADA TOADER | F65: LOT164 - 170 - Liaison D | G65: SPL34'!A1 | H65: ='SPL34'!D48 -> 0.35666685
A66: SPL56 | B66: VIAPOSTE | C66: ='SPL56'!B7 -> DJAFFAR | D66: ='SPL56'!C7 -> MOUSSA TRAORE | F66: LOT 164 -168 | G66: SPL56'!A1 | H66: ='SPL56'!D49 -> 0.35745639
A67: CM7 | B67: COLISSIMO | C67: ='CM7'!B7 -> JAMES Fabrice | F67: Zalando Vatry X2 | G67: CM7'!A1 | H67: ='CM7'!D48 -> 0.36197111
A68: SPL70 | B68: VIAPOSTE | C68: ='SPL70'!B7 -> GLISSANT | F68: lot 163 | G68: SPL70'!A1 | H68: ='SPL70'!D48 -> 0.36795776
A69: SPL23 | B69: FEDEX / CHRONOPOST / UPS/ DHL | C69: ='SPL23'!B7 -> TROUDI | D69: ='SPL23'!C7 -> DIOP ASSANE | F69: Creteil / 23R68 | G69: SPL23'!A1 | H69: ='SPL23'!D48 -> 0.37621397
A70: CM10 | B70: DACHSER VILLEPARISIS / Chronopost | C70: ='CM10'!B7 -> BEZZAOUYA | F70: ROUEN / Chrono 29096 | G70: CM10'!A1 | H70: ='CM10'!D48 -> 0.39421541
A71: CM41 | B71: CHRONOPOST | C71: ='CM41'!B7 -> LAMBERT | F71: BEAUGRENELLE | G71: CM41'!A1 | H71: ='CM41'!D48 -> 0.3978527
A72: SPL68 | B72: VIAPOSTE - UPS | C72: ='SPL68'!B7 -> DIALLO Maliki | D72: ='SPL68'!C7 -> MOUSSA FALL | F72: LOT 164-170-PA95 | G72: SPL68'!A1 | H72: ='SPL68'!D49 -> 0.40454175

Sheet CM4
A1: FICHE DE RENTABILITE
A3: DONNEES EXPLOITATION
B4: Immatriculation | D4: Conso au 100 (Moyenne) | F4: Semaine | G4: S15
A5: Tracteur (s) | B5: FV-146-XG | D5: 37.58
A6: Semi (s) | B6: Remorque | D6: 0.019
A7: Conducteurs | B7: VITALI
A8: AMPLITUDE Hebdo | B8: 67.45
A9: TDS Hebdo | B9: 49.69
B10: KM Hebdo | G10: Hotel (semaine)
B11: 2098 | G11: 0
A12: Autoroute / jour : | B12: 0 | F12: SPL | G12: CM
E13: €/ Hebdo | F13: 1000 | G13: 1100
A14: Détails CA
A15: Référence prestations | B15: Fréquence | C15: Montant unitaire | D15: Quantité | E15: Total Hors IGO | F15: Indexation | G15: Montant Total
A16: DACHSER Cergy : Parisienne | B16: Lundi => Vendredi | C16: 360.2 | D16: 5 | E16: =C16*D16 -> 1801 | F16: -0.0444 | G16: =(E16*F16)+E16 -> 1721.0356
A17: COLISSIMO : IDFN-LTH-017-CM | B17: Mardi => Samedi | C17: 2.5021 | D17: =92*5 -> 460 | E17: =C17*D17 -> 1150.966 | F17: 0 | G17: =(E17*F17)+E17 -> 1150.966
A18: WE : FEDEX GB4 (Dimanche) | B18: Dimanche | C18: 335 | D18: 1 | E18: =C18*D18 -> 335 | F18: 0 | G18: =(E18*F18)+E18 -> 335
E19: =C19*D19 -> 0 | G19: =(E19*F19)+E19 -> 0
E20: =C20*D20 -> 0 | G20: =(E20*F20)+E20 -> 0
E21: =C21*D21 -> 0 | G21: =(E21*F21)+E21 -> 0
E22: =C22*D22 -> 0 | G22: =(E22*F22)+E22 -> 0
A24: CM4 | B24: CA DE LA LIGNE | F24: =SUM(G16:G22) -> 3207.0016
A25: SOMMAIRE
A27: Coûts de la Ligne
B28: Type | C28: unité | D28: Cout Semaine
A29: Moteur | B29: Porteur SWAPGO | C29: =IFERROR(VLOOKUP(B29,Liste!C1:D5,2,FALSE),"") -> 2500 | D29: =IFERROR(C29/4.33,0) -> 577.36721
A30: Semi (1) | B30: Remorque SWAP | C30: =IFERROR(VLOOKUP(B30,Liste!$C$7:$D$15,2,FALSE),"") -> 400 | D30: =IFERROR(C30/4.33,0) -> 92.378753
A31: Semi (2) | B31: AUCUNE | C31: =IFERROR(VLOOKUP(B31,Liste!$C$7:$D$15,2,FALSE),"") | D31: =IFERROR(C31/4.33,0) -> 0
A32: Semi (3) | B32: AUCUNE | C32: =IFERROR(VLOOKUP(B32,Liste!$C$7:$D$15,2,FALSE),"") | D32: =IFERROR(C32/4.33,0) -> 0
A33: Semi (4) | B33: AUCUNE | C33: =IFERROR(VLOOKUP(B33,Liste!$C$7:$D$15,2,FALSE),"") | D33: =IFERROR(C33/4.33,0) -> 0
A34: Carburant | B34: GO | C34: 1.3554 | D34: =(B11*D5/100)*C34 -> 1068.6359
A35: Carburant | B35: GNC | C35: 0 | D35: =(D5*B11/100)*C35 -> 0
A36: AD Blue | C36: 0.4309 | D36: =(D6*B11)*C36 -> 17.176536
A37: Fuel | C37: 1.1225
A38: Casse / Pneumatique / Lavage ( hors entretien) | C38: 0.04 | D38: =C38*B11 -> 83.92
A39: Autoroute | B39: =B12 -> 0 | C39: 5 | D39: =C39*B39 -> 0
A40: Salaires | B40: CM | C40: 1 | D40: 1259.61
A41: Frais Hotel | D41: =G11 -> 0
A42: Tirpalette | B42: NON | C42: =IF(B42=Liste!A24,Liste!B18,0) -> 0 | D42: =C42/4.33 -> 0
A43: Sous-Traitance | C43: 0 | D43: 0
C45: TOTAL COUT | D45: =SUM(D29:D43) -> 3099.0883
C46: Marge Exploitation | D46: =F24-D45 -> 107.91325
C48: % Marge | D48: =D46/F24 -> 0.033649267

Sheet CM6
A1: FICHE DE RENTABILITE
A3: DONNEES EXPLOITATION
B4: Immatriculation | D4: Conso au 100 (Moyenne) | F4: Semaine | G4: S15
A5: Tracteur (s) | B5: GY-247-BQ | D5: 23.82
A6: Semi (s) | B6: Remorque | D6: 0.019
A7: Conducteurs | B7: TATAR F.
A8: AMPLITUDE Hebdo | B8: 57.07
A9: TDS Hebdo | B9: 44.82
B10: KM Hebdo | G10: Hotel (semaine)
B11: 2633 | G11: 0
A12: Autoroute / jour : | B12: 34.16 | C12: (non Facturé) | F12: SPL | G12: CM
E13: €/ Hebdo | F13: 1000 | G13: 1100
A14: Détails CA
A15: Référence prestations | B15: Fréquence | C15: Montant unitaire | D15: Quantité | E15: Total Hors IGO | F15: Indexation | G15: Montant Total
A16: DACHSER CERGY : Orléans | B16: Lundi => Vendredi | C16: 483.3 | D16: 5 | E16: =C16*D16 -> 2416.5 | F16: -0.0392 | G16: =(E16*F16)+E16 -> 2321.7732
A17: CHRONOPOST : 31010 | B17: Mardi => Samedi | C17: 283 | D17: 5 | E17: =C17*D17 -> 1415 | F17: =13.44*5 -> 67.2 | G17: =(E17+F17) -> 1482.2 | I17: Indexation Gaz sur porteur GO
A18: Tourne sur 5 Jours | E18: =C18*D18 -> 0 | G18: =(E18*F18)+E18 -> 0
E19: =C19*D19 -> 0 | G19: =(E19*F19)+E19 -> 0
E20: =C20*D20 -> 0 | G20: =(E20*F20)+E20 -> 0
E21: =C21*D21 -> 0 | G21: =(E21*F21)+E21 -> 0
E22: =C22*D22 -> 0 | G22: =(E22*F22)+E22 -> 0
A24: CM6 | B24: CA DE LA LIGNE | F24: =SUM(G16:G22) -> 3803.9732
A25: SOMMAIRE
A27: Coûts de la Ligne
B28: Type | C28: unité | D28: Cout Semaine
A29: Moteur | B29: Porteur SWAPGO | C29: =IFERROR(VLOOKUP(B29,Liste!C1:D5,2,FALSE),"") -> 2500 | D29: =IFERROR(C29/4.33,0) -> 577.36721
A30: Semi (1) | B30: Remorque SWAP | C30: =IFERROR(VLOOKUP(B30,Liste!$C$7:$D$15,2,FALSE),"") -> 400 | D30: =IFERROR(C30/4.33,0) -> 92.378753
A31: Semi (2) | B31: AUCUNE | C31: =IFERROR(VLOOKUP(B31,Liste!$C$7:$D$15,2,FALSE),"") | D31: =IFERROR(C31/4.33,0) -> 0
A32: Semi (3) | B32: AUCUNE | C32: =IFERROR(VLOOKUP(B32,Liste!$C$7:$D$15,2,FALSE),"") | D32: =IFERROR(C32/4.33,0) -> 0
A33: Semi (4) | B33: AUCUNE | C33: =IFERROR(VLOOKUP(B33,Liste!$C$7:$D$15,2,FALSE),"") | D33: =IFERROR(C33/4.33,0) -> 0
A34: Carburant | B34: GO | C34: 1.3554 | D34: =(B11*D5/100)*C34 -> 850.08059
A35: Carburant | B35: GNC | C35: 0 | D35: =(D5*B11/100)*C35 -> 0
A36: AD Blue | C36: 0.4309 | D36: =(D6*B11)*C36 -> 21.556634
A37: Fuel | C37: 1.1225
A38: Casse / Pneumatique / Lavage ( hors entretien) | C38: 0.04 | D38: =C38*B11 -> 105.32
A39: Autoroute | B39: =B12 -> 34.16 | C39: 5 | D39: =C39*B39 -> 170.8
A40: Salaires | B40: CM | C40: 1 | D40: 1437.07
A41: Frais Hotel | D41: =G11 -> 0
A42: Tirpalette | B42: NON | C42: =IF(B42=Liste!A24,Liste!B18,0) -> 0 | D42: =C42/4.33 -> 0
A43: Sous-Traitance | C43: 0 | D43: 0
C45: TOTAL COUT | D45: =SUM(D29:D43) -> 3254.5732
C46: Marge Exploitation | D46: =F24-D45 -> 549.40002
C48: % Marge | D48: =D46/F24 -> 0.14442794

Sheet CM8
A1: FICHE DE RENTABILITE
A3: DONNEES EXPLOITATION
B4: Immatriculation | D4: Conso au 100 (Moyenne) | F4: Semaine | G4: S16
A5: Tracteur (s) | B5: GX-734-TC | D5: 28.45
A6: Semi (s) | B6: Remorque | D6: 0.019
A7: Conducteurs | B7: AZZOUZ Nordine | C7: AZZOUZ Mustapha
A8: AMPLITUDE Hebdo | B8: 38.84 | C8: 65.47
A9: TDS Hebdo | B9: 32.79 | C9: 46.84
B10: KM Hebdo | G10: Hotel (semaine)
B11: 4328 | G11: 0
A12: Autoroute / jour : | B12: 164 | C12: 152.69 | F12: SPL | G12: CM
E13: €/ Hebdo | F13: 1000 | G13: 1100
A14: Détails CA
A15: Référence prestations | B15: Fréquence | C15: Montant unitaire | D15: Quantité | E15: Total Hors IGO | F15: Indexation | G15: Montant Total
A16: DACHSER Villeparisis : T962 | B16: Lundi => Vendredi | C16: 367 | D16: 5 | E16: =C16*D16 -> 1835 | F16: 0.0729 | G16: =(E16*F16)+E16 -> 1968.7715
A17: DACHSER Villeparisis : Uberherrn | B17: Lundi => Vendredi | C17: 907.69 | D17: 5 | E17: =C17*D17 -> 4538.45 | F17: 0.1072 | G17: =((E17-(C12*5))*F17)+E17 -> 4943.13
E18: =C18*D18 -> 0 | G18: =(E18*F18)+E18 -> 0
A19: Tourne sur 5 Jours | E19: =C19*D19 -> 0 | G19: =(E19*F19)+E19 -> 0
E20: =C20*D20 -> 0 | G20: =(E20*F20)+E20 -> 0
E21: =C21*D21 -> 0 | G21: =(E21*F21)+E21 -> 0
E22: =C22*D22 -> 0 | G22: =(E22*F22)+E22 -> 0
A24: CM8 | B24: CA DE LA LIGNE | F24: =SUM(G16:G22) -> 6911.9015
A25: SOMMAIRE
A27: Coûts de la Ligne
B28: Type | C28: unité | D28: Cout Semaine
A29: Moteur | B29: Porteur SWAPGO | C29: =IFERROR(VLOOKUP(B29,Liste!C1:D5,2,FALSE),"") -> 2500 | D29: =IFERROR(C29/4.33,0) -> 577.36721
A30: Semi (1) | B30: Remorque SWAP | C30: =IFERROR(VLOOKUP(B30,Liste!$C$7:$D$15,2,FALSE),"") -> 400 | D30: =IFERROR(C30/4.33,0) -> 92.378753
A31: Semi (2) | B31: AUCUNE | C31: =IFERROR(VLOOKUP(B31,Liste!$C$7:$D$15,2,FALSE),"") | D31: =IFERROR(C31/4.33,0) -> 0
A32: Semi (3) | B32: AUCUNE | C32: =IFERROR(VLOOKUP(B32,Liste!$C$7:$D$15,2,FALSE),"") | D32: =IFERROR(C32/4.33,0) -> 0
A33: Semi (4) | B33: AUCUNE | C33: =IFERROR(VLOOKUP(B33,Liste!$C$7:$D$15,2,FALSE),"") | D33: =IFERROR(C33/4.33,0) -> 0
A34: Carburant | B34: GO | C34: 1.3554 | D34: =(B11*D5/100)*C34 -> 1668.9257
A35: Carburant | B35: GNC | C35: 0 | D35: =(D5*B11/100)*C35 -> 0
A36: AD Blue | C36: 0.4309 | D36: =(D6*B11)*C36 -> 35.433769
A37: Fuel | C37: 1.1225
A38: Casse / Pneumatique / Lavage ( hors entretien) | C38: 0.04 | D38: =C38*B11 -> 173.12
A39: Autoroute | B39: =B12 -> 164 | C39: 5 | D39: =C39*B39 -> 820
A40: Salaires | B40: CM | C40: 2 | D40: =1016.6+975.01 -> 1991.61
A41: Frais Hotel | D41: =G11 -> 0
A42: Tirpalette | B42: NON | C42: =IF(B42=Liste!A24,Liste!B18,0) -> 0 | D42: =C42/4.33 -> 0
A43: Sous-Traitance | C43: 0 | D43: 0
C45: TOTAL COUT | D45: =SUM(D29:D43) -> 5358.8354
C46: Marge Exploitation | D46: =F24-D45 -> 1553.0661
C48: % Marge | D48: =D46/F24 -> 0.22469447

Sheet CM9
A1: FICHE DE RENTABILITE
A3: DONNEES EXPLOITATION
B4: Immatriculation | D4: Conso au 100 (Moyenne) | F4: Semaine | G4: S16
A5: Tracteur (s) | B5: GX-202-QC | D5: 26.88
A6: Semi (s) | B6: Remorque | D6: 0.019
A7: Conducteurs | B7: MIC Marius | C7: OUAHABI Mourad
A8: AMPLITUDE Hebdo | B8: 49.09 | C8: 52.24
A9: TDS Hebdo | B9: 37.59 | C9: 47.2
B10: KM Hebdo | G10: Hotel (semaine)
B11: =879+3656 -> 4535 | G11: 0
A12: Autoroute / jour : | B12: 127.67 | C12: 102.99 | F12: SPL | G12: CM
E13: €/ Hebdo | F13: 1000 | G13: 1100
A14: Détails CA
A15: Référence prestations | B15: Fréquence | C15: Montant unitaire | D15: Quantité | E15: Total Hors IGO | F15: Indexation | G15: Montant Total
A16: DACHSER Villeparisis : T964 | B16: Lundi => Vendredi | C16: 367 | D16: 5 | E16: =C16*D16 -> 1835 | F16: 0.0729 | G16: =(E16*F16)+E16 -> 1968.7715
A17: DACHSER Villeparisis : Dijon | B17: Lundi => Vendredi | C17: 854.89 | D17: 5 | E17: =C17*D17 -> 4274.45 | F17: 0.1082 | G17: =((E17-(C12*5))*F17)+E17 -> 4681.2279
A18: CHRONOPOST : 27860 | B18: Lundi | C18: 300 | D18: 1 | E18: =C18*D18 -> 300 | F18: =80*0.2922 -> 23.376 | G18: =(E18+F18) -> 323.376
E19: =C19*D19 -> 0 | G19: =(E19*F19)+E19 -> 0
A20: Tourne sur 5 Jours | E20: =C20*D20 -> 0 | G20: =(E20*F20)+E20 -> 0
E21: =C21*D21 -> 0 | G21: =(E21*F21)+E21 -> 0
E22: =C22*D22 -> 0 | G22: =(E22*F22)+E22 -> 0
A24: CM9 | B24: CA DE LA LIGNE | F24: =SUM(G16:G22) -> 6973.3754
A25: SOMMAIRE
A27: Coûts de la Ligne
B28: Type | C28: unité | D28: Cout Semaine
A29: Moteur | B29: Porteur SWAPGO | C29: =IFERROR(VLOOKUP(B29,Liste!C1:D5,2,FALSE),"") -> 2500 | D29: =IFERROR(C29/4.33,0) -> 577.36721
A30: Semi (1) | B30: Remorque SWAP | C30: =IFERROR(VLOOKUP(B30,Liste!$C$7:$D$15,2,FALSE),"") -> 400 | D30: =IFERROR(C30/4.33,0) -> 92.378753
A31: Semi (2) | B31: AUCUNE | C31: =IFERROR(VLOOKUP(B31,Liste!$C$7:$D$15,2,FALSE),"") | D31: =IFERROR(C31/4.33,0) -> 0
A32: Semi (3) | B32: AUCUNE | C32: =IFERROR(VLOOKUP(B32,Liste!$C$7:$D$15,2,FALSE),"") | D32: =IFERROR(C32/4.33,0) -> 0
A33: Semi (4) | B33: AUCUNE | C33: =IFERROR(VLOOKUP(B33,Liste!$C$7:$D$15,2,FALSE),"") | D33: =IFERROR(C33/4.33,0) -> 0
A34: Carburant | B34: GO | C34: 1.3554 | D34: =(B11*D5/100)*C34 -> 1652.2434
A35: Carburant | B35: GNC | C35: 0 | D35: =(D5*B11/100)*C35 -> 0
A36: AD Blue | C36: 0.4309 | D36: =(D6*B11)*C36 -> 37.128498
A37: Fuel | C37: 1.1225
A38: Casse / Pneumatique / Lavage ( hors entretien) | C38: 0.04 | D38: =C38*B11 -> 181.4
A39: Autoroute | B39: =B12 -> 127.67 | C39: 5 | D39: =C39*B39 -> 638.35
A40: Salaires | B40: CM | C40: 2 | D40: =791.12+1148.93 -> 1940.05
A41: Frais Hotel | D41: =G11 -> 0
A42: Tirpalette | B42: NON | C42: =IF(B42=Liste!A24,Liste!B18,0) -> 0 | D42: =C42/4.33 -> 0
A43: Sous-Traitance | C43: 0 | D43: 0
C45: TOTAL COUT | D45: =SUM(D29:D43) -> 5118.9179
C46: Marge Exploitation | D46: =F24-D45 -> 1854.4575
C48: % Marge | D48: =D46/F24 -> 0.26593398

Sheet CM10
A1: FICHE DE RENTABILITE
A3: DONNEES EXPLOITATION
B4: Immatriculation | D4: Conso au 100 (Moyenne) | F4: Semaine | G4: S16
A5: Tracteur (s) | B5: FB730VT | D5: 34.24
A6: Semi (s) | B6: Remorque | D6: 0.019
A7: Conducteurs | B7: BEZZAOUYA
A8: AMPLITUDE Hebdo | B8: 69.07
A9: TDS Hebdo | B9: 59.7
B10: KM Hebdo | G10: Hotel (semaine)
B11: 2263 | G11: 0
A12: Autoroute / jour : | B12: 21 | C12: (non Facturé) | F12: SPL | G12: CM
E13: €/ Hebdo | F13: 1000 | G13: 1100
A14: Détails CA
A15: Référence prestations | B15: Fréquence | C15: Montant unitaire | D15: Quantité | E15: Total Hors IGO | F15: Indexation | G15: Montant Total
A16: DACHSER VILLEPARISIS : Rouen | B16: Lundi => Vendredi | C16: 565 | D16: 5 | E16: =C16*D16 -> 2825 | F16: 0.0208 | G16: =(E16*F16)+E16 -> 2883.76
A17: CHRONOPOST : 29096 | B17: Mardi => Samedi | C17: 265 | D17: 5 | E17: =C17*D17 -> 1325 | F17: =(70*5)*0.2922 -> 102.27 | G17: =(E17+F17) -> 1427.27
A18: WE : Viapost : 170-14 | B18: Dimanche | C18: 96.85 | D18: 1 | E18: =C18*D18 -> 96.85 | F18: 0.04271 | G18: =(E18*F18)+E18 -> 100.98646 | I18: Activité en Semi
A19: WE : Viapost : 164-14/22 | B19: Dimanche | C19: =210.67+160.79 -> 371.46 | D19: 1 | E19: =C19*D19 -> 371.46 | F19: 0.039775 | G19: =(E19*F19)+E19 -> 386.23482
E20: =C20*D20 -> 0 | G20: =(E20*F20)+E20 -> 0
E21: =C21*D21 -> 0 | G21: =(E21*F21)+E21 -> 0
E22: =C22*D22 -> 0 | G22: =(E22*F22)+E22 -> 0
A24: CM10 | B24: CA DE LA LIGNE | F24: =SUM(G16:G22) -> 4798.2513
A25: SOMMAIRE
A27: Coûts de la Ligne
B28: Type | C28: unité | D28: Cout Semaine
A29: Moteur | B29: Porteur SWAPGO | C29: =IFERROR(VLOOKUP(B29,Liste!C1:D5,2,FALSE),"") -> 2500 | D29: =IFERROR(C29/4.33,0) -> 577.36721
A30: Semi (1) | B30: Remorque SWAP | C30: =IFERROR(VLOOKUP(B30,Liste!$C$7:$D$15,2,FALSE),"") -> 400 | D30: =IFERROR(C30/4.33,0) -> 92.378753
A31: Semi (2) | B31: AUCUNE | C31: =IFERROR(VLOOKUP(B31,Liste!$C$7:$D$15,2,FALSE),"") | D31: =IFERROR(C31/4.33,0) -> 0
A32: Semi (3) | B32: AUCUNE | C32: =IFERROR(VLOOKUP(B32,Liste!$C$7:$D$15,2,FALSE),"") | D32: =IFERROR(C32/4.33,0) -> 0
A33: Semi (4) | B33: AUCUNE | C33: =IFERROR(VLOOKUP(B33,Liste!$C$7:$D$15,2,FALSE),"") | D33: =IFERROR(C33/4.33,0) -> 0
A34: Carburant | B34: GO | C34: 1.3554 | D34: =(B11*D5/100)*C34 -> 1050.2333
A35: Carburant | B35: GNC | C35: 0 | D35: =(D5*B11/100)*C35 -> 0
A36: AD Blue | C36: 0.4309 | D36: =(D6*B11)*C36 -> 18.527407
A37: Fuel | C37: 1.1225
A38: Casse / Pneumatique / Lavage ( hors entretien) | C38: 0.04 | D38: =C38*B11 -> 90.52
A39: Autoroute | B39: =B12 -> 21 | C39: 5 | D39: =C39*B39 -> 105
A40: Salaires | B40: CM | C40: 1 | D40: 972.68
A41: Frais Hotel | D41: =G11 -> 0
A42: Tirpalette | B42: NON | C42: =IF(B42=Liste!A24,Liste!B18,0) -> 0 | D42: =C42/4.33 -> 0
A43: Sous-Traitance | C43: 0 | D43: 0
C45: TOTAL COUT | D45: =SUM(D29:D43) -> 2906.7067
C46: Marge Exploitation | D46: =F24-D45 -> 1891.5446
C48: % Marge | D48: =D46/F24 -> 0.39421541

Sheet CM5
A1: FICHE DE RENTABILITE
A3: DONNEES EXPLOITATION
B4: Immatriculation | D4: Conso au 100 (Moyenne) | F4: Semaine | G4: S16
A5: Tracteur (s) | B5: FC-240-JS | C5: GB-212-EM | D5: 30.82
A6: Semi (s) | B6: Remorque | C6: Remorque | D6: 0.019
A7: Conducteurs | B7: KONTE | C7: DAJ Victor | D7: ABDAL
A8: AMPLITUDE Hebdo | B8: 50.62 | C8: 36.71 | D8: 43.05
A9: TDS Hebdo | B9: 40.65 | C9: 31.83 | D9: 37.27
B10: KM Hebdo | G10: Hotel (semaine)
B11: =2404+2153+1248 -> 5805 | G11: 0
A12: Autoroute / jour : | B12: 191 | C12: 152.86 | F12: SPL | G12: CM
E13: €/ Hebdo | F13: 1000 | G13: 1100
A14: Détails CA
A15: Référence prestations | B15: Fréquence | C15: Montant unitaire | D15: Quantité | E15: Total Hors IGO | F15: Indexation | G15: Montant Total
A16: DACHSER Villeparisis : LA VERRIE | B16: Lundi => Vendredi | C16: 1164.26 | D16: 5 | E16: =C16*D16 -> 5821.3 | F16: 0.0614 | G16: =((E16-(C12*5))*F16)+E16 -> 6131.7998
A17: COLISSIMO : IDF-LTH-004-CM | B17: Mardi => Samedi | C17: 4.1631 | D17: =10*5 -> 50 | E17: =C17*D17 -> 208.155 | F17: 0 | G17: =(E17*F17)+E17 -> 208.155
A18: DACHSER Villeparisis : T962 | B18: Lundi => Vendredi | C18: 367 | D18: 5 | E18: =C18*D18 -> 1835 | F18: 0.0729 | G18: =(E18*F18)+E18 -> 1968.7715
A19: Daj + Abdal = 5 jours semaine | E19: =C19*D19 -> 0 | G19: =(E19*F19)+E19 -> 0
A20: WE: (Konte) FEDEX FRT03410 | B20: Dimanche | C20: 160 | D20: 1 | E20: =C20*D20 -> 160 | F20: -0.0091 | G20: =(E20*F20)+E20 -> 158.544
A21: WE: (Konte) DHL FR9894C | B21: Dimanche | C21: 190 | D21: 1 | E21: =C21*D21 -> 190 | F21: -0.0301 | G21: =(E21*F21)+E21 -> 184.281
A22: WE : (Konte ) FEDEX FRT03381 | B22: Dimanche | C22: 132.5 | D22: 1 | E22: =C22*D22 -> 132.5 | F22: -0.0091 | G22: =(E22*F22)+E22 -> 131.29425
A24: CM5 | B24: CA DE LA LIGNE | F24: =SUM(G16:G22) -> 8782.8456
A25: SOMMAIRE
A27: Coûts de la Ligne
B28: Type | C28: unité | D28: Cout Semaine
A29: Moteur (1) | B29: Porteur SWAPGO | C29: =IFERROR(VLOOKUP(B29,Liste!C1:D5,2,FALSE),"") -> 2500 | D29: =IFERROR(C29/4.33,0) -> 577.36721
A30: Moteur (2) | B30: Porteur SWAPGO | C30: =IFERROR(VLOOKUP(B30,Liste!C2:D6,2,FALSE),"") -> 2500 | D30: =IFERROR(C30/4.33,0) -> 577.36721
A31: Semi (1) | B31: Remorque SWAP | C31: =IFERROR(VLOOKUP(B31,Liste!$C$7:$D$15,2,FALSE),"") -> 400 | D31: =IFERROR(C31/4.33,0) -> 92.378753
A32: Semi (2) | B32: Remorque SWAP | C32: =IFERROR(VLOOKUP(B32,Liste!$C$7:$D$15,2,FALSE),"") -> 400 | D32: =IFERROR(C32/4.33,0) -> 92.378753
A33: Semi (3) | B33: AUCUNE | C33: =IFERROR(VLOOKUP(B33,Liste!$C$7:$D$15,2,FALSE),"") | D33: =IFERROR(C33/4.33,0) -> 0
A34: Semi (4) | B34: AUCUNE | C34: =IFERROR(VLOOKUP(B34,Liste!$C$7:$D$15,2,FALSE),"") | D34: =IFERROR(C34/4.33,0) -> 0
A35: Carburant | B35: GO | C35: 1.3554 | D35: =(B11*D5/100)*C35 -> 2424.9475
A36: Carburant | B36: GNC | C36: 0 | D36: =(D5*B11/100)*C36 -> 0
A37: AD Blue | C37: 0.4309 | D37: =(D6*B11)*C37 -> 47.526116
A38: Fuel | C38: 1.1225
A39: Casse / Pneumatique / Lavage ( hors entretien) | C39: 0.04 | D39: =C39*B11 -> 232.2
A40: Autoroute | B40: =B12 -> 191 | C40: 5 | D40: =C40*B40 -> 955
A41: Salaires | B41: CM | C41: 3 | D41: =1039.77+1002.21+1097.15 -> 3139.13
A42: Frais Hotel | D42: =G11 -> 0
A43: Tirpalette | B43: NON | C43: =IF(B43=Liste!A24,Liste!B18,0) -> 0 | D43: =C43/4.33 -> 0
A44: Sous-Traitance | C44: 0 | D44: 0
C46: TOTAL COUT | D46: =SUM(D29:D44) -> 8138.2955
C47: Marge Exploitation | D47: =F24-D46 -> 644.55002
C49: % Marge | D49: =D47/F24 -> 0.07338738

Sheet CM44
A1: FICHE DE RENTABILITE
A3: DONNEES EXPLOITATION
B4: Immatriculation | D4: Conso au 100 (Moyenne) | F4: Semaine | G4: S16
A5: Tracteur (s) | B5: GN-649-LZ | C5: GN-276-WA | D5: 30.5
A6: Semi (s) | B6: Remorque | C6: Remorque | D6: 0.019
A7: Conducteurs | B7: MALLE Karim | C7: PIEL Flavien
A8: AMPLITUDE Hebdo | B8: 55.22 | C8: 47.82
A9: TDS Hebdo | B9: 48.73 | C9: 43.79
B10: KM Hebdo | G10: Hotel (semaine)
B11: =2458+2776 -> 5234 | G11: 0
A12: Autoroute / jour : | B12: 178.66 | C12: 150.61 | F12: SPL | G12: CM
E13: €/ Hebdo | F13: 1000 | G13: 1100
A14: Détails CA
A15: Référence prestations | B15: Fréquence | C15: Montant unitaire | D15: Quantité | E15: Total Hors IGO | F15: Indexation | G15: Montant Total
A16: DACHSER Cergy : NIORT | B16: Lundi => Vendredi | C16: 1320.84 | D16: 5 | E16: =C16*D16 -> 6604.2 | F16: -0.0406 | G16: =((E16-(C12*5))*F16)+E16 -> 6366.6433
A17: Colissimo - IDFN-LTH-014-CM | B17: Mercredi et Jeudi | C17: 2.5043 | D17: =56*2 -> 112 | E17: =C17*D17 -> 280.4816 | G17: =(E17*F17)+E17 -> 280.4816
A18: Piel sur 5 Jours / Semaine | E18: =C18*D18 -> 0 | G18: =(E18*F18)+E18 -> 0
A19: WE : (MALLE) : Colissimo DOT-00A-CM | B19: Samedi | C19: 2.4411 | D19: 50 | E19: =C19*D19 -> 122.055 | G19: =(E19*F19)+E19 -> 122.055
A20: WE : (Malle) CHRONOPOST : LWCDGHNI02 | B20: Samedi | C20: 65 | D20: 1 | E20: =C20*D20 -> 65 | F20: =14*0.2922 -> 4.0908 | G20: =F20+E20 -> 69.0908
E21: =C21*D21 -> 0 | G21: =(E21*F21)+E21 -> 0
E22: =C22*D22 -> 0 | G22: =(E22*F22)+E22 -> 0
A24: CM44 | B24: CA DE LA LIGNE | F24: =SUM(G16:G22) -> 6838.2707
A25: SOMMAIRE
A27: Coûts de la Ligne
B28: Type | C28: unité | D28: Cout Semaine
A29: Moteur (1) | B29: Porteur SWAPGO | C29: =IFERROR(VLOOKUP(B29,Liste!C1:D5,2,FALSE),"") -> 2500 | D29: =IFERROR(C29/4.33,0) -> 577.36721
A30: Moteur (2) | B30: Porteur SWAPGO | C30: =IFERROR(VLOOKUP(B30,Liste!C2:D6,2,FALSE),"") -> 2500 | D30: =IFERROR(C30/4.33,0) -> 577.36721
A31: Semi (1) | B31: Remorque SWAP | C31: =IFERROR(VLOOKUP(B31,Liste!$C$7:$D$15,2,FALSE),"") -> 400 | D31: =IFERROR(C31/4.33,0) -> 92.378753
A32: Semi (2) | B32: Remorque SWAP | C32: =IFERROR(VLOOKUP(B32,Liste!$C$7:$D$15,2,FALSE),"") -> 400 | D32: =IFERROR(C32/4.33,0) -> 92.378753
A33: Semi (3) | B33: AUCUNE | C33: =IFERROR(VLOOKUP(B33,Liste!$C$7:$D$15,2,FALSE),"") | D33: =IFERROR(C33/4.33,0) -> 0
A34: Semi (4) | B34: AUCUNE | C34: =IFERROR(VLOOKUP(B34,Liste!$C$7:$D$15,2,FALSE),"") | D34: =IFERROR(C34/4.33,0) -> 0
A35: Carburant | B35: GO | C35: 1.3554 | D35: =(B11*D5/100)*C35 -> 2163.7199
A36: Carburant | B36: GNC | C36: 0 | D36: =(D5*B11/100)*C36 -> 0
A37: AD Blue | C37: 0.4309 | D37: =(D6*B11)*C37 -> 42.851281
A38: Fuel | C38: 1.1225
A39: Casse / Pneumatique / Lavage ( hors entretien) | C39: 0.04 | D39: =C39*B11 -> 209.36
A40: Autoroute | B40: =B12 -> 178.66 | C40: 5 | D40: =C40*B40 -> 893.3
A41: Salaires | B41: CM | C41: 2 | D41: =1037.7+845.11 -> 1882.81
A42: Frais Hotel | D42: =G11 -> 0
A43: Tirpalette | B43: NON | C43: =IF(B43=Liste!A24,Liste!B18,0) -> 0 | D43: =C43/4.33 -> 0
A44: Sous-Traitance | C44: 0 | D44: 0
C46: TOTAL COUT | D46: =SUM(D29:D44) -> 6531.5331
C47: Marge Exploitation | D47: =F24-D46 -> 306.73761
C49: % Marge | D49: =D47/F24 -> 0.044856021

Sheet CM53
A1: FICHE DE RENTABILITE
A3: DONNEES EXPLOITATION
B4: Immatriculation | D4: Conso au 100 (Moyenne) | F4: Semaine | G4: S16
A5: Tracteur (s) | B5: GY-244-BQ | C5: GN-648-LZ | D5: 28.6
A6: Semi (s) | B6: Remorque | C6: Remorque | D6: 0.019
A7: Conducteurs | B7: HAMMADI Redha | C7: TAGMI Karim
A8: AMPLITUDE Hebdo | B8: 62.66
A9: TDS Hebdo | B9: 52.38
B10: KM Hebdo | G10: Hotel (semaine)
B11: =2912+2389 -> 5301 | G11: 0
A12: Autoroute / jour : | B12: 213.43 | C12: 195.31 | F12: SPL | G12: CM
E13: €/ Hebdo | F13: 1000 | G13: 1100
A14: Détails CA
A15: Référence prestations | B15: Fréquence | C15: Montant unitaire | D15: Quantité | E15: Total Hors IGO | F15: Indexation | G15: Montant Total
A16: DACHSER Cergy : Nantes | B16: Lundi => Vendredi | C16: 1395.31 | D16: 5 | E16: =C16*D16 -> 6976.55 | F16: -0.0365 | G16: =((E16-(C12*5))*F16)+E16 -> 6757.55
A17: COLISSIMO : IDFN-LTH-017-CM | B17: Mardi => Samedi | C17: 2.5021 | D17: =70*5 -> 350 | E17: =C17*D17 -> 875.735 | G17: =(E17*F17)+E17 -> 875.735
E18: =C18*D18 -> 0 | G18: =(E18*F18)+E18 -> 0
A19: WE : (Hammadi) Viaposte 168-2 / 6 | B19: Dimanche | C19: =179.42+104.98 -> 284.4 | D19: 1 | E19: =C19*D19 -> 284.4 | F19: 0.04773 | G19: =(E19*F19)+E19 -> 297.97441
A20: WE : (Hammadi) Viaposte 164-19 | B20: Dimanche | C20: 195.33 | D20: 1 | E20: =C20*D20 -> 195.33 | F20: 0.039775 | G20: =(E20*F20)+E20 -> 203.09925
E21: =C21*D21 -> 0 | G21: =(E21*F21)+E21 -> 0
E22: =C22*D22 -> 0 | G22: =(E22*F22)+E22 -> 0
A24: CM53 | B24: CA DE LA LIGNE | F24: =SUM(G16:G22) -> 8134.3587
A25: SOMMAIRE
A27: Coûts de la Ligne
B28: Type | C28: unité | D28: Cout Semaine
A29: Moteur (1) | B29: Porteur SWAPGO | C29: =IFERROR(VLOOKUP(B29,Liste!C1:D5,2,FALSE),"") -> 2500 | D29: =IFERROR(C29/4.33,0) -> 577.36721
A30: Moteur (2) | B30: Porteur SWAPGO | C30: =IFERROR(VLOOKUP(B30,Liste!C2:D6,2,FALSE),"") -> 2500 | D30: =IFERROR(C30/4.33,0) -> 577.36721
A31: Semi (1) | B31: Remorque SWAP | C31: =IFERROR(VLOOKUP(B31,Liste!$C$7:$D$15,2,FALSE),"") -> 400 | D31: =IFERROR(C31/4.33,0) -> 92.378753
A32: Semi (2) | B32: Remorque SWAP | C32: =IFERROR(VLOOKUP(B32,Liste!$C$7:$D$15,2,FALSE),"") -> 400 | D32: =IFERROR(C32/4.33,0) -> 92.378753
A33: Semi (3) | B33: AUCUNE | C33: =IFERROR(VLOOKUP(B33,Liste!$C$7:$D$15,2,FALSE),"") | D33: =IFERROR(C33/4.33,0) -> 0
A34: Semi (4) | B34: AUCUNE | C34: =IFERROR(VLOOKUP(B34,Liste!$C$7:$D$15,2,FALSE),"") | D34: =IFERROR(C34/4.33,0) -> 0
A35: Carburant | B35: GO | C35: 1.3554 | D35: =(B11*D5/100)*C35 -> 2054.903
A36: Carburant | B36: GNC | C36: 0 | D36: =(D5*B11/100)*C36 -> 0
A37: AD Blue | C37: 0.4309 | D37: =(D6*B11)*C37 -> 43.399817
A38: Fuel | C38: 1.1225
A39: Casse / Pneumatique / Lavage ( hors entretien) | C39: 0.04 | D39: =C39*B11 -> 212.04
A40: Autoroute | B40: =B12 -> 213.43 | C40: 5 | D40: =C40*B40 -> 1067.15
A41: Salaires | B41: CM | C41: 2 | D41: =1451.93+957.88 -> 2409.81
A42: Frais Hotel | D42: =G11 -> 0
A43: Tirpalette | B43: NON | C43: =IF(B43=Liste!A24,Liste!B18,0) -> 0 | D43: =C43/4.33 -> 0
A44: Sous-Traitance | C44: 0 | D44: 0
C46: TOTAL COUT | D46: =SUM(D29:D44) -> 7126.7947
C47: Marge Exploitation | D47: =F24-D46 -> 1007.564
C49: % Marge | D49: =D47/F24 -> 0.1238652

Sheet CM7
A1: FICHE DE RENTABILITE
A3: DONNEES EXPLOITATION
B4: Immatriculation | D4: Conso au 100 (Moyenne) | F4: Semaine | G4: S16
A5: Tracteur (s) | B5: FA826ZA | D5: 32
A6: Semi (s) | B6: Remorque | D6: 0.019
A7: Conducteurs | B7: JAMES Fabrice
A8: AMPLITUDE Hebdo | B8: 61.13
A9: TDS Hebdo | B9: 52.78
B10: KM Hebdo | G10: Hotel (semaine)
B11: 2889 | G11: 0
A12: Autoroute / jour : | B12: 0 | F12: SPL | G12: CM
E13: €/ Hebdo | F13: 1000 | G13: 1100
A14: Détails CA
A15: Référence prestations | B15: Fréquence | C15: Montant unitaire | D15: Quantité | E15: Total Hors IGO | F15: Indexation | G15: Montant Total
A16: Coliposte Zalando Vatry | B16: Lundi au Vendredi | C16: 480 | D16: 5 | E16: =C16*D16 -> 2400 | F16: 0 | G16: =(E16*F16)+E16 -> 2400
A17: Coliposte Zalando Vatry | B17: Lundi au Vendredi | C17: 480 | D17: 5 | E17: =C17*D17 -> 2400 | F17: 0 | G17: =(E17*F17)+E17 -> 2400
M18: u
E19: =C19*D19 -> 0 | G19: =(E19*F19)+E19 -> 0
E20: =C20*D20 -> 0 | G20: =(E20*F20)+E20 -> 0
E21: =C21*D21 -> 0 | G21: =(E21*F21)+E21 -> 0
E22: =C22*D22 -> 0 | G22: =(E22*F22)+E22 -> 0
A24: CM7 | B24: CA DE LA LIGNE | F24: =SUM(G16:G22) -> 4800
A25: SOMMAIRE
A27: Coûts de la Ligne
B28: Type | C28: unité | D28: Cout Semaine
A29: Moteur | B29: Porteur SWAPGO | C29: =IFERROR(VLOOKUP(B29,Liste!C1:D5,2,FALSE),"") -> 2500 | D29: =IFERROR(C29/4.33,0) -> 577.36721
A30: Semi (1) | B30: Remorque SWAP | C30: =IFERROR(VLOOKUP(B30,Liste!$C$7:$D$15,2,FALSE),"") -> 400 | D30: =IFERROR(C30/4.33,0) -> 92.378753
A31: Semi (2) | B31: AUCUNE | C31: =IFERROR(VLOOKUP(B31,Liste!$C$7:$D$15,2,FALSE),"") | D31: =IFERROR(C31/4.33,0) -> 0
A32: Semi (3) | B32: AUCUNE | C32: =IFERROR(VLOOKUP(B32,Liste!$C$7:$D$15,2,FALSE),"") | D32: =IFERROR(C32/4.33,0) -> 0
A33: Semi (4) | B33: AUCUNE | C33: =IFERROR(VLOOKUP(B33,Liste!$C$7:$D$15,2,FALSE),"") | D33: =IFERROR(C33/4.33,0) -> 0
A34: Carburant | B34: GO | C34: 1.3554 | D34: =(B11*D5/100)*C34 -> 1253.0402
A35: Carburant | B35: GNC | C35: 0 | D35: =(D5*B11/100)*C35 -> 0
A36: AD Blue | C36: 0.4309 | D36: =(D6*B11)*C36 -> 23.652532
A37: Fuel | C37: 1.1225
A38: Casse / Pneumatique / Lavage ( hors entretien) | C38: 0.04 | D38: =C38*B11 -> 115.56
A39: Autoroute | B39: =B12 -> 0 | C39: 5 | D39: =C39*B39 -> 0
A40: Salaires | B40: CM | C40: 1 | D40: 1000.54
A41: Frais Hotel | D41: =G11 -> 0
A42: Tirpalette | B42: NON | C42: =IF(B42=Liste!A24,Liste!B18,0) -> 0 | D42: =C42/4.33 -> 0
A43: Sous-Traitance | C43: 0 | D43: 0
C45: TOTAL COUT | D45: =SUM(D29:D43) -> 3062.5387
C46: Marge Exploitation | D46: =F24-D45 -> 1737.4613
C48: % Marge | D48: =D46/F24 -> 0.36197111

Sheet CM14
A1: FICHE DE RENTABILITE
A3: DONNEES EXPLOITATION
B4: Immatriculation | D4: Conso au 100 (Moyenne) | F4: Semaine | G4: S16
A5: Tracteur (s) | B5: GC-623-YH | D5: 30.53
A6: Semi (s) | B6: Remorque | D6: 0.019
A7: Conducteurs | B7: BEZDIGA | C7: ANDRY
A8: AMPLITUDE Hebdo | B8: 65.31 | C8: 51.48
A9: TDS Hebdo | B9: 43.96 | C9: 45.53
B10: KM Hebdo | G10: Hotel (semaine)
B11: =2939+1157 -> 4096 | G11: 0
A12: Autoroute / jour : | B12: 136.16 | F12: SPL | G12: CM
E13: €/ Hebdo | F13: 1000 | G13: 1100
A14: Détails CA
A15: Référence prestations | B15: Fréquence | C15: Montant unitaire | D15: Quantité | E15: Total Hors IGO | F15: Indexation | G15: Montant Total
A16: Chronopost : 29802 | B16: Lundi => Vendredi | C16: 614 | D16: 5 | E16: =C16*D16 -> 3070 | F16: =(0.2922*452)*5 -> 660.372 | G16: =E16+F16 -> 3730.372
A17: COLISSIMO : IDFN-DOT-00A-CM | B17: Lundi => Vendredi | C17: 2.4411 | D17: =(60+50+42)*5 -> 760 | E17: =C17*D17 -> 1855.236 | F17: 0 | G17: =(E17*F17)+E17 -> 1855.236
A18: WE : (Bezdiga) VIAPOST 163-13/9 | B18: Dimanche | C18: =208.26+268.88 -> 477.14 | D18: 1 | E18: =C18*D18 -> 477.14 | F18: 0.039775 | G18: =(E18*F18)+E18 -> 496.11824
A19: WE : (Andry) Colissimo DOT-00A-CM | B19: Samedi | C19: 2.4411 | D19: =60+66 -> 126 | E19: =C19*D19 -> 307.5786 | G19: =(E19*F19)+E19 -> 307.5786
E20: =C20*D20 -> 0 | G20: =(E20*F20)+E20 -> 0
E21: =C21*D21 -> 0 | G21: =(E21*F21)+E21 -> 0
E22: =C22*D22 -> 0 | G22: =(E22*F22)+E22 -> 0
A24: CM14 | B24: CA DE LA LIGNE | F24: =SUM(G16:G22) -> 6389.3048
A25: SOMMAIRE
A27: Coûts de la Ligne
B28: Type | C28: unité | D28: Cout Semaine
A29: Moteur | B29: Porteur SWAPGNC | C29: =IFERROR(VLOOKUP(B29,Liste!C1:D5,2,FALSE),"") -> 3000 | D29: =IFERROR(C29/4.33,0) -> 692.84065
A30: Semi (1) | B30: Remorque SWAP | C30: =IFERROR(VLOOKUP(B30,Liste!$C$7:$D$15,2,FALSE),"") -> 400 | D30: =IFERROR(C30/4.33,0) -> 92.378753
A31: Semi (2) | B31: AUCUNE | C31: =IFERROR(VLOOKUP(B31,Liste!$C$7:$D$15,2,FALSE),"") | D31: =IFERROR(C31/4.33,0) -> 0
A32: Semi (3) | B32: AUCUNE | C32: =IFERROR(VLOOKUP(B32,Liste!$C$7:$D$15,2,FALSE),"") | D32: =IFERROR(C32/4.33,0) -> 0
A33: Semi (4) | B33: AUCUNE | C33: =IFERROR(VLOOKUP(B33,Liste!$C$7:$D$15,2,FALSE),"") | D33: =IFERROR(C33/4.33,0) -> 0
A34: Carburant | B34: GO | C34: 0 | D34: =(B11*D5/100)*C34 -> 0
A35: Carburant | B35: GNC | C35: 1.365 | D35: =(D5*B11/100)*C35 -> 1706.9445
A36: AD Blue | C36: 0 | D36: =(D6*B11)*C36 -> 0
A37: Fuel | C37: 1.1225
A38: Casse / Pneumatique / Lavage ( hors entretien) | C38: 0.04 | D38: =C38*B11 -> 163.84
A39: Autoroute | B39: =B12 -> 136.16 | C39: 5 | D39: =C39*B39 -> 680.8
A40: Salaires | B40: CM | C40: 2 | D40: =948.83+1030.95 -> 1979.78
A41: Frais Hotel | D41: =G11 -> 0
A42: Tirpalette | B42: NON | C42: =IF(B42=Liste!A24,Liste!B18,0) -> 0 | D42: =C42/4.33 -> 0
A43: Sous-Traitance | C43: 0 | D43: 0
C45: TOTAL COUT | D45: =SUM(D29:D43) -> 5316.5839
C46: Marge Exploitation | D46: =F24-D45 -> 1072.7209
C48: % Marge | D48: =D46/F24 -> 0.16789322

Sheet CM15
A1: FICHE DE RENTABILITE
A3: DONNEES EXPLOITATION
B4: Immatriculation | D4: Conso au 100 (Moyenne) | F4: Semaine | G4: S16
A5: Tracteur (s) | B5: EJ-937-FF | D5: 24.17
A6: Semi (s) | B6: Remorque | D6: 0.019
A7: Conducteurs | B7: VIOREL
A8: AMPLITUDE Hebdo | B8: 71.05
A9: TDS Hebdo | B9: 33.51
B10: KM Hebdo | G10: Hotel (semaine)
B11: 1303 | G11: 0
A12: Autoroute / jour : | B12: 0 | F12: SPL | G12: CM
E13: €/ Hebdo | F13: 1000 | G13: 1100
A14: Détails CA
A15: Référence prestations | B15: Fréquence | C15: Montant unitaire | D15: Quantité | E15: Total Hors IGO | F15: Indexation | G15: Montant Total
A16: UPS : PA07 | B16: lundi => Vendredi | C16: 275 | D16: 5 | E16: =C16*D16 -> 1375 | F16: -0.0226 | G16: =(E16*F16)+E16 -> 1343.925
A17: Chronopost : 38853 | B17: lundi => Vendredi | C17: 198 | D17: 5 | E17: =C17*D17 -> 990 | F17: =(87*5)*0.2922 -> 127.107 | G17: =(E17+F17) -> 1117.107 | I17: Indexation gaz sur véhicule go
A18: WE : Colissimo LTH-004-CM | B18: Dimanche | C18: 4.1631 | D18: 10 | E18: =C18*D18 -> 41.631 | G18: =(E18*F18)+E18 -> 41.631
A19: WE : Colissimo LTH-081-CM | B19: Dimanche | C19: 2.4933 | D19: 74 | E19: =C19*D19 -> 184.5042 | G19: =(E19*F19)+E19 -> 184.5042
E20: =C20*D20 -> 0 | G20: =(E20*F20)+E20 -> 0
E21: =C21*D21 -> 0 | G21: =(E21*F21)+E21 -> 0
E22: =C22*D22 -> 0 | G22: =(E22*F22)+E22 -> 0
A24: CM15 | B24: CA DE LA LIGNE | F24: =SUM(G16:G22) -> 2687.1672
A25: SOMMAIRE
A27: Coûts de la Ligne
B28: Type | C28: unité | D28: Cout Semaine
A29: Moteur | B29: Porteur SWAPGO | C29: =IFERROR(VLOOKUP(B29,Liste!C1:D5,2,FALSE),"") -> 2500 | D29: =IFERROR(C29/4.33,0) -> 577.36721
A30: Semi (1) | B30: Remorque SWAP | C30: =IFERROR(VLOOKUP(B30,Liste!$C$7:$D$15,2,FALSE),"") -> 400 | D30: =IFERROR(C30/4.33,0) -> 92.378753
A31: Semi (2) | B31: AUCUNE | C31: =IFERROR(VLOOKUP(B31,Liste!$C$7:$D$15,2,FALSE),"") | D31: =IFERROR(C31/4.33,0) -> 0
A32: Semi (3) | B32: AUCUNE | C32: =IFERROR(VLOOKUP(B32,Liste!$C$7:$D$15,2,FALSE),"") | D32: =IFERROR(C32/4.33,0) -> 0
A33: Semi (4) | B33: AUCUNE | C33: =IFERROR(VLOOKUP(B33,Liste!$C$7:$D$15,2,FALSE),"") | D33: =IFERROR(C33/4.33,0) -> 0
A34: Carburant | B34: GO | C34: 1.3554 | D34: =(B11*D5/100)*C34 -> 426.86303
A35: Carburant | B35: GNC | D35: =(D5*B11/100)*C35 -> 0
A36: AD Blue | C36: 0.4309 | D36: =(D6*B11)*C36 -> 10.667791
A37: Fuel | C37: 1.1225
A38: Casse / Pneumatique / Lavage ( hors entretien) | C38: 0.04 | D38: =C38*B11 -> 52.12
A39: Autoroute | B39: =B12 -> 0 | C39: 5 | D39: =C39*B39 -> 0
A40: Salaires | B40: CM | C40: 1 | D40: 935.4
A41: Frais Hotel | D41: =G11 -> 0
A42: Tirpalette | B42: NON | C42: =IF(B42=Liste!A24,Liste!B18,0) -> 0 | D42: =C42/4.33 -> 0
A43: Sous-Traitance | C43: 0 | D43: 0
C45: TOTAL COUT | D45: =SUM(D29:D43) -> 2094.7968
C46: Marge Exploitation | D46: =F24-D45 -> 592.37042
C48: % Marge | D48: =D46/F24 -> 0.2204442

Sheet CM19
A1: FICHE DE RENTABILITE
A3: DONNEES EXPLOITATION
B4: Immatriculation | D4: Conso au 100 (Moyenne) | F4: Semaine | G4: S15
A5: Tracteur (s) | B5: FZ-654-JG | C5: FZ-643-JG | D5: 28.47
A6: Semi (s) | B6: Remorque | C6: Remorque | D6: 0.019
A7: Conducteurs | B7: TAHLA | C7: NAILI
A8: AMPLITUDE Hebdo | B8: 64.83 | C8: 51.97
A9: TDS Hebdo | B9: 41.6 | C9: 42.59
B10: KM Hebdo | G10: Hotel (semaine)
B11: =3615+2082 -> 5697 | G11: 0
A12: Autoroute / jour : | B12: 262.88 | F12: SPL | G12: CM
E13: €/ Hebdo | F13: 1000 | G13: 1100
A14: Détails CA
A15: Référence prestations | B15: Fréquence | C15: Montant unitaire | D15: Quantité | E15: Total Hors IGO | F15: Indexation | G15: Montant Total
A16: Chronopost : 29957 | B16: lundi => Vendredi | C16: 330 | D16: 5 | E16: =C16*D16 -> 1650 | F16: =(49.5*5)*0.2922 -> 72.3195 | G16: =(E16+F16) -> 1722.3195 | I16: Indexation Gaz - véhicule GO
A17: Chronopost : 29800 | B17: lundi => Vendredi | C17: 1398 | D17: 5 | E17: =C17*D17 -> 6990 | F17: =(1026*5)*0.2922 -> 1498.986 | G17: =(E17+F17) -> 8488.986
A18: Chronopost : 29092 | B18: lundi => Vendredi | C18: 170 | D18: 5 | E18: =C18*D18 -> 850 | F18: =(33*5)*0.2922 -> 48.213 | G18: =(E18+F18) -> 898.213
A19: Naili tourne sur 5 Jours | E19: =C19*D19 -> 0 | G19: =(E19*F19)+E19 -> 0
A20: WE : (Tahla) UPS Ramasse Evry | B20: Dimanche | C20: 197.5 | D20: 1 | E20: =C20*D20 -> 197.5 | F20: 0.0409 | G20: =(E20*F20)+E20 -> 205.57775
A21: WE : (Tahla) Chronopost 38920 | B21: Dimanche | C21: 300 | D21: 1 | E21: =C21*D21 -> 300 | F21: =0.2673*96 -> 25.6608 | G21: =F21+E21 -> 325.6608
A22: WE : (Tahla) Chronopost 29101 | B22: Dimanche | C22: 195 | D22: 1 | E22: =C22*D22 -> 195 | F22: =64*0.2922 -> 18.7008 | G22: =F22+E22 -> 213.7008
A24: CM19 | B24: CA DE LA LIGNE | F24: =SUM(G16:G22) -> 11854.458
A25: SOMMAIRE
A27: Coûts de la Ligne
B28: Type | C28: unité | D28: Cout Semaine
A29: Moteur(1) | B29: Porteur SWAPGO | C29: =IFERROR(VLOOKUP(B29,Liste!C1:D5,2,FALSE),"") -> 2500 | D29: =IFERROR(C29/4.33,0) -> 577.36721
A30: Moteur (2) | B30: Porteur SWAPGO | C30: =IFERROR(VLOOKUP(B30,Liste!C2:D6,2,FALSE),"") -> 2500 | D30: =IFERROR(C30/4.33,0) -> 577.36721
A31: Semi (1) | B31: Remorque SWAP | C31: =IFERROR(VLOOKUP(B31,Liste!$C$7:$D$15,2,FALSE),"") -> 400 | D31: =IFERROR(C31/4.33,0) -> 92.378753
A32: Semi (2) | B32: Remorque SWAP | C32: =IFERROR(VLOOKUP(B32,Liste!$C$7:$D$15,2,FALSE),"") -> 400 | D32: =IFERROR(C32/4.33,0) -> 92.378753
A33: Semi (3) | B33: AUCUNE | C33: =IFERROR(VLOOKUP(B33,Liste!$C$7:$D$15,2,FALSE),"") | D33: =IFERROR(C33/4.33,0) -> 0
A34: Semi (4) | B34: AUCUNE | C34: =IFERROR(VLOOKUP(B34,Liste!$C$7:$D$15,2,FALSE),"") | D34: =IFERROR(C34/4.33,0) -> 0
A35: Carburant | B35: GO | C35: 1.3554 | D35: =(B11*D5/100)*C35 -> 2198.3719
A36: Carburant | B36: GNC | C36: 0 | D36: =(D5*B11/100)*C36 -> 0
A37: AD Blue | C37: 0.4309 | D37: =(D6*B11)*C37 -> 46.641909
A38: Fuel | C38: 1.1225
A39: Casse / Pneumatique / Lavage ( hors entretien) | C39: 0.04 | D39: =C39*B11 -> 227.88
A40: Autoroute | B40: =B12 -> 262.88 | C40: 5 | D40: =(C40*B40)+11.5 -> 1325.9 | E40: rajout 11,50 pour le dimanche (montataire)
A41: Salaires | B41: CM | C41: 2 | D41: =1200.04+1418.11 -> 2618.15
A42: Frais Hotel | D42: =G11 -> 0
A43: Tirpalette | B43: NON | C43: =IF(B43=Liste!A24,Liste!B18,0) -> 0 | D43: =C43/4.33 -> 0
A44: Sous-Traitance | C44: 0 | D44: 0
C46: TOTAL COUT | D46: =SUM(D29:D44) -> 7756.4357
C47: Marge Exploitation | D47: =F24-D46 -> 4098.0221
C49: % Marge | D49: =D47/F24 -> 0.3456946

Sheet CM23
A1: FICHE DE RENTABILITE
A3: DONNEES EXPLOITATION
B4: Immatriculation | D4: Conso au 100 (Moyenne) | F4: Semaine | G4: S16
A5: Tracteur (s) | B5: FB-491-MH | D5: 29.18
A6: Semi (s) | B6: Remorque | D6: 0.019
A7: Conducteurs | B7: ANSEUR
A8: AMPLITUDE Hebdo | B8: 49.75
A9: TDS Hebdo | B9: 39.92
B10: KM Hebdo | G10: Hotel (semaine)
B11: 2301 | G11: 0
A12: Autoroute / jour : | B12: 170.9 | F12: SPL | G12: CM
E13: €/ Hebdo | F13: 1000 | G13: 1100
A14: Détails CA
A15: Référence prestations | B15: Fréquence | C15: Montant unitaire | D15: Quantité | E15: Total Hors IGO | F15: Indexation | G15: Montant Total
A16: CHRONOPOST : 38838 | B16: Lundi => Vendredi | C16: 211 | D16: 5 | E16: =C16*D16 -> 1055 | F16: =(165*5)*0.2922 -> 241.065 | G16: =(E16+F16) -> 1296.065 | I16: Indexation Gaz - véhicule GO
A17: CHRONOPOST : 38492 | B17: Lundi => Vendredi | C17: 289 | D17: 5 | E17: =C17*D17 -> 1445 | F17: =(225*5)*0.2922 -> 328.725 | G17: =(E17+F17) -> 1773.725
A18: Colissimo : LTH-017-CM | B18: Lundi => Vendredi | C18: 2.5021 | D18: =76*5 -> 380 | E18: =C18*D18 -> 950.798 | F18: 0 | G18: =(E18+F18) -> 950.798
A19: Tourne sur 5 jours | E19: =C19*D19 -> 0 | G19: =(E19*F19)+E19 -> 0
E20: =C20*D20 -> 0 | G20: =(E20*F20)+E20 -> 0
E21: =C21*D21 -> 0 | G21: =(E21*F21)+E21 -> 0
E22: =C22*D22 -> 0 | G22: =(E22*F22)+E22 -> 0
A24: CM23 | B24: CA DE LA LIGNE | F24: =SUM(G16:G22) -> 4020.588
A25: SOMMAIRE
A27: Coûts de la Ligne
B28: Type | C28: unité | D28: Cout Semaine
A29: Moteur(1) | B29: Porteur SWAPGO | C29: =IFERROR(VLOOKUP(B29,Liste!C1:D5,2,FALSE),"") -> 2500 | D29: =IFERROR(C29/4.33,0) -> 577.36721
A30: Semi (1) | B30: Remorque SWAP | C30: =IFERROR(VLOOKUP(B30,Liste!$C$7:$D$15,2,FALSE),"") -> 400 | D30: =IFERROR(C30/4.33,0) -> 92.378753
A31: Semi (2) | B31: AUCUNE | C31: =IFERROR(VLOOKUP(B31,Liste!$C$7:$D$15,2,FALSE),"") | D31: =IFERROR(C31/4.33,0) -> 0
A32: Semi (3) | B32: AUCUNE | C32: =IFERROR(VLOOKUP(B32,Liste!$C$7:$D$15,2,FALSE),"") | D32: =IFERROR(C32/4.33,0) -> 0
A33: Semi (4) | B33: AUCUNE | C33: =IFERROR(VLOOKUP(B33,Liste!$C$7:$D$15,2,FALSE),"") | D33: =IFERROR(C33/4.33,0) -> 0
A34: Carburant | B34: GO | C34: 1.3554 | D34: =(B11*D5/100)*C34 -> 910.05866
A35: Carburant | B35: GNC | C35: 0 | D35: =(D5*B11/100)*C35 -> 0
A36: AD Blue | C36: 0.4309 | D36: =(D6*B11)*C36 -> 18.838517
A37: Fuel | C37: 1.1225
A38: Casse / Pneumatique / Lavage ( hors entretien) | C38: 0.04 | D38: =C38*B11 -> 92.04
A39: Autoroute | B39: =B12 -> 170.9 | C39: 5 | D39: =C39*B39 -> 854.5
A40: Salaires | B40: CM | C40: 1 | D40: 1247.23
A41: Frais Hotel | D41: =G11 -> 0
A42: Tirpalette | B42: NON | C42: =IF(B42=Liste!A24,Liste!B18,0) -> 0 | D42: =C42/4.33 -> 0
A43: Sous-Traitance | C43: 0 | D43: 0
C45: TOTAL COUT | D45: =SUM(D29:D43) -> 3792.4131
C46: Marge Exploitation | D46: =F24-D45 -> 228.17486
C48: % Marge | D48: =D46/F24 -> 0.056751615

Sheet CM25
A1: FICHE DE RENTABILITE
A3: DONNEES EXPLOITATION
B4: Immatriculation | D4: Conso au 100 (Moyenne) | F4: Semaine | G4: S15
A5: Tracteur (s) | B5: EY-873-GA | D5: 35.09
A6: Semi (s) | B6: Remorque | D6: 0.019
A7: Conducteurs | B7: WAGNER
A8: AMPLITUDE Hebdo | B8: 47.91
A9: TDS Hebdo | B9: 40.62
B10: KM Hebdo | G10: Hotel (semaine)
B11: 2014 | G11: 0
A12: Autoroute / jour : | B12: 43 | F12: SPL | G12: CM
E13: €/ Hebdo | F13: 1000 | G13: 1100
A14: Détails CA
A15: Référence prestations | B15: Fréquence | C15: Montant unitaire | D15: Quantité | E15: Total Hors IGO | F15: Indexation | G15: Montant Total
A16: Chronopost Amiens Chilly 38468 | B16: Lundi au Vendredi | C16: 530 | D16: 5 | E16: =C16*D16 -> 2650 | F16: =(350*5)*0.2922 -> 511.35 | G16: =(E16+F16) -> 3161.35 | I16: Indexation Gaz - véhicule GO
A17: Chronopost Chilly Bobigny 29599 | B17: Lundi au Vendredi | C17: 160 | D17: 5 | E17: =C17*D17 -> 800 | F17: =(40*5)*0.2922 -> 58.44 | G17: =(E17+F17) -> 858.44
E18: =C18*D18 -> 0 | G18: =(E18+F18) -> 0
A19: Tourne sur 5 jours | E19: =C19*D19 -> 0 | G19: =(E19*F19)+E19 -> 0
E20: =C20*D20 -> 0 | G20: =(E20*F20)+E20 -> 0
E21: =C21*D21 -> 0 | G21: =(E21*F21)+E21 -> 0
E22: =C22*D22 -> 0 | G22: =(E22*F22)+E22 -> 0
A24: CM25 | B24: CA DE LA LIGNE | F24: =SUM(G16:G22) -> 4019.79
A25: SOMMAIRE
A27: Coûts de la Ligne
B28: Type | C28: unité | D28: Cout Semaine
A29: Moteur(1) | B29: Porteur SWAPGO | C29: =IFERROR(VLOOKUP(B29,Liste!C1:D5,2,FALSE),"") -> 2500 | D29: =IFERROR(C29/4.33,0) -> 577.36721
A30: Semi (1) | B30: Remorque SWAP | C30: =IFERROR(VLOOKUP(B30,Liste!$C$7:$D$15,2,FALSE),"") -> 400 | D30: =IFERROR(C30/4.33,0) -> 92.378753
A31: Semi (2) | B31: AUCUNE | C31: =IFERROR(VLOOKUP(B31,Liste!$C$7:$D$15,2,FALSE),"") | D31: =IFERROR(C31/4.33,0) -> 0
A32: Semi (3) | B32: AUCUNE | C32: =IFERROR(VLOOKUP(B32,Liste!$C$7:$D$15,2,FALSE),"") | D32: =IFERROR(C32/4.33,0) -> 0
A33: Semi (4) | B33: AUCUNE | C33: =IFERROR(VLOOKUP(B33,Liste!$C$7:$D$15,2,FALSE),"") | D33: =IFERROR(C33/4.33,0) -> 0
A34: Carburant | B34: GO | C34: 1.3554 | D34: =(B11*D5/100)*C34 -> 957.87826
A35: Carburant | B35: GNC | C35: 0 | D35: =(D5*B11/100)*C35 -> 0
A36: AD Blue | C36: 0.4309 | D36: =(D6*B11)*C36 -> 16.488819
A37: Fuel | C37: 1.1225
A38: Casse / Pneumatique / Lavage ( hors entretien) | C38: 0.04 | D38: =C38*B11 -> 80.56
A39: Autoroute | B39: =B12 -> 43 | C39: 5 | D39: =C39*B39 -> 215
A40: Salaires | B40: CM | C40: 1 | D40: 1028.42
A41: Frais Hotel | D41: =G11 -> 0
A42: Tirpalette | B42: NON | C42: =IF(B42=Liste!A24,Liste!B18,0) -> 0 | D42: =C42/4.33 -> 0
A43: Sous-Traitance | C43: 0 | D43: 0
C45: TOTAL COUT | D45: =SUM(D29:D43) -> 2968.093
C46: Marge Exploitation | D46: =F24-D45 -> 1051.697
C48: % Marge | D48: =D46/F24 -> 0.26162983

Sheet CM26
A1: FICHE DE RENTABILITE
A3: DONNEES EXPLOITATION
B4: Immatriculation | D4: Conso au 100 (Moyenne) | F4: Semaine | G4: S16
A5: Tracteur (s) | B5: EJ-141-TS | D5: 30.66
A6: Semi (s) | B6: Remorque | D6: 0.019
A7: Conducteurs | B7: BENALI
A8: AMPLITUDE Hebdo | B8: 73.98
A9: TDS Hebdo | B9: 50.18
B10: KM Hebdo | G10: Hotel (semaine)
B11: 3591 | G11: 0
A12: Autoroute / jour : | B12: =45.75+136.5 -> 182.25 | F12: SPL | G12: CM
E13: €/ Hebdo | F13: 1000 | G13: 1100
A14: Détails CA
A15: Référence prestations | B15: Fréquence | C15: Montant unitaire | D15: Quantité | E15: Total Hors IGO | F15: Indexation | G15: Montant Total
A16: CHRONOPOST Arras Aulnay 38492 | B16: Lundi au vendredi | C16: 606 | D16: 5 | E16: =C16*D16 -> 3030 | F16: =(487*5)*0.2922 -> 711.507 | G16: =(E16+F16) -> 3741.507 | I16: Indexation Gaz - véhicule GO
A17: CHRONOPOST Arras Aulnay 38838 | B17: Lundi au vendredi | C17: 194 | D17: 5 | E17: =C17*D17 -> 970 | F17: =(165*5)*0.2922 -> 241.065 | G17: =(E17+F17) -> 1211.065
E18: =C18*D18 -> 0 | G18: =(E18+F18) -> 0
A19: Tourne sur 5 jours | E19: =C19*D19 -> 0 | G19: =(E19*F19)+E19 -> 0
E20: =C20*D20 -> 0 | G20: =(E20*F20)+E20 -> 0
E21: =C21*D21 -> 0 | G21: =(E21*F21)+E21 -> 0
E22: =C22*D22 -> 0 | G22: =(E22*F22)+E22 -> 0
A24: CM26 | B24: CA DE LA LIGNE | F24: =SUM(G16:G22) -> 4952.572
A25: SOMMAIRE
A27: Coûts de la Ligne
B28: Type | C28: unité | D28: Cout Semaine
A29: Moteur(1) | B29: Porteur SWAPGO | C29: =IFERROR(VLOOKUP(B29,Liste!C1:D5,2,FALSE),"") -> 2500 | D29: =IFERROR(C29/4.33,0) -> 577.36721
A30: Semi (1) | B30: Remorque SWAP | C30: =IFERROR(VLOOKUP(B30,Liste!$C$7:$D$15,2,FALSE),"") -> 400 | D30: =IFERROR(C30/4.33,0) -> 92.378753
A31: Semi (2) | B31: AUCUNE | C31: =IFERROR(VLOOKUP(B31,Liste!$C$7:$D$15,2,FALSE),"") | D31: =IFERROR(C31/4.33,0) -> 0
A32: Semi (3) | B32: AUCUNE | C32: =IFERROR(VLOOKUP(B32,Liste!$C$7:$D$15,2,FALSE),"") | D32: =IFERROR(C32/4.33,0) -> 0
A33: Semi (4) | B33: AUCUNE | C33: =IFERROR(VLOOKUP(B33,Liste!$C$7:$D$15,2,FALSE),"") | D33: =IFERROR(C33/4.33,0) -> 0
A34: Carburant | B34: GO | C34: 1.3554 | D34: =(B11*D5/100)*C34 -> 1492.2962
A35: Carburant | B35: GNC | C35: 0 | D35: =(D5*B11/100)*C35 -> 0
A36: AD Blue | C36: 0.4309 | D36: =(D6*B11)*C36 -> 29.399876
A37: Fuel | C37: 1.1225
A38: Casse / Pneumatique / Lavage ( hors entretien) | C38: 0.04 | D38: =C38*B11 -> 143.64
A39: Autoroute | B39: =B12 -> 182.25 | C39: 5 | D39: =C39*B39 -> 911.25
A40: Salaires | B40: CM | C40: 1 | D40: 1315.68
A41: Frais Hotel | D41: =G11 -> 0
A42: Tirpalette | B42: NON | C42: =IF(B42=Liste!A24,Liste!B18,0) -> 0 | D42: =C42/4.33 -> 0
A43: Sous-Traitance | C43: 0 | D43: 0
C45: TOTAL COUT | D45: =SUM(D29:D43) -> 4562.012
C46: Marge Exploitation | D46: =F24-D45 -> 390.55995
C48: % Marge | D48: =D46/F24 -> 0.078860025

Sheet CM59
A1: FICHE DE RENTABILITE
A3: DONNEES EXPLOITATION
B4: Immatriculation | D4: Conso au 100 (Moyenne) | F4: Semaine | G4: S15
A5: Tracteur (s) | B5: GP-189-NY | D5: 34.84
A6: Semi (s) | B6: Remorque | D6: 0.019
A7: Conducteurs | B7: MOROAINU Mihail
A8: AMPLITUDE Hebdo | B8: 64
A9: TDS Hebdo | B9: 44.19
B10: KM Hebdo | G10: Hotel (semaine)
B11: 2036 | G11: 0
A12: Autoroute / jour : | B12: 33.98 | F12: SPL | G12: CM
E13: €/ Hebdo | F13: 1000 | G13: 1100
A14: Détails CA
A15: Référence prestations | B15: Fréquence | C15: Montant unitaire | D15: Quantité | E15: Total Hors IGO | F15: Indexation | G15: Montant Total
A16: CHRONOPOST : 38922 | B16: Lundi au vendredi | C16: 695 | D16: 5 | E16: =C16*D16 -> 3475 | F16: =(288*5)*0.2922 -> 420.768 | G16: =(E16+F16) -> 3895.768
A17: WE : Colissimo LTH-007-CM | B17: Samedi | C17: 2.5021 | D17: 103 | E17: =C17*D17 -> 257.7163 | F17: 0 | G17: =(E17*F17)+E17 -> 257.7163
A18: COLISSIMO : LTH-007-CM | B18: Jeudi & Vendredi | C18: 2.5021 | D18: =84*2 -> 168 | E18: =C18*D18 -> 420.3528 | F18: 0 | G18: =(E18+F18) -> 420.3528
E19: =C19*D19 -> 0 | G19: =(E19*F19)+E19 -> 0
E20: =C20*D20 -> 0 | G20: =(E20*F20)+E20 -> 0
E21: =C21*D21 -> 0 | G21: =(E21*F21)+E21 -> 0
E22: =C22*D22 -> 0 | G22: =(E22*F22)+E22 -> 0
A24: CM59 | B24: CA DE LA LIGNE | F24: =SUM(G16:G22) -> 4573.8371
A25: SOMMAIRE
A27: Coûts de la Ligne
B28: Type | C28: unité | D28: Cout Semaine
A29: Moteur(1) | B29: Porteur SWAPGNC | C29: =IFERROR(VLOOKUP(B29,Liste!C1:D5,2,FALSE),"") -> 3000 | D29: =IFERROR(C29/4.33,0) -> 692.84065
A30: Semi (1) | B30: Remorque SWAP | C30: =IFERROR(VLOOKUP(B30,Liste!$C$7:$D$15,2,FALSE),"") -> 400 | D30: =IFERROR(C30/4.33,0) -> 92.378753
A31: Semi (2) | B31: AUCUNE | C31: =IFERROR(VLOOKUP(B31,Liste!$C$7:$D$15,2,FALSE),"") | D31: =IFERROR(C31/4.33,0) -> 0
A32: Semi (3) | B32: AUCUNE | C32: =IFERROR(VLOOKUP(B32,Liste!$C$7:$D$15,2,FALSE),"") | D32: =IFERROR(C32/4.33,0) -> 0
A33: Semi (4) | B33: AUCUNE | C33: =IFERROR(VLOOKUP(B33,Liste!$C$7:$D$15,2,FALSE),"") | D33: =IFERROR(C33/4.33,0) -> 0
A34: Carburant | B34: GO | C34: 0 | D34: =(B11*D5/100)*C34 -> 0
A35: Carburant | B35: GNC | C35: 1.365 | D35: =(D5*B11/100)*C35 -> 968.25238
A36: AD Blue | C36: 0 | D36: =(D6*B11)*C36 -> 0
A37: Fuel | C37: 1.1225
A38: Casse / Pneumatique / Lavage ( hors entretien) | C38: 0.04 | D38: =C38*B11 -> 81.44
A39: Autoroute | B39: =B12 -> 33.98 | C39: 5 | D39: =(C39*B39) -> 169.9
A40: Salaires | B40: CM | C40: 1 | D40: 1230.07
A41: Frais Hotel | D41: =G11 -> 0
A42: Tirpalette | B42: NON | C42: =IF(B42=Liste!A24,Liste!B18,0) -> 0 | D42: =C42/4.33 -> 0
A43: Sous-Traitance | C43: 0 | D43: 0
C45: TOTAL COUT | D45: =SUM(D29:D43) -> 3234.8818
C46: Marge Exploitation | D46: =F24-D45 -> 1338.9553
C48: % Marge | D48: =D46/F24 -> 0.29274224

Sheet CM60
A1: FICHE DE RENTABILITE
A3: DONNEES EXPLOITATION
B4: Immatriculation | D4: Conso au 100 (Moyenne) | F4: Semaine | G4: S16
A5: Tracteur (s) | B5: GC-075-RE | D5: 33.5
A6: Semi (s) | B6: Remorque | D6: 0.019
A7: Conducteurs | B7: MOROAINU ION
A8: AMPLITUDE Hebdo | B8: 63.08
A9: TDS Hebdo | B9: 54.09
B10: KM Hebdo | G10: Hotel (semaine)
B11: 1408 | G11: 0
A12: Autoroute / jour : | B12: 34.74 | F12: SPL | G12: CM
E13: €/ Hebdo | F13: 1000 | G13: 1100
A14: Détails CA
A15: Référence prestations | B15: Fréquence | C15: Montant unitaire | D15: Quantité | E15: Total Hors IGO | F15: Indexation | G15: Montant Total
A16: COLISSIMO : LTH-007-CM | B16: Lundi au vendredi | C16: 2.5021 | D16: =84+84+168+336+420 -> 1092 | E16: =C16*D16 -> 2732.2932 | F16: 0 | G16: =(E16+F16) -> 2732.2932
A17: WE : Colissimo LTH-007-CM | B17: Samedi | C17: 2.5021 | D17: 103 | E17: =C17*D17 -> 257.7163 | F17: 0 | G17: =(E17*F17)+E17 -> 257.7163
A19: Colissimo : LTH-004-CM | B19: Lundi au Vendredi | C19: 4.1631 | D19: =10*5 -> 50 | E19: =C19*D19 -> 208.155 | F19: 0 | G19: =(E19*F19)+E19 -> 208.155
E20: =C20*D20 -> 0 | G20: =(E20*F20)+E20 -> 0
E21: =C21*D21 -> 0 | G21: =(E21*F21)+E21 -> 0
E22: =C22*D22 -> 0 | G22: =(E22*F22)+E22 -> 0
A24: CM60 | B24: CA DE LA LIGNE | F24: =SUM(G16:G22) -> 3198.1645
A25: SOMMAIRE
A27: Coûts de la Ligne
B28: Type | C28: unité | D28: Cout Semaine
A29: Moteur(1) | B29: Porteur SWAPGNC | C29: =IFERROR(VLOOKUP(B29,Liste!C1:D5,2,FALSE),"") -> 3000 | D29: =IFERROR(C29/4.33,0) -> 692.84065
A30: Semi (1) | B30: Remorque SWAP | C30: =IFERROR(VLOOKUP(B30,Liste!$C$7:$D$15,2,FALSE),"") -> 400 | D30: =IFERROR(C30/4.33,0) -> 92.378753
A31: Semi (2) | B31: AUCUNE | C31: =IFERROR(VLOOKUP(B31,Liste!$C$7:$D$15,2,FALSE),"") | D31: =IFERROR(C31/4.33,0) -> 0
A32: Semi (3) | B32: AUCUNE | C32: =IFERROR(VLOOKUP(B32,Liste!$C$7:$D$15,2,FALSE),"") | D32: =IFERROR(C32/4.33,0) -> 0
A33: Semi (4) | B33: AUCUNE | C33: =IFERROR(VLOOKUP(B33,Liste!$C$7:$D$15,2,FALSE),"") | D33: =IFERROR(C33/4.33,0) -> 0
A34: Carburant | B34: GO | C34: 0 | D34: =(B11*D5/100)*C34 -> 0
A35: Carburant | B35: GNC | C35: 1.365 | D35: =(D5*B11/100)*C35 -> 643.8432
A36: AD Blue | C36: 0 | D36: =(D6*B11)*C36 -> 0
A37: Fuel | C37: 1.1225
A38: Casse / Pneumatique / Lavage ( hors entretien) | C38: 0.04 | D38: =C38*B11 -> 56.32
A39: Autoroute | B39: =B12 -> 34.74 | C39: 5 | D39: =13*9.16 -> 119.08
A40: Salaires | B40: CM | C40: 1 | D40: 1297.18
A41: Frais Hotel | D41: =G11 -> 0
A42: Tirpalette | B42: NON | C42: =IF(B42=Liste!A24,Liste!B18,0) -> 0 | D42: =C42/4.33 -> 0
A43: Sous-Traitance | C43: 0 | D43: 0
C45: TOTAL COUT | D45: =SUM(D29:D43) -> 2901.6426
C46: Marge Exploitation | D46: =F24-D45 -> 296.5219
C48: % Marge | D48: =D46/F24 -> 0.092716275

Sheet CM48
A1: FICHE DE RENTABILITE
A3: DONNEES EXPLOITATION
B4: Immatriculation | D4: Conso au 100 (Moyenne) | F4: Semaine | G4: S15
A5: Tracteur (s) | B5: DM-332-AC | D5: 30.54
A6: Semi (s) | B6: Remorque | D6: 0.019
A7: Conducteurs | B7: BOUTCHIHI
A8: AMPLITUDE Hebdo | B8: 58.81
A9: TDS Hebdo | B9: 52.42
B10: KM Hebdo | G10: Hotel (semaine)
B11: 3121 | G11: 0
A12: Autoroute / jour : | B12: 165.76 | F12: SPL | G12: CM
E13: €/ Hebdo | F13: 1000 | G13: 1100
A14: Détails CA
A15: Référence prestations | B15: Fréquence | C15: Montant unitaire | D15: Quantité | E15: Total Hors IGO | F15: Indexation | G15: Montant Total
A16: UPS : Le Mans | B16: Lundi au Vendredi | C16: 800 | D16: 5 | E16: =C16*D16 -> 4000 | F16: -0.0226 | G16: =(E16*F16)+E16 -> 3909.6
E17: =C17*D17 -> 0 | G17: =(E17*F17)+E17 -> 0
A18: Tourne sur 5 jours | E18: =C18*D18 -> 0 | G18: =(E18*F18)+E18 -> 0
E19: =C19*D19 -> 0 | G19: =(E19*F19)+E19 -> 0
E20: =C20*D20 -> 0 | G20: =(E20*F20)+E20 -> 0
E21: =C21*D21 -> 0 | G21: =(E21*F21)+E21 -> 0
E22: =C22*D22 -> 0 | G22: =(E22*F22)+E22 -> 0
A24: CM48 | B24: CA DE LA LIGNE | F24: =SUM(G16:G22) -> 3909.6
A25: SOMMAIRE
A27: Coûts de la Ligne
B28: Type | C28: unité | D28: Cout Semaine
A29: Moteur(1) | B29: Porteur SWAPGO | C29: =IFERROR(VLOOKUP(B29,Liste!C1:D5,2,FALSE),"") -> 2500 | D29: =IFERROR(C29/4.33,0) -> 577.36721
A30: Semi (1) | B30: Remorque SWAP | C30: =IFERROR(VLOOKUP(B30,Liste!$C$7:$D$15,2,FALSE),"") -> 400 | D30: =IFERROR(C30/4.33,0) -> 92.378753
A31: Semi (2) | B31: AUCUNE | C31: =IFERROR(VLOOKUP(B31,Liste!$C$7:$D$15,2,FALSE),"") | D31: =IFERROR(C31/4.33,0) -> 0
A32: Semi (3) | B32: AUCUNE | C32: =IFERROR(VLOOKUP(B32,Liste!$C$7:$D$15,2,FALSE),"") | D32: =IFERROR(C32/4.33,0) -> 0
A33: Semi (4) | B33: AUCUNE | C33: =IFERROR(VLOOKUP(B33,Liste!$C$7:$D$15,2,FALSE),"") | D33: =IFERROR(C33/4.33,0) -> 0
A34: Carburant | B34: GO | C34: 1.3554 | D34: =(B11*D5/100)*C34 -> 1291.9041
A35: Carburant | B35: GNC | C35: 0 | D35: =(D5*B11/100)*C35 -> 0
A36: AD Blue | C36: 0.4309 | D36: =(D6*B11)*C36 -> 25.551939
A37: Fuel | C37: 1.1225
A38: Casse / Pneumatique / Lavage ( hors entretien) | C38: 0.04 | D38: =C38*B11 -> 124.84
A39: Autoroute | B39: =B12 -> 165.76 | C39: 5 | D39: =(C39*B39) -> 828.8
A40: Salaires | B40: CM | C40: 1 | D40: 977.57
A41: Frais Hotel | D41: =G11 -> 0
A42: Tirpalette | B42: NON | C42: =IF(B42=Liste!A24,Liste!B18,0) -> 0 | D42: =C42/4.33 -> 0
A43: Sous-Traitance | C43: 0 | D43: 0
C45: TOTAL COUT | D45: =SUM(D29:D43) -> 3918.412
C46: Marge Exploitation | D46: =F24-D45 -> -8.8120159
C48: % Marge | D48: =D46/F24 -> -0.0022539431

Sheet CM42
A1: FICHE DE RENTABILITE
A3: DONNEES EXPLOITATION
B4: Immatriculation | D4: Conso au 100 (Moyenne) | F4: Semaine | G4: S16
A5: Tracteur (s) | B5: ED-021-WG | D5: 30.32
A6: Semi (s) | B6: Remorque | D6: 0.019
A7: Conducteurs | B7: MADANI
A8: AMPLITUDE Hebdo | B8: 54.18
A9: TDS Hebdo | B9: 42.12
B10: KM Hebdo | G10: Hotel (semaine)
B11: 2607 | G11: 0
A12: Autoroute / jour : | B12: 91.5 | F12: SPL | G12: CM
E13: €/ Hebdo | F13: 1000 | G13: 1100
A14: Détails CA
A15: Référence prestations | B15: Fréquence | C15: Montant unitaire | D15: Quantité | E15: Total Hors IGO | F15: Indexation | G15: Montant Total
A16: UPS : Lesquin | B16: Lundi au Vendredi | C16: 680 | D16: 5 | E16: =C16*D16 -> 3400 | F16: -0.0226 | G16: =(E16*F16)+E16 -> 3323.16
E17: =C17*D17 -> 0 | G17: =(E17*F17)+E17 -> 0
A18: Tourne sur 5 jours | E18: =C18*D18 -> 0 | G18: =(E18*F18)+E18 -> 0
E19: =C19*D19 -> 0 | G19: =(E19*F19)+E19 -> 0
E20: =C20*D20 -> 0 | G20: =(E20*F20)+E20 -> 0
E21: =C21*D21 -> 0 | G21: =(E21*F21)+E21 -> 0
E22: =C22*D22 -> 0 | G22: =(E22*F22)+E22 -> 0
A24: CM42 | B24: CA DE LA LIGNE | F24: =SUM(G16:G22) -> 3323.16
A25: SOMMAIRE
A27: Coûts de la Ligne
B28: Type | C28: unité | D28: Cout Semaine
A29: Moteur(1) | B29: Porteur SWAPGO | C29: =IFERROR(VLOOKUP(B29,Liste!C1:D5,2,FALSE),"") -> 2500 | D29: =IFERROR(C29/4.33,0) -> 577.36721
A30: Semi (1) | B30: Remorque SWAP | C30: =IFERROR(VLOOKUP(B30,Liste!$C$7:$D$15,2,FALSE),"") -> 400 | D30: =IFERROR(C30/4.33,0) -> 92.378753
A31: Semi (2) | B31: AUCUNE | C31: =IFERROR(VLOOKUP(B31,Liste!$C$7:$D$15,2,FALSE),"") | D31: =IFERROR(C31/4.33,0) -> 0
A32: Semi (3) | B32: AUCUNE | C32: =IFERROR(VLOOKUP(B32,Liste!$C$7:$D$15,2,FALSE),"") | D32: =IFERROR(C32/4.33,0) -> 0
A33: Semi (4) | B33: AUCUNE | C33: =IFERROR(VLOOKUP(B33,Liste!$C$7:$D$15,2,FALSE),"") | D33: =IFERROR(C33/4.33,0) -> 0
A34: Carburant | B34: GO | C34: 1.3554 | D34: =(B11*D5/100)*C34 -> 1071.3656
A35: Carburant | B35: GNC | C35: 0 | D35: =(D5*B11/100)*C35 -> 0
A36: AD Blue | C36: 0.4309 | D36: =(D6*B11)*C36 -> 21.34377
A37: Fuel | C37: 1.1225
A38: Casse / Pneumatique / Lavage ( hors entretien) | C38: 0.04 | D38: =C38*B11 -> 104.28
A39: Autoroute | B39: =B12 -> 91.5 | C39: 5 | D39: =(C39*B39) -> 457.5
A40: Salaires | B40: CM | C40: 1 | D40: 1093.27
A41: Frais Hotel | D41: =G11 -> 0
A42: Tirpalette | B42: NON | C42: =IF(B42=Liste!A24,Liste!B18,0) -> 0 | D42: =C42/4.33 -> 0
A43: Sous-Traitance | C43: 0 | D43: 0
C45: TOTAL COUT | D45: =SUM(D29:D43) -> 3417.5054
C46: Marge Exploitation | D46: =F24-D45 -> -94.345357
C48: % Marge | D48: =D46/F24 -> -0.028390254

Sheet CM41
A1: FICHE DE RENTABILITE
A3: DONNEES EXPLOITATION
B4: Immatriculation | D4: Conso au 100 (Moyenne) | F4: Semaine | G4: S16
A5: Tracteur (s) | B5: GC-656-JM | D5: 31.75
A6: Semi (s) | B6: Remorque | D6: 0.019
A7: Conducteurs | B7: LAMBERT
A8: AMPLITUDE Hebdo | B8: 57.87
A9: TDS Hebdo | B9: 37
B10: KM Hebdo | G10: Hotel (semaine)
B11: 1084 | G11: 0
A12: Autoroute / jour : | B12: 0 | F12: SPL | G12: CM
E13: €/ Hebdo | F13: 1000 | G13: 1100
A14: Détails CA
A15: Référence prestations | B15: Fréquence | C15: Montant unitaire | D15: Quantité | E15: Total Hors IGO | F15: Indexation | G15: Montant Total
A16: CHRONOPOST Chilly : 40U96 | B16: Mardi au Samedi | C16: 155 | D16: 5 | E16: =C16*D16 -> 775 | F16: =0.28*5 -> 1.4 | G16: =F16+E16 -> 776.4
A17: CHRONOPOST Beaugrenelle : 28395 | B17: Mardi au Samedi | C17: 164 | D17: 5 | E17: =C17*D17 -> 820 | F17: =(65*5)*0.2922 -> 94.965 | G17: =F17+E17 -> 914.965
A18: CHRONOPOST MAD : 38853 | B18: Lundi au Vendredi | C18: 476 | D18: 5 | E18: =C18*D18 -> 2380 | F18: 0 | G18: =(E18*F18)+E18 -> 2380
E19: =C19*D19 -> 0 | G19: =(E19*F19)+E19 -> 0
E20: =C20*D20 -> 0 | G20: =(E20*F20)+E20 -> 0
E21: =C21*D21 -> 0 | G21: =(E21*F21)+E21 -> 0
E22: =C22*D22 -> 0 | G22: =(E22*F22)+E22 -> 0
A24: CM41 | B24: CA DE LA LIGNE | F24: =SUM(G16:G22) -> 4071.365
A25: SOMMAIRE
A27: Coûts de la Ligne
B28: Type | C28: unité | D28: Cout Semaine
A29: Moteur(1) | B29: Porteur SWAPGNC | C29: =IFERROR(VLOOKUP(B29,Liste!C1:D5,2,FALSE),"") -> 3000 | D29: =IFERROR(C29/4.33,0) -> 692.84065
A30: Semi (1) | B30: Remorque SWAP | C30: =IFERROR(VLOOKUP(B30,Liste!$C$7:$D$15,2,FALSE),"") -> 400 | D30: =IFERROR(C30/4.33,0) -> 92.378753
A31: Semi (2) | B31: AUCUNE | C31: =IFERROR(VLOOKUP(B31,Liste!$C$7:$D$15,2,FALSE),"") | D31: =IFERROR(C31/4.33,0) -> 0
A32: Semi (3) | B32: AUCUNE | C32: =IFERROR(VLOOKUP(B32,Liste!$C$7:$D$15,2,FALSE),"") | D32: =IFERROR(C32/4.33,0) -> 0
A33: Semi (4) | B33: AUCUNE | C33: =IFERROR(VLOOKUP(B33,Liste!$C$7:$D$15,2,FALSE),"") | D33: =IFERROR(C33/4.33,0) -> 0
A34: Carburant | B34: GO | C34: 0 | D34: =(B11*D5/100)*C34 -> 0
A35: Carburant | B35: GNC | C35: 1.365 | D35: =(D5*B11/100)*C35 -> 469.79205
A36: AD Blue | C36: 0 | D36: =(D6*B11)*C36 -> 0
A37: Fuel | C37: 1.1225
A38: Casse / Pneumatique / Lavage ( hors entretien) | C38: 0.04 | D38: =C38*B11 -> 43.36
A39: Autoroute | B39: =B12 -> 0 | C39: 5 | D39: =(C39*B39) -> 0
A40: Salaires | B40: CM | C40: 1 | D40: 1153.19
A41: Frais Hotel | D41: =G11 -> 0
A42: Tirpalette | B42: NON | C42: =IF(B42=Liste!A24,Liste!B18,0) -> 0 | D42: =C42/4.33 -> 0
A43: Sous-Traitance | C43: 0 | D43: 0
C45: TOTAL COUT | D45: =SUM(D29:D43) -> 2451.5614
C46: Marge Exploitation | D46: =F24-D45 -> 1619.8036
C48: % Marge | D48: =D46/F24 -> 0.3978527

Sheet CM39
A1: FICHE DE RENTABILITE
A3: DONNEES EXPLOITATION
B4: Immatriculation | D4: Conso au 100 (Moyenne) | F4: Semaine | G4: S16
A5: Tracteur (s) | B5: GD-286-BZ | D5: 30.32
A6: Semi (s) | B6: Remorque | D6: 0.019
A7: Conducteurs | B7: ROMAN Alexandru
A8: AMPLITUDE Hebdo | B8: 62.29
A9: TDS Hebdo | B9: 39.45
B10: KM Hebdo | G10: Hotel (semaine)
B11: 1335 | G11: 0
A12: Autoroute / jour : | B12: 0 | F12: SPL | G12: CM
E13: €/ Hebdo | F13: 1000 | G13: 1100
A14: Détails CA
A15: Référence prestations | B15: Fréquence | C15: Montant unitaire | D15: Quantité | E15: Total Hors IGO | F15: Indexation | G15: Montant Total
A16: CHRONOPOST : 28395 | B16: Lundi au Vendredi | C16: 164 | D16: 5 | E16: =C16*D16 -> 820 | F16: =(65*5)*0.2922 -> 94.965 | G16: =F16+E16 -> 914.965
A17: CHRONOPOST : 28386 | B17: Mardi au Samedi | C17: 442 | D17: 5 | E17: =C17*D17 -> 2210 | F17: =(133*5)*0.2922 -> 194.313 | G17: =F17+E17 -> 2404.313
E18: =C18*D18 -> 0 | G18: =(E18*F18)+E18 -> 0
A19: Tourne sur 5 jours | E19: =C19*D19 -> 0 | G19: =(E19*F19)+E19 -> 0
E20: =C20*D20 -> 0 | G20: =(E20*F20)+E20 -> 0
E21: =C21*D21 -> 0 | G21: =(E21*F21)+E21 -> 0
E22: =C22*D22 -> 0 | G22: =(E22*F22)+E22 -> 0
A24: CM39 | B24: CA DE LA LIGNE | F24: =SUM(G16:G22) -> 3319.278
A25: SOMMAIRE
A27: Coûts de la Ligne
B28: Type | C28: unité | D28: Cout Semaine
A29: Moteur(1) | B29: Porteur SWAPGNC | C29: =IFERROR(VLOOKUP(B29,Liste!C1:D5,2,FALSE),"") -> 3000 | D29: =IFERROR(C29/4.33,0) -> 692.84065
A30: Semi (1) | B30: Remorque SWAP | C30: =IFERROR(VLOOKUP(B30,Liste!$C$7:$D$15,2,FALSE),"") -> 400 | D30: =IFERROR(C30/4.33,0) -> 92.378753
A31: Semi (2) | B31: AUCUNE | C31: =IFERROR(VLOOKUP(B31,Liste!$C$7:$D$15,2,FALSE),"") | D31: =IFERROR(C31/4.33,0) -> 0
A32: Semi (3) | B32: AUCUNE | C32: =IFERROR(VLOOKUP(B32,Liste!$C$7:$D$15,2,FALSE),"") | D32: =IFERROR(C32/4.33,0) -> 0
A33: Semi (4) | B33: AUCUNE | C33: =IFERROR(VLOOKUP(B33,Liste!$C$7:$D$15,2,FALSE),"") | D33: =IFERROR(C33/4.33,0) -> 0
A34: Carburant | B34: GO | C34: 0 | D34: =(B11*D5/100)*C34 -> 0
A35: Carburant | B35: GNC | C35: 1.365 | D35: =(D5*B11/100)*C35 -> 552.51378
A36: AD Blue | C36: 0 | D36: =(D6*B11)*C36 -> 0
A37: Fuel | C37: 1.1225
A38: Casse / Pneumatique / Lavage ( hors entretien) | C38: 0.04 | D38: =C38*B11 -> 53.4
A39: Autoroute | B39: =B12 -> 0 | C39: 5 | D39: =(C39*B39) -> 0
A40: Salaires | B40: CM | C40: 1 | D40: 913.33
A41: Frais Hotel | D41: =G11 -> 0
A42: Tirpalette | B42: NON | C42: =IF(B42=Liste!A24,Liste!B18,0) -> 0 | D42: =C42/4.33 -> 0
A43: Sous-Traitance | C43: 0 | D43: 0
C45: TOTAL COUT | D45: =SUM(D29:D43) -> 2304.4632
C46: Marge Exploitation | D46: =F24-D45 -> 1014.8148
C48: % Marge | D48: =D46/F24 -> 0.3057336

Sheet CM37
A1: FICHE DE RENTABILITE
A3: DONNEES EXPLOITATION
B4: Immatriculation | D4: Conso au 100 (Moyenne) | F4: Semaine | G4: S15
A5: Tracteur (s) | B5: GG-157-FX | D5: 30.2
A6: Semi (s) | B6: Remorque | D6: 0.019
A7: Conducteurs | B7: HELLOU
A8: AMPLITUDE Hebdo | B8: 72.87
A9: TDS Hebdo | B9: 41.2
B10: KM Hebdo | G10: Hotel (semaine)
B11: 992 | G11: 0
A12: Autoroute / jour : | B12: 0 | F12: SPL | G12: CM
E13: €/ Hebdo | F13: 1000 | G13: 1100
A14: Détails CA
A15: Référence prestations | B15: Fréquence | C15: Montant unitaire | D15: Quantité | E15: Total Hors IGO | F15: Indexation | G15: Montant Total
A16: CHRONOPOST : 29093 | B16: Lundi au Vendredi | C16: 226 | D16: 5 | E16: =C16*D16 -> 1130 | F16: =(31*5)*0.2922 -> 45.291 | G16: =F16+E16 -> 1175.291
A17: CHRONOPOST : 28525 | B17: Lundi au Vendredi | C17: 350 | D17: 5 | E17: =C17*D17 -> 1750 | F17: 0 | G17: =F17+E17 -> 1750
A18: WE : Colissimo LTH-004-CM | B18: Dimanche | C18: 4.1631 | D18: 10 | E18: =C18*D18 -> 41.631 | F18: 0 | G18: =(E18*F18)+E18 -> 41.631
A19: WE : Colissimo LTH-081-CM | B19: Dimanche | C19: 2.4933 | D19: 74 | E19: =C19*D19 -> 184.5042 | F19: 0 | G19: =(E19*F19)+E19 -> 184.5042
E20: =C20*D20 -> 0 | G20: =(E20*F20)+E20 -> 0
E21: =C21*D21 -> 0 | G21: =(E21*F21)+E21 -> 0
E22: =C22*D22 -> 0 | G22: =(E22*F22)+E22 -> 0
A24: CM37 | B24: CA DE LA LIGNE | F24: =SUM(G16:G22) -> 3151.4262
A25: SOMMAIRE
A27: Coûts de la Ligne
B28: Type | C28: unité | D28: Cout Semaine
A29: Moteur(1) | B29: Porteur SWAPGNC | C29: =IFERROR(VLOOKUP(B29,Liste!C1:D5,2,FALSE),"") -> 3000 | D29: =IFERROR(C29/4.33,0) -> 692.84065
A30: Semi (1) | B30: Remorque SWAP | C30: =IFERROR(VLOOKUP(B30,Liste!$C$7:$D$15,2,FALSE),"") -> 400 | D30: =IFERROR(C30/4.33,0) -> 92.378753
A31: Semi (2) | B31: AUCUNE | C31: =IFERROR(VLOOKUP(B31,Liste!$C$7:$D$15,2,FALSE),"") | D31: =IFERROR(C31/4.33,0) -> 0
A32: Semi (3) | B32: AUCUNE | C32: =IFERROR(VLOOKUP(B32,Liste!$C$7:$D$15,2,FALSE),"") | D32: =IFERROR(C32/4.33,0) -> 0
A33: Semi (4) | B33: AUCUNE | C33: =IFERROR(VLOOKUP(B33,Liste!$C$7:$D$15,2,FALSE),"") | D33: =IFERROR(C33/4.33,0) -> 0
A34: Carburant | B34: GO | C34: 0 | D34: =(B11*D5/100)*C34 -> 0
A35: Carburant | B35: GNC | C35: 1.365 | D35: =(D5*B11/100)*C35 -> 408.93216
A36: AD Blue | C36: 0 | D36: =(D6*B11)*C36 -> 0
A37: Fuel | C37: 1.1225
A38: Casse / Pneumatique / Lavage ( hors entretien) | C38: 0.04 | D38: =C38*B11 -> 39.68
A39: Autoroute | B39: =B12 -> 0 | C39: 5 | D39: =(C39*B39) -> 0
A40: Salaires | B40: CM | C40: 1 | D40: 1178.82
A41: Frais Hotel | D41: =G11 -> 0
A42: Tirpalette | B42: NON | C42: =IF(B42=Liste!A24,Liste!B18,0) -> 0 | D42: =C42/4.33 -> 0
A43: Sous-Traitance | C43: 0 | D43: 0
C45: TOTAL COUT | D45: =SUM(D29:D43) -> 2412.6516
C46: Marge Exploitation | D46: =F24-D45 -> 738.77464
C48: % Marge | D48: =D46/F24 -> 0.23442549

Sheet CM34
A1: FICHE DE RENTABILITE
A3: DONNEES EXPLOITATION
B4: Immatriculation | D4: Conso au 100 (Moyenne) | F4: Semaine | G4: S16
A5: Tracteur (s) | B5: FA-004-GR | D5: 32.26
A6: Semi (s) | B6: Remorque | D6: 0.019
A7: Conducteurs | B7: Faveur
A8: AMPLITUDE Hebdo | B8: 53.36
A9: TDS Hebdo | B9: 36.38
B10: KM Hebdo | G10: Hotel (semaine)
B11: 1569 | G11: 0
A12: Autoroute / jour : | B12: 60.25 | C12: Vérifier itinéraire Péages | F12: SPL | G12: CM
B13: (Au lieu de 8€ / jour) | C13: Faveur Remplace kinguele, n'a pas pris le bon itinéraire | E13: €/ Hebdo | F13: 1000 | G13: 1100
A14: Détails CA
A15: Référence prestations | B15: Fréquence | C15: Montant unitaire | D15: Quantité | E15: Total Hors IGO | F15: Indexation | G15: Montant Total
A16: CHRONOPOST : 30529 | B16: Lundi au Vendredi | C16: 536 | D16: 5 | E16: =C16*D16 -> 2680 | F16: =(316*5)*0.2673 -> 422.334 | G16: =F16+E16 -> 3102.334 | I16: Indexation GAZ - Véhicule GO
E17: =C17*D17 -> 0 | G17: =F17+E17 -> 0
A18: Tourne sur 5 jours | E18: =C18*D18 -> 0 | G18: =(E18*F18)+E18 -> 0
E19: =C19*D19 -> 0 | G19: =(E19*F19)+E19 -> 0
E20: =C20*D20 -> 0 | G20: =(E20*F20)+E20 -> 0
E21: =C21*D21 -> 0 | G21: =(E21*F21)+E21 -> 0
E22: =C22*D22 -> 0 | G22: =(E22*F22)+E22 -> 0
A24: CM34 | B24: CA DE LA LIGNE | F24: =SUM(G16:G22) -> 3102.334
A25: SOMMAIRE
A27: Coûts de la Ligne
B28: Type | C28: unité | D28: Cout Semaine
A29: Moteur(1) | B29: Porteur SWAPGO | C29: =IFERROR(VLOOKUP(B29,Liste!C1:D5,2,FALSE),"") -> 2500 | D29: =IFERROR(C29/4.33,0) -> 577.36721
A30: Semi (1) | B30: Remorque SWAP | C30: =IFERROR(VLOOKUP(B30,Liste!$C$7:$D$15,2,FALSE),"") -> 400 | D30: =IFERROR(C30/4.33,0) -> 92.378753
A31: Semi (2) | B31: AUCUNE | C31: =IFERROR(VLOOKUP(B31,Liste!$C$7:$D$15,2,FALSE),"") | D31: =IFERROR(C31/4.33,0) -> 0
A32: Semi (3) | B32: AUCUNE | C32: =IFERROR(VLOOKUP(B32,Liste!$C$7:$D$15,2,FALSE),"") | D32: =IFERROR(C32/4.33,0) -> 0
A33: Semi (4) | B33: AUCUNE | C33: =IFERROR(VLOOKUP(B33,Liste!$C$7:$D$15,2,FALSE),"") | D33: =IFERROR(C33/4.33,0) -> 0
A34: Carburant | B34: GO | C34: 1.3554 | D34: =(B11*D5/100)*C34 -> 686.04845
A35: Carburant | B35: GNC | C35: 0 | D35: =(D5*B11/100)*C35 -> 0
A36: AD Blue | C36: 0.4309 | D36: =(D6*B11)*C36 -> 12.84556
A37: Fuel | C37: 1.1225
A38: Casse / Pneumatique / Lavage ( hors entretien) | C38: 0.04 | D38: =C38*B11 -> 62.76
A39: Autoroute | B39: =B12 -> 60.25 | C39: 5 | D39: =(C39*B39) -> 301.25
A40: Salaires | B40: CM | C40: 1 | D40: 961.95
A41: Frais Hotel | D41: =G11 -> 0
A42: Tirpalette | B42: NON | C42: =IF(B42=Liste!A24,Liste!B18,0) -> 0 | D42: =C42/4.33 -> 0
A43: Sous-Traitance | C43: 0 | D43: 0
C45: TOTAL COUT | D45: =SUM(D29:D43) -> 2694.6
C46: Marge Exploitation | D46: =F24-D45 -> 407.73403
C48: % Marge | D48: =D46/F24 -> 0.13142815

Sheet CM29
A1: FICHE DE RENTABILITE
A3: DONNEES EXPLOITATION
B4: Immatriculation | D4: Conso au 100 (Moyenne) | F4: Semaine | G4: S16
A5: Tracteur (s) | B5: GK-737-LW | D5: 28.44
A6: Semi (s) | B6: Remorque | D6: 0.019
A7: Conducteurs | B7: BOUGHEZAL
A8: AMPLITUDE Hebdo | B8: 61.9
A9: TDS Hebdo | B9: 42.03
B10: KM Hebdo | G10: Hotel (semaine)
B11: 2591 | G11: 0
A12: Autoroute / jour : | B12: 91.5 | F12: SPL | G12: CM
E13: €/ Hebdo | F13: 1000 | G13: 1100
A14: Détails CA
A15: Référence prestations | B15: Fréquence | C15: Montant unitaire | D15: Quantité | E15: Total Hors IGO | F15: Indexation | G15: Montant Total
A16: CHRONOPOST : 29805 | B16: Lundi au Vendredi | C16: 680 | D16: 5 | E16: =C16*D16 -> 3400 | F16: =(466*5)*0.2922 -> 680.826 | G16: =F16+E16 -> 4080.826
E17: =C17*D17 -> 0 | G17: =F17+E17 -> 0
A18: Tourne sur 5 jours | E18: =C18*D18 -> 0 | G18: =(E18*F18)+E18 -> 0
E19: =C19*D19 -> 0 | G19: =(E19*F19)+E19 -> 0
E20: =C20*D20 -> 0 | G20: =(E20*F20)+E20 -> 0
E21: =C21*D21 -> 0 | G21: =(E21*F21)+E21 -> 0
E22: =C22*D22 -> 0 | G22: =(E22*F22)+E22 -> 0
A24: CM29 | B24: CA DE LA LIGNE | F24: =SUM(G16:G22) -> 4080.826
A25: SOMMAIRE
A27: Coûts de la Ligne
B28: Type | C28: unité | D28: Cout Semaine
A29: Moteur(1) | B29: Porteur SWAPGNC | C29: =IFERROR(VLOOKUP(B29,Liste!C1:D5,2,FALSE),"") -> 3000 | D29: =IFERROR(C29/4.33,0) -> 692.84065
A30: Semi (1) | B30: Remorque SWAP | C30: =IFERROR(VLOOKUP(B30,Liste!$C$7:$D$15,2,FALSE),"") -> 400 | D30: =IFERROR(C30/4.33,0) -> 92.378753
A31: Semi (2) | B31: AUCUNE | C31: =IFERROR(VLOOKUP(B31,Liste!$C$7:$D$15,2,FALSE),"") | D31: =IFERROR(C31/4.33,0) -> 0
A32: Semi (3) | B32: AUCUNE | C32: =IFERROR(VLOOKUP(B32,Liste!$C$7:$D$15,2,FALSE),"") | D32: =IFERROR(C32/4.33,0) -> 0
A33: Semi (4) | B33: AUCUNE | C33: =IFERROR(VLOOKUP(B33,Liste!$C$7:$D$15,2,FALSE),"") | D33: =IFERROR(C33/4.33,0) -> 0
A34: Carburant | B34: GO | C34: 0 | D34: =(B11*D5/100)*C34 -> 0
A35: Carburant | B35: GNC | C35: 1.365 | D35: =(D5*B11/100)*C35 -> 1005.8417
A36: AD Blue | C36: 0 | D36: =(D6*B11)*C36 -> 0
A37: Fuel | C37: 1.1225
A38: Casse / Pneumatique / Lavage ( hors entretien) | C38: 0.04 | D38: =C38*B11 -> 103.64
A39: Autoroute | B39: =B12 -> 91.5 | C39: 5 | D39: =(C39*B39) -> 457.5
A40: Salaires | B40: CM | C40: 1 | D40: 1157.76
A41: Frais Hotel | D41: =G11 -> 0
A42: Tirpalette | B42: NON | C42: =IF(B42=Liste!A24,Liste!B18,0) -> 0 | D42: =C42/4.33 -> 0
A43: Sous-Traitance | C43: 0 | D43: 0
C45: TOTAL COUT | D45: =SUM(D29:D43) -> 3509.9611
C46: Marge Exploitation | D46: =F24-D45 -> 570.86485
C48: % Marge | D48: =D46/F24 -> 0.13988954

Sheet CM27
A1: FICHE DE RENTABILITE
A3: DONNEES EXPLOITATION
B4: Immatriculation | D4: Conso au 100 (Moyenne) | F4: Semaine | G4: S16
A5: Tracteur (s) | B5: GC-975-VE | D5: 29.66
A6: Semi (s) | B6: Remorque | D6: 0.019
A7: Conducteurs | B7: JARDANI
A8: AMPLITUDE Hebdo | B8: 50.16
A9: TDS Hebdo | B9: 37.51
B10: KM Hebdo | G10: Hotel (semaine)
B11: 2130 | G11: 0
A12: Autoroute / jour : | B12: 43 | F12: SPL | G12: CM
E13: €/ Hebdo | F13: 1000 | G13: 1100
A14: Détails CA
A15: Référence prestations | B15: Fréquence | C15: Montant unitaire | D15: Quantité | E15: Total Hors IGO | F15: Indexation | G15: Montant Total
A16: CHRONOPOST : 38467 | B16: Lundi au Vendredi | C16: 530 | D16: 5 | E16: =C16*D16 -> 2650 | F16: =(336*5)*0.2922 -> 490.896 | G16: =F16+E16 -> 3140.896
E17: =C17*D17 -> 0 | G17: =F17+E17 -> 0
A18: Tourne sur 5 jours | E18: =C18*D18 -> 0 | G18: =(E18*F18)+E18 -> 0
E19: =C19*D19 -> 0 | G19: =(E19*F19)+E19 -> 0
E20: =C20*D20 -> 0 | G20: =(E20*F20)+E20 -> 0
E21: =C21*D21 -> 0 | G21: =(E21*F21)+E21 -> 0
E22: =C22*D22 -> 0 | G22: =(E22*F22)+E22 -> 0
A24: CM27 | B24: CA DE LA LIGNE | F24: =SUM(G16:G22) -> 3140.896
A25: SOMMAIRE
A27: Coûts de la Ligne
B28: Type | C28: unité | D28: Cout Semaine
A29: Moteur(1) | B29: Porteur SWAPGNC | C29: =IFERROR(VLOOKUP(B29,Liste!C1:D5,2,FALSE),"") -> 3000 | D29: =IFERROR(C29/4.33,0) -> 692.84065
A30: Semi (1) | B30: Remorque SWAP | C30: =IFERROR(VLOOKUP(B30,Liste!$C$7:$D$15,2,FALSE),"") -> 400 | D30: =IFERROR(C30/4.33,0) -> 92.378753
A31: Semi (2) | B31: AUCUNE | C31: =IFERROR(VLOOKUP(B31,Liste!$C$7:$D$15,2,FALSE),"") | D31: =IFERROR(C31/4.33,0) -> 0
A32: Semi (3) | B32: AUCUNE | C32: =IFERROR(VLOOKUP(B32,Liste!$C$7:$D$15,2,FALSE),"") | D32: =IFERROR(C32/4.33,0) -> 0
A33: Semi (4) | B33: AUCUNE | C33: =IFERROR(VLOOKUP(B33,Liste!$C$7:$D$15,2,FALSE),"") | D33: =IFERROR(C33/4.33,0) -> 0
A34: Carburant | B34: GO | C34: 0 | D34: =(B11*D5/100)*C34 -> 0
A35: Carburant | B35: GNC | C35: 1.3554 | D35: =(D5*B11/100)*C35 -> 856.28479
A36: AD Blue | C36: 0 | D36: =(D6*B11)*C36 -> 0
A37: Fuel | C37: 1.1225
A38: Casse / Pneumatique / Lavage ( hors entretien) | C38: 0.04 | D38: =C38*B11 -> 85.2
A39: Autoroute | B39: =B12 -> 43 | C39: 5 | D39: =(C39*B39) -> 215
A40: Salaires | B40: CM | C40: 1 | D40: 1201.03
A41: Frais Hotel | D41: =G11 -> 0
A42: Tirpalette | B42: NON | C42: =IF(B42=Liste!A24,Liste!B18,0) -> 0 | D42: =C42/4.33 -> 0
A43: Sous-Traitance | C43: 0 | D43: 0
C45: TOTAL COUT | D45: =SUM(D29:D43) -> 3142.7342
C46: Marge Exploitation | D46: =F24-D45 -> -1.8381927
C48: % Marge | D48: =D46/F24 -> -0.0005852447

Sheet CM24
A1: FICHE DE RENTABILITE
A3: DONNEES EXPLOITATION
B4: Immatriculation | D4: Conso au 100 (Moyenne) | F4: Semaine | G4: S15
A5: Tracteur (s) | B5: EJ-881-TR | D5: 32.45
A6: Semi (s) | B6: Remorque | D6: 0.019
A7: Conducteurs | B7: MOREL
A8: AMPLITUDE Hebdo | B8: 46.85
A9: TDS Hebdo | B9: 35.53
B10: KM Hebdo | G10: Hotel (semaine)
B11: 2368 | G11: 0
A12: Autoroute / jour : | B12: 138 | F12: SPL | G12: CM
E13: €/ Hebdo | F13: 1000 | G13: 1100
A14: Détails CA
A15: Référence prestations | B15: Fréquence | C15: Montant unitaire | D15: Quantité | E15: Total Hors IGO | F15: Indexation | G15: Montant Total
A16: UPS : E371 | B16: Lundi au Vendredi | C16: 640 | D16: 5 | E16: =C16*D16 -> 3200 | F16: -0.0226 | G16: =(E16*F16)+E16 -> 3127.68
A17: WE : VIAPOST : 163-14 | B17: Samedi | C17: 196.64 | D17: 1 | E17: =C17*D17 -> 196.64 | F17: 0.039775 | G17: =(E17*F17)+E17 -> 204.46136
A18: WE : VIAPOST : 163-7 | B18: Samedi | C18: 228.27 | D18: 1 | E18: =C18*D18 -> 228.27 | F18: 0.039775 | G18: =(E18*F18)+E18 -> 237.34944
A19: WE : VIAPOST : 164-9 | B19: Samedi | C19: 127.84 | D19: 1 | E19: =C19*D19 -> 127.84 | F19: 0.039775 | G19: =(E19*F19)+E19 -> 132.92484
E20: =C20*D20 -> 0 | G20: =(E20*F20)+E20 -> 0
E21: =C21*D21 -> 0 | G21: =(E21*F21)+E21 -> 0
E22: =C22*D22 -> 0 | G22: =(E22*F22)+E22 -> 0
A24: CM24 | B24: CA DE LA LIGNE | F24: =SUM(G16:G22) -> 3702.4156
A25: SOMMAIRE
A27: Coûts de la Ligne
B28: Type | C28: unité | D28: Cout Semaine
A29: Moteur(1) | B29: Porteur SWAPGO | C29: =IFERROR(VLOOKUP(B29,Liste!C1:D5,2,FALSE),"") -> 2500 | D29: =IFERROR(C29/4.33,0) -> 577.36721
A30: Semi (1) | B30: Remorque SWAP | C30: =IFERROR(VLOOKUP(B30,Liste!$C$7:$D$15,2,FALSE),"") -> 400 | D30: =IFERROR(C30/4.33,0) -> 92.378753
A31: Semi (2) | B31: AUCUNE | C31: =IFERROR(VLOOKUP(B31,Liste!$C$7:$D$15,2,FALSE),"") | D31: =IFERROR(C31/4.33,0) -> 0
A32: Semi (3) | B32: AUCUNE | C32: =IFERROR(VLOOKUP(B32,Liste!$C$7:$D$15,2,FALSE),"") | D32: =IFERROR(C32/4.33,0) -> 0
A33: Semi (4) | B33: AUCUNE | C33: =IFERROR(VLOOKUP(B33,Liste!$C$7:$D$15,2,FALSE),"") | D33: =IFERROR(C33/4.33,0) -> 0
A34: Carburant | B34: GO | C34: 1.3554 | D34: =(B11*D5/100)*C34 -> 1041.511
A35: Carburant | B35: GNC | C35: 0 | D35: =(D5*B11/100)*C35 -> 0
A36: AD Blue | C36: 0.4309 | D36: =(D6*B11)*C36 -> 19.387053
A37: Fuel | C37: 1.1225
A38: Casse / Pneumatique / Lavage ( hors entretien) | C38: 0.04 | D38: =C38*B11 -> 94.72
A39: Autoroute | B39: =B12 -> 138 | C39: 5 | D39: =(C39*B39) -> 690
A40: Salaires | B40: CM | C40: 1 | D40: 1233.87
A41: Frais Hotel | D41: =G11 -> 0
A42: Tirpalette | B42: NON | C42: =IF(B42=Liste!A24,Liste!B18,0) -> 0 | D42: =C42/4.33 -> 0
A43: Sous-Traitance | C43: 0 | D43: 0
C45: TOTAL COUT | D45: =SUM(D29:D43) -> 3749.2341
C46: Marge Exploitation | D46: =F24-D45 -> -46.818426
C48: % Marge | D48: =D46/F24 -> -0.012645373

Sheet CM21
A1: FICHE DE RENTABILITE
A3: DONNEES EXPLOITATION
B4: Immatriculation | D4: Conso au 100 (Moyenne) | F4: Semaine | G4: S16
A5: Tracteur (s) | B5: EK-841-AF | D5: 36.57
A6: Semi (s) | B6: Remorque | D6: 0.019
A7: Conducteurs | B7: BAJURA
A8: AMPLITUDE Hebdo | B8: 42.87
A9: TDS Hebdo | B9: 29.73
B10: KM Hebdo | G10: Hotel (semaine)
B11: 1227 | G11: 0
A12: Autoroute / jour : | B12: 0 | C12: Refacturation au réel | F12: SPL | G12: CM
E13: €/ Hebdo | F13: 1000 | G13: 1100
A14: Détails CA
A15: Référence prestations | B15: Fréquence | C15: Montant unitaire | D15: Quantité | E15: Total Hors IGO | F15: Indexation | G15: Montant Total
A16: TAB : Caisse Mobile | B16: Lundi au Vendredi | C16: 559 | D16: 5 | E16: =C16*D16 -> 2795 | F16: -0.043 | G16: =(E16*F16)+E16 -> 2674.815
E17: =C17*D17 -> 0 | G17: =(E17*F17)+E17 -> 0
A18: Tourne sur 5 jours | E18: =C18*D18 -> 0 | G18: =(E18*F18)+E18 -> 0
E19: =C19*D19 -> 0 | G19: =(E19*F19)+E19 -> 0
E20: =C20*D20 -> 0 | G20: =(E20*F20)+E20 -> 0
E21: =C21*D21 -> 0 | G21: =(E21*F21)+E21 -> 0
E22: =C22*D22 -> 0 | G22: =(E22*F22)+E22 -> 0
A24: CM21 | B24: CA DE LA LIGNE | F24: =SUM(G16:G22) -> 2674.815
A25: SOMMAIRE
A27: Coûts de la Ligne
B28: Type | C28: unité | D28: Cout Semaine
A29: Moteur(1) | B29: Porteur SWAPGO | C29: =IFERROR(VLOOKUP(B29,Liste!C1:D5,2,FALSE),"") -> 2500 | D29: =IFERROR(C29/4.33,0) -> 577.36721
A30: Semi (1) | B30: Remorque SWAP | C30: =IFERROR(VLOOKUP(B30,Liste!$C$7:$D$15,2,FALSE),"") -> 400 | D30: =IFERROR(C30/4.33,0) -> 92.378753
A31: Semi (2) | B31: AUCUNE | C31: =IFERROR(VLOOKUP(B31,Liste!$C$7:$D$15,2,FALSE),"") | D31: =IFERROR(C31/4.33,0) -> 0
A32: Semi (3) | B32: AUCUNE | C32: =IFERROR(VLOOKUP(B32,Liste!$C$7:$D$15,2,FALSE),"") | D32: =IFERROR(C32/4.33,0) -> 0
A33: Semi (4) | B33: AUCUNE | C33: =IFERROR(VLOOKUP(B33,Liste!$C$7:$D$15,2,FALSE),"") | D33: =IFERROR(C33/4.33,0) -> 0
A34: Carburant | B34: GO | C34: 1.3554 | D34: =(B11*D5/100)*C34 -> 608.18682
A35: Carburant | B35: GNC | C35: 0 | D35: =(D5*B11/100)*C35 -> 0
A36: AD Blue | C36: 0.4309 | D36: =(D6*B11)*C36 -> 10.045572
A37: Fuel | C37: 1.1225
A38: Casse / Pneumatique / Lavage ( hors entretien) | C38: 0.04 | D38: =C38*B11 -> 49.08
A39: Autoroute | B39: =B12 -> 0 | C39: 5 | D39: =(C39*B39) -> 0
A40: Salaires | B40: CM | C40: 1 | D40: 939.75
A41: Frais Hotel | D41: =G11 -> 0
A42: Tirpalette | B42: NON | C42: =IF(B42=Liste!A24,Liste!B18,0) -> 0 | D42: =C42/4.33 -> 0
A43: Sous-Traitance | C43: 0 | D43: 0
C45: TOTAL COUT | D45: =SUM(D29:D43) -> 2276.8084
C46: Marge Exploitation | D46: =F24-D45 -> 398.00665
C48: % Marge | D48: =D46/F24 -> 0.14879782

Sheet CM61
A1: FICHE DE RENTABILITE
A3: DONNEES EXPLOITATION
B4: Immatriculation | D4: Conso au 100 (Moyenne) | F4: Semaine | G4: S15
A5: Tracteur (s) | B5: EE-081-CX | D5: 35
A6: Semi (s) | D6: 0.019
A7: Conducteurs | B7: ALI MOHAMED
A8: AMPLITUDE Hebdo | B8: 53.25
A9: TDS Hebdo | B9: 46.17
B10: KM Hebdo | G10: Hotel (semaine)
B11: 351 | G11: 0
A12: Autoroute / jour : | B12: 0 | C12: Refacturation au réel | F12: SPL | G12: CM
E13: €/ Hebdo | F13: 1000 | G13: 1100
A14: Détails CA
A15: Référence prestations | B15: Fréquence | C15: Montant unitaire | D15: Quantité | E15: Total Hors IGO | F15: Indexation | G15: Montant Total
A16: Colissimo : PARC NANTERRE | B16: Mardi au Samedi | C16: 310.66 | D16: 5 | E16: =C16*D16 -> 1553.3 | F16: 0 | G16: =(E16*F16)+E16 -> 1553.3 | I16: Forfait 8h00/ jour
A17: WE : FEDEX FRT03412 | B17: Dimanche | C17: 410 | D17: 1 | E17: =C17*D17 -> 410 | F17: -0.0091 | G17: =(E17*F17)+E17 -> 406.269
E18: =C18*D18 -> 0 | G18: =(E18*F18)+E18 -> 0
E19: =C19*D19 -> 0 | G19: =(E19*F19)+E19 -> 0
E20: =C20*D20 -> 0 | G20: =(E20*F20)+E20 -> 0
E21: =C21*D21 -> 0 | G21: =(E21*F21)+E21 -> 0
E22: =C22*D22 -> 0 | G22: =(E22*F22)+E22 -> 0
A24: CM61 | B24: CA DE LA LIGNE | F24: =SUM(G16:G22) -> 1959.569
A25: SOMMAIRE
A27: Coûts de la Ligne
B28: Type | C28: unité | D28: Cout Semaine
A29: Moteur(1) | B29: Porteur SWAPGO | C29: =IFERROR(VLOOKUP(B29,Liste!C1:D5,2,FALSE),"") -> 2500 | D29: =IFERROR(C29/4.33,0) -> 577.36721
A30: Semi (1) | B30: AUCUNE | C30: =IFERROR(VLOOKUP(B30,Liste!$C$7:$D$15,2,FALSE),"") | D30: =IFERROR(C30/4.33,0) -> 0
A31: Semi (2) | B31: AUCUNE | C31: =IFERROR(VLOOKUP(B31,Liste!$C$7:$D$15,2,FALSE),"") | D31: =IFERROR(C31/4.33,0) -> 0
A32: Semi (3) | B32: AUCUNE | C32: =IFERROR(VLOOKUP(B32,Liste!$C$7:$D$15,2,FALSE),"") | D32: =IFERROR(C32/4.33,0) -> 0
A33: Semi (4) | B33: AUCUNE | C33: =IFERROR(VLOOKUP(B33,Liste!$C$7:$D$15,2,FALSE),"") | D33: =IFERROR(C33/4.33,0) -> 0
A34: Carburant | B34: GO | C34: 1.3554 | D34: =(B11*D5/100)*C34 -> 166.51089
A35: Carburant | B35: GNC | C35: 0 | D35: =(D5*B11/100)*C35 -> 0
A36: AD Blue | C36: 0.4309 | D36: =(D6*B11)*C36 -> 2.8736721
A37: Fuel | C37: 1.1225
A38: Casse / Pneumatique / Lavage ( hors entretien) | C38: 0.04 | D38: =C38*B11 -> 14.04
A39: Autoroute | B39: =B12 -> 0 | C39: 5 | D39: =(C39*B39) -> 0
A40: Salaires | B40: CM | C40: 1 | D40: 957.28
A41: Frais Hotel | D41: =G11 -> 0
A42: Tirpalette | B42: NON | C42: =IF(B42=Liste!A24,Liste!B18,0) -> 0 | D42: =C42/4.33 -> 0
A43: Sous-Traitance | C43: 0 | D43: 0
C45: TOTAL COUT | D45: =SUM(D29:D43) -> 1718.0718
C46: Marge Exploitation | D46: =F24-D45 -> 241.49723
C48: % Marge | D48: =D46/F24 -> 0.12323997

Sheet Cumul CM
A1: FICHE DE RENTABILITE
A3: DONNEES EXPLOITATION
B4: Immatriculation | D4: Conso au 100 (Moyenne) | F4: Semaine | G4: S11
A5: Tracteur (s)
A6: Semi (s) | D6: 0.019
A7: Conducteurs
A8: AMPLITUDE Hebdo
A9: TDS Hebdo
B10: KM Hebdo | G10: Hotel (semaine)
G11: 0
A12: Autoroute / jour : | B12: 0 | F12: SPL | G12: CM
E13: €/ Hebdo | F13: 1000 | G13: 1100
A14: Détails CA
A15: Référence prestations | B15: Fréquence | C15: Montant unitaire | D15: Quantité | E15: Total Hors IGO | F15: Indexation | G15: Montant Total
A16: CUMUL CM
A24: CUMUL CM | B24: CA DE LA LIGNE | F24: ='CM21'!F24+'CM24'!F24+'CM27'!F24+'CM29'!F24+'CM34'!F24+'CM37'!F24+'CM39'!F24+'CM41'!F24+'CM42'!F24+'CM48'!F24+'CM60'!F24+'CM59'!F24+'CM26'!F24+'CM25'!F24+'CM23'!F24+'CM19'!F24+'CM15'!F24+'CM14'!F24+'CM7'!F24+'CM53'!F24+'CM44'!F24+'CM5'!F24+'CM10'!F24+'CM9'!F24+'CM8'!F24+'CM6'!F24+'CM4'!F24+'CM61'!F24 -> 132381.54
A25: SOMMAIRE
A27: Coûts de la Ligne
B28: Type | C28: unité | D28: Cout Semaine
A29: Moteur(1) | B29: Porteur SWAPGO | D29: ='CM4'!D29+'CM6'!D29+'CM8'!D29+'CM9'!D29+'CM10'!D29+'CM5'!D29+'CM5'!D30+'CM44'!D29+'CM44'!D30+'CM53'!D29+'CM53'!D30+'CM7'!D29+'CM14'!D29+'CM15'!D29+'CM19'!D29+'CM19'!D30+'CM23'!D29+'CM25'!D29+'CM26'!D29+'CM59'!D29+'CM60'!D29+'CM48'!D29+'CM42'!D29+'CM41'!D29+'CM39'!D29+'CM37'!D29+'CM34'!D29+'CM29'!D29+'CM27'!D29+'CM24'!D29+'CM21'!D29+'CM61'!D29 -> 19399.538
A30: Semi (1) | B30: Remorque SWAP | D30: ='CM4'!D30+'CM6'!D30+'CM8'!D30+'CM9'!D30+'CM10'!D30+'CM5'!D31+'CM5'!D32+'CM44'!D31+'CM44'!D32+'CM53'!D31+'CM53'!D32+'CM7'!D30+'CM14'!D30+'CM15'!D30+'CM19'!D31+'CM19'!D32+'CM23'!D30+'CM25'!D30+'CM26'!D30+'CM59'!D30+'CM60'!D30+'CM48'!D30+'CM42'!D30+'CM41'!D30+'CM39'!D30+'CM37'!D30+'CM34'!D30+'CM29'!D30+'CM27'!D30+'CM24'!D30+'CM21'!D30 -> 2863.7413
A31: Semi (2) | B31: AUCUNE | C31: =IFERROR(VLOOKUP(B31,Liste!$C$7:$D$15,2,FALSE),"")
A32: Semi (3) | B32: AUCUNE | C32: =IFERROR(VLOOKUP(B32,Liste!$C$7:$D$15,2,FALSE),"")
A33: Semi (4) | B33: AUCUNE | C33: =IFERROR(VLOOKUP(B33,Liste!$C$7:$D$15,2,FALSE),"")
A34: Carburant | B34: GO | D34: ='CM21'!D34+'CM24'!D34+'CM27'!D34+'CM29'!D34+'CM34'!D34+'CM37'!D34+'CM39'!D34+'CM41'!D34+'CM42'!D34+'CM48'!D34+'CM60'!D34+'CM59'!D34+'CM26'!D34+'CM25'!D34+'CM23'!D34+'CM19'!D35+'CM15'!D34+'CM14'!D34+'CM7'!D34+'CM53'!D35+'CM44'!D35+'CM5'!D35+'CM10'!D34+'CM9'!D34+'CM8'!D34+'CM6'!D34+'CM4'!D34+'CM61'!D34 -> 25037.724
A35: Carburant | B35: GNC | D35: ='CM21'!D35+'CM24'!D35+'CM27'!D35+'CM29'!D35+'CM34'!D35+'CM37'!D35+'CM39'!D35+'CM41'!D35+'CM42'!D35+'CM48'!D35+'CM60'!D35+'CM59'!D35+'CM26'!D35+'CM25'!D35+'CM23'!D35+'CM19'!D36+'CM15'!D35+'CM14'!D35+'CM7'!D35+'CM53'!D36+'CM44'!D36+'CM5'!D36+'CM10'!D35+'CM9'!D35+'CM8'!D35+'CM6'!D35+'CM4'!D35 -> 6612.4046
A36: AD Blue | D36: ='CM21'!D36+'CM24'!D36+'CM27'!D36+'CM29'!D36+'CM34'!D36+'CM37'!D36+'CM39'!D36+'CM41'!D36+'CM42'!D36+'CM48'!D36+'CM60'!D36+'CM59'!D36+'CM26'!D36+'CM25'!D36+'CM23'!D36+'CM19'!D37+'CM15'!D36+'CM14'!D36+'CM7'!D36+'CM53'!D37+'CM44'!D37+'CM5'!D37+'CM10'!D36+'CM9'!D36+'CM8'!D36+'CM6'!D36+'CM4'!D36+'CM61'!D36 -> 501.33707
A37: Fuel
A38: Casse / Pneumatique / Lavage ( hors entretien) | C38: 0.04 | D38: ='CM21'!D38+'CM24'!D38+'CM27'!D38+'CM29'!D38+'CM34'!D38+'CM37'!D38+'CM39'!D38+'CM41'!D38+'CM42'!D38+'CM48'!D38+'CM60'!D38+'CM59'!D38+'CM26'!D38+'CM25'!D38+'CM23'!D38+'CM19'!D39+'CM15'!D38+'CM14'!D38+'CM7'!D38+'CM53'!D39+'CM44'!D39+'CM5'!D39+'CM10'!D38+'CM9'!D38+'CM8'!D38+'CM6'!D38+'CM4'!D38+'CM61'!D38 -> 3076.28
A39: Autoroute | B39: =B12 -> 0 | D39: ='CM21'!D39+'CM24'!D39+'CM27'!D39+'CM29'!D39+'CM34'!D39+'CM37'!D39+'CM39'!D39+'CM41'!D39+'CM42'!D39+'CM48'!D39+'CM60'!D39+'CM59'!D39+'CM26'!D39+'CM25'!D39+'CM23'!D39+'CM19'!D40+'CM15'!D39+'CM14'!D39+'CM7'!D39+'CM53'!D40+'CM44'!D40+'CM5'!D40+'CM10'!D39+'CM9'!D39+'CM8'!D39+'CM6'!D39+'CM4'!D39 -> 11876.08
A40: Salaires | B40: CM | C40: 1 | D40: ='CM21'!D40+'CM24'!D40+'CM27'!D40+'CM29'!D40+'CM34'!D40+'CM37'!D40+'CM39'!D40+'CM41'!D40+'CM42'!D40+'CM48'!D40+'CM60'!D40+'CM59'!D40+'CM26'!D40+'CM25'!D40+'CM23'!D40+'CM19'!D41+'CM15'!D40+'CM14'!D40+'CM7'!D40+'CM53'!D41+'CM44'!D41+'CM5'!D41+'CM10'!D40+'CM9'!D40+'CM8'!D40+'CM6'!D40+'CM4'!D40+'CM61'!D40 -> 39453.04
A41: Frais Hotel | D41: ='CM21'!D41+'CM24'!D41+'CM27'!D41+'CM29'!D41+'CM34'!D41+'CM37'!D41+'CM39'!D41+'CM41'!D41+'CM42'!D41+'CM48'!D41+'CM59'!D41+'CM26'!D41+'CM25'!D41+'CM23'!D41+'CM19'!D42+'CM15'!D41+'CM14'!D41+'CM7'!D41+'CM53'!D42+'CM44'!D42+'CM5'!D42+'CM10'!D41+'CM9'!D41+'CM8'!D41+'CM6'!D41+'CM4'!D41 -> 0
A42: Tirpalette | B42: NON | C42: =IF(B42=Liste!A24,Liste!B18,0) -> 0 | D42: ='CM21'!D42+'CM24'!D42+'CM27'!D42+'CM29'!D42+'CM34'!D42+'CM37'!D42+'CM39'!D42+'CM41'!D42+'CM42'!D42+'CM48'!D42+'CM59'!D42+'CM26'!D42+'CM25'!D42+'CM23'!D42+'CM19'!D42+'CM15'!D42+'CM14'!D42+'CM7'!D42+'CM53'!D42+'CM44'!D42+'CM5'!D42+'CM10'!D42+'CM9'!D42+'CM8'!D42+'CM6'!D42+'CM4'!D42 -> 0
A43: Sous-Traitance | C43: 0 | D43: ='CM21'!D43+'CM24'!D43+'CM27'!D43+'CM29'!D43+'CM34'!D43+'CM37'!D43+'CM39'!D43+'CM41'!D43+'CM42'!D43+'CM48'!D43+'CM59'!D43+'CM26'!D43+'CM25'!D43+'CM23'!D43+'CM19'!D43+'CM15'!D43+'CM14'!D43+'CM7'!D43+'CM53'!D43+'CM44'!D43+'CM5'!D43+'CM10'!D43+'CM9'!D43+'CM8'!D43+'CM6'!D43+'CM4'!D43 -> 0
C45: TOTAL COUT | D45: =SUM(D29:D43) -> 108820.15
C46: Marge Exploitation | D46: =F24-D45 -> 23561.399
C48: % Marge | D48: =D46/F24 -> 0.17798099

Sheet SPL72
A1: FICHE DE RENTABILITE
A3: DONNEES EXPLOITATION
B4: Immatriculation | D4: Conso au 100 (Moyenne) | F4: Semaine | G4: S16
A5: Tracteur (s) | B5: GW-579-LF | D5: 24.18
A6: Semi (s) | B6: SOLO | D6: 0.019
A7: Conducteurs | B7: Hanzi
A8: AMPLITUDE Hebdo | B8: 57.95
A9: TDS Hebdo | B9: 46.68
B10: KM Hebdo | G10: Hotel (semaine)
B11: 2784 | G11: 0
A12: Autoroute / jour : | B12: 94 | C12: 73 | F12: SPL | G12: CM
E13: €/ Hebdo | F13: 1000 | G13: 1100
A14: Détails CA
A15: Référence prestations | B15: Fréquence | C15: Montant unitaire | D15: Quantité | E15: Total Hors IGO | F15: Indexation | G15: Montant Total
A16: DACHSER PANTIN : Pernod | B16: Lundi => Vendredi | C16: 753 | D16: 5 | E16: =C16*D16 -> 3765 | F16: 0.0946 | G16: =((E16-(C12*5))*F16)+E16 -> 4086.64 | I16: indexation gaz avec un tracteur GO
E17: =C17*D17 -> 0 | G17: =(E17*F17)+E17 -> 0
A18: Tourne sur 5 Jours | E18: =C18*D18 -> 0 | G18: =(E18*F18)+E18 -> 0
E19: =C19*D19 -> 0 | G19: =(E19*F19)+E19 -> 0
E20: =C20*D20 -> 0 | G20: =(E20*F20)+E20 -> 0
E21: =C21*D21 -> 0 | G21: =(E21*F21)+E21 -> 0
E22: =C22*D22 -> 0 | G22: =(E22*F22)+E22 -> 0
A24: SPL72 | B24: CA DE LA LIGNE | F24: =SUM(G16:G22) -> 4086.64
A25: SOMMAIRE
A27: Coûts de la Ligne
B28: Type | C28: unité | D28: Cout Semaine
A29: Moteur (1) | B29: Tracteur GO | C29: =IFERROR(VLOOKUP(B29,Liste!C1:D5,2,FALSE),"") -> 2300 | D29: =IFERROR(C29/4.33,0) -> 531.17783
A30: Semi (1) | B30: AUCUNE | C30: =IFERROR(VLOOKUP(B30,Liste!$C$7:$D$15,2,FALSE),"") | D30: =IFERROR(C30/4.33,0) -> 0
A31: Semi (2) | B31: AUCUNE | C31: =IFERROR(VLOOKUP(B31,Liste!$C$7:$D$15,2,FALSE),"") | D31: =IFERROR(C31/4.33,0) -> 0
A32: Semi (3) | B32: AUCUNE | C32: =IFERROR(VLOOKUP(B32,Liste!$C$7:$D$15,2,FALSE),"") | D32: =IFERROR(C32/4.33,0) -> 0
A33: Semi (4) | B33: AUCUNE | C33: =IFERROR(VLOOKUP(B33,Liste!$C$7:$D$15,2,FALSE),"") | D33: =IFERROR(C33/4.33,0) -> 0
A34: Carburant | B34: GO | C34: 1.3554 | D34: =(B11*D5/100)*C34 -> 912.41624
A35: Carburant | B35: GNC | C35: 0 | D35: =(D5*B11/100)*C35 -> 0
A36: AD Blue | C36: 0.4309 | D36: =(D6*B11)*C36 -> 22.792886
A37: Fuel | C37: 1.1225
A38: Casse / Pneumatique / Lavage ( hors entretien) | C38: 0.04 | D38: =C38*B11 -> 111.36
A39: Autoroute | B39: =B12 -> 94 | C39: 5 | D39: =C39*B39 -> 470
A40: Salaires | B40: SPL | C40: 1 | D40: 1348.46
A41: Frais Hotel | D41: =G11 -> 0
A42: Tirpalette | B42: NON | C42: =IF(B42=Liste!A24,Liste!B18,0) -> 0 | D42: =C42/4.33 -> 0
A43: Sous-Traitance | C43: 0 | D43: 0
C45: TOTAL COUT | D45: =SUM(D29:D43) -> 3396.207
C46: Marge Exploitation | D46: =F24-D45 -> 690.43304
C48: % Marge | D48: =D46/F24 -> 0.16894883

Sheet SPL7
A1: FICHE DE RENTABILITE
A3: DONNEES EXPLOITATION
B4: Immatriculation | D4: Conso au 100 (Moyenne) | F4: Semaine | G4: S15
A5: Tracteur (s) | B5: FQ-491-PN | D5: 28.01
A6: Semi (s) | B6: 1 Semi Frigo | D6: 0.019
A7: Conducteurs | B7: AMRAOUI | C7: TURQUETIL Y.
A8: AMPLITUDE Hebdo | B8: 50.63 | C8: 41.64
A9: TDS Hebdo | B9: 43.6 | C9: 34.81
B10: KM Hebdo | G10: Hotel (semaine)
B11: =1549+696 -> 2245 | G11: 0
A12: Autoroute / jour : | B12: 9.06 | C12: (Non Refacturé) | F12: SPL | G12: CM
E13: €/ Hebdo | F13: 1000 | G13: 1100
A14: Détails CA
A15: Référence prestations | B15: Fréquence | C15: Montant unitaire | D15: Quantité | E15: Total Hors IGO | F15: Indexation | G15: Montant Total
A16: STG : CVL CREPY | B16: Lundi => Samedi | C16: 440 | D16: 6 | E16: =C16*D16 -> 2640 | F16: -0.0134 | G16: =((E16*F16)+E16) -> 2604.624 | I16: Indexation au Go => Véhicule Gaz
A17: STG : Scapnor AM | B17: Lundi => Vendredi | C17: 0 | D17: 5 | E17: =C17*D17 -> 0 | F17: -0.0134 | G17: =((E17*F17)+E17) -> 0 | I17: Non tournée sur Avril
A18: STG : Ramasse AMD 95 | B18: Lundi => Vendredi | C18: 175 | D18: 5 | E18: =C18*D18 -> 875 | F18: -0.0134 | G18: =((E18*F18)+E18) -> 863.275
E19: =C19*D19 -> 0 | F19: 0 | G19: =(E19*F19)+E19 -> 0
E20: =C20*D20 -> 0 | G20: =(E20*F20)+E20 -> 0
E21: =C21*D21 -> 0 | G21: =(E21*F21)+E21 -> 0
E22: =C22*D22 -> 0 | G22: =(E22*F22)+E22 -> 0
A24: SPL7 | B24: CA DE LA LIGNE | F24: =SUM(G16:G22) -> 3467.899
A25: SOMMAIRE
A27: Coûts de la Ligne
B28: Type | C28: unité | D28: Cout Semaine
A29: Moteur (1) | B29: Tracteur GNC | C29: =IFERROR(VLOOKUP(B29,Liste!C1:D5,2,FALSE),"") -> 2500 | D29: =IFERROR(C29/4.33,0) -> 577.36721
A30: Semi (1) | B30: SR Frigo | C30: =IFERROR(VLOOKUP(B30,Liste!$C$7:$D$15,2,FALSE),"") -> 1400 | D30: =IFERROR(C30/4.33,0) -> 323.32564
A31: Semi (2) | B31: AUCUNE | C31: =IFERROR(VLOOKUP(B31,Liste!$C$7:$D$15,2,FALSE),"") | D31: =IFERROR(C31/4.33,0) -> 0
A32: Semi (3) | B32: AUCUNE | C32: =IFERROR(VLOOKUP(B32,Liste!$C$7:$D$15,2,FALSE),"") | D32: =IFERROR(C32/4.33,0) -> 0
A33: Semi (4) | B33: AUCUNE | C33: =IFERROR(VLOOKUP(B33,Liste!$C$7:$D$15,2,FALSE),"") | D33: =IFERROR(C33/4.33,0) -> 0
A34: Carburant | B34: GO | C34: 0 | D34: =(B11*D5/100)*C34 -> 0
A35: Carburant | B35: GNC | C35: 1.365 | D35: =(D5*B11/100)*C35 -> 858.34544
A36: AD Blue | C36: 0 | D36: =(D6*B11)*C36 -> 0
A37: Fuel | C37: 1.1225 | D37: =30*1.12 -> 33.6
A38: Casse / Pneumatique / Lavage ( hors entretien) | C38: 0.04 | D38: =C38*B11 -> 89.8
A39: Autoroute | B39: =B12 -> 9.06 | C39: 5 | D39: =C39*B39 -> 45.3
A40: Salaires | B40: SPL | C40: 2 | D40: =1041.68+980.04 -> 2021.72
A41: Frais Hotel | D41: =G11 -> 0
A42: Tirpalette | B42: NON | C42: =IF(B42=Liste!A24,Liste!B18,0) -> 0 | D42: =C42/4.33 -> 0
A43: Sous-Traitance | C43: 0 | D43: 0
C45: TOTAL COUT | D45: =SUM(D29:D43) -> 3949.4583
C46: Marge Exploitation | D46: =F24-D45 -> -481.55928
C48: % Marge | D48: =D46/F24 -> -0.13886197

Sheet SPL22
A1: FICHE DE RENTABILITE
A3: DONNEES EXPLOITATION
B4: Immatriculation | D4: Conso au 100 (Moyenne) | F4: Semaine | G4: S15
A5: Tracteur (s) | B5: FB-526-MA | D5: 38.93 | E5: Fuel ?
A6: Semi (s) | B6: 1 Semi Frigo | D6: 0.019
A7: Conducteurs | B7: TOUHAMI
A8: AMPLITUDE Hebdo | B8: 49.42
A9: TDS Hebdo | B9: 29.62
B10: KM Hebdo | G10: Hotel (semaine)
B11: 1103 | G11: 0
A12: Autoroute / jour : | B12: 0 | C12: (Non Refacturé) | F12: SPL | G12: CM
E13: €/ Hebdo | F13: 1000 | G13: 1100
A14: Détails CA
A15: Référence prestations | B15: Fréquence | C15: Montant unitaire | D15: Quantité | E15: Total Hors IGO | F15: Indexation | G15: Montant Total
A16: STG : Barbery | B16: Lundi => Samedi | C16: 440 | D16: 6 | E16: =C16*D16 -> 2640 | F16: -0.0134 | G16: =(E16*F16)+E16 -> 2604.624
E17: =C17*D17 -> 0 | G17: =(E17*F17)+E17 -> 0
E18: =C18*D18 -> 0 | G18: =(E18*F18)+E18 -> 0
E19: =C19*D19 -> 0 | G19: =(E19*F19)+E19 -> 0
E20: =C20*D20 -> 0 | G20: =(E20*F20)+E20 -> 0
E21: =C21*D21 -> 0 | G21: =(E21*F21)+E21 -> 0
E22: =C22*D22 -> 0 | G22: =(E22*F22)+E22 -> 0
A24: SPL22 | B24: CA DE LA LIGNE | F24: =SUM(G16:G22) -> 2604.624
A25: SOMMAIRE
A27: Coûts de la Ligne
B28: Type | C28: unité | D28: Cout Semaine
A29: Moteur (1) | B29: Tracteur GO | C29: =IFERROR(VLOOKUP(B29,Liste!C1:D5,2,FALSE),"") -> 2300 | D29: =IFERROR(C29/4.33,0) -> 531.17783
A30: Semi (1) | B30: SR Frigo | C30: =IFERROR(VLOOKUP(B30,Liste!$C$7:$D$15,2,FALSE),"") -> 1400 | D30: =IFERROR(C30/4.33,0) -> 323.32564
A31: Semi (2) | B31: AUCUNE | C31: =IFERROR(VLOOKUP(B31,Liste!$C$7:$D$15,2,FALSE),"") | D31: =IFERROR(C31/4.33,0) -> 0
A32: Semi (3) | B32: AUCUNE | C32: =IFERROR(VLOOKUP(B32,Liste!$C$7:$D$15,2,FALSE),"") | D32: =IFERROR(C32/4.33,0) -> 0
A33: Semi (4) | B33: AUCUNE | C33: =IFERROR(VLOOKUP(B33,Liste!$C$7:$D$15,2,FALSE),"") | D33: =IFERROR(C33/4.33,0) -> 0
A34: Carburant | B34: GO | C34: 1.3554 | D34: =(B11*D5/100)*C34 -> 582.00591
A35: Carburant | B35: GNC | C35: 0 | D35: =(D5*B11/100)*C35 -> 0
A36: AD Blue | C36: 0.4309 | D36: =(D6*B11)*C36 -> 9.0303713
A37: Fuel | C37: 1.1225 | E37: Go au lieu de Fuel ? => Conso élévé
A38: Casse / Pneumatique / Lavage ( hors entretien) | C38: 0.04 | D38: =C38*B11 -> 44.12
A39: Autoroute | B39: =B12 -> 0 | C39: 5 | D39: =C39*B39 -> 0
A40: Salaires | B40: SPL | C40: 1 | D40: 892.61
A41: Frais Hotel | D41: =G11 -> 0
A42: Tirpalette | B42: NON | C42: =IF(B42=Liste!A24,Liste!B18,0) -> 0 | D42: =C42/4.33 -> 0
A43: Sous-Traitance | C43: 0 | D43: 0
C45: TOTAL COUT | D45: =SUM(D29:D43) -> 2382.2697
C46: Marge Exploitation | D46: =F24-D45 -> 222.35425
C48: % Marge | D48: =D46/F24 -> 0.08536904

Sheet SPL33
A1: FICHE DE RENTABILITE
A3: DONNEES EXPLOITATION
B4: Immatriculation | D4: Conso au 100 (Moyenne) | F4: Semaine | G4: S16
A5: Tracteur (s) | B5: FA-455-ST | D5: 34.49 | E5: Fuel ?
A6: Semi (s) | B6: 1 Semi Frigo | D6: 0.019
A7: Conducteurs | B7: MOREIRA
A8: AMPLITUDE Hebdo | B8: 51.08
A9: TDS Hebdo | B9: 41.41
B10: KM Hebdo | G10: Hotel (semaine)
B11: 1021 | G11: 0
A12: Autoroute / jour : | B12: 0 | F12: SPL | G12: CM
E13: €/ Hebdo | F13: 1000 | G13: 1100
A14: Détails CA
A15: Référence prestations | B15: Fréquence | C15: Montant unitaire | D15: Quantité | E15: Total Hors IGO | F15: Indexation | G15: Montant Total
A16: STG : Su Nanteuil | B16: Lundi => Samedi | C16: 440 | D16: 6 | E16: =C16*D16 -> 2640 | F16: -0.0134 | G16: =(E16*F16)+E16 -> 2604.624
E17: =C17*D17 -> 0 | G17: =(E17*F17)+E17 -> 0
E18: =C18*D18 -> 0 | G18: =(E18*F18)+E18 -> 0
E19: =C19*D19 -> 0 | G19: =(E19*F19)+E19 -> 0
E20: =C20*D20 -> 0 | G20: =(E20*F20)+E20 -> 0
E21: =C21*D21 -> 0 | G21: =(E21*F21)+E21 -> 0
E22: =C22*D22 -> 0 | G22: =(E22*F22)+E22 -> 0
A24: SPL33 | B24: CA DE LA LIGNE | F24: =SUM(G16:G22) -> 2604.624
A25: SOMMAIRE
A27: Coûts de la Ligne
B28: Type | C28: unité | D28: Cout Semaine
A29: Moteur (1) | B29: Tracteur GO | C29: =IFERROR(VLOOKUP(B29,Liste!C1:D5,2,FALSE),"") -> 2300 | D29: =IFERROR(C29/4.33,0) -> 531.17783
A30: Semi (1) | B30: SR Frigo | C30: =IFERROR(VLOOKUP(B30,Liste!$C$7:$D$15,2,FALSE),"") -> 1400 | D30: =IFERROR(C30/4.33,0) -> 323.32564
A31: Semi (2) | B31: AUCUNE | C31: =IFERROR(VLOOKUP(B31,Liste!$C$7:$D$15,2,FALSE),"") | D31: =IFERROR(C31/4.33,0) -> 0
A32: Semi (3) | B32: AUCUNE | C32: =IFERROR(VLOOKUP(B32,Liste!$C$7:$D$15,2,FALSE),"") | D32: =IFERROR(C32/4.33,0) -> 0
A33: Semi (4) | B33: AUCUNE | C33: =IFERROR(VLOOKUP(B33,Liste!$C$7:$D$15,2,FALSE),"") | D33: =IFERROR(C33/4.33,0) -> 0
A34: Carburant | B34: GO | C34: 1.3554 | D34: =(B11*D5/100)*C34 -> 477.29449
A35: Carburant | B35: GNC | C35: 0 | D35: =(D5*B11/100)*C35 -> 0
A36: AD Blue | C36: 0.4309 | D36: =(D6*B11)*C36 -> 8.3590291
A37: Fuel | C37: 1.1225 | E37: Go au lieu de Fuel ? => Conso élévé
A38: Casse / Pneumatique / Lavage ( hors entretien) | C38: 0.04 | D38: =C38*B11 -> 40.84
A39: Autoroute | B39: =B12 -> 0 | C39: 5 | D39: =C39*B39 -> 0
A40: Salaires | B40: SPL | C40: 1 | D40: 893.37
A41: Frais Hotel | D41: =G11 -> 0
A42: Tirpalette | B42: NON | C42: =IF(B42=Liste!A24,Liste!B18,0) -> 0 | D42: =C42/4.33 -> 0
A43: Sous-Traitance | C43: 0 | D43: 0
C45: TOTAL COUT | D45: =SUM(D29:D43) -> 2274.367
C46: Marge Exploitation | D46: =F24-D45 -> 330.25702
C48: % Marge | D48: =D46/F24 -> 0.12679643

Sheet SPL73
A1: FICHE DE RENTABILITE
A3: DONNEES EXPLOITATION
B4: Immatriculation | D4: Conso au 100 (Moyenne) | F4: Semaine | G4: S16
A5: Tracteur (s) | B5: EZ-517-SN | D5: 31.8
A6: Semi (s) | B6: 1 Semi Frigo | D6: 0.019
A7: Conducteurs | B7: BURLACU
A8: AMPLITUDE Hebdo | B8: 57.86
A9: TDS Hebdo | B9: 44.59
B10: KM Hebdo | G10: Hotel (semaine)
B11: 958 | G11: 0
A12: Autoroute / jour : | B12: 0 | C12: (Non Refacturé) | F12: SPL | G12: CM
E13: €/ Hebdo | F13: 1000 | G13: 1100
A14: Détails CA
A15: Référence prestations | B15: Fréquence | C15: Montant unitaire | D15: Quantité | E15: Total Hors IGO | F15: Indexation | G15: Montant Total
A16: STG : Scapnor Matin | B16: Lundi => Samedi | C16: 440 | D16: 6 | E16: =C16*D16 -> 2640 | F16: -0.0134 | G16: =(E16*F16)+E16 -> 2604.624
E17: =C17*D17 -> 0 | G17: =(E17*F17)+E17 -> 0
E18: =C18*D18 -> 0 | G18: =(E18*F18)+E18 -> 0
E19: =C19*D19 -> 0 | G19: =(E19*F19)+E19 -> 0
E20: =C20*D20 -> 0 | G20: =(E20*F20)+E20 -> 0
E21: =C21*D21 -> 0 | G21: =(E21*F21)+E21 -> 0
E22: =C22*D22 -> 0 | G22: =(E22*F22)+E22 -> 0
A24: SPL73 | B24: CA DE LA LIGNE | F24: =SUM(G16:G22) -> 2604.624
A25: SOMMAIRE
A27: Coûts de la Ligne
B28: Type | C28: unité | D28: Cout Semaine
A29: Moteur (1) | B29: Tracteur GO | C29: =IFERROR(VLOOKUP(B29,Liste!C1:D5,2,FALSE),"") -> 2300 | D29: =IFERROR(C29/4.33,0) -> 531.17783
A30: Semi (1) | B30: SR Frigo | C30: =IFERROR(VLOOKUP(B30,Liste!$C$7:$D$15,2,FALSE),"") -> 1400 | D30: =IFERROR(C30/4.33,0) -> 323.32564
A31: Semi (2) | B31: AUCUNE | C31: =IFERROR(VLOOKUP(B31,Liste!$C$7:$D$15,2,FALSE),"") | D31: =IFERROR(C31/4.33,0) -> 0
A32: Semi (3) | B32: AUCUNE | C32: =IFERROR(VLOOKUP(B32,Liste!$C$7:$D$15,2,FALSE),"") | D32: =IFERROR(C32/4.33,0) -> 0
A33: Semi (4) | B33: AUCUNE | C33: =IFERROR(VLOOKUP(B33,Liste!$C$7:$D$15,2,FALSE),"") | D33: =IFERROR(C33/4.33,0) -> 0
A34: Carburant | B34: GO | C34: 1.3554 | D34: =(B11*D5/100)*C34 -> 412.91448
A35: Carburant | B35: GNC | C35: 0 | D35: =(D5*B11/100)*C35 -> 0
A36: AD Blue | C36: 0.4309 | D36: =(D6*B11)*C36 -> 7.8432418
A37: Fuel | C37: 1.1225 | D37: =(199.36/26)*6 -> 46.006154
A38: Casse / Pneumatique / Lavage ( hors entretien) | C38: 0.04 | D38: =C38*B11 -> 38.32
A39: Autoroute | B39: =B12 -> 0 | C39: 5 | D39: =C39*B39 -> 0
A40: Salaires | B40: SPL | C40: 1 | D40: 1075.29
A41: Frais Hotel | D41: =G11 -> 0
A42: Tirpalette | B42: NON | C42: =IF(B42=Liste!A24,Liste!B18,0) -> 0 | D42: =C42/4.33 -> 0
A43: Sous-Traitance | C43: 0 | D43: 0
C45: TOTAL COUT | D45: =SUM(D29:D43) -> 2434.8773
C46: Marge Exploitation | D46: =F24-D45 -> 169.74666
C48: % Marge | D48: =D46/F24 -> 0.065171273

Sheet SPL8
A1: FICHE DE RENTABILITE
A3: DONNEES EXPLOITATION
B4: Immatriculation | D4: Conso au 100 (Moyenne) | F4: Semaine | G4: S16
A5: Tracteur (s) | B5: FN036CX | D5: 26.44
A6: Semi (s) | B6: 3 Semi Classic | D6: 0.019
A7: Conducteurs | B7: PARISOT
A8: AMPLITUDE Hebdo | B8: 61.3
A9: TDS Hebdo | B9: 41.13
B10: KM Hebdo | G10: Hotel (semaine)
B11: 3158 | G11: 0
A12: Autoroute / jour : | B12: 109.92 | F12: SPL | G12: CM
E13: €/ Hebdo | F13: 1000 | G13: 1100
A14: Détails CA
A15: Référence prestations | B15: Fréquence | C15: Montant unitaire | D15: Quantité | E15: Total Hors IGO | F15: Indexation | G15: Montant Total
A16: GLS Coudray - Troyes | B16: Lundi au Vendredi | C16: 773 | D16: 5 | E16: =C16*D16 -> 3865 | F16: 0.137 | G16: =(E16*F16)+E16 -> 4394.505
E17: =C17*D17 -> 0 | G17: =(E17*F17)+E17 -> 0
A18: Tourne sur 5 jours | E18: =C18*D18 -> 0 | G18: =(E18*F18)+E18 -> 0
E19: =C19*D19 -> 0 | G19: =(E19*F19)+E19 -> 0
E20: =C20*D20 -> 0 | G20: =(E20*F20)+E20 -> 0
E21: =C21*D21 -> 0 | G21: =(E21*F21)+E21 -> 0
E22: =C22*D22 -> 0 | G22: =(E22*F22)+E22 -> 0
A24: SPL8 | B24: CA DE LA LIGNE | F24: =SUM(G16:G22) -> 4394.505
A25: SOMMAIRE
A27: Coûts de la Ligne
B28: Type | C28: unité | D28: Cout Semaine
A29: Moteur (1) | B29: Tracteur GO | C29: =IFERROR(VLOOKUP(B29,Liste!C1:D5,2,FALSE),"") -> 2300 | D29: =IFERROR(C29/4.33,0) -> 531.17783
A30: Semi (1) | B30: SR Classique | C30: =IFERROR(VLOOKUP(B30,Liste!$C$7:$D$15,2,FALSE),"") -> 1000 | D30: =IFERROR(C30/4.33,0) -> 230.94688
A31: Semi (2) | B31: SR Classique | C31: =IFERROR(VLOOKUP(B31,Liste!$C$7:$D$15,2,FALSE),"") -> 1000 | D31: =IFERROR(C31/4.33,0) -> 230.94688
A32: Semi (3) | B32: SR Classique | C32: =IFERROR(VLOOKUP(B32,Liste!$C$7:$D$15,2,FALSE),"") -> 1000 | D32: =IFERROR(C32/4.33,0) -> 230.94688
A33: Semi (4) | B33: AUCUNE | C33: =IFERROR(VLOOKUP(B33,Liste!$C$7:$D$15,2,FALSE),"") | D33: =IFERROR(C33/4.33,0) -> 0
A34: Carburant | B34: GO | C34: 1.3554 | D34: =(B11*D5/100)*C34 -> 1131.7254
A35: Carburant | B35: GNC | C35: 0 | D35: =(D5*B11/100)*C35 -> 0
A36: AD Blue | C36: 0.4309 | D36: =(D6*B11)*C36 -> 25.854862
A37: Fuel | C37: 1.1225
A38: Casse / Pneumatique / Lavage ( hors entretien) | C38: 0.04 | D38: =C38*B11 -> 126.32
A39: Autoroute | B39: =B12 -> 109.92 | C39: 5 | D39: =C39*B39 -> 549.6
A40: Salaires | B40: SPL | C40: 1 | D40: 887.65
A41: Frais Hotel | D41: =G11 -> 0
A42: Tirpalette | B42: NON | C42: =IF(B42=Liste!A24,Liste!B18,0) -> 0 | D42: =C42/4.33 -> 0
A43: Sous-Traitance | C43: 0 | D43: 0
C45: TOTAL COUT | D45: =SUM(D29:D43) -> 3945.1687
C46: Marge Exploitation | D46: =F24-D45 -> 449.33628
C48: % Marge | D48: =D46/F24 -> 0.10224958

Sheet SPL9
A1: FICHE DE RENTABILITE
A3: DONNEES EXPLOITATION
B4: Immatriculation | D4: Conso au 100 (Moyenne) | F4: Semaine | G4: S16
A5: Tracteur (s) | B5: EZ-794-DA | D5: 50.15
A6: Semi (s) | B6: 1 Classique | C6: 1 Aerienne | D6: 0.019
A7: Conducteurs | B7: WILSON
A8: AMPLITUDE Hebdo | B8: 65.35
A9: TDS Hebdo | B9: 48.13
B10: KM Hebdo | G10: Hotel (semaine)
B11: 573 | G11: 0
A12: Autoroute / jour : | B12: 0 | F12: SPL | G12: CM
E13: €/ Hebdo | F13: 1000 | G13: 1100
A14: Détails CA
A15: Référence prestations | B15: Fréquence | C15: Montant unitaire | D15: Quantité | E15: Total Hors IGO | F15: Indexation | G15: Montant Total
A16: FEDEX GB4 | B16: Lundi au vendredi | C16: 455 | D16: 5 | E16: =C16*D16 -> 2275 | F16: 0 | G16: =(E16*F16)+E16 -> 2275
A17: WE : FEDEX GB4 | B17: Samedi | C17: 455 | D17: 1 | E17: =C17*D17 -> 455 | F17: 0 | G17: =(E17*F17)+E17 -> 455
A18: WE : CHRONO ROISSY - Orly | B18: Samedi | C18: 220 | D18: 1 | E18: =C18*D18 -> 220 | F18: 0 | G18: =(E18*F18)+E18 -> 220
E19: =C19*D19 -> 0 | G19: =(E19*F19)+E19 -> 0
E20: =C20*D20 -> 0 | G20: =(E20*F20)+E20 -> 0
E21: =C21*D21 -> 0 | G21: =(E21*F21)+E21 -> 0
E22: =C22*D22 -> 0 | G22: =(E22*F22)+E22 -> 0
A24: SPL9 | B24: CA DE LA LIGNE | F24: =SUM(G16:G22) -> 2950
A25: SOMMAIRE
A27: Coûts de la Ligne
B28: Type | C28: unité | D28: Cout Semaine
A29: Moteur (1) | B29: Tracteur GO | C29: =IFERROR(VLOOKUP(B29,Liste!C1:D5,2,FALSE),"") -> 2300 | D29: =IFERROR(C29/4.33,0) -> 531.17783
A30: Semi (1) | B30: SR Classique | C30: =IFERROR(VLOOKUP(B30,Liste!$C$7:$D$15,2,FALSE),"") -> 1000 | D30: =IFERROR(C30/4.33,0) -> 230.94688
A31: Semi (2) | B31: Aérienne Classique | C31: =IFERROR(VLOOKUP(B31,Liste!$C$7:$D$15,2,FALSE),"") -> 1200 | D31: =IFERROR(C31/4.33,0) -> 277.13626
A32: Semi (3) | B32: AUCUNE | C32: =IFERROR(VLOOKUP(B32,Liste!$C$7:$D$15,2,FALSE),"") | D32: =IFERROR(C32/4.33,0) -> 0
A33: Semi (4) | B33: AUCUNE | C33: =IFERROR(VLOOKUP(B33,Liste!$C$7:$D$15,2,FALSE),"") | D33: =IFERROR(C33/4.33,0) -> 0
A34: Carburant | B34: GO | C34: 1.3554 | D34: =(B11*D5/100)*C34 -> 389.48707
A35: Carburant | B35: GNC | C35: 0 | D35: =(D5*B11/100)*C35 -> 0
A36: AD Blue | C36: 0.4309 | D36: =(D6*B11)*C36 -> 4.6912083
A37: Fuel | C37: 1.1225
A38: Casse / Pneumatique / Lavage ( hors entretien) | C38: 0.04 | D38: =C38*B11 -> 22.92
A39: Autoroute | B39: =B12 -> 0 | C39: 5 | D39: =C39*B39 -> 0
A40: Salaires | B40: SPL | C40: 1 | D40: 1002.52
A41: Frais Hotel | D41: =G11 -> 0
A42: Tirpalette | B42: NON | C42: =IF(B42=Liste!A24,Liste!B18,0) -> 0 | D42: =C42/4.33 -> 0
A43: Sous-Traitance | C43: 0 | D43: 0
C45: TOTAL COUT | D45: =SUM(D29:D43) -> 2458.8792
C46: Marge Exploitation | D46: =F24-D45 -> 491.12076
C48: % Marge | D48: =D46/F24 -> 0.16648161

Sheet SPL75
A1: FICHE DE RENTABILITE
A3: DONNEES EXPLOITATION
B4: Immatriculation | D4: Conso au 100 (Moyenne) | F4: Semaine | G4: S16
A5: Tracteur (s) | B5: DY-532-ZW | D5: 36.64
A6: Semi (s) | B6: 1 Classique | C6: 1 Classique | D6: 0.019
A7: Conducteurs | B7: JADE ZINE
A8: AMPLITUDE Hebdo | B8: 59.79
A9: TDS Hebdo | B9: 54.58
B10: KM Hebdo | G10: Hotel (semaine)
B11: 1225 | G11: 0
A12: Autoroute / jour : | B12: 0 | F12: SPL | G12: CM
E13: €/ Hebdo | F13: 1000 | G13: 1100
A14: Détails CA
A15: Référence prestations | B15: Fréquence | C15: Montant unitaire | D15: Quantité | E15: Total Hors IGO | F15: Indexation | G15: Montant Total
A16: GLS ; Trappes - Coudray | B16: Lundi au Vendredi | C16: =126.25+112.5+112.5+126.25 -> 477.5 | D16: 5 | E16: =C16*D16 -> 2387.5 | F16: -0.017 | G16: =(E16*F16)+E16 -> 2346.9125
E17: =C17*D17 -> 0 | G17: =(E17*F17)+E17 -> 0
A18: Tourne sur 5 jours | E18: =C18*D18 -> 0 | G18: =(E18*F18)+E18 -> 0
E19: =C19*D19 -> 0 | G19: =(E19*F19)+E19 -> 0
E20: =C20*D20 -> 0 | G20: =(E20*F20)+E20 -> 0
E21: =C21*D21 -> 0 | G21: =(E21*F21)+E21 -> 0
E22: =C22*D22 -> 0 | G22: =(E22*F22)+E22 -> 0
A24: SPL75 | B24: CA DE LA LIGNE | F24: =SUM(G16:G22) -> 2346.9125
A25: SOMMAIRE
A27: Coûts de la Ligne
B28: Type | C28: unité | D28: Cout Semaine
A29: Moteur (1) | B29: Tracteur GO | C29: =IFERROR(VLOOKUP(B29,Liste!C1:D5,2,FALSE),"") -> 2300 | D29: =IFERROR(C29/4.33,0) -> 531.17783
A30: Semi (1) | B30: SR Classique | C30: =IFERROR(VLOOKUP(B30,Liste!$C$7:$D$15,2,FALSE),"") -> 1000 | D30: =IFERROR(C30/4.33,0) -> 230.94688
A31: Semi (2) | B31: SR Classique | C31: =IFERROR(VLOOKUP(B31,Liste!$C$7:$D$15,2,FALSE),"") -> 1000 | D31: =IFERROR(C31/4.33,0) -> 230.94688
A32: Semi (3) | B32: AUCUNE | C32: =IFERROR(VLOOKUP(B32,Liste!$C$7:$D$15,2,FALSE),"") | D32: =IFERROR(C32/4.33,0) -> 0
A33: Semi (4) | B33: AUCUNE | C33: =IFERROR(VLOOKUP(B33,Liste!$C$7:$D$15,2,FALSE),"") | D33: =IFERROR(C33/4.33,0) -> 0
A34: Carburant | B34: GO | C34: 1.3554 | D34: =(B11*D5/100)*C34 -> 608.35774
A35: Carburant | B35: GNC | C35: 0 | D35: =(D5*B11/100)*C35 -> 0
A36: AD Blue | C36: 0.4309 | D36: =(D6*B11)*C36 -> 10.029197
A37: Fuel | C37: 1.1225
A38: Casse / Pneumatique / Lavage ( hors entretien) | C38: 0.04 | D38: =C38*B11 -> 49
A39: Autoroute | B39: =B12 -> 0 | C39: 5 | D39: =C39*B39 -> 0
A40: Salaires | B40: SPL | C40: 1 | D40: 877.03
A41: Frais Hotel | D41: =G11 -> 0
A42: Tirpalette | B42: NON | C42: =IF(B42=Liste!A24,Liste!B18,0) -> 0 | D42: =C42/4.33 -> 0
A43: Sous-Traitance | C43: 0 | D43: 0
C45: TOTAL COUT | D45: =SUM(D29:D43) -> 2537.4885
C46: Marge Exploitation | D46: =F24-D45 -> -190.57603
C48: % Marge | D48: =D46/F24 -> -0.081202868

Sheet SPL76
A1: FICHE DE RENTABILITE
A3: DONNEES EXPLOITATION
B4: Immatriculation | D4: Conso au 100 (Moyenne) | F4: Semaine | G4: S16
A5: Tracteur (s) | B5: EY-171-TQ | D5: 34.85
A6: Semi (s) | B6: 1 Classique | C6: 1 Classique | D6: 0.019
A7: Conducteurs | B7: EL MOUMNI
A8: AMPLITUDE Hebdo | B8: 42.98
A9: TDS Hebdo | B9: 27.96
B10: KM Hebdo | G10: Hotel (semaine)
B11: 1340 | G11: 0
A12: Autoroute / jour : | B12: 0 | F12: SPL | G12: CM
E13: €/ Hebdo | F13: 1000 | G13: 1100
A14: Détails CA
A15: Référence prestations | B15: Fréquence | C15: Montant unitaire | D15: Quantité | E15: Total Hors IGO | F15: Indexation | G15: Montant Total
A16: GLS : Trappes - Gennevilliers | B16: Lundi au Vendredi | C16: =126.25+126.25+126.25+112.5 -> 491.25 | D16: 5 | E16: =C16*D16 -> 2456.25 | F16: -0.017 | G16: =(E16*F16)+E16 -> 2414.4938
A18: Tourne sur 5 jours
E19: =C19*D19 -> 0 | G19: =(E19*F19)+E19 -> 0
E20: =C20*D20 -> 0 | G20: =(E20*F20)+E20 -> 0
E21: =C21*D21 -> 0 | G21: =(E21*F21)+E21 -> 0
E22: =C22*D22 -> 0 | G22: =(E22*F22)+E22 -> 0
A24: SPL76 | B24: CA DE LA LIGNE | F24: =SUM(G16:G22) -> 2414.4938
A25: SOMMAIRE
A27: Coûts de la Ligne
B28: Type | C28: unité | D28: Cout Semaine
A29: Moteur (1) | B29: Tracteur GO | C29: =IFERROR(VLOOKUP(B29,Liste!C1:D5,2,FALSE),"") -> 2300 | D29: =IFERROR(C29/4.33,0) -> 531.17783
A30: Semi (1) | B30: SR Classique | C30: =IFERROR(VLOOKUP(B30,Liste!$C$7:$D$15,2,FALSE),"") -> 1000 | D30: =IFERROR(C30/4.33,0) -> 230.94688
A31: Semi (2) | B31: SR Classique | C31: =IFERROR(VLOOKUP(B31,Liste!$C$7:$D$15,2,FALSE),"") -> 1000 | D31: =IFERROR(C31/4.33,0) -> 230.94688
A32: Semi (3) | B32: AUCUNE | C32: =IFERROR(VLOOKUP(B32,Liste!$C$7:$D$15,2,FALSE),"") | D32: =IFERROR(C32/4.33,0) -> 0
A33: Semi (4) | B33: AUCUNE | C33: =IFERROR(VLOOKUP(B33,Liste!$C$7:$D$15,2,FALSE),"") | D33: =IFERROR(C33/4.33,0) -> 0
A34: Carburant | B34: GO | C34: 1.3554 | D34: =(B11*D5/100)*C34 -> 632.95825
A35: Carburant | B35: GNC | C35: 0 | D35: =(D5*B11/100)*C35 -> 0
A36: AD Blue | C36: 0.4309 | D36: =(D6*B11)*C36 -> 10.970714
A37: Fuel | C37: 1.1225
A38: Casse / Pneumatique / Lavage ( hors entretien) | C38: 0.04 | D38: =C38*B11 -> 53.6
A39: Autoroute | B39: =B12 -> 0 | C39: 5 | D39: =C39*B39 -> 0
A40: Salaires | B40: SPL | C40: 1 | D40: 812.6
A41: Frais Hotel | D41: =G11 -> 0
A42: Tirpalette | B42: NON | C42: =IF(B42=Liste!A24,Liste!B18,0) -> 0 | D42: =C42/4.33 -> 0
A43: Sous-Traitance | C43: 0 | D43: 0
C45: TOTAL COUT | D45: =SUM(D29:D43) -> 2503.2006
C46: Marge Exploitation | D46: =F24-D45 -> -88.706804
C48: % Marge | D48: =D46/F24 -> -0.036739297

Sheet SPL77
A1: FICHE DE RENTABILITE
A3: DONNEES EXPLOITATION
B4: Immatriculation | D4: Conso au 100 (Moyenne) | F4: Semaine | G4: S15
A5: Tracteur (s) | B5: FA-433-ST | D5: 31.87
A6: Semi (s) | B6: 1 Classique | C6: 3 Classique | D6: 0.019
A7: Conducteurs | B7: KONE
A8: AMPLITUDE Hebdo | B8: 58.01
A9: TDS Hebdo | B9: 48.82
B10: KM Hebdo | G10: Hotel (semaine)
B11: 1926 | G11: 0
A12: Autoroute / jour : | B12: 0 | F12: SPL | G12: CM
E13: €/ Hebdo | F13: 1000 | G13: 1100
A14: Détails CA
A15: Référence prestations | B15: Fréquence | C15: Montant unitaire | D15: Quantité | E15: Total Hors IGO | F15: Indexation | G15: Montant Total
A16: GLS : Trappes - Gennevilliers - Garonor | B16: Lundi au Vendredi | C16: =505+112.5+112.5 -> 730 | D16: 5 | E16: =C16*D16 -> 3650 | F16: -0.017 | G16: =(E16*F16)+E16 -> 3587.95
A17: WE : Colissimo LTH-016-S33 | B17: Dimanche | C17: 4.6478 | D17: 5 | E17: =C17*D17 -> 23.239 | F17: 0 | G17: =(E17*F17)+E17 -> 23.239
A18: + MAD Parnass | B18: Dimanche | C18: 0 | D18: 0 | E18: =C18*D18 -> 0 | F18: 0 | G18: =(E18*F18)+E18 -> 0
A19: WE : DHL 9892A | B19: Dimanche | C19: 170 | D19: 1 | E19: =C19*D19 -> 170 | F19: 0.0358 | G19: =(E19*F19)+E19 -> 176.086
E20: =C20*D20 -> 0 | G20: =(E20*F20)+E20 -> 0
E21: =C21*D21 -> 0 | G21: =(E21*F21)+E21 -> 0
E22: =C22*D22 -> 0 | G22: =(E22*F22)+E22 -> 0
A24: SPL77 | B24: CA DE LA LIGNE | F24: =SUM(G16:G22) -> 3787.275
A25: SOMMAIRE
A27: Coûts de la Ligne
B28: Type | C28: unité | D28: Cout Semaine
A29: Moteur (1) | B29: Tracteur GO | C29: =IFERROR(VLOOKUP(B29,Liste!C1:D5,2,FALSE),"") -> 2300 | D29: =IFERROR(C29/4.33,0) -> 531.17783
A30: Semi (1) | B30: SR Classique | C30: =IFERROR(VLOOKUP(B30,Liste!$C$7:$D$15,2,FALSE),"") -> 1000 | D30: =IFERROR(C30/4.33,0) -> 230.94688
A31: Semi (2) | B31: SR Classique | C31: =IFERROR(VLOOKUP(B31,Liste!$C$7:$D$15,2,FALSE),"") -> 1000 | D31: =IFERROR(C31/4.33,0) -> 230.94688
A32: Semi (3) | B32: SR Classique | C32: =IFERROR(VLOOKUP(B32,Liste!$C$7:$D$15,2,FALSE),"") -> 1000 | D32: =IFERROR(C32/4.33,0) -> 230.94688
A33: Semi (4) | B33: SR Classique | C33: =IFERROR(VLOOKUP(B33,Liste!$C$7:$D$15,2,FALSE),"") -> 1000 | D33: =IFERROR(C33/4.33,0) -> 230.94688
A34: Carburant | B34: GO | C34: 1.3554 | D34: =(B11*D5/100)*C34 -> 831.96648
A35: Carburant | B35: GNC | C35: 0 | D35: =(D5*B11/100)*C35 -> 0
A36: AD Blue | C36: 0.4309 | D36: =(D6*B11)*C36 -> 15.768355
A37: Fuel | C37: 1.1225
A38: Casse / Pneumatique / Lavage ( hors entretien) | C38: 0.04 | D38: =C38*B11 -> 77.04
A39: Autoroute | B39: =B12 -> 0 | C39: 5 | D39: =C39*B39 -> 0
A40: Salaires | B40: SPL | C40: 1 | D40: 821.12
A41: Frais Hotel | D41: =G11 -> 0
A42: Tirpalette | B42: NON | C42: =IF(B42=Liste!A24,Liste!B18,0) -> 0 | D42: =C42/4.33 -> 0
A43: Sous-Traitance | C43: 0 | D43: 0
C45: TOTAL COUT | D45: =SUM(D29:D43) -> 3200.8602
C46: Marge Exploitation | D46: =F24-D45 -> 586.41481
C48: % Marge | D48: =D46/F24 -> 0.15483819

Sheet SPL74
A1: FICHE DE RENTABILITE
A3: DONNEES EXPLOITATION
B4: Immatriculation | D4: Conso au 100 (Moyenne) | F4: Semaine | G4: S16
A5: Tracteur (s) | B5: GL-254-JR | D5: 30.5
A6: Semi (s) | B6: 1 Classique | D6: 0.019
A7: Conducteurs | B7: OLIMPIO (AT) | C7: BENDRIF
A8: AMPLITUDE Hebdo | B8: 0 | C8: 61.31
A9: TDS Hebdo | B9: 0 | C9: 54.06
B10: KM Hebdo | G10: Hotel (semaine)
B11: 1477 | C11: OLIMPIO REMPLACER PAR BRB | G11: 0
A12: Autoroute / jour : | B12: 0 | F12: SPL | G12: CM
E13: €/ Hebdo | F13: 1000 | G13: 1100
A14: Détails CA
A15: Référence prestations | B15: Fréquence | C15: Montant unitaire | D15: Quantité | E15: Total Hors IGO | F15: Indexation | G15: Montant Total
A18: CHRNOPOST : Cdiscount | B18: Lundi au Vendredi | C18: 165 | D18: 5 | E18: =C18*D18 -> 825 | F18: =(35*5)*2.27 -> 397.25 | G18: =F18+E18 -> 1222.25
A19: VIAPOSTE : 163-20 | B19: Lundi au Vendredi | C19: 204.26 | D19: 6 | E19: =C19*D19 -> 1225.56 | F19: 0.039775 | G19: =(E19*F19)+E19 -> 1274.3066
A21: WE : VIAPOSTE 170-20 | B21: Samedi | C21: 139.79 | D21: 1 | E21: =C21*D21 -> 139.79 | F21: 0.04271 | G21: =(E21*F21)+E21 -> 145.76043
A24: SPL74 | B24: CA DE LA LIGNE | F24: =SUM(G16:G22) -> 2642.3171
A25: SOMMAIRE
A27: Coûts de la Ligne
B28: Type | C28: unité | D28: Cout Semaine
A29: Moteur (1) | B29: Tracteur GNC | C29: =IFERROR(VLOOKUP(B29,Liste!C1:D5,2,FALSE),"") -> 2500 | D29: =IFERROR(C29/4.33,0) -> 577.36721
A30: Semi (1) | B30: SR Classique | C30: =IFERROR(VLOOKUP(B30,Liste!$C$7:$D$15,2,FALSE),"") -> 1000 | D30: =IFERROR(C30/4.33,0) -> 230.94688
A31: Semi (2) | B31: AUCUNE | C31: =IFERROR(VLOOKUP(B31,Liste!$C$7:$D$15,2,FALSE),"") | D31: =IFERROR(C31/4.33,0) -> 0
A32: Semi (3) | B32: AUCUNE | C32: =IFERROR(VLOOKUP(B32,Liste!$C$7:$D$15,2,FALSE),"") | D32: =IFERROR(C32/4.33,0) -> 0
A33: Semi (4) | B33: AUCUNE | C33: =IFERROR(VLOOKUP(B33,Liste!$C$7:$D$15,2,FALSE),"") | D33: =IFERROR(C33/4.33,0) -> 0
A34: Carburant | B34: GO | C34: 0 | D34: =(B11*D5/100)*C34 -> 0
A35: Carburant | B35: GNC | C35: 1.365 | D35: =(D5*B11/100)*C35 -> 614.91202
A36: AD Blue | C36: 0 | D36: =(D6*B11)*C36 -> 0
A37: Fuel | C37: 1.1225
A38: Casse / Pneumatique / Lavage ( hors entretien) | C38: 0.04 | D38: =C38*B11 -> 59.08
A39: Autoroute | B39: =B12 -> 0 | C39: 5 | D39: =C39*B39 -> 0
A40: Salaires | B40: SPL | C40: 1 | D40: =888.26 -> 888.26
A41: Frais Hotel | D41: =G11 -> 0
A42: Tirpalette | B42: NON | C42: =IF(B42=Liste!A24,Liste!B18,0) -> 0 | D42: =C42/4.33 -> 0
A43: Sous-Traitance | C43: 0 | D43: 0
C45: TOTAL COUT | D45: =SUM(D29:D43) -> 2370.5661
C46: Marge Exploitation | D46: =F24-D45 -> 271.75097
C48: % Marge | D48: =D46/F24 -> 0.10284571

Sheet SPL70
A1: FICHE DE RENTABILITE
A3: DONNEES EXPLOITATION
B4: Immatriculation | D4: Conso au 100 (Moyenne) | F4: Semaine | G4: S15
A5: Tracteur (s) | B5: GZ-480-YC | D5: 27.76
A6: Semi (s) | B6: 1 Classique | D6: 0.019
A7: Conducteurs | B7: GLISSANT
A8: AMPLITUDE Hebdo | B8: 41.63
A9: TDS Hebdo | B9: 34.8
B10: KM Hebdo | G10: Hotel (semaine)
B11: 696 | G11: 0
A12: Autoroute / jour : | B12: 0 | F12: SPL | G12: CM
E13: €/ Hebdo | F13: 1000 | G13: 1100
A14: Détails CA
A15: Référence prestations | B15: Fréquence | C15: Montant unitaire | D15: Quantité | E15: Total Hors IGO | F15: Indexation | G15: Montant Total
A16: CHRONOPOST : DARMSSCMZ01 | B16: Lundi au Vendredi | C16: 250 | D16: 5 | E16: =C16*D16 -> 1250 | F16: 0 | G16: =(E16*F16)+E16 -> 1250
A17: VIAPOSTE : 163-16 | B17: Lundi au Vendredi | C17: 198.76 | D17: 5 | E17: =C17*D17 -> 993.8 | F17: 0.039775 | G17: =(E17*F17)+E17 -> 1033.3284
A18: VIAPOSTE : 163-21 | B18: Lundi au Vendredi | C18: 159.02 | D18: 5 | E18: =C18*D18 -> 795.1 | F18: 0.039775 | G18: =(E18*F18)+E18 -> 826.7251
E19: =C19*D19 -> 0 | G19: =(E19*F19)+E19 -> 0
A20: Tourné 5 jours | E20: =C20*D20 -> 0 | G20: =(E20*F20)+E20 -> 0
E21: =C21*D21 -> 0 | G21: =(E21*F21)+E21 -> 0
E22: =C22*D22 -> 0 | G22: =(E22*F22)+E22 -> 0
A24: SPL70 | B24: CA DE LA LIGNE | F24: =SUM(G16:G22) -> 3110.0535
A25: SOMMAIRE
A27: Coûts de la Ligne
B28: Type | C28: unité | D28: Cout Semaine
A29: Moteur (1) | B29: Tracteur GNC | C29: =IFERROR(VLOOKUP(B29,Liste!C1:D5,2,FALSE),"") -> 2500 | D29: =IFERROR(C29/4.33,0) -> 577.36721
A30: Semi (1) | B30: SR Classique | C30: =IFERROR(VLOOKUP(B30,Liste!$C$7:$D$15,2,FALSE),"") -> 1000 | D30: =IFERROR(C30/4.33,0) -> 230.94688
A31: Semi (2) | B31: AUCUNE | C31: =IFERROR(VLOOKUP(B31,Liste!$C$7:$D$15,2,FALSE),"") | D31: =IFERROR(C31/4.33,0) -> 0
A32: Semi (3) | B32: AUCUNE | C32: =IFERROR(VLOOKUP(B32,Liste!$C$7:$D$15,2,FALSE),"") | D32: =IFERROR(C32/4.33,0) -> 0
A33: Semi (4) | B33: AUCUNE | C33: =IFERROR(VLOOKUP(B33,Liste!$C$7:$D$15,2,FALSE),"") | D33: =IFERROR(C33/4.33,0) -> 0
A34: Carburant | B34: GO | C34: 0 | D34: =(B11*D5/100)*C34 -> 0
A35: Carburant | B35: GNC | C35: 1.365 | D35: =(D5*B11/100)*C35 -> 263.7311
A36: AD Blue | C36: 0 | D36: =(D6*B11)*C36 -> 0
A37: Fuel | C37: 1.1225
A38: Casse / Pneumatique / Lavage ( hors entretien) | C38: 0.04 | D38: =C38*B11 -> 27.84
A39: Autoroute | B39: =B12 -> 0 | C39: 5 | D39: =C39*B39 -> 0
A40: Salaires | B40: SPL | C40: 1 | D40: 865.8
A41: Frais Hotel | D41: =G11 -> 0
A42: Tirpalette | B42: NON | C42: =IF(B42=Liste!A24,Liste!B18,0) -> 0 | D42: =C42/4.33 -> 0
A43: Sous-Traitance | C43: 0 | D43: 0
C45: TOTAL COUT | D45: =SUM(D29:D43) -> 1965.6852
C46: Marge Exploitation | D46: =F24-D45 -> 1144.3683
C48: % Marge | D48: =D46/F24 -> 0.36795776

Sheet SPL69
A1: FICHE DE RENTABILITE
A3: DONNEES EXPLOITATION
B4: Immatriculation | D4: Conso au 100 (Moyenne) | F4: Semaine | G4: S16
A5: Tracteur (s) | B5: GC-563-VF | D5: 28.92
A6: Semi (s) | B6: 1 Classique | D6: 0.019
A7: Conducteurs | B7: COSTA | C7: DIABATE
A8: AMPLITUDE Hebdo | B8: 74.13 | C8: 46.49
A9: TDS Hebdo | B9: 39.48 | C9: 23.92
B10: KM Hebdo | G10: Hotel (semaine)
B11: =1547+1043 -> 2590 | G11: 0
A12: Autoroute / jour : | B12: 0 | F12: SPL | G12: CM
E13: €/ Hebdo | F13: 1000 | G13: 1100
A14: Détails CA
A15: Référence prestations | B15: Fréquence | C15: Montant unitaire | D15: Quantité | E15: Total Hors IGO | F15: Indexation | G15: Montant Total
A16: VIAPOSTE : 163-7 | B16: Lundi au Vendredi | C16: 228.27 | D16: 5 | E16: =C16*D16 -> 1141.35 | F16: 0.039775 | G16: =(E16*F16)+E16 -> 1186.7472
A17: VIAPOSTE : 163-17 | B17: Lundi au Vendredi | C17: 199.26 | D17: 6 | E17: =C17*D17 -> 1195.56 | F17: 0.039775 | G17: =(E17*F17)+E17 -> 1243.1134
A18: VIAPOSTE : 163-10 | B18: Lundi au Vendredi | C18: 191.98 | D18: 5 | E18: =C18*D18 -> 959.9 | F18: 0.039775 | G18: =(E18*F18)+E18 -> 998.08002
A19: VIAPOSTE : 163-11 / 164-9Z | B19: Lundi au Vendredi | C19: =173.7+88.24 -> 261.94 | D19: 5 | E19: =C19*D19 -> 1309.7 | F19: 0.039775 | G19: =(E19*F19)+E19 -> 1361.7933
A20: WE : VIAPOSTE 163-16 | B20: Samedi | C20: 198.76 | D20: 1 | E20: =C20*D20 -> 198.76 | F20: 0.039775 | G20: =(E20*F20)+E20 -> 206.66568
A21: Diabaté sur 5 jours
A24: SPL69 | B24: CA DE LA LIGNE | F24: =SUM(G16:G22) -> 4996.3996
A25: SOMMAIRE
A27: Coûts de la Ligne
B28: Type | C28: unité | D28: Cout Semaine
A29: Moteur (1) | B29: Tracteur GNC | C29: =IFERROR(VLOOKUP(B29,Liste!C1:D5,2,FALSE),"") -> 2500 | D29: =IFERROR(C29/4.33,0) -> 577.36721
A30: Semi (1) | B30: SR Classique | C30: =IFERROR(VLOOKUP(B30,Liste!$C$7:$D$15,2,FALSE),"") -> 1000 | D30: =IFERROR(C30/4.33,0) -> 230.94688
A31: Semi (2) | B31: AUCUNE | C31: =IFERROR(VLOOKUP(B31,Liste!$C$7:$D$15,2,FALSE),"") | D31: =IFERROR(C31/4.33,0) -> 0
A32: Semi (3) | B32: AUCUNE | C32: =IFERROR(VLOOKUP(B32,Liste!$C$7:$D$15,2,FALSE),"") | D32: =IFERROR(C32/4.33,0) -> 0
A33: Semi (4) | B33: AUCUNE | C33: =IFERROR(VLOOKUP(B33,Liste!$C$7:$D$15,2,FALSE),"") | D33: =IFERROR(C33/4.33,0) -> 0
A34: Carburant | B34: GO | C34: 0 | D34: =(B11*D5/100)*C34 -> 0
A35: Carburant | B35: GNC | C35: 1.365 | D35: =(D5*B11/100)*C35 -> 1022.4232
A36: AD Blue | C36: 0 | D36: =(D6*B11)*C36 -> 0
A37: Fuel | C37: 1.1225
A38: Casse / Pneumatique / Lavage ( hors entretien) | C38: 0.04 | D38: =C38*B11 -> 103.6
A39: Autoroute | B39: =B12 -> 0 | C39: 5 | D39: =C39*B39 -> 0
A40: Salaires | B40: SPL | C40: 2 | D40: =942.39+1007.96 -> 1950.35
A41: Frais Hotel | D41: =G11 -> 0
A42: Tirpalette | B42: NON | C42: =IF(B42=Liste!A24,Liste!B18,0) -> 0 | D42: =C42/4.33 -> 0
A43: Sous-Traitance | C43: 0 | D43: 0
C45: TOTAL COUT | D45: =SUM(D29:D43) -> 3884.6873
C46: Marge Exploitation | D46: =F24-D45 -> 1111.7123
C48: % Marge | D48: =D46/F24 -> 0.22250268

Sheet SPL68
A1: FICHE DE RENTABILITE
A3: DONNEES EXPLOITATION
B4: Immatriculation | D4: Conso au 100 (Moyenne) | F4: Semaine | G4: S15
A5: Tracteur (s) | B5: FN-808-QA | D5: 25.02
A6: Semi (s) | B6: 1 Classique | C6: 1 classique | D6: 0.019
A7: Conducteurs | B7: DIALLO Maliki | C7: MOUSSA FALL
A8: AMPLITUDE Hebdo | B8: 58.2 | C8: 66.15
A9: TDS Hebdo | B9: 35.58 | C9: 47.59
B10: KM Hebdo | G10: Hotel (semaine)
B11: =1313+1293 -> 2606 | G11: 0
A12: Autoroute / jour : | B12: 0 | F12: SPL | G12: CM
E13: €/ Hebdo | F13: 1000 | G13: 1100
A14: Détails CA
A15: Référence prestations | B15: Fréquence | C15: Montant unitaire | D15: Quantité | E15: Total Hors IGO | F15: Indexation | G15: Montant Total
A16: VIAPOSTE : 164-2 | B16: Lundi | C16: 107.52 | D16: 1 | E16: =C16*D16 -> 107.52 | F16: 0.039775 | G16: =(E16*F16)+E16 -> 111.79661 | I16: Indexation Gaz - Utilisation d'un GO
A17: VIAPOSTE : 164-26 | B17: Lundi au Vendredi | C17: 186.69 | D17: 6 | E17: =C17*D17 -> 1120.14 | F17: 0.039775 | G17: =(E17*F17)+E17 -> 1164.6936
A18: UPS : PA95 | B18: Mardi au Vendredi | C18: 220 | D18: 4 | E18: =C18*D18 -> 880 | F18: -0.0226 | G18: =(E18*F18)+E18 -> 860.112
A19: CHRONOPOST : 23R09 | B19: Lundi au Vendredi | C19: 305 | D19: 5 | E19: =C19*D19 -> 1525 | F19: 0 | G19: =(E19*F19)+E19 -> 1525
A20: UPS : Livraison Senlis | B20: Lundi au Vendredi | C20: 197.5 | D20: 5 | E20: =C20*D20 -> 987.5 | F20: 0.0409 | G20: =(E20*F20)+E20 -> 1027.8888
A21: CHRONOPOST : DARMSSHNI03 | B21: Lundi au Vendredi | C21: 160 | D21: 5 | E21: =C21*D21 -> 800 | F21: 0 | G21: =(E21*F21)+E21 -> 800
A22: WE: VIAPOSTE : 170-15 | B22: Samedi | C22: 157.23 | D22: 1 | E22: =C22*D22 -> 157.23 | F22: 0.04271 | G22: =(E22*F22)+E22 -> 163.94529
A23: WE : Colissimo LTH-009-S33 | B23: Samedi | C23: 2.0588 | D23: =68+138 -> 206 | E23: =C23*D23 -> 424.1128 | F23: 0 | G23: =(E23*F23)+E23 -> 424.1128
A25: SPL68 | B25: CA DE LA LIGNE | F25: =SUM(G16:G23) -> 6077.549
A26: SOMMAIRE
A28: Coûts de la Ligne
B29: Type | C29: unité | D29: Cout Semaine
A30: Moteur (1) | B30: Tracteur GO | C30: =IFERROR(VLOOKUP(B30,Liste!C1:D5,2,FALSE),"") -> 2300 | D30: =IFERROR(C30/4.33,0) -> 531.17783
A31: Semi (1) | B31: SR Classique | C31: =IFERROR(VLOOKUP(B31,Liste!$C$7:$D$15,2,FALSE),"") -> 1000 | D31: =IFERROR(C31/4.33,0) -> 230.94688
A32: Semi (2) | B32: SR Classique | C32: =IFERROR(VLOOKUP(B32,Liste!$C$7:$D$15,2,FALSE),"") -> 1000 | D32: =IFERROR(C32/4.33,0) -> 230.94688
A33: Semi (3) | B33: AUCUNE | C33: =IFERROR(VLOOKUP(B33,Liste!$C$7:$D$15,2,FALSE),"") | D33: =IFERROR(C33/4.33,0) -> 0
A34: Semi (4) | B34: AUCUNE | C34: =IFERROR(VLOOKUP(B34,Liste!$C$7:$D$15,2,FALSE),"") | D34: =IFERROR(C34/4.33,0) -> 0
A35: Carburant | B35: GO | C35: 1.3554 | D35: =(B11*D5/100)*C35 -> 883.74953
A36: Carburant | B36: GNC | C36: 0 | D36: =(D5*B11/100)*C36 -> 0
A37: AD Blue | C37: 0.4309 | D37: =(D6*B11)*C37 -> 21.335583
A38: Fuel | C38: 1.1225
A39: Casse / Pneumatique / Lavage ( hors entretien) | C39: 0.04 | D39: =C39*B11 -> 104.24
A40: Autoroute | B40: =B12 -> 0 | C40: 5 | D40: =C40*B40 -> 0
A41: Salaires | B41: SPL | C41: 2 | D41: =892.45+724.08 -> 1616.53
A42: Frais Hotel | D42: =G11 -> 0
A43: Tirpalette | B43: NON | C43: =IF(B43=Liste!A24,Liste!B18,0) -> 0 | D43: =C43/4.33 -> 0
A44: Sous-Traitance | C44: 0 | D44: 0
C46: TOTAL COUT | D46: =SUM(D30:D44) -> 3618.9267
C47: Marge Exploitation | D47: =F25-D46 -> 2458.6223
C49: % Marge | D49: =D47/F25 -> 0.40454175

Sheet SPL67
A1: FICHE DE RENTABILITE
A3: DONNEES EXPLOITATION
B4: Immatriculation | D4: Conso au 100 (Moyenne) | F4: Semaine | G4: S16
A5: Tracteur (s) | B5: FN-479-HD | D5: 25.59
A6: Semi (s) | B6: 1 Aerienne | D6: 0.019
A7: Conducteurs | B7: CIMPEAN
A8: AMPLITUDE Hebdo | B8: 66.24
A9: TDS Hebdo | B9: 37.22
B10: KM Hebdo | G10: Hotel (semaine)
B11: 2320 | G11: 0
A12: Autoroute / jour : | B12: 137.15 | F12: SPL | G12: CM
E13: €/ Hebdo | F13: 1000 | G13: 1100
A14: Détails CA
A15: Référence prestations | B15: Fréquence | C15: Montant unitaire | D15: Quantité | E15: Total Hors IGO | F15: Indexation | G15: Montant Total
A16: DHL : FR9876A | B16: Lundi au Vendredi | C16: 350 | D16: 5 | E16: =C16*D16 -> 1750 | F16: -0.0301 | G16: =(E16*F16)+E16 -> 1697.325
A17: DHL : FR7698B | B17: Lundi au Vendredi | C17: 350 | D17: 5 | E17: =C17*D17 -> 1750 | F17: -0.0301 | G17: =(E17*F17)+E17 -> 1697.325
A18: FEDEX : FRT03383 | B18: Mardi au Vendredi | C18: 205 | D18: 4 | E18: =C18*D18 -> 820 | F18: 0.0097 | G18: =(E18*F18)+E18 -> 827.954
E19: =C19*D19 -> 0 | G19: =(E19*F19)+E19 -> 0
A20: Tourne sur 5 jours | E20: =C20*D20 -> 0 | G20: =(E20*F20)+E20 -> 0
E21: =C21*D21 -> 0 | G21: =(E21*F21)+E21 -> 0
E22: =C22*D22 -> 0 | G22: =(E22*F22)+E22 -> 0
A24: SPL67 | B24: CA DE LA LIGNE | F24: =SUM(G16:G22) -> 4222.604
A25: SOMMAIRE
A27: Coûts de la Ligne
B28: Type | C28: unité | D28: Cout Semaine
A29: Moteur (1) | B29: Tracteur GO | C29: =IFERROR(VLOOKUP(B29,Liste!C1:D5,2,FALSE),"") -> 2300 | D29: =IFERROR(C29/4.33,0) -> 531.17783
A30: Semi (1) | B30: Aérienne Classique | C30: =IFERROR(VLOOKUP(B30,Liste!$C$7:$D$15,2,FALSE),"") -> 1200 | D30: =IFERROR(C30/4.33,0) -> 277.13626
A31: Semi (2) | B31: AUCUNE | C31: =IFERROR(VLOOKUP(B31,Liste!$C$7:$D$15,2,FALSE),"") | D31: =IFERROR(C31/4.33,0) -> 0
A32: Semi (3) | B32: AUCUNE | C32: =IFERROR(VLOOKUP(B32,Liste!$C$7:$D$15,2,FALSE),"") | D32: =IFERROR(C32/4.33,0) -> 0
A33: Semi (4) | B33: AUCUNE | C33: =IFERROR(VLOOKUP(B33,Liste!$C$7:$D$15,2,FALSE),"") | D33: =IFERROR(C33/4.33,0) -> 0
A34: Carburant | B34: GO | C34: 1.3554 | D34: =(B11*D5/100)*C34 -> 804.68472
A35: Carburant | B35: GNC | C35: 0 | D35: =(D5*B11/100)*C35 -> 0
A36: AD Blue | C36: 0.4309 | D36: =(D6*B11)*C36 -> 18.994072
A37: Fuel | C37: 1.1225
A38: Casse / Pneumatique / Lavage ( hors entretien) | C38: 0.04 | D38: =C38*B11 -> 92.8
A39: Autoroute | B39: =B12 -> 137.15 | C39: 5 | D39: =C39*B39 -> 685.75
A40: Salaires | B40: SPL | C40: 1 | D40: 899.34
A41: Frais Hotel | D41: =G11 -> 0
A42: Tirpalette | B42: NON | C42: =IF(B42=Liste!A24,Liste!B18,0) -> 0 | D42: =C42/4.33 -> 0
A43: Sous-Traitance | C43: 0 | D43: 0
C45: TOTAL COUT | D45: =SUM(D29:D43) -> 3309.8829
C46: Marge Exploitation | D46: =F24-D45 -> 912.72113
C48: % Marge | D48: =D46/F24 -> 0.21615125

Sheet SPL62
A1: FICHE DE RENTABILITE
A3: DONNEES EXPLOITATION
B4: Immatriculation | D4: Conso au 100 (Moyenne) | F4: Semaine | G4: S15
A5: Tracteur (s) | B5: FA-982-BG | D5: 27.39
A6: Semi (s) | B6: 1 Classique | D6: 0.019
A7: Conducteurs | B7: CISSE M.
A8: AMPLITUDE Hebdo | B8: 51.16
A9: TDS Hebdo | B9: 37.02
B10: KM Hebdo | G10: Hotel (semaine)
B11: 1893 | G11: 0
A12: Autoroute / jour : | B12: 0 | F12: SPL | G12: CM
E13: €/ Hebdo | F13: 1000 | G13: 1100
A14: Détails CA
A15: Référence prestations | B15: Fréquence | C15: Montant unitaire | D15: Quantité | E15: Total Hors IGO | F15: Indexation | G15: Montant Total
A16: Mondial Relay : Cergy - Reau | B16: Lundi au Vendredi | C16: 280 | D16: 5 | E16: =C16*D16 -> 1400 | F16: -0.0137 | G16: =(E16*F16)+E16 -> 1380.82
A17: UPS : PA18 | B17: Lundi au Vendredi | C17: 147.5 | D17: 5 | E17: =C17*D17 -> 737.5 | F17: -0.0226 | G17: =(E17*F17)+E17 -> 720.8325
A18: Ramasse UPS | B18: Lundi au Vendredi | C18: 197.5 | D18: 5 | E18: =C18*D18 -> 987.5 | F18: 0.0409 | G18: =(E18*F18)+E18 -> 1027.8888
E19: =C19*D19 -> 0 | G19: =(E19*F19)+E19 -> 0
A20: A tourné que 5 jours semaine | E20: =C20*D20 -> 0 | G20: =(E20*F20)+E20 -> 0
E21: =C21*D21 -> 0 | G21: =(E21*F21)+E21 -> 0
E22: =C22*D22 -> 0 | G22: =(E22*F22)+E22 -> 0
A24: SPL62 | B24: CA DE LA LIGNE | F24: =SUM(G16:G22) -> 3129.5413
A25: SOMMAIRE
A27: Coûts de la Ligne
B28: Type | C28: unité | D28: Cout Semaine
A29: Moteur (1) | B29: Tracteur GO | C29: =IFERROR(VLOOKUP(B29,Liste!C1:D5,2,FALSE),"") -> 2300 | D29: =IFERROR(C29/4.33,0) -> 531.17783
A30: Semi (1) | B30: SR Classique | C30: =IFERROR(VLOOKUP(B30,Liste!$C$7:$D$15,2,FALSE),"") -> 1000 | D30: =IFERROR(C30/4.33,0) -> 230.94688
A31: Semi (2) | B31: AUCUNE | C31: =IFERROR(VLOOKUP(B31,Liste!$C$7:$D$15,2,FALSE),"") | D31: =IFERROR(C31/4.33,0) -> 0
A32: Semi (3) | B32: AUCUNE | C32: =IFERROR(VLOOKUP(B32,Liste!$C$7:$D$15,2,FALSE),"") | D32: =IFERROR(C32/4.33,0) -> 0
A33: Semi (4) | B33: AUCUNE | C33: =IFERROR(VLOOKUP(B33,Liste!$C$7:$D$15,2,FALSE),"") | D33: =IFERROR(C33/4.33,0) -> 0
A34: Carburant | B34: GO | C34: 1.3554 | D34: =(B11*D5/100)*C34 -> 702.76501
A35: Carburant | B35: GNC | C35: 0 | D35: =(D5*B11/100)*C35 -> 0
A36: AD Blue | C36: 0.4309 | D36: =(D6*B11)*C36 -> 15.49818
A37: Fuel | C37: 1.1225
A38: Casse / Pneumatique / Lavage ( hors entretien) | C38: 0.04 | D38: =C38*B11 -> 75.72
A39: Autoroute | B39: =B12 -> 0 | C39: 5 | D39: =C39*B39 -> 0
A40: Salaires | B40: SPL | C40: 1 | D40: 1051.97
A41: Frais Hotel | D41: =G11 -> 0
A42: Tirpalette | B42: NON | C42: =IF(B42=Liste!A24,Liste!B18,0) -> 0 | D42: =C42/4.33 -> 0
A43: Sous-Traitance | C43: 0 | D43: 0
C45: TOTAL COUT | D45: =SUM(D29:D43) -> 2608.0779
C46: Marge Exploitation | D46: =F24-D45 -> 521.46335
C48: % Marge | D48: =D46/F24 -> 0.16662613

Sheet SPL59
A1: FICHE DE RENTABILITE
A3: DONNEES EXPLOITATION
B4: Immatriculation | D4: Conso au 100 (Moyenne) | F4: Semaine | G4: S16
A5: Tracteur (s) | B5: FN-491-QA | D5: 26.23
A6: Semi (s) | B6: 1 Classic | C6: 1 Bachée | D6: 0.019
A7: Conducteurs | B7: PHILIBERT | C7: GONCALVES Kama
A8: AMPLITUDE Hebdo | B8: 67.69 | C8: 52.65
A9: TDS Hebdo | B9: 35.29 | C9: 48.75
B10: KM Hebdo | G10: Hotel (semaine)
B11: =2650+1297 -> 3947 | G11: 0
A12: Autoroute / jour : | B12: 110.78 | F12: SPL | G12: CM
E13: €/ Hebdo | F13: 1000 | G13: 1100
A14: Détails CA
A15: Référence prestations | B15: Fréquence | C15: Montant unitaire | D15: Quantité | E15: Total Hors IGO | F15: Indexation | G15: Montant Total
A16: UPS : Livraison Amazon Senlis | B16: Lundi au Vendredi | C16: 197.5 | D16: 5 | E16: =C16*D16 -> 987.5 | F16: 0.0409 | G16: =(E16*F16)+E16 -> 1027.8888
A17: DGF : Navette Helicopter | B17: Lundi au Vendredi | C17: 430 | D17: 5 | E17: =C17*D17 -> 2150 | F17: 0 | G17: =(E17*F17)+E17 -> 2150
A18: SCHENKER | B18: Lundi au Vendredi | C18: 570 | D18: 5 | E18: =C18*D18 -> 2850 | F18: 0.0525 | G18: =(E18*F18)+E18 -> 2999.625
A19: WE : Chrono : Cdiscount | B19: Samedi | C19: 200 | D19: 1 | E19: =C19*D19 -> 200 | F19: 3.5 | G19: =F19+E19 -> 203.5
A20: WE : Colissimo LTH-009-S33 | B20: Samedi | C20: 2.0588 | D20: =68+138 -> 206 | E20: =C20*D20 -> 424.1128 | F20: 0 | G20: =(E20*F20)+E20 -> 424.1128
A21: Kama Tourne Sur 5 jours | E21: =C21*D21 -> 0 | G21: =(E21*F21)+E21 -> 0
E22: =C22*D22 -> 0 | G22: =(E22*F22)+E22 -> 0
A24: SPL59 | B24: CA DE LA LIGNE | F24: =SUM(G16:G22) -> 6805.1265
A25: SOMMAIRE
A27: Coûts de la Ligne
B28: Type | C28: unité | D28: Cout Semaine
A29: Moteur (1) | B29: Tracteur GO | C29: =IFERROR(VLOOKUP(B29,Liste!C1:D5,2,FALSE),"") -> 2300 | D29: =IFERROR(C29/4.33,0) -> 531.17783
A30: Semi (1) | B30: SR Classique | C30: =IFERROR(VLOOKUP(B30,Liste!$C$7:$D$15,2,FALSE),"") -> 1000 | D30: =IFERROR(C30/4.33,0) -> 230.94688
A31: Semi (2) | B31: Aérienne Bachée | C31: =IFERROR(VLOOKUP(B31,Liste!$C$7:$D$15,2,FALSE),"") -> 1200 | D31: =IFERROR(C31/4.33,0) -> 277.13626
A32: Semi (3) | B32: AUCUNE | C32: =IFERROR(VLOOKUP(B32,Liste!$C$7:$D$15,2,FALSE),"") | D32: =IFERROR(C32/4.33,0) -> 0
A33: Semi (4) | B33: AUCUNE | C33: =IFERROR(VLOOKUP(B33,Liste!$C$7:$D$15,2,FALSE),"") | D33: =IFERROR(C33/4.33,0) -> 0
A34: Carburant | B34: GO | C34: 1.3554 | D34: =(B11*D5/100)*C34 -> 1403.243
A35: Carburant | B35: GNC | C35: 0 | D35: =(D5*B11/100)*C35 -> 0
A36: AD Blue | C36: 0.4309 | D36: =(D6*B11)*C36 -> 32.314484
A37: Fuel | C37: 1.1225
A38: Casse / Pneumatique / Lavage ( hors entretien) | C38: 0.04 | D38: =C38*B11 -> 157.88
A39: Autoroute | B39: =B12 -> 110.78 | C39: 5 | D39: =C39*B39 -> 553.9
A40: Salaires | B40: SPL | C40: 2 | D40: =1000+559.12 -> 1559.12
A41: Frais Hotel | D41: =G11 -> 0
A42: Tirpalette | B42: NON | C42: =IF(B42=Liste!A24,Liste!B18,0) -> 0 | D42: =C42/4.33 -> 0
A43: Sous-Traitance | C43: 0 | D43: 0
C45: TOTAL COUT | D45: =SUM(D29:D43) -> 4745.7185
C46: Marge Exploitation | D46: =F24-D45 -> 2059.4081
C48: % Marge | D48: =D46/F24 -> 0.30262597

Sheet SPL56
A1: FICHE DE RENTABILITE
A3: DONNEES EXPLOITATION
B4: Immatriculation | D4: Conso au 100 (Moyenne) | F4: Semaine | G4: S16
A5: Tracteur (s) | B5: GG-921-EB | D5: 34.14
A6: Semi (s) | B6: 1 Classic | D6: 0.019
A7: Conducteurs | B7: DJAFFAR | C7: MOUSSA TRAORE
A8: AMPLITUDE Hebdo | B8: 69.28 | C8: 55.31
A9: TDS Hebdo | B9: 34.89 | C9: 33.4
B10: KM Hebdo | G10: Hotel (semaine)
B11: =957+993 -> 1950 | G11: 0
A12: Autoroute / jour : | B12: 0 | F12: SPL | G12: CM
E13: €/ Hebdo | F13: 1000 | G13: 1100
A14: Détails CA
A15: Référence prestations | B15: Fréquence | C15: Montant unitaire | D15: Quantité | E15: Total Hors IGO | F15: Indexation | G15: Montant Total
A16: VIAPOSTE : 164-13 | B16: Lundi au Vendredi | C16: 121.45 | D16: 6 | E16: =C16*D16 -> 728.7 | F16: 0.039775 | G16: =(E16*F16)+E16 -> 757.68404
A17: VIAPOSTE : 164-21 | B17: Lundi au Vendredi | C17: 183.01 | D17: 6 | E17: =C17*D17 -> 1098.06 | F17: 0.039775 | G17: =(E17*F17)+E17 -> 1141.7353
A18: VIAPOSTE : 164-24 | B18: Lundi au Vendredi | C18: 186.69 | D18: 6 | E18: =C18*D18 -> 1120.14 | F18: 0.039775 | G18: =(E18*F18)+E18 -> 1164.6936
A19: VIAPOSTE : 164-24Z | B19: Lundi au Vendredi | C19: 198.79 | D19: 5 | E19: =C19*D19 -> 993.95 | F19: 0.039775 | G19: =(E19*F19)+E19 -> 1033.4844
A20: VIAPOSTE : 164-4 | B20: Lundi au Vendredi | C20: 177.33 | D20: 5 | E20: =C20*D20 -> 886.65 | F20: 0.039775 | G20: =(E20*F20)+E20 -> 921.9165
A21: VIAPOSTE : 168-5Z | B21: Lundi au Vendredi | C21: 102.8 | D21: 5 | E21: =C21*D21 -> 514 | F21: 0.04773 | G21: =(E21*F21)+E21 -> 538.53322
A22: WE : GB4 | B22: Samedi | C22: 295 | D22: 1 | E22: =C22*D22 -> 295 | F22: 0 | G22: =(E22*F22)+E22 -> 295
A23: WE : VIAPOSTE 170-7 | B23: Samedi | C23: 100.67 | D23: 1 | E23: =C23*D23 -> 100.67 | F23: 0.04271 | G23: =(E23*F23)+E23 -> 104.96962
A25: SPL56 | B25: CA DE LA LIGNE | F25: =SUM(G16:G23) -> 5958.0166
A26: SOMMAIRE
A28: Coûts de la Ligne
B29: Type | C29: unité | D29: Cout Semaine
A30: Moteur (1) | B30: Tracteur GNC | C30: =IFERROR(VLOOKUP(B30,Liste!C1:D5,2,FALSE),"") -> 2500 | D30: =IFERROR(C30/4.33,0) -> 577.36721
A31: Semi (1) | B31: SR Classique | C31: =IFERROR(VLOOKUP(B31,Liste!$C$7:$D$15,2,FALSE),"") -> 1000 | D31: =IFERROR(C31/4.33,0) -> 230.94688
A32: Semi (2) | B32: AUCUNE | C32: =IFERROR(VLOOKUP(B32,Liste!$C$7:$D$15,2,FALSE),"") | D32: =IFERROR(C32/4.33,0) -> 0
A33: Semi (3) | B33: AUCUNE | C33: =IFERROR(VLOOKUP(B33,Liste!$C$7:$D$15,2,FALSE),"") | D33: =IFERROR(C33/4.33,0) -> 0
A34: Semi (4) | B34: AUCUNE | C34: =IFERROR(VLOOKUP(B34,Liste!$C$7:$D$15,2,FALSE),"") | D34: =IFERROR(C34/4.33,0) -> 0
A35: Carburant | B35: GO | C35: 0 | D35: =(B11*D5/100)*C35 -> 0
A36: Carburant | B36: GNC | C36: 1.365 | D36: =(D5*B11/100)*C36 -> 908.72145
A37: AD Blue | C37: 0 | D37: =(D6*B11)*C37 -> 0
A38: Fuel | C38: 1.1225
A39: Casse / Pneumatique / Lavage ( hors entretien) | C39: 0.04 | D39: =C39*B11 -> 78
A40: Autoroute | B40: =B12 -> 0 | C40: 5 | D40: =C40*B40 -> 0
A41: Salaires | B41: SPL | C41: 2 | D41: =961.21+1072.04 -> 2033.25
A42: Frais Hotel | D42: =G11 -> 0
A43: Tirpalette | B43: NON | C43: =IF(B43=Liste!A24,Liste!B18,0) -> 0 | D43: =C43/4.33 -> 0
A44: Sous-Traitance | C44: 0 | D44: 0
C46: TOTAL COUT | D46: =SUM(D30:D44) -> 3828.2855
C47: Marge Exploitation | D47: =F25-D46 -> 2129.7311
C49: % Marge | D49: =D47/F25 -> 0.35745639

Sheet SPL54
A1: FICHE DE RENTABILITE
A3: DONNEES EXPLOITATION
B4: Immatriculation | D4: Conso au 100 (Moyenne) | F4: Semaine | G4: S16
A5: Tracteur (s) | B5: EZ-504-SN | D5: 29.51
A6: Semi (s) | B6: 1 Classic | C6: 1 aerienne | D6: 0.019
A7: Conducteurs | B7: JEBALI
A8: AMPLITUDE Hebdo | B8: 59.98
A9: TDS Hebdo | B9: 35.95
B10: KM Hebdo | G10: Hotel (semaine)
B11: 1996 | G11: 0
A12: Autoroute / jour : | B12: 38.99 | F12: SPL | G12: CM
E13: €/ Hebdo | F13: 1000 | G13: 1100
A14: Détails CA
A15: Référence prestations | B15: Fréquence | C15: Montant unitaire | D15: Quantité | E15: Total Hors IGO | F15: Indexation | G15: Montant Total
A16: DHL : Troyes- Roissy | B16: Lundi au Vendredi | C16: 310 | D16: 5 | E16: =C16*D16 -> 1550 | F16: -0.0301 | G16: =(E16*F16)+E16 -> 1503.345
A17: Chronopost : 38620 | B17: Lundi au Vendredi | C17: 330 | D17: 5 | E17: =C17*D17 -> 1650 | F17: =(161*5)*0.1412 -> 113.666 | G17: =F17+E17 -> 1763.666
E18: =C18*D18 -> 0 | G18: =(E18*F18)+E18 -> 0
E19: =C19*D19 -> 0 | G19: =(E19*F19)+E19 -> 0
E20: =C20*D20 -> 0 | G20: =(E20*F20)+E20 -> 0
E21: =C21*D21 -> 0 | G21: =(E21*F21)+E21 -> 0
E22: =C22*D22 -> 0 | G22: =(E22*F22)+E22 -> 0
A24: SPL54 | B24: CA DE LA LIGNE | F24: =SUM(G16:G22) -> 3267.011
A25: SOMMAIRE
A27: Coûts de la Ligne
B28: Type | C28: unité | D28: Cout Semaine
A29: Moteur (1) | B29: Tracteur GO | C29: =IFERROR(VLOOKUP(B29,Liste!C1:D5,2,FALSE),"") -> 2300 | D29: =IFERROR(C29/4.33,0) -> 531.17783
A30: Semi (1) | B30: SR Classique | C30: =IFERROR(VLOOKUP(B30,Liste!$C$7:$D$15,2,FALSE),"") -> 1000 | D30: =IFERROR(C30/4.33,0) -> 230.94688
A31: Semi (2) | B31: Aérienne Classique | C31: =IFERROR(VLOOKUP(B31,Liste!$C$7:$D$15,2,FALSE),"") -> 1200 | D31: =IFERROR(C31/4.33,0) -> 277.13626
A32: Semi (3) | B32: AUCUNE | C32: =IFERROR(VLOOKUP(B32,Liste!$C$7:$D$15,2,FALSE),"") | D32: =IFERROR(C32/4.33,0) -> 0
A33: Semi (4) | B33: AUCUNE | C33: =IFERROR(VLOOKUP(B33,Liste!$C$7:$D$15,2,FALSE),"") | D33: =IFERROR(C33/4.33,0) -> 0
A34: Carburant | B34: GO | C34: 1.3554 | D34: =(B11*D5/100)*C34 -> 798.35717
A35: Carburant | B35: GNC | C35: 0 | D35: =(D5*B11/100)*C35 -> 0
A36: AD Blue | C36: 0.4309 | D36: =(D6*B11)*C36 -> 16.341452
A37: Fuel | C37: 1.1225
A38: Casse / Pneumatique / Lavage ( hors entretien) | C38: 0.04 | D38: =C38*B11 -> 79.84
A39: Autoroute | B39: =B12 -> 38.99 | C39: 5 | D39: =C39*B39 -> 194.95
A40: Salaires | B40: SPL | C40: 1 | D40: 889.05
A41: Frais Hotel | D41: =G11 -> 0
A42: Tirpalette | B42: NON | C42: =IF(B42=Liste!A24,Liste!B18,0) -> 0 | D42: =C42/4.33 -> 0
A43: Sous-Traitance | C43: 0 | D43: 0
C45: TOTAL COUT | D45: =SUM(D29:D43) -> 3017.7996
C46: Marge Exploitation | D46: =F24-D45 -> 249.21141
C48: % Marge | D48: =D46/F24 -> 0.076281167

Sheet SPL53
A1: FICHE DE RENTABILITE
A3: DONNEES EXPLOITATION
B4: Immatriculation | D4: Conso au 100 (Moyenne) | F4: Semaine | G4: S16
A5: Tracteur (s) | B5: FR-901-DK | D5: 26.25
A6: Semi (s) | B6: 1 Classic | D6: 0.019
A7: Conducteurs | B7: DIFALLAH
A8: AMPLITUDE Hebdo | B8: 64.54
A9: TDS Hebdo | B9: 44.51
B10: KM Hebdo | G10: Hotel (semaine)
B11: 1881 | G11: 0
A12: Autoroute / jour : | B12: 67.32 | F12: SPL | G12: CM
E13: €/ Hebdo | F13: 1000 | G13: 1100
A14: Détails CA
A15: Référence prestations | B15: Fréquence | C15: Montant unitaire | D15: Quantité | E15: Total Hors IGO | F15: Indexation | G15: Montant Total
A16: DHL : 9851B | B16: Lundi au Vendredi | C16: 300 | D16: 5 | E16: =C16*D16 -> 1500 | F16: -0.0301 | G16: =(E16*F16)+E16 -> 1454.85
A17: DHL : 5198A | B17: Lundi au Vendredi | C17: 300 | D17: 5 | E17: =C17*D17 -> 1500 | F17: -0.0301 | G17: =(E17*F17)+E17 -> 1454.85
A18: DHL : Enlevement Cormontreuil + La veuve | B18: Lundi au Vendredi | C18: 90 | D18: 5 | E18: =C18*D18 -> 450 | F18: 0 | G18: =(E18*F18)+E18 -> 450
E19: =C19*D19 -> 0 | G19: =(E19*F19)+E19 -> 0
E20: =C20*D20 -> 0 | G20: =(E20*F20)+E20 -> 0
E21: =C21*D21 -> 0 | G21: =(E21*F21)+E21 -> 0
E22: =C22*D22 -> 0 | G22: =(E22*F22)+E22 -> 0
A24: SPL53 | B24: CA DE LA LIGNE | F24: =SUM(G16:G22) -> 3359.7
A25: SOMMAIRE
A27: Coûts de la Ligne
B28: Type | C28: unité | D28: Cout Semaine
A29: Moteur (1) | B29: Tracteur GO | C29: =IFERROR(VLOOKUP(B29,Liste!C1:D5,2,FALSE),"") -> 2300 | D29: =IFERROR(C29/4.33,0) -> 531.17783
A30: Semi (1) | B30: SR Classique | C30: =IFERROR(VLOOKUP(B30,Liste!$C$7:$D$15,2,FALSE),"") -> 1000 | D30: =IFERROR(C30/4.33,0) -> 230.94688
A31: Semi (2) | B31: AUCUNE | C31: =IFERROR(VLOOKUP(B31,Liste!$C$7:$D$15,2,FALSE),"") | D31: =IFERROR(C31/4.33,0) -> 0
A32: Semi (3) | B32: AUCUNE | C32: =IFERROR(VLOOKUP(B32,Liste!$C$7:$D$15,2,FALSE),"") | D32: =IFERROR(C32/4.33,0) -> 0
A33: Semi (4) | B33: AUCUNE | C33: =IFERROR(VLOOKUP(B33,Liste!$C$7:$D$15,2,FALSE),"") | D33: =IFERROR(C33/4.33,0) -> 0
A34: Carburant | B34: GO | C34: 1.3554 | D34: =(B11*D5/100)*C34 -> 669.24569
A35: Carburant | B35: GNC | C35: 0 | D35: =(D5*B11/100)*C35 -> 0
A36: AD Blue | C36: 0.4309 | D36: =(D6*B11)*C36 -> 15.399935
A37: Fuel | C37: 1.1225
A38: Casse / Pneumatique / Lavage ( hors entretien) | C38: 0.04 | D38: =C38*B11 -> 75.24
A39: Autoroute | B39: =B12 -> 67.32 | C39: 5 | D39: =C39*B39 -> 336.6
A40: Salaires | B40: SPL | C40: 1 | D40: 1127.77
A41: Frais Hotel | D41: =G11 -> 0
A42: Tirpalette | B42: NON | C42: =IF(B42=Liste!A24,Liste!B18,0) -> 0 | D42: =C42/4.33 -> 0
A43: Sous-Traitance | C43: 0 | D43: 0
C45: TOTAL COUT | D45: =SUM(D29:D43) -> 2986.3803
C46: Marge Exploitation | D46: =F24-D45 -> 373.31966
C48: % Marge | D48: =D46/F24 -> 0.11111696

Sheet SPL51
A1: FICHE DE RENTABILITE
A3: DONNEES EXPLOITATION
B4: Immatriculation | D4: Conso au 100 (Moyenne) | F4: Semaine | G4: S16
A5: Tracteur (s) | B5: DL-031-HB | D5: 29.45
A6: Semi (s) | B6: SOLO | C6: 1 Semi Classique (50%) | D6: 0.019
A7: Conducteurs | B7: BAHYAYA
A8: AMPLITUDE Hebdo | B8: =52.5+14.9 -> 67.4
A9: TDS Hebdo | B9: =40.33+7.78 -> 48.11
B10: KM Hebdo | G10: Hotel (semaine)
B11: =1290+281 -> 1571 | G11: 0
A12: Autoroute / jour : | B12: 0 | C12: (Refacturation Autoroute) | F12: SPL | G12: CM
E13: €/ Hebdo | F13: 1000 | G13: 1100
A14: Détails CA
A15: Référence prestations | B15: Fréquence | C15: Montant unitaire | D15: Quantité | E15: Total Hors IGO | F15: Indexation | G15: Montant Total
A16: TAB : MAD Semi | B16: Lundi au Vendredi | C16: 390 | D16: 5 | E16: =C16*D16 -> 1950 | F16: -0.0336 | G16: =(E16*F16)+E16 -> 1884.48
A17: WE : Colissimo GEN202212891SLOT4 | B17: Samedi | C17: 3.4172 | D17: =18*4 -> 72 | E17: =C17*D17 -> 246.0384 | F17: 0 | G17: =(E17*F17)+E17 -> 246.0384
A18: VIAPOSTE : 163-4 | B18: Lundi au Vendredi | C18: 129 | D18: 5 | E18: =C18*D18 -> 645 | F18: 0.039775 | G18: =(E18*F18)+E18 -> 670.65487
E19: =C19*D19 -> 0 | G19: =(E19*F19)+E19 -> 0
E20: =C20*D20 -> 0 | G20: =(E20*F20)+E20 -> 0
E21: =C21*D21 -> 0 | G21: =(E21*F21)+E21 -> 0
E22: =C22*D22 -> 0 | G22: =(E22*F22)+E22 -> 0
A24: SPL51 | B24: CA DE LA LIGNE | F24: =SUM(G16:G22) -> 2801.1733
A25: SOMMAIRE
A27: Coûts de la Ligne
B28: Type | C28: unité | D28: Cout Semaine
A29: Moteur (1) | B29: Tracteur GO | C29: =IFERROR(VLOOKUP(B29,Liste!C1:D5,2,FALSE),"") -> 2300 | D29: =IFERROR(C29/4.33,0) -> 531.17783
A30: Semi (1) | B30: SR Classique | C30: =IFERROR(VLOOKUP(B30,Liste!$C$7:$D$15,2,FALSE),"") -> 1000 | D30: =IFERROR(C30/4.33,0)/2 -> 115.47344 | E30: 50% de semi
A31: Semi (2) | B31: AUCUNE | C31: =IFERROR(VLOOKUP(B31,Liste!$C$7:$D$15,2,FALSE),"") | D31: =IFERROR(C31/4.33,0) -> 0
A32: Semi (3) | B32: AUCUNE | C32: =IFERROR(VLOOKUP(B32,Liste!$C$7:$D$15,2,FALSE),"") | D32: =IFERROR(C32/4.33,0) -> 0
A33: Semi (4) | B33: AUCUNE | C33: =IFERROR(VLOOKUP(B33,Liste!$C$7:$D$15,2,FALSE),"") | D33: =IFERROR(C33/4.33,0) -> 0
A34: Carburant | B34: GO | C34: 1.3554 | D34: =(B11*D5/100)*C34 -> 627.08869
A35: Carburant | B35: GNC | C35: 0 | D35: =(D5*B11/100)*C35 -> 0
A36: AD Blue | C36: 0.4309 | D36: =(D6*B11)*C36 -> 12.861934
A37: Fuel | C37: 1.1225
A38: Casse / Pneumatique / Lavage ( hors entretien) | C38: 0.04 | D38: =C38*B11 -> 62.84
A39: Autoroute | B39: =B12 -> 0 | C39: 5 | D39: =C39*B39 -> 0
A40: Salaires | B40: SPL | C40: 1 | D40: 975.63
A41: Frais Hotel | D41: =G11 -> 0
A42: Tirpalette | B42: NON | C42: =IF(B42=Liste!A24,Liste!B18,0) -> 0 | D42: =C42/4.33 -> 0
A43: Sous-Traitance | C43: 0 | D43: 0
C45: TOTAL COUT | D45: =SUM(D29:D43) -> 2325.0719
C46: Marge Exploitation | D46: =F24-D45 -> 476.10138
C48: % Marge | D48: =D46/F24 -> 0.16996499

Sheet SPL47
A1: FICHE DE RENTABILITE
A3: DONNEES EXPLOITATION
B4: Immatriculation | D4: Conso au 100 (Moyenne) | F4: Semaine | G4: S15
A5: Tracteur (s) | B5: EJ-491-FX | D5: 28.81
A6: Semi (s) | B6: 1 Classique | D6: 0.019
A7: Conducteurs | B7: CHLIBET
A8: AMPLITUDE Hebdo | B8: =52.34+8.25 -> 60.59
A9: TDS Hebdo | B9: =34.49+6.95 -> 41.44
B10: KM Hebdo | G10: Hotel (semaine)
B11: =1906+175 -> 2081 | G11: 0
A12: Autoroute / jour : | B12: 64 | F12: SPL | G12: CM
E13: €/ Hebdo | F13: 1000 | G13: 1100
A14: Détails CA
A15: Référence prestations | B15: Fréquence | C15: Montant unitaire | D15: Quantité | E15: Total Hors IGO | F15: Indexation | G15: Montant Total
A16: CHRONOPOST 91 : Alloga | B16: Lundi au Vendredi | C16: 370 | D16: 5 | E16: =C16*D16 -> 1850 | F16: =(-11.44*5) -> -57.2 | G16: =F16+E16 -> 1792.8
A17: FEDEX : A5166 | B17: Lundi au Vendredi | C17: 355 | D17: 5 | E17: =C17*D17 -> 1775 | F17: -0.0203 | G17: =(E17*F17)+E17 -> 1738.9675
A18: WE : VIAPOST 163-1 | B18: Dimanche | C18: 251.68 | D18: 1 | E18: =C18*D18 -> 251.68 | F18: 0.039775 | G18: =(E18*F18)+E18 -> 261.69057
E19: =C19*D19 -> 0 | G19: =(E19*F19)+E19 -> 0
E20: =C20*D20 -> 0 | G20: =(E20*F20)+E20 -> 0
E21: =C21*D21 -> 0 | G21: =(E21*F21)+E21 -> 0
E22: =C22*D22 -> 0 | G22: =(E22*F22)+E22 -> 0
A24: SPL47 | B24: CA DE LA LIGNE | F24: =SUM(G16:G22) -> 3793.4581
A25: SOMMAIRE
A27: Coûts de la Ligne
B28: Type | C28: unité | D28: Cout Semaine
A29: Moteur (1) | B29: Tracteur GO | C29: =IFERROR(VLOOKUP(B29,Liste!C1:D5,2,FALSE),"") -> 2300 | D29: =IFERROR(C29/4.33,0) -> 531.17783
A30: Semi (1) | B30: SR Classique | C30: =IFERROR(VLOOKUP(B30,Liste!$C$7:$D$15,2,FALSE),"") -> 1000 | D30: =IFERROR(C30/4.33,0) -> 230.94688
A31: Semi (2) | B31: AUCUNE | C31: =IFERROR(VLOOKUP(B31,Liste!$C$7:$D$15,2,FALSE),"") | D31: =IFERROR(C31/4.33,0) -> 0
A32: Semi (3) | B32: AUCUNE | C32: =IFERROR(VLOOKUP(B32,Liste!$C$7:$D$15,2,FALSE),"") | D32: =IFERROR(C32/4.33,0) -> 0
A33: Semi (4) | B33: AUCUNE | C33: =IFERROR(VLOOKUP(B33,Liste!$C$7:$D$15,2,FALSE),"") | D33: =IFERROR(C33/4.33,0) -> 0
A34: Carburant | B34: GO | C34: 1.3554 | D34: =(B11*D5/100)*C34 -> 812.61123
A35: Carburant | B35: GNC | C35: 0 | D35: =(D5*B11/100)*C35 -> 0
A36: AD Blue | C36: 0.4309 | D36: =(D6*B11)*C36 -> 17.037355
A37: Fuel | C37: 1.1225
A38: Casse / Pneumatique / Lavage ( hors entretien) | C38: 0.04 | D38: =C38*B11 -> 83.24
A39: Autoroute | B39: =B12 -> 64 | C39: 5 | D39: =C39*B39 -> 320
A40: Salaires | B40: SPL | C40: 1 | D40: 885.77
A41: Frais Hotel | D41: =G11 -> 0
A42: Tirpalette | B42: NON | C42: =IF(B42=Liste!A24,Liste!B18,0) -> 0 | D42: =C42/4.33 -> 0
A43: Sous-Traitance | C43: 0 | D43: 0
C45: TOTAL COUT | D45: =SUM(D29:D43) -> 2880.7833
C46: Marge Exploitation | D46: =F24-D45 -> 912.67478
C48: % Marge | D48: =D46/F24 -> 0.24059177

Sheet SPL13
A1: FICHE DE RENTABILITE
A3: DONNEES EXPLOITATION
B4: Immatriculation | D4: Conso au 100 (Moyenne) | F4: Semaine | G4: S16
A5: Tracteur (s) | B5: FN-814-DX | D5: 23.71
A6: Semi (s) | B6: 1 Classique | D6: 0.019
A7: Conducteurs | B7: BODEA | C7: VIVIENS
A8: AMPLITUDE Hebdo | B8: 42.64 | C8: 41.22
A9: TDS Hebdo | B9: 35.9 | C9: 37.33
B10: KM Hebdo | G10: Hotel (semaine)
B11: =1217+2138 -> 3355 | G11: 0
A12: Autoroute / jour : | B12: =29.08*2 -> 58.16 | F12: SPL | G12: CM
E13: €/ Hebdo | F13: 1000 | G13: 1100
A14: Détails CA
A15: Référence prestations | B15: Fréquence | C15: Montant unitaire | D15: Quantité | E15: Total Hors IGO | F15: Indexation | G15: Montant Total
A16: CEVA : Quincy + Torcy … | B16: Mardi au Samedi | C16: 330 | D16: 5 | E16: =C16*D16 -> 1650 | G16: =(E16*F16)+E16 -> 1650
A17: SCHENKER : 7797-1 | B17: Lundi au Vendredi | C17: 540 | D17: 5 | E17: =C17*D17 -> 2700 | F17: 0.0525 | G17: =(E17*F17)+E17 -> 2841.75
E18: =C18*D18 -> 0 | G18: =(E18*F18)+E18 -> 0
E19: =C19*D19 -> 0 | G19: =F19+E19 -> 0
E20: =C20*D20 -> 0 | G20: =(E20*F20)+E20 -> 0
A21: M. Bodea / Viviens Tourne sur 5 jours | E21: =C21*D21 -> 0 | G21: =(E21*F21)+E21 -> 0
E22: =C22*D22 -> 0 | G22: =(E22*F22)+E22 -> 0
A24: SPL13 | B24: CA DE LA LIGNE | F24: =SUM(G16:G22) -> 4491.75
A25: SOMMAIRE
A27: Coûts de la Ligne
B28: Type | C28: unité | D28: Cout Semaine
A29: Moteur (1) | B29: Tracteur GO | C29: =IFERROR(VLOOKUP(B29,Liste!C1:D5,2,FALSE),"") -> 2300 | D29: =IFERROR(C29/4.33,0) -> 531.17783
A30: Semi (1) | B30: SR Classique | C30: =IFERROR(VLOOKUP(B30,Liste!$C$7:$D$15,2,FALSE),"") -> 1000 | D30: =IFERROR(C30/4.33,0) -> 230.94688
A31: Semi (2) | B31: AUCUNE | C31: =IFERROR(VLOOKUP(B31,Liste!$C$7:$D$15,2,FALSE),"") | D31: =IFERROR(C31/4.33,0) -> 0
A32: Semi (3) | B32: AUCUNE | C32: =IFERROR(VLOOKUP(B32,Liste!$C$7:$D$15,2,FALSE),"") | D32: =IFERROR(C32/4.33,0) -> 0
A33: Semi (4) | B33: AUCUNE | C33: =IFERROR(VLOOKUP(B33,Liste!$C$7:$D$15,2,FALSE),"") | D33: =IFERROR(C33/4.33,0) -> 0
A34: Carburant | B34: GO | C34: 1.3554 | D34: =(B11*D5/100)*C34 -> 1078.1807
A35: Carburant | B35: GNC | C35: 0 | D35: =(D5*B11/100)*C35 -> 0
A36: AD Blue | C36: 0.4309 | D36: =(D6*B11)*C36 -> 27.46772
A37: Fuel | C37: 1.1225
A38: Casse / Pneumatique / Lavage ( hors entretien) | C38: 0.04 | D38: =C38*B11 -> 134.2
A39: Autoroute | B39: =B12 -> 58.16 | C39: 5 | D39: =C39*B39 -> 290.8
A40: Salaires | B40: SPL | C40: 2 | D40: =811.13+857.75 -> 1668.88
A41: Frais Hotel | D41: =G11 -> 0
A42: Tirpalette | B42: NON | C42: =IF(B42=Liste!A24,Liste!B18,0) -> 0 | D42: =C42/4.33 -> 0
A43: Sous-Traitance | C43: 0 | D43: 0
C45: TOTAL COUT | D45: =SUM(D29:D43) -> 3961.6531
C46: Marge Exploitation | D46: =F24-D45 -> 530.09685
C48: % Marge | D48: =D46/F24 -> 0.11801566

Sheet SPL14
A1: FICHE DE RENTABILITE
A3: DONNEES EXPLOITATION
B4: Immatriculation | D4: Conso au 100 (Moyenne) | F4: Semaine | G4: S16
A5: Tracteur (s) | B5: GH-350-LV | D5: 27.48
A6: Semi (s) | B6: 1 Classique | D6: 0.019
A7: Conducteurs | B7: DIALLO O. | C7: KAMARA
A8: AMPLITUDE Hebdo | B8: 56.45 | C8: 62.45
A9: TDS Hebdo | B9: 29.73 | C9: 44.86
B10: KM Hebdo | G10: Hotel (semaine)
B11: =1136+2350 -> 3486 | G11: 0
A12: Autoroute / jour : | B12: 78 | F12: SPL | G12: CM
E13: €/ Hebdo | F13: 1000 | G13: 1100
A14: Détails CA
A15: Référence prestations | B15: Fréquence | C15: Montant unitaire | D15: Quantité | E15: Total Hors IGO | F15: Indexation | G15: Montant Total
A16: VIAPOSTE : 163-15 | B16: Lundi au Vendredi | C16: 199.09 | D16: 6 | E16: =C16*D16 -> 1194.54 | F16: 0.039775 | G16: =(E16*F16)+E16 -> 1242.0528
A17: VIAPOSTE : 168-3 | B17: Lundi au Vendredi | C17: 119.79 | D17: 6 | E17: =C17*D17 -> 718.74 | F17: 0.04773 | G17: =(E17*F17)+E17 -> 753.04546
A18: CHRONOPOST : DYSON | B18: Lundi au Vendredi | C18: 335 | D18: 5 | E18: =C18*D18 -> 1675 | F18: =6.64*5 -> 33.2 | G18: =F18+E18 -> 1708.2 | I18: indexation Go , Roule au Gaz
A19: VIAPOSTE : 163-22 | B19: Lundi au Vendredi | C19: 224.26 | D19: 5 | E19: =C19*D19 -> 1121.3 | F19: 0.039775 | G19: =(E19*F19)+E19 -> 1165.8997
A20: WE : Colissimo LIN164S7776AS | B20: Samedi | C20: 2.3949 | D20: 180 | E20: =C20*D20 -> 431.082 | F20: 0 | G20: =F20+E20 -> 431.082
E21: =C21*D21 -> 0 | G21: =(E21*F21)+E21 -> 0
E22: =C22*D22 -> 0 | G22: =(E22*F22)+E22 -> 0
E23: =C23*D23 -> 0 | G23: =(E23*F23)+E23 -> 0
A25: SPL14 | B25: CA DE LA LIGNE | F25: =SUM(G16:G23) -> 5300.28
A26: SOMMAIRE
A28: Coûts de la Ligne
B29: Type | C29: unité | D29: Cout Semaine
A30: Moteur (1) | B30: Tracteur GNC | C30: =IFERROR(VLOOKUP(B30,Liste!C1:D5,2,FALSE),"") -> 2500 | D30: =IFERROR(C30/4.33,0) -> 577.36721
A31: Semi (1) | B31: SR Classique | C31: =IFERROR(VLOOKUP(B31,Liste!$C$7:$D$15,2,FALSE),"") -> 1000 | D31: =IFERROR(C31/4.33,0) -> 230.94688
A32: Semi (2) | B32: AUCUNE | C32: =IFERROR(VLOOKUP(B32,Liste!$C$7:$D$15,2,FALSE),"") | D32: =IFERROR(C32/4.33,0) -> 0
A33: Semi (3) | B33: AUCUNE | C33: =IFERROR(VLOOKUP(B33,Liste!$C$7:$D$15,2,FALSE),"") | D33: =IFERROR(C33/4.33,0) -> 0
A34: Semi (4) | B34: AUCUNE | C34: =IFERROR(VLOOKUP(B34,Liste!$C$7:$D$15,2,FALSE),"") | D34: =IFERROR(C34/4.33,0) -> 0
A35: Carburant | B35: GO | C35: 0 | D35: =(B11*D5/100)*C35 -> 0
A36: Carburant | B36: GNC | C36: 1.365 | D36: =(D5*B11/100)*C36 -> 1307.6056
A37: AD Blue | C37: 0 | D37: =(D6*B11)*C37 -> 0
A38: Fuel | C38: 1.1225
A39: Casse / Pneumatique / Lavage ( hors entretien) | C39: 0.04 | D39: =C39*B11 -> 139.44
A40: Autoroute | B40: =B12 -> 78 | C40: 5 | D40: =(C40*B40)+42 -> 432 | E40: +42 le samedi
A41: Salaires | B41: SPL | C41: 2 | D41: =880.93+874.06 -> 1754.99
A42: Frais Hotel | D42: =G11 -> 0
A43: Tirpalette | B43: NON | C43: =IF(B43=Liste!A24,Liste!B18,0) -> 0 | D43: =C43/4.33 -> 0
A44: Sous-Traitance | C44: 0 | D44: 0
C46: TOTAL COUT | D46: =SUM(D30:D44) -> 4442.3497
C47: Marge Exploitation | D47: =F25-D46 -> 857.93034
C49: % Marge | D49: =D47/F25 -> 0.1618651

Sheet SPL16
A1: FICHE DE RENTABILITE
A3: DONNEES EXPLOITATION
B4: Immatriculation | D4: Conso au 100 (Moyenne) | F4: Semaine | G4: S16
A5: Tracteur (s) | B5: HA-724-QR | D5: 31.6
A6: Semi (s) | B6: 1 Classique | C6: 1 Classique | D6: 0.019
A7: Conducteurs | B7: HAMID | C7: BORGES
A8: AMPLITUDE Hebdo | B8: 47.36 | C8: 59.36
A9: TDS Hebdo | B9: 37.75 | C9: 48.53
B10: KM Hebdo | G10: Hotel (semaine)
B11: =832+988 -> 1820 | G11: 0
A12: Autoroute / jour : | B12: 0 | F12: SPL | G12: CM
E13: €/ Hebdo | F13: 1000 | G13: 1100
A14: Détails CA
A15: Référence prestations | B15: Fréquence | C15: Montant unitaire | D15: Quantité | E15: Total Hors IGO | F15: Indexation | G15: Montant Total
A16: VIAPOSTE : 164-23Z | B16: Lundi au Vendredi | C16: 186.69 | D16: 5 | E16: =C16*D16 -> 933.45 | F16: 0.039775 | G16: =(E16*F16)+E16 -> 970.57797
A17: VIAPOSTE : 164-5 | B17: Lundi au Vendredi | C17: 192.63 | D17: 5 | E17: =C17*D17 -> 963.15 | F17: 0.039775 | G17: =(E17*F17)+E17 -> 1001.4593
A18: VIAPOSTE : 164-10 | B18: Lundi au Vendredi | C18: 100 | D18: 6 | E18: =C18*D18 -> 600 | F18: 0.039775 | G18: =(E18*F18)+E18 -> 623.865
A19: VIAPOSTE : 164-16 | B19: Lundi au Vendredi | C19: 176.79 | D19: 6 | E19: =C19*D19 -> 1060.74 | F19: 0.039775 | G19: =(E19*F19)+E19 -> 1102.9309
A20: VIAPOSTE : 164-11 | B20: Lundi au Vendredi | C20: 97.32 | D20: 6 | E20: =C20*D20 -> 583.92 | F20: 0.039775 | G20: =(E20*F20)+E20 -> 607.14542
A21: DHL : 9894C | B21: Mardi au Vendredi | C21: 190 | D21: 4 | E21: =C21*D21 -> 760 | F21: -0.0301 | G21: =(E21*F21)+E21 -> 737.124 | I21: indexation GO avec véhicule Gaz
A22: WE : FEDEX GB4 | B22: Samedi | C22: 137 | D22: 1 | E22: =C22*D22 -> 137 | F22: 0 | G22: =(E22*F22)+E22 -> 137
E23: =C23*D23 -> 0
A25: SPL16 | B25: CA DE LA LIGNE | F25: =SUM(G16:G23) -> 5180.1026
A26: SOMMAIRE
A28: Coûts de la Ligne
B29: Type | C29: unité | D29: Cout Semaine
A30: Moteur (1) | B30: Tracteur GNC | C30: =IFERROR(VLOOKUP(B30,Liste!C1:D5,2,FALSE),"") -> 2500 | D30: =IFERROR(C30/4.33,0) -> 577.36721
A31: Semi (1) | B31: SR Classique | C31: =IFERROR(VLOOKUP(B31,Liste!$C$7:$D$15,2,FALSE),"") -> 1000 | D31: =IFERROR(C31/4.33,0) -> 230.94688
A32: Semi (2) | B32: SR Classique | C32: =IFERROR(VLOOKUP(B32,Liste!$C$7:$D$15,2,FALSE),"") -> 1000 | D32: =IFERROR(C32/4.33,0) -> 230.94688
A33: Semi (3) | B33: AUCUNE | C33: =IFERROR(VLOOKUP(B33,Liste!$C$7:$D$15,2,FALSE),"") | D33: =IFERROR(C33/4.33,0) -> 0
A34: Semi (4) | B34: AUCUNE | C34: =IFERROR(VLOOKUP(B34,Liste!$C$7:$D$15,2,FALSE),"") | D34: =IFERROR(C34/4.33,0) -> 0
A35: Carburant | B35: GO | C35: 0 | D35: =(B11*D5/100)*C35 -> 0
A36: Carburant | B36: GNC | C36: 1.365 | D36: =(D5*B11/100)*C36 -> 785.0388
A37: AD Blue | C37: 0 | D37: =(D6*B11)*C37 -> 0
A38: Fuel | C38: 1.1225
A39: Casse / Pneumatique / Lavage ( hors entretien) | C39: 0.04 | D39: =C39*B11 -> 72.8
A40: Autoroute | B40: =B12 -> 0 | C40: 5 | D40: =(C40*B40) -> 0
A41: Salaires | B41: SPL | C41: 2 | D41: =1106.38+1137.37 -> 2243.75
A42: Frais Hotel | D42: =G11 -> 0
A43: Tirpalette | B43: NON | C43: =IF(B43=Liste!A24,Liste!B18,0) -> 0 | D43: =C43/4.33 -> 0
A44: Sous-Traitance | C44: 0 | D44: 0
C46: TOTAL COUT | D46: =SUM(D30:D44) -> 4140.8498
C47: Marge Exploitation | D47: =F25-D46 -> 1039.2528
C49: % Marge | D49: =D47/F25 -> 0.20062399

Sheet SPL17
A1: FICHE DE RENTABILITE
A3: DONNEES EXPLOITATION
B4: Immatriculation | D4: Conso au 100 (Moyenne) | F4: Semaine | G4: S16
A5: Tracteur (s) | B5: GG-728-EB | D5: 28.95
A6: Semi (s) | B6: 1 Classique | C6: 1 Classique | D6: 0.019
A7: Conducteurs | B7: PECCATUS | C7: Moreira Tavares
A8: AMPLITUDE Hebdo | B8: 47.8 | C8: 55.76
A9: TDS Hebdo | B9: 36.67 | C9: 51.07
B10: KM Hebdo | G10: Hotel (semaine)
B11: =1234+1262 -> 2496 | G11: 0
A12: Autoroute / jour : | B12: 0 | F12: SPL | G12: CM
E13: €/ Hebdo | F13: 1000 | G13: 1100
A14: Détails CA
A15: Référence prestations | B15: Fréquence | C15: Montant unitaire | D15: Quantité | E15: Total Hors IGO | F15: Indexation | G15: Montant Total
A16: VIAPOSTE : 163-18 | B16: Lundi au Vendredi | C16: 198.16 | D16: 6 | E16: =C16*D16 -> 1188.96 | F16: 0.039775 | G16: =(E16*F16)+E16 -> 1236.2509
A17: VIAPOSTE : 163-19 | B17: Lundi au Vendredi | C17: 198.76 | D17: 6 | E17: =C17*D17 -> 1192.56 | F17: 0.039775 | G17: =(E17*F17)+E17 -> 1239.9941
A18: VIAPOSTE : 163-8 | B18: Lundi au Vendredi | C18: 199.63 | D18: 5 | E18: =C18*D18 -> 998.15 | F18: 0.039775 | G18: =(E18*F18)+E18 -> 1037.8514
A19: VIAPOSTE : 163-12 | B19: Lundi au Vendredi | C19: 158.07 | D19: 5 | E19: =C19*D19 -> 790.35 | F19: 0.039775 | G19: =(E19*F19)+E19 -> 821.78617
A20: VIAPOSTE : 163-2 | B20: Lundi au Vendredi | C20: 221.26 | D20: 5 | E20: =C20*D20 -> 1106.3 | F20: 0.039775 | G20: =(E20*F20)+E20 -> 1150.3031
A21: MOREIRA sur 5 jours | E21: =C21*D21 -> 0 | G21: =(E21*F21)+E21 -> 0
E22: =C22*D22 -> 0 | G22: =(E22*F22)+E22 -> 0
A24: SPL17 | B24: CA DE LA LIGNE | F24: =SUM(G16:G22) -> 5486.1856
A25: SOMMAIRE
A27: Coûts de la Ligne
B28: Type | C28: unité | D28: Cout Semaine
A29: Moteur (1) | B29: Tracteur GNC | C29: =IFERROR(VLOOKUP(B29,Liste!C1:D5,2,FALSE),"") -> 2500 | D29: =IFERROR(C29/4.33,0) -> 577.36721
A30: Semi (1) | B30: SR Classique | C30: =IFERROR(VLOOKUP(B30,Liste!$C$7:$D$15,2,FALSE),"") -> 1000 | D30: =IFERROR(C30/4.33,0) -> 230.94688
A31: Semi (2) | B31: SR Classique | C31: =IFERROR(VLOOKUP(B31,Liste!$C$7:$D$15,2,FALSE),"") -> 1000 | D31: =IFERROR(C31/4.33,0) -> 230.94688
A32: Semi (3) | B32: AUCUNE | C32: =IFERROR(VLOOKUP(B32,Liste!$C$7:$D$15,2,FALSE),"") | D32: =IFERROR(C32/4.33,0) -> 0
A33: Semi (4) | B33: AUCUNE | C33: =IFERROR(VLOOKUP(B33,Liste!$C$7:$D$15,2,FALSE),"") | D33: =IFERROR(C33/4.33,0) -> 0
A34: Carburant | B34: GO | C34: 0 | D34: =(B11*D5/100)*C34 -> 0
A35: Carburant | B35: GNC | C35: 1.365 | D35: =(D5*B11/100)*C35 -> 986.33808
A36: AD Blue | C36: 0 | D36: =(D6*B11)*C36 -> 0
A37: Fuel | C37: 1.1225
A38: Casse / Pneumatique / Lavage ( hors entretien) | C38: 0.04 | D38: =C38*B11 -> 99.84
A39: Autoroute | B39: =B12 -> 0 | C39: 5 | D39: =(C39*B39) -> 0
A40: Salaires | B40: SPL | C40: 2 | D40: =878.62+535.54 -> 1414.16
A41: Frais Hotel | D41: =G11 -> 0
A42: Tirpalette | B42: NON | C42: =IF(B42=Liste!A24,Liste!B18,0) -> 0 | D42: =C42/4.33 -> 0
A43: Sous-Traitance | C43: 0 | D43: 0
C45: TOTAL COUT | D45: =SUM(D29:D43) -> 3539.599
C46: Marge Exploitation | D46: =F24-D45 -> 1946.5866
C48: % Marge | D48: =D46/F24 -> 0.35481603

Sheet SPL18
A1: FICHE DE RENTABILITE
A3: DONNEES EXPLOITATION
B4: Immatriculation | D4: Conso au 100 (Moyenne) | F4: Semaine | G4: S16
A5: Tracteur (s) | B5: GZ-279-YC | D5: 32.91
A6: Semi (s) | B6: 1 Classique | C6: 1 aeriene | D6: 0.019
A7: Conducteurs | B7: ROMUALD | C7: KILIAN
A8: AMPLITUDE Hebdo | B8: 73.35 | C8: 56.17
A9: TDS Hebdo | B9: 52.38 | C9: 47.04
B10: KM Hebdo | G10: Hotel (semaine)
B11: =1552+1261 -> 2813 | G11: 0
A12: Autoroute / jour : | B12: 11.66 | F12: SPL | G12: CM
E13: €/ Hebdo | F13: 1000 | G13: 1100
A14: Détails CA
A15: Référence prestations | B15: Fréquence | C15: Montant unitaire | D15: Quantité | E15: Total Hors IGO | F15: Indexation | G15: Montant Total
A16: DHL : 9877A | B16: Lundi au Vendredi | C16: 170 | D16: 5 | E16: =C16*D16 -> 850 | F16: -0.0301 | G16: =(E16*F16)+E16 -> 824.415
A17: VIAPOSTE : 170-8 | B17: Lundi au Vendredi | C17: 122.35 | D17: 6 | E17: =C17*D17 -> 734.1 | F17: 0.04271 | G17: =(E17*F17)+E17 -> 765.45341
A18: VIAPOSTE : 170-9 | B18: Lundi au Vendredi | C18: 122.35 | D18: 6 | E18: =C18*D18 -> 734.1 | F18: 0.04271 | G18: =(E18*F18)+E18 -> 765.45341
A19: VIAPOSTE : 170-12 | B19: Lundi au Vendredi | C19: 131.61 | D19: 6 | E19: =C19*D19 -> 789.66 | F19: 0.04271 | G19: =(E19*F19)+E19 -> 823.38638
A20: VIAPOSTE : 170-13 | B20: Lundi au Vendredi | C20: 115.38 | D20: 5 | E20: =C20*D20 -> 576.9 | F20: 0.04271 | G20: =(E20*F20)+E20 -> 601.5394
A21: UPS : Ramasse AMAZON | B21: Lundi au Vendredi | C21: 197.5 | D21: 5 | E21: =C21*D21 -> 987.5 | F21: 0.0409 | G21: =(E21*F21)+E21 -> 1027.8888
A22: VIAPOSTE : 170-14 | B22: Lundi au Vendredi | C22: 96.85 | D22: 5 | E22: =C22*D22 -> 484.25 | F22: 0.04271 | G22: =(E22*F22)+E22 -> 504.93232
A23: VIAPOSTE : 164-1 | B23: Lundi au Vendredi | C23: 134.94 | D23: 5 | E23: =C23*D23 -> 674.7 | F23: 0.039775 | G23: =(E23*F23)+E23 -> 701.53619
A24: WE : VIAPOSTE : 168-5Z - 164-9 - 163-5 | B24: Samedi | C24: =127.84+102.8+148.98 -> 379.62 | D24: 1 | E24: =C24*D24 -> 379.62 | F24: 0.039775 | G24: =(E24*F24)+E24 -> 394.71939
A25: SPL18 | B25: CA DE LA LIGNE | F25: =SUM(G16:G24) -> 6409.3242
A26: SOMMAIRE
A28: Coûts de la Ligne
B29: Type | C29: unité | D29: Cout Semaine
A30: Moteur (1) | B30: Tracteur GNC | C30: =IFERROR(VLOOKUP(B30,Liste!C1:D5,2,FALSE),"") -> 2500 | D30: =IFERROR(C30/4.33,0) -> 577.36721
A31: Semi (1) | B31: SR Classique | C31: =IFERROR(VLOOKUP(B31,Liste!$C$7:$D$15,2,FALSE),"") -> 1000 | D31: =IFERROR(C31/4.33,0) -> 230.94688
A32: Semi (2) | B32: Aérienne Classique | C32: =IFERROR(VLOOKUP(B32,Liste!$C$7:$D$15,2,FALSE),"") -> 1200 | D32: =IFERROR(C32/4.33,0) -> 277.13626
A33: Semi (3) | B33: AUCUNE | C33: =IFERROR(VLOOKUP(B33,Liste!$C$7:$D$15,2,FALSE),"") | D33: =IFERROR(C33/4.33,0) -> 0
A34: Semi (4) | B34: AUCUNE | C34: =IFERROR(VLOOKUP(B34,Liste!$C$7:$D$15,2,FALSE),"") | D34: =IFERROR(C34/4.33,0) -> 0
A35: Carburant | B35: GO | C35: 0 | D35: =(B11*D5/100)*C35 -> 0
A36: Carburant | B36: GNC | C36: 1.365 | D36: =(D5*B11/100)*C36 -> 1263.6601
A37: AD Blue | C37: 0 | D37: =(D6*B11)*C37 -> 0
A38: Fuel | C38: 1.1225
A39: Casse / Pneumatique / Lavage ( hors entretien) | C39: 0.04 | D39: =C39*B11 -> 112.52
A40: Autoroute | B40: =B12 -> 11.66 | C40: 5 | D40: =(C40*B40) -> 58.3
A41: Salaires | B41: SPL | C41: 2 | D41: =886.96+975.82 -> 1862.78
A42: Frais Hotel | D42: =G11 -> 0
A43: Tirpalette | B43: NON | C43: =IF(B43=Liste!A24,Liste!B18,0) -> 0 | D43: =C43/4.33 -> 0
A44: Sous-Traitance | C44: 0 | D44: 0
C46: TOTAL COUT | D46: =SUM(D30:D44) -> 4382.7104
C47: Marge Exploitation | D47: =F25-D46 -> 2026.6138
C49: % Marge | D49: =D47/F25 -> 0.31619774

Sheet SPL20
A1: FICHE DE RENTABILITE
A3: DONNEES EXPLOITATION
B4: Immatriculation | D4: Conso au 100 (Moyenne) | F4: Semaine | G4: S16
A5: Tracteur (s) | B5: GH-635-LG | D5: 30.6
A6: Semi (s) | B6: 1 Classique | C6: 1 Classique | D6: 0.019
A7: Conducteurs | B7: MBEKA R. | C7: QUINOL
A8: AMPLITUDE Hebdo | B8: 71.23 | C8: 58.02
A9: TDS Hebdo | B9: 64.41 | C9: 49.18
B10: KM Hebdo | G10: Hotel (semaine)
B11: =1410+1260 -> 2670 | G11: 0
A12: Autoroute / jour : | B12: 13.56 | F12: SPL | G12: CM
E13: €/ Hebdo | F13: 1000 | G13: 1100
A14: Détails CA
A15: Référence prestations | B15: Fréquence | C15: Montant unitaire | D15: Quantité | E15: Total Hors IGO | F15: Indexation | G15: Montant Total
A16: VIAPOSTE : 164-23 | B16: Lundi au Vendredi | C16: 186.69 | D16: 6 | E16: =C16*D16 -> 1120.14 | F16: 0.039775 | G16: =(E16*F16)+E16 -> 1164.6936
A17: VIAPOSTE : 164-25 | B17: Lundi au Vendredi | C17: 160.57 | D17: 6 | E17: =C17*D17 -> 963.42 | F17: 0.039775 | G17: =(E17*F17)+E17 -> 1001.74
A18: VIAPOSTE : 164-25Z | B18: Lundi au Vendredi | C18: 161.12 | D18: 6 | E18: =C18*D18 -> 966.72 | F18: 0.039775 | G18: =(E18*F18)+E18 -> 1005.1713
A19: VIAPOSTE : 164-14 | B19: Lundi au Vendredi | C19: 160.79 | D19: 6 | E19: =C19*D19 -> 964.74 | F19: 0.039775 | G19: =(E19*F19)+E19 -> 1003.1125
A20: VIAPOSTE : 164-22 | B20: Lundi au Vendredi | C20: 210.67 | D20: 6 | E20: =C20*D20 -> 1264.02 | F20: 0.039775 | G20: =(E20*F20)+E20 -> 1314.2964
E21: =C21*D21 -> 0 | G21: =(E21*F21)+E21 -> 0
E22: =C22*D22 -> 0 | G22: =(E22*F22)+E22 -> 0
E23: =C23*D23 -> 0 | G23: =(E23*F23)+E23 -> 0
A24: SPL20 | B24: CA DE LA LIGNE | F24: =SUM(G16:G23) -> 5489.0138
A25: SOMMAIRE
A27: Coûts de la Ligne
B28: Type | C28: unité | D28: Cout Semaine
A29: Moteur (1) | B29: Tracteur GNC | C29: =IFERROR(VLOOKUP(B29,Liste!C1:D5,2,FALSE),"") -> 2500 | D29: =IFERROR(C29/4.33,0) -> 577.36721
A30: Semi (1) | B30: SR Classique | C30: =IFERROR(VLOOKUP(B30,Liste!$C$7:$D$15,2,FALSE),"") -> 1000 | D30: =IFERROR(C30/4.33,0) -> 230.94688
A31: Semi (2) | B31: SR Classique | C31: =IFERROR(VLOOKUP(B31,Liste!$C$7:$D$15,2,FALSE),"") -> 1000 | D31: =IFERROR(C31/4.33,0) -> 230.94688
A32: Semi (3) | B32: AUCUNE | C32: =IFERROR(VLOOKUP(B32,Liste!$C$7:$D$15,2,FALSE),"") | D32: =IFERROR(C32/4.33,0) -> 0
A33: Semi (4) | B33: AUCUNE | C33: =IFERROR(VLOOKUP(B33,Liste!$C$7:$D$15,2,FALSE),"") | D33: =IFERROR(C33/4.33,0) -> 0
A34: Carburant | B34: GO | C34: 0 | D34: =(B11*D5/100)*C34 -> 0
A35: Carburant | B35: GNC | C35: 1.365 | D35: =(D5*B11/100)*C35 -> 1115.2323
A36: AD Blue | C36: 0 | D36: =(D6*B11)*C36 -> 0
A37: Fuel | C37: 1.1225
A38: Casse / Pneumatique / Lavage ( hors entretien) | C38: 0.04 | D38: =C38*B11 -> 106.8
A39: Autoroute | B39: =B12 -> 13.56 | C39: 5 | D39: =(C39*B39) -> 67.8
A40: Salaires | B40: SPL | C40: 2 | D40: =842.61+921.93 -> 1764.54
A41: Frais Hotel | D41: =G11 -> 0
A42: Tirpalette | B42: NON | C42: =IF(B42=Liste!A24,Liste!B18,0) -> 0 | D42: =C42/4.33 -> 0
A43: Sous-Traitance | C43: 0 | D43: 0
C45: TOTAL COUT | D45: =SUM(D29:D43) -> 4093.6333
C46: Marge Exploitation | D46: =F24-D45 -> 1395.3805
C48: % Marge | D48: =D46/F24 -> 0.25421334

Sheet SPL23
A1: FICHE DE RENTABILITE
A3: DONNEES EXPLOITATION
B4: Immatriculation | D4: Conso au 100 (Moyenne) | F4: Semaine | G4: S16
A5: Tracteur (s) | B5: EJ-197-GQ | D5: 29.13
A6: Semi (s) | B6: 1 Classique | C6: 2 classique débord | D6: 0.019
A7: Conducteurs | B7: TROUDI | C7: DIOP ASSANE
A8: AMPLITUDE Hebdo | B8: 51.09 | C8: 65.15
A9: TDS Hebdo | B9: 41.79 | C9: 40.95
B10: KM Hebdo | G10: Hotel (semaine)
A11: (TROUDI tourne sur 5 jours) | B11: =1972+1422 -> 3394 | G11: 0
A12: Autoroute / jour : | B12: 0 | F12: SPL | G12: CM
E13: €/ Hebdo | F13: 1000 | G13: 1100
A14: Détails CA
A15: Référence prestations | B15: Fréquence | C15: Montant unitaire | D15: Quantité | E15: Total Hors IGO | F15: Indexation | G15: Montant Total
A16: FEDEX : FRT03413 - FRT03411 | B16: Lundi au Vendredi | C16: 385 | D16: 5 | E16: =C16*D16 -> 1925 | F16: -0.0091 | G16: =(E16*F16)+E16 -> 1907.4825
A17: FEDEX : Ploisy (R488) | B17: Lundi au Vendredi | C17: 215 | D17: 5 | E17: =C17*D17 -> 1075 | G17: =(E17*F17)+E17 -> 1075
A18: CHRONOPOST : 23R68 | B18: Lundi au Vendredi | C18: 220 | D18: 5 | E18: =C18*D18 -> 1100 | F18: =-16.069*5 -> -80.345 | G18: =F18+E18 -> 1019.655
A19: UPS : Amazon Savigny | B19: Lundi au Vendredi | C19: 190 | D19: 5 | E19: =C19*D19 -> 950 | F19: -0.0123 | G19: =(E19*F19)+E19 -> 938.315
A20: CHRONOPOST : Cdiscount - Chiilly | B20: Lundi au Vendredi | C20: 165 | D20: 5 | E20: =C20*D20 -> 825 | F20: =2.27*5 -> 11.35 | G20: =F20+E20 -> 836.35
A21: UPS : Ramasse Evry - Goussainville | B21: Lundi au Vendredi | C21: 197.5 | D21: 5 | E21: =C21*D21 -> 987.5 | F21: 0.0409 | G21: =(E21*F21)+E21 -> 1027.8888
A22: WE : Viaposte 164-15/15Z | B22: SAMEDI | C22: 282.86 | D22: 1 | E22: =C22*D22 -> 282.86 | F22: 0.039775 | G22: =(E22*F22)+E22 -> 294.11076
A23: WE : CHRONOPOST : 39139 | B23: SAMEDI | C23: 120 | D23: 1 | E23: =C23*D23 -> 120 | F23: =50*0.1412 -> 7.06 | G23: =F23+E23 -> 127.06
A24: SPL23 | B24: CA DE LA LIGNE | F24: =SUM(G16:G23) -> 7225.862
A25: SOMMAIRE
A27: Coûts de la Ligne
B28: Type | C28: unité | D28: Cout Semaine
A29: Moteur (1) | B29: Tracteur GO | C29: =IFERROR(VLOOKUP(B29,Liste!C1:D5,2,FALSE),"") -> 2300 | D29: =IFERROR(C29/4.33,0) -> 531.17783
A30: Semi (1) | B30: SR Classique | C30: =IFERROR(VLOOKUP(B30,Liste!$C$7:$D$15,2,FALSE),"") -> 1000 | D30: =IFERROR(C30/4.33,0) -> 230.94688
A31: Semi (2) | B31: SR Classique | C31: =IFERROR(VLOOKUP(B31,Liste!$C$7:$D$15,2,FALSE),"") -> 1000 | D31: =IFERROR(C31/4.33,0) -> 230.94688
A32: Semi (3) | B32: SR Classique | C32: =IFERROR(VLOOKUP(B32,Liste!$C$7:$D$15,2,FALSE),"") -> 1000 | D32: =IFERROR(C32/4.33,0) -> 230.94688
A33: Semi (4) | B33: AUCUNE | C33: =IFERROR(VLOOKUP(B33,Liste!$C$7:$D$15,2,FALSE),"") | D33: =IFERROR(C33/4.33,0) -> 0
A34: Carburant | B34: GO | C34: 1.3554 | D34: =(B11*D5/100)*C34 -> 1340.0463
A35: Carburant | B35: GNC | C35: 0 | D35: =(D5*B11/100)*C35 -> 0
A36: AD Blue | C36: 0.4309 | D36: =(D6*B11)*C36 -> 27.787017
A37: Fuel | C37: 1.1225
A38: Casse / Pneumatique / Lavage ( hors entretien) | C38: 0.04 | D38: =C38*B11 -> 135.76
A39: Autoroute | B39: =B12 -> 0 | C39: 5 | D39: =(C39*B39) -> 0
A40: Salaires | B40: SPL | C40: 2 | D40: =908.53+871.25 -> 1779.78
A41: Frais Hotel | D41: =G11 -> 0
A42: Tirpalette | B42: NON | C42: =IF(B42=Liste!A24,Liste!B18,0) -> 0 | D42: =C42/4.33 -> 0
A43: Sous-Traitance | C43: 0 | D43: 0
C45: TOTAL COUT | D45: =SUM(D29:D43) -> 4507.3918
C46: Marge Exploitation | D46: =F24-D45 -> 2718.4702
C48: % Marge | D48: =D46/F24 -> 0.37621397

Sheet SPL25
A1: FICHE DE RENTABILITE
A3: DONNEES EXPLOITATION
B4: Immatriculation | D4: Conso au 100 (Moyenne) | F4: Semaine | G4: S16
A5: Tracteur (s) | B5: FN-483-HD | D5: 22.78
A6: Semi (s) | B6: 1 Classique | D6: 0.019
A7: Conducteurs | B7: CRISAN G.
A8: AMPLITUDE Hebdo | B8: 61.2
A9: TDS Hebdo | B9: 48.19
B10: KM Hebdo | G10: Hotel (semaine)
B11: 2970 | G11: 0
A12: Autoroute / jour : | B12: =59.42+6.42+30.17 -> 96.01 | F12: SPL | G12: CM
E13: €/ Hebdo | F13: 1000 | G13: 1100
A14: Détails CA
A15: Référence prestations | B15: Fréquence | C15: Montant unitaire | D15: Quantité | E15: Total Hors IGO | F15: Indexation | G15: Montant Total
A16: DHL : FRD 4506 | B16: Lundi au Vendredi | C16: 510 | D16: 5 | E16: =C16*D16 -> 2550 | F16: 0 | G16: =(E16*F16)+E16 -> 2550
A17: CHRONOPOST : 29806 | B17: Lundi au Vendredi | C17: 500 | D17: 5 | E17: =C17*D17 -> 2500 | F17: =(225*5)*0.1412 -> 158.85 | G17: =F17+E17 -> 2658.85
E18: =C18*D18 -> 0 | G18: =F18+E18 -> 0
A19: Tourne 5 jours | E19: =C19*D19 -> 0 | G19: =(E19*F19)+E19 -> 0
E20: =C20*D20 -> 0 | G20: =(E20*F20)+E20 -> 0
E21: =C21*D21 -> 0 | G21: =(E21*F21)+E21 -> 0
E22: =C22*D22 -> 0 | G22: =(E22*F22)+E22 -> 0
E23: =C23*D23 -> 0 | G23: =(E23*F23)+E23 -> 0
A24: SPL25 | B24: CA DE LA LIGNE | F24: =SUM(G16:G23) -> 5208.85
A25: SOMMAIRE
A27: Coûts de la Ligne
B28: Type | C28: unité | D28: Cout Semaine
A29: Moteur (1) | B29: Tracteur GO | C29: =IFERROR(VLOOKUP(B29,Liste!C1:D5,2,FALSE),"") -> 2300 | D29: =IFERROR(C29/4.33,0) -> 531.17783
A30: Semi (1) | B30: SR Classique | C30: =IFERROR(VLOOKUP(B30,Liste!$C$7:$D$15,2,FALSE),"") -> 1000 | D30: =IFERROR(C30/4.33,0) -> 230.94688
A31: Semi (2) | B31: AUCUNE | C31: =IFERROR(VLOOKUP(B31,Liste!$C$7:$D$15,2,FALSE),"") | D31: =IFERROR(C31/4.33,0) -> 0
A32: Semi (3) | B32: AUCUNE | C32: =IFERROR(VLOOKUP(B32,Liste!$C$7:$D$15,2,FALSE),"") | D32: =IFERROR(C32/4.33,0) -> 0
A33: Semi (4) | B33: AUCUNE | C33: =IFERROR(VLOOKUP(B33,Liste!$C$7:$D$15,2,FALSE),"") | D33: =IFERROR(C33/4.33,0) -> 0
A34: Carburant | B34: GO | C34: 1.3554 | D34: =(B11*D5/100)*C34 -> 917.01756
A35: Carburant | B35: GNC | C35: 0 | D35: =(D5*B11/100)*C35 -> 0
A36: AD Blue | C36: 0.4309 | D36: =(D6*B11)*C36 -> 24.315687
A37: Fuel | C37: 1.1225
A38: Casse / Pneumatique / Lavage ( hors entretien) | C38: 0.04 | D38: =C38*B11 -> 118.8
A39: Autoroute | B39: =B12 -> 96.01 | C39: 5 | D39: =(C39*B39) -> 480.05
A40: Salaires | B40: SPL | C40: 1 | D40: 1417.87
A41: Frais Hotel | D41: =G11 -> 0
A42: Tirpalette | B42: NON | C42: =IF(B42=Liste!A24,Liste!B18,0) -> 0 | D42: =C42/4.33 -> 0
A43: Sous-Traitance | C43: 0 | D43: 0
C45: TOTAL COUT | D45: =SUM(D29:D43) -> 3720.178
C46: Marge Exploitation | D46: =F24-D45 -> 1488.672
C48: % Marge | D48: =D46/F24 -> 0.28579668

Sheet SPL26
A1: FICHE DE RENTABILITE
A3: DONNEES EXPLOITATION
B4: Immatriculation | D4: Conso au 100 (Moyenne) | F4: Semaine | G4: S16
A5: Tracteur (s) | B5: GL317JR | D5: 28.76
A6: Semi (s) | B6: 1 Classique | C6: 1 aerienne | D6: 0.019
A7: Conducteurs | B7: LEKRICHI | C7: AZZIZ CHEMLAL
A8: AMPLITUDE Hebdo | B8: 58.2 | C8: 50.16
A9: TDS Hebdo | B9: 35.1 | C9: 27.87
B10: KM Hebdo | G10: Hotel (semaine)
B11: =1275+1065 -> 2340 | G11: 0
A12: Autoroute / jour : | B12: 0 | F12: SPL | G12: CM
E13: €/ Hebdo | F13: 1000 | G13: 1100
A14: Détails CA
A15: Référence prestations | B15: Fréquence | C15: Montant unitaire | D15: Quantité | E15: Total Hors IGO | F15: Indexation | G15: Montant Total
A16: FEDEX : AIDF40 | B16: Mardi au Samedi | C16: 75 | D16: 5 | E16: =C16*D16 -> 375 | F16: -0.0019 | G16: =(E16*F16)+E16 -> 374.2875
A17: CEVA : Kiabi St Brice | B17: Lundi au Vendredi | C17: 405 | D17: 6 | E17: =C17*D17 -> 2430 | F17: 0 | G17: =F17+E17 -> 2430
A18: CHRONOPOST : Ramasse STACI 95 (40U04) | B18: Lundi au Vendredi | C18: 245 | D18: 5 | E18: =C18*D18 -> 1225 | F18: 0 | G18: =F18+E18 -> 1225
A19: DHL : FR6098C | B19: Lundi au Vendredi | C19: 190 | D19: 5 | E19: =C19*D19 -> 950 | F19: -0.0301 | G19: =(E19*F19)+E19 -> 921.405
A20: WE : Parc DHL | B20: Samedi | C20: 340 | D20: 1 | E20: =C20*D20 -> 340 | F20: 0 | G20: =(E20*F20)+E20 -> 340
A21: WE : DHL : FR9859A | B21: Samedi | C21: 300 | D21: 1 | E21: =C21*D21 -> 300 | F21: -0.0301 | G21: =(E21*F21)+E21 -> 290.97
A22: WE : Fedex Sup Sézane | B22: Samedi | C22: 265 | D22: 1 | E22: =C22*D22 -> 265 | F22: 0 | G22: =(E22*F22)+E22 -> 265
A23: WE : DHL EUROAD : CDG1753 | B23: Samedi | C23: 240 | D23: 1 | E23: =C23*D23 -> 240 | F23: 0.0582 | G23: =(E23*F23)+E23 -> 253.968
A24: SPL26 | B24: CA DE LA LIGNE | F24: =SUM(G16:G23) -> 6100.6305
A25: SOMMAIRE
A27: Coûts de la Ligne
B28: Type | C28: unité | D28: Cout Semaine
A29: Moteur (1) | B29: Tracteur GNC | C29: =IFERROR(VLOOKUP(B29,Liste!C1:D5,2,FALSE),"") -> 2500 | D29: =IFERROR(C29/4.33,0) -> 577.36721
A30: Semi (1) | B30: SR Classique | C30: =IFERROR(VLOOKUP(B30,Liste!$C$7:$D$15,2,FALSE),"") -> 1000 | D30: =IFERROR(C30/4.33,0) -> 230.94688
A31: Semi (2) | B31: Aérienne Classique | C31: =IFERROR(VLOOKUP(B31,Liste!$C$7:$D$15,2,FALSE),"") -> 1200 | D31: =IFERROR(C31/4.33,0) -> 277.13626
A32: Semi (3) | B32: AUCUNE | C32: =IFERROR(VLOOKUP(B32,Liste!$C$7:$D$15,2,FALSE),"") | D32: =IFERROR(C32/4.33,0) -> 0
A33: Semi (4) | B33: AUCUNE | C33: =IFERROR(VLOOKUP(B33,Liste!$C$7:$D$15,2,FALSE),"") | D33: =IFERROR(C33/4.33,0) -> 0
A34: Carburant | B34: GO | C34: 0 | D34: =(B11*D5/100)*C34 -> 0
A35: Carburant | B35: GNC | C35: 1.3554 | D35: =(D5*B11/100)*C35 -> 912.16251
A36: AD Blue | C36: 0 | D36: =(D6*B11)*C36 -> 0
A37: Fuel | C37: 1.1225
A38: Casse / Pneumatique / Lavage ( hors entretien) | C38: 0.04 | D38: =C38*B11 -> 93.6
A39: Autoroute | B39: =B12 -> 0 | C39: 5 | D39: =(C39*B39) -> 0
A40: Salaires | B40: SPL | C40: 2 | D40: =1154.92+956.78 -> 2111.7
A41: Frais Hotel | D41: =G11 -> 0
A42: Tirpalette | B42: NON | C42: =IF(B42=Liste!A24,Liste!B18,0) -> 0 | D42: =C42/4.33 -> 0
A43: Sous-Traitance | C43: 0 | D43: 0
C45: TOTAL COUT | D45: =SUM(D29:D43) -> 4202.9129
C46: Marge Exploitation | D46: =F24-D45 -> 1897.7176
C48: % Marge | D48: =D46/F24 -> 0.3110691

Sheet SPL27
A1: FICHE DE RENTABILITE
A3: DONNEES EXPLOITATION
B4: Immatriculation | D4: Conso au 100 (Moyenne) | F4: Semaine | G4: S16
A5: Tracteur (s) | B5: GD252JX | D5: 27.41
A6: Semi (s) | B6: 1 Classique | C6: 1 Classique | D6: 0.019
A7: Conducteurs | B7: AGOUA | C7: SINGH
A8: AMPLITUDE Hebdo | B8: 56.28 | C8: 58.06
A9: TDS Hebdo | B9: 38.85 | C9: 39.45
B10: KM Hebdo | G10: Hotel (semaine)
B11: =1741+1459 -> 3200 | G11: 0
A12: Autoroute / jour : | B12: =12.25*2 -> 24.5 | F12: SPL | G12: CM
E13: €/ Hebdo | F13: 1000 | G13: 1100
A14: Détails CA
A15: Référence prestations | B15: Fréquence | C15: Montant unitaire | D15: Quantité | E15: Total Hors IGO | F15: Indexation | G15: Montant Total
A16: VIAPOSTE : 168-4 | B16: Lundi au Vendredi | C16: 80.65 | D16: 6 | E16: =C16*D16 -> 483.9 | F16: 0.04773 | G16: =(E16*F16)+E16 -> 506.99655
A17: VIAPOSTE : 168-1Z | B17: Lundi au Vendredi | C17: 102.54 | D17: 6 | E17: =C17*D17 -> 615.24 | F17: 0.04773 | G17: =(E17*F17)+E17 -> 644.60541
A18: VIAPOSTE : 168-1 | B18: Lundi au Vendredi | C18: 235.76 | D18: 6 | E18: =C18*D18 -> 1414.56 | F18: 0.04773 | G18: =(E18*F18)+E18 -> 1482.0769
A19: UPS : Ramasse Evry | B19: Lundi au Vendredi | C19: 197.5 | D19: 6 | E19: =C19*D19 -> 1185 | F19: 0.0409 | G19: =(E19*F19)+E19 -> 1233.4665
A20: CHRONOPOST : Ramasse STACI (40U13) | B20: Lundi au Vendredi | C20: 285 | D20: 5 | E20: =C20*D20 -> 1425 | F20: 0 | G20: =(E20*F20)+E20 -> 1425
E21: =C21*D21 -> 0 | G21: =(E21*F21)+E21 -> 0
A22: WE : VIAPOSTE 170-20 | B22: Samedi | C22: 139.79 | D22: 1 | E22: =C22*D22 -> 139.79 | F22: 0.04271 | G22: =(E22*F22)+E22 -> 145.76043
A23: WE : VIAPOSTE 163-20 | B23: Samedi | C23: 204.26 | D23: 1 | E23: =C23*D23 -> 204.26 | F23: 0.039775 | G23: =(E23*F23)+E23 -> 212.38444
A24: SPL27 | B24: CA DE LA LIGNE | F24: =SUM(G16:G23) -> 5650.2903
A25: SOMMAIRE
A27: Coûts de la Ligne
B28: Type | C28: unité | D28: Cout Semaine
A29: Moteur (1) | B29: Tracteur GNC | C29: =IFERROR(VLOOKUP(B29,Liste!C1:D5,2,FALSE),"") -> 2500 | D29: =IFERROR(C29/4.33,0) -> 577.36721
A30: Semi (1) | B30: SR Classique | C30: =IFERROR(VLOOKUP(B30,Liste!$C$7:$D$15,2,FALSE),"") -> 1000 | D30: =IFERROR(C30/4.33,0) -> 230.94688
A31: Semi (2) | B31: SR Classique | C31: =IFERROR(VLOOKUP(B31,Liste!$C$7:$D$15,2,FALSE),"") -> 1000 | D31: =IFERROR(C31/4.33,0) -> 230.94688
A32: Semi (3) | B32: AUCUNE | C32: =IFERROR(VLOOKUP(B32,Liste!$C$7:$D$15,2,FALSE),"") | D32: =IFERROR(C32/4.33,0) -> 0
A33: Semi (4) | B33: AUCUNE | C33: =IFERROR(VLOOKUP(B33,Liste!$C$7:$D$15,2,FALSE),"") | D33: =IFERROR(C33/4.33,0) -> 0
A34: Carburant | B34: GO | C34: 0 | D34: =(B11*D5/100)*C34 -> 0
A35: Carburant | B35: GNC | C35: 1.365 | D35: =(D5*B11/100)*C35 -> 1197.2688
A36: AD Blue | C36: 0 | D36: =(D6*B11)*C36 -> 0
A37: Fuel | C37: 1.1225
A38: Casse / Pneumatique / Lavage ( hors entretien) | C38: 0.04 | D38: =C38*B11 -> 128
A39: Autoroute | B39: =B12 -> 24.5 | C39: 5 | D39: =(C39*B39) -> 122.5
A40: Salaires | B40: SPL | C40: 2 | D40: =895.32+876.57 -> 1771.89
A41: Frais Hotel | D41: =G11 -> 0
A42: Tirpalette | B42: NON | C42: =IF(B42=Liste!A24,Liste!B18,0) -> 0 | D42: =C42/4.33 -> 0
A43: Sous-Traitance | C43: 0 | D43: 0
C45: TOTAL COUT | D45: =SUM(D29:D43) -> 4258.9198
C46: Marge Exploitation | D46: =F24-D45 -> 1391.3705
C48: % Marge | D48: =D46/F24 -> 0.24624761

Sheet SPL30
A1: FICHE DE RENTABILITE
A3: DONNEES EXPLOITATION
B4: Immatriculation | D4: Conso au 100 (Moyenne) | F4: Semaine | G4: S16
A5: Tracteur (s) | B5: HA-788-QR | D5: 27.44
A6: Semi (s) | B6: 1 Classique | D6: 0.019
A7: Conducteurs | B7: GUEYE
A8: AMPLITUDE Hebdo | B8: 59.04
A9: TDS Hebdo | B9: 53.92
B10: KM Hebdo | G10: Hotel (semaine)
B11: 1628 | G11: 0
A12: Autoroute / jour : | B12: 0 | F12: SPL | G12: CM
E13: €/ Hebdo | F13: 1000 | G13: 1100
A14: Détails CA
A15: Référence prestations | B15: Fréquence | C15: Montant unitaire | D15: Quantité | E15: Total Hors IGO | F15: Indexation | G15: Montant Total
A16: VIAPOSTE : 163-13 | B16: Lundi au Vendredi | C16: 208.26 | D16: 6 | E16: =C16*D16 -> 1249.56 | F16: 0.039775 | G16: =(E16*F16)+E16 -> 1299.2612
A17: VIAPOSTE : 163-9 | B17: Lundi au Vendredi | C17: 268.88 | D17: 6 | E17: =C17*D17 -> 1613.28 | F17: 0.039775 | G17: =(E17*F17)+E17 -> 1677.4482
E18: =C18*D18 -> 0 | G18: =(E18*F18)+E18 -> 0
E19: =C19*D19 -> 0 | G19: =(E19*F19)+E19 -> 0
E20: =C20*D20 -> 0 | G20: =(E20*F20)+E20 -> 0
E21: =C21*D21 -> 0 | G21: =(E21*F21)+E21 -> 0
E22: =C22*D22 -> 0 | G22: =(E22*F22)+E22 -> 0
E23: =C23*D23 -> 0 | G23: =(E23*F23)+E23 -> 0
A24: SPL30 | B24: CA DE LA LIGNE | F24: =SUM(G16:G23) -> 2976.7095
A25: SOMMAIRE
A27: Coûts de la Ligne
B28: Type | C28: unité | D28: Cout Semaine
A29: Moteur (1) | B29: Tracteur GNC | C29: =IFERROR(VLOOKUP(B29,Liste!C1:D5,2,FALSE),"") -> 2500 | D29: =IFERROR(C29/4.33,0) -> 577.36721
A30: Semi (1) | B30: SR Classique | C30: =IFERROR(VLOOKUP(B30,Liste!$C$7:$D$15,2,FALSE),"") -> 1000 | D30: =IFERROR(C30/4.33,0) -> 230.94688
A31: Semi (2) | B31: AUCUNE | C31: =IFERROR(VLOOKUP(B31,Liste!$C$7:$D$15,2,FALSE),"") | D31: =IFERROR(C31/4.33,0) -> 0
A32: Semi (3) | B32: AUCUNE | C32: =IFERROR(VLOOKUP(B32,Liste!$C$7:$D$15,2,FALSE),"") | D32: =IFERROR(C32/4.33,0) -> 0
A33: Semi (4) | B33: AUCUNE | C33: =IFERROR(VLOOKUP(B33,Liste!$C$7:$D$15,2,FALSE),"") | D33: =IFERROR(C33/4.33,0) -> 0
A34: Carburant | B34: GO | C34: 0 | D34: =(B11*D5/100)*C34 -> 0
A35: Carburant | B35: GNC | C35: 1.365 | D35: =(D5*B11/100)*C35 -> 609.77717
A36: AD Blue | C36: 0 | D36: =(D6*B11)*C36 -> 0
A37: Fuel | C37: 1.1225
A38: Casse / Pneumatique / Lavage ( hors entretien) | C38: 0.04 | D38: =C38*B11 -> 65.12
A39: Autoroute | B39: =B12 -> 0 | C39: 5 | D39: =(C39*B39) -> 0
A40: Salaires | B40: SPL | C40: 1 | D40: 909.42
A41: Frais Hotel | D41: =G11 -> 0
A42: Tirpalette | B42: NON | C42: =IF(B42=Liste!A24,Liste!B18,0) -> 0 | D42: =C42/4.33 -> 0
A43: Sous-Traitance | C43: 0 | D43: 0
C45: TOTAL COUT | D45: =SUM(D29:D43) -> 2392.6313
C46: Marge Exploitation | D46: =F24-D45 -> 584.07821
C48: % Marge | D48: =D46/F24 -> 0.19621606

Sheet SPL34
A1: FICHE DE RENTABILITE
A3: DONNEES EXPLOITATION
B4: Immatriculation | D4: Conso au 100 (Moyenne) | F4: Semaine | G4: S15
A5: Tracteur (s) | B5: GH-013-LH | D5: 29.93
A6: Semi (s) | B6: 1 Classique | C6: 1 Classique | D6: 0.019
A7: Conducteurs | B7: BEN SALEM | C7: COADA TOADER
A8: AMPLITUDE Hebdo | B8: 65.37 | C8: 54.04
A9: TDS Hebdo | B9: 55.4 | C9: 31
B10: KM Hebdo | G10: Hotel (semaine)
B11: =1173+1158 -> 2331 | G11: 0
A12: Autoroute / jour : | B12: 0 | F12: SPL | G12: CM
E13: €/ Hebdo | F13: 1000 | G13: 1100
A14: Détails CA
A15: Référence prestations | B15: Fréquence | C15: Montant unitaire | D15: Quantité | E15: Total Hors IGO | F15: Indexation | G15: Montant Total
A16: VIAPOSTE : 164-15 | B16: Lundi au Vendredi | C16: 155.29 | D16: 6 | E16: =C16*D16 -> 931.74 | F16: 0.039775 | G16: =(E16*F16)+E16 -> 968.79996
A17: VIAPOSTE : 164-15Z | B17: Lundi au Vendredi | C17: 127.57 | D17: 6 | E17: =C17*D17 -> 765.42 | F17: 0.039775 | G17: =(E17*F17)+E17 -> 795.86458
A18: VIAPOSTE sup : Liaison D | B18: Lundi au Vendredi | C18: =150+145 -> 295 | D18: 6 | E18: =C18*D18 -> 1770 | F18: 0 | G18: =(E18*F18)+E18 -> 1770
A19: VIAPOSTE : 164-12Z | B19: Lundi au Vendredi | C19: 160.79 | D19: 5 | E19: =C19*D19 -> 803.95 | F19: 0.039775 | G19: =(E19*F19)+E19 -> 835.92711
A20: VIAPOSTE : 164-12 | B20: Lundi au Vendredi | C20: 160.72 | D20: 5 | E20: =C20*D20 -> 803.6 | F20: 0.039775 | G20: =(E20*F20)+E20 -> 835.56319
A21: VIAPOSTE : 164-10Z | B21: Lundi au Vendredi | C21: 87.14 | D21: 5 | E21: =C21*D21 -> 435.7 | F21: 0.039775 | G21: =(E21*F21)+E21 -> 453.02997
A22: VIAPOSTE : 170-19 | B22: Lundi au Vendredi | C22: 175.08 | D22: 5 | E22: =C22*D22 -> 875.4 | F22: 0.04271 | G22: =(E22*F22)+E22 -> 912.78833
A23: COADA sur 5 jours | E23: =C23*D23 -> 0 | G23: =(E23*F23)+E23 -> 0
A24: SPL34 | B24: CA DE LA LIGNE | F24: =SUM(G16:G23) -> 6571.9731
A25: SOMMAIRE
A27: Coûts de la Ligne
B28: Type | C28: unité | D28: Cout Semaine
A29: Moteur (1) | B29: Tracteur GNC | C29: =IFERROR(VLOOKUP(B29,Liste!C1:D5,2,FALSE),"") -> 2500 | D29: =IFERROR(C29/4.33,0) -> 577.36721
A30: Semi (1) | B30: SR Classique | C30: =IFERROR(VLOOKUP(B30,Liste!$C$7:$D$15,2,FALSE),"") -> 1000 | D30: =IFERROR(C30/4.33,0) -> 230.94688
A31: Semi (2) | B31: SR Classique | C31: =IFERROR(VLOOKUP(B31,Liste!$C$7:$D$15,2,FALSE),"") -> 1000 | D31: =IFERROR(C31/4.33,0) -> 230.94688
A32: Semi (3) | B32: AUCUNE | C32: =IFERROR(VLOOKUP(B32,Liste!$C$7:$D$15,2,FALSE),"") | D32: =IFERROR(C32/4.33,0) -> 0
A33: Semi (4) | B33: AUCUNE | C33: =IFERROR(VLOOKUP(B33,Liste!$C$7:$D$15,2,FALSE),"") | D33: =IFERROR(C33/4.33,0) -> 0
A34: Carburant | B34: GO | C34: 0 | D34: =(B11*D5/100)*C34 -> 0
A35: Carburant | B35: GNC | C35: 1.365 | D35: =(D5*B11/100)*C35 -> 952.31723
A36: AD Blue | C36: 0 | D36: =(D6*B11)*C36 -> 0
A37: Fuel | C37: 1.1225
A38: Casse / Pneumatique / Lavage ( hors entretien) | C38: 0.04 | D38: =C38*B11 -> 93.24
A39: Autoroute | B39: =B12 -> 0 | C39: 5 | D39: =(C39*B39) -> 0
A40: Salaires | B40: SPL | C40: 2 | D40: =960.55+1182.6 -> 2143.15
A41: Frais Hotel | D41: =G11 -> 0
A42: Tirpalette | B42: NON | C42: =IF(B42=Liste!A24,Liste!B18,0) -> 0 | D42: =C42/4.33 -> 0
A43: Sous-Traitance | C43: 0 | D43: 0
C45: TOTAL COUT | D45: =SUM(D29:D43) -> 4227.9682
C46: Marge Exploitation | D46: =F24-D45 -> 2344.0049
C48: % Marge | D48: =D46/F24 -> 0.35666685

Sheet SPL36
A1: FICHE DE RENTABILITE
A3: DONNEES EXPLOITATION
B4: Immatriculation | D4: Conso au 100 (Moyenne) | F4: Semaine | G4: S16
A5: Tracteur (s) | B5: GG-817-EB | D5: 29.42
A6: Semi (s) | B6: 1 Classique | D6: 0.019
A7: Conducteurs | B7: SAGAL | C7: LATIFA
A8: AMPLITUDE Hebdo | B8: 64.72 | C8: 49.11
A9: TDS Hebdo | B9: 53.81 | C9: 34.2
B10: KM Hebdo | G10: Hotel (semaine)
B11: =1634+1703 -> 3337 | G11: 0
A12: Autoroute / jour : | B12: 0 | F12: SPL | G12: CM
E13: €/ Hebdo | F13: 1000 | G13: 1100
A14: Détails CA
A15: Référence prestations | B15: Fréquence | C15: Montant unitaire | D15: Quantité | E15: Total Hors IGO | F15: Indexation | G15: Montant Total
A16: VIAPOSTE : 170-10 | B16: Lundi au Vendredi | C16: 190.09 | D16: 6 | E16: =C16*D16 -> 1140.54 | F16: 0.04271 | G16: =(E16*F16)+E16 -> 1189.2525
A17: VIAPOSTE : 170-11 | B17: Lundi au Vendredi | C17: 197.17 | D17: 5 | E17: =C17*D17 -> 985.85 | F17: 0.04271 | G17: =(E17*F17)+E17 -> 1027.9557
A18: VIAPOSTE : 170-2 | B18: Lundi au Vendredi | C18: 235.74 | D18: 6 | E18: =C18*D18 -> 1414.44 | F18: 0.04271 | G18: =(E18*F18)+E18 -> 1474.8507
A19: VIAPOSTE : 163-6 | B19: Lundi au Vendredi | C19: 117.85 | D19: 6 | E19: =C19*D19 -> 707.1 | F19: 0.039775 | G19: =(E19*F19)+E19 -> 735.2249
E20: =C20*D20 -> 0 | G20: =(E20*F20)+E20 -> 0
A21: WE : CHRONO : REAU - AULNAY | B21: Samedi | C21: 200 | D21: 1 | E21: =C21*D21 -> 200 | F21: 3.5 | G21: =F21+E21 -> 203.5
E22: =C22*D22 -> 0 | G22: =(E22*F22)+E22 -> 0
E23: =C23*D23 -> 0 | G23: =(E23*F23)+E23 -> 0
A24: SPL36 | B24: CA DE LA LIGNE | F24: =SUM(G16:G23) -> 4630.7838
A25: SOMMAIRE
A27: Coûts de la Ligne
B28: Type | C28: unité | D28: Cout Semaine
A29: Moteur (1) | B29: Tracteur GNC | C29: =IFERROR(VLOOKUP(B29,Liste!C1:D5,2,FALSE),"") -> 2500 | D29: =IFERROR(C29/4.33,0) -> 577.36721
A30: Semi (1) | B30: SR Classique | C30: =IFERROR(VLOOKUP(B30,Liste!$C$7:$D$15,2,FALSE),"") -> 1000 | D30: =IFERROR(C30/4.33,0) -> 230.94688
A31: Semi (2) | B31: AUCUNE | C31: =IFERROR(VLOOKUP(B31,Liste!$C$7:$D$15,2,FALSE),"") | D31: =IFERROR(C31/4.33,0) -> 0
A32: Semi (3) | B32: AUCUNE | C32: =IFERROR(VLOOKUP(B32,Liste!$C$7:$D$15,2,FALSE),"") | D32: =IFERROR(C32/4.33,0) -> 0
A33: Semi (4) | B33: AUCUNE | C33: =IFERROR(VLOOKUP(B33,Liste!$C$7:$D$15,2,FALSE),"") | D33: =IFERROR(C33/4.33,0) -> 0
A34: Carburant | B34: GO | C34: 0 | D34: =(B11*D5/100)*C34 -> 0
A35: Carburant | B35: GNC | C35: 1.365 | D35: =(D5*B11/100)*C35 -> 1340.0825
A36: AD Blue | C36: 0 | D36: =(D6*B11)*C36 -> 0
A37: Fuel | C37: 1.1225
A38: Casse / Pneumatique / Lavage ( hors entretien) | C38: 0.04 | D38: =C38*B11 -> 133.48
A39: Autoroute | B39: =B12 -> 0 | C39: 5 | D39: =(C39*B39) -> 0
A40: Salaires | B40: SPL | C40: 2 | D40: =894.45+736.25 -> 1630.7
A41: Frais Hotel | D41: =G11 -> 0
A42: Tirpalette | B42: NON | C42: =IF(B42=Liste!A24,Liste!B18,0) -> 0 | D42: =C42/4.33 -> 0
A43: Sous-Traitance | C43: 0 | D43: 0
C45: TOTAL COUT | D45: =SUM(D29:D43) -> 3912.5766
C46: Marge Exploitation | D46: =F24-D45 -> 718.20719
C48: % Marge | D48: =D46/F24 -> 0.15509409

Sheet SPL37
A1: FICHE DE RENTABILITE
A3: DONNEES EXPLOITATION
B4: Immatriculation | D4: Conso au 100 (Moyenne) | F4: Semaine | G4: S17
A5: Tracteur (s) | B5: FN-813-DX | D5: 29.74
A6: Semi (s) | B6: 1 aerienne | D6: 0.019
A7: Conducteurs | B7: KAMAGATE
A8: AMPLITUDE Hebdo | B8: 68.06
A9: TDS Hebdo | B9: 38.07
B10: KM Hebdo | G10: Hotel (semaine)
B11: 1818 | G11: 0
A12: Autoroute / jour : | B12: =30.17*2 -> 60.34 | F12: SPL | G12: CM
E13: €/ Hebdo | F13: 1000 | G13: 1100
A14: Détails CA
